Workbook
Name _ftnref1: 'Inhaltliche Bewertung - Angebot'!$U$53
Name _ftnref1: 'Inhaltliche Bewertung - GI'!$U$53
Name _ftnref2: 'Inhaltliche Bewertung - Angebot'!$U$65
Name _ftnref2: 'Inhaltliche Bewertung - GI'!$U$65
Name _ftnref3: 'Inhaltliche Bewertung - Angebot'!$E$74
Name _ftnref3: 'Inhaltliche Bewertung - GI'!$E$74
Name aig_MaxDeckungssumme: 'AIG Facility - Tarif'!$C$32
Name aig_MaxUmsatz: 'AIG Facility - Tarif'!$C$33
Name aig1usedClauses: 'Daten-Abzug'!$D$32
Name aig2usedClauses: 'Daten-Abzug'!$E$32
Name aig3usedClauses: 'Daten-Abzug'!$F$32
Name aigArbitrationCourtPercentage: Deckungsoptionen!$B$13
Name aigArbitrationCourtPremiumNeutral: Deckungsoptionen!$B$12
Name aigArbitrationCourtSelected: Deckungsoptionen!$B$11
Name aigDefaultKlauseln: 'Default-Klauseln'!$B$5
Name aigDoublePerYearPercentage: Deckungsoptionen!$B$8
Name aigDoublePerYearPremiumNeutral: Deckungsoptionen!$B$7
Name aigDoublePerYearSelected: Deckungsoptionen!$B$6
Name AIGFacilityAngeboteneDS: 'AIG Facility - Preisrechner'!$B$5:$G$5
Name AIGFacilityKriterien: Flussdiagramm!$L$10
Name AIGFacilityKriterien1: Flussdiagramm!$L$10
Name AIGFacilityKriterien2: Flussdiagramm!$M$10
Name AIGFacilityKriterien3: Flussdiagramm!$N$10
Name aigFacilityYesNo: 'Daten-Abzug'!$D$24
Name aigLimit1CoverageOptions: 'Daten-Abzug'!$D$31
Name aigLimit1FacilityYesNo: 'Daten-Abzug'!$D$24
Name aigLimit1HowdenNetProvision: 'Daten-Abzug'!$D$29
Name aigLimit1Offered: 'Daten-Abzug'!$D$27
Name aigLimit1Premium: 'Daten-Abzug'!$D$28
Name aigLimit1Stars: 'Daten-Abzug'!$D$25
Name aigLimit1Status: 'Daten-Abzug'!$D$33
Name aigLimit2CoverageOptions: 'Daten-Abzug'!$E$31
Name aigLimit2HowdenNetProvision: 'Daten-Abzug'!$E$29
Name aigLimit2Offered: 'Daten-Abzug'!$E$27
Name aigLimit2Premium: 'Daten-Abzug'!$E$28
Name aigLimit2Stars: 'Daten-Abzug'!$E$25
Name aigLimit2Status: 'Daten-Abzug'!$E$33
Name aigLimit3CoverageOptions: 'Daten-Abzug'!$F$31
Name aigLimit3HowdenNetProvision: 'Daten-Abzug'!$F$29
Name aigLimit3Offered: 'Daten-Abzug'!$F$27
Name aigLimit3Premium: 'Daten-Abzug'!$F$28
Name aigLimit3Stars: 'Daten-Abzug'!$F$25
Name aigLimit3Status: 'Daten-Abzug'!$F$33
Name AIGMax10Mio: Fragenkatalog!$K$63
Name aigUsedClauses: Fragenkatalog!$Z$6
Name aigWpHGPercentage: Deckungsoptionen!$B$18
Name aigWpHGPremiumNeutral: Deckungsoptionen!$B$17
Name aigWpHGSelected: Deckungsoptionen!$B$16
Name AnteileAnDerBörseGehandelt: Fragenkatalog!$K$61
Name Außenumsatz: Fragenkatalog!$K$57
Name AußenumsatzGI: Fragenkatalog!$F$57
Name axa_MaxDeckungssumme: 'AXA - Tarif ab 20230601'!$K$19
Name axa_MaxUmsatz: 'AXA - Tarif ab 20230601'!$K$20
Name axa_PremiumAdjustment: 'SIC-Liste'!$K$3
Name axa_Referral: 'SIC-Liste'!$J$3
Name axa1usedClauses: 'Daten-Abzug'!$D$22
Name axa2usedClauses: 'Daten-Abzug'!$E$22
Name axa3usedClauses: 'Daten-Abzug'!$F$22
Name axaArbitrationCourtPercentage: Deckungsoptionen!$D$13
Name axaArbitrationCourtPremiumNeutral: Deckungsoptionen!$D$12

Sheet Fragenkatalog
F1: 43557 | Q1: Anzahl Referrals | S1: Zu- / Abschläge | W1: Anzahl Referrals | Y1: Zu- / Abschläge | AC1: Anzahl Referrals | AE1: Zu- / Abschläge | AI1: Anzahl Referrals | AK1: Zu- / Abschläge | AO1: Anzahl Referrals | AQ1: Zu- / Abschläge | AU1: Anzahl Referrals | AW1: Zu- / Abschläge | BA1: Anzahl Referrals | BC1: Zu- / Abschläge | BG1: Anzahl Referrals | BI1: Zu- / Abschläge | BM1: Anzahl Referrals | BO1: Zu- / Abschläge
F2: 0.47 | Q2: =COUNTIF(Q7:Q148,"Referral") -> 1 | S2: =SUM(S7:S210) -> 0 | W2: =COUNTIF(W7:W148,"Referral") -> 1 | Y2: =SUM(Y7:Y210) -> 0 | AC2: =COUNTIF(AC8:AC148,"Referral") -> 2 | AE2: =SUM(AE7:AE210) -> 0 | AI2: =COUNTIF(AI7:AI148,"Referral") -> 2 | AK2: =SUM(AK7:AK210) -> 0 | AO2: =COUNTIF(AO7:AO148,"Referral") -> 1 | AQ2: =SUM(AQ7:AQ210) -> 0 | AU2: =COUNTIF(AU7:AU148,"Referral") -> 1 | AW2: =SUM(AW7:AW210) -> 0 | BA2: =COUNTIF(BA7:BA148,"Referral") -> 0 | BC2: =SUM(BC7:BC210) -> 0 | BG2: =COUNTIF(BG8:BG148,"Referral") -> 0 | BI2: =SUM(BI7:BI210) -> 0
F3: Philipp Thier | AI3: =NewlineEigenkapitalquote -> 0 | AU3: =WVAGEigenkapitalquote -> 0
F4: Grobindikation | K4: Angebotsindikation | P4: DUAL | V4: AIG Facility | AB4: Berkley | AH4: Newline | AN4: AXA | AT4: WVAG | AZ4: Markel | BF4: Liberty | BL4: Ergo
A5: Struktur für Testfälle | B5: Nr: Frage | C5: Fragebogen / Tasks | D5: Frage | E5: Folgefrage | F5: Hilfsspalte 1 für zusätzliche Berechnungen | G5: DigPos- ODER Testfall-Daten | H5: Mögliche Antwort-Optionen | I5: Zellen-Name für DigPos-Input | J5: Hilfsspalte 2 für zusätzliche Berechnungen | K5: Hilfsspalte 1 für zusätzliche Berechnungen | L5: DigPos- ODER Testfall-Daten | M5: Mögliche Antwort-Optionen | N5: Zellen-Name für DigPos-Input | O5: Hilfsspalte 2 für zusätzliche Berechnungen | P5: Dunkelverarbeitung / Referral / KO | Q5: Refferal Triggers | R5: KO Triggers | S5: Zu- und Abschläge | T5: Klauseln | U5: Limit für DS | V5: Dunkelverarbeitung / Referral / KO | W5: Refferal Triggers | X5: KO Triggers | Y5: Zu- und Abschläge | Z5: Klauseln | AA5: Limit für DS | AB5: Dunkelverarbeitung / Referral / KO | AC5: Refferal Triggers | AD5: KO Triggers | AE5: Zu- und Abschläge | AF5: Klauseln | AG5: Limit für DS | AH5: Dunkelverarbeitung / Referral / KO | AI5: Refferal Triggers | AJ5: KO Triggers | AK5: Zu- und Abschläge | AL5: Klauseln | AM5: Limit für DS | AN5: Dunkelverarbeitung / Referral / KO | AO5: Refferal Triggers | AP5: KO Triggers | AQ5: Zu- und Abschläge | AR5: Klauseln | AS5: Limit für DS | AT5: Dunkelverarbeitung / Referral / KO | AU5: Refferal Triggers | AV5: KO Triggers | AW5: Zu- und Abschläge | AX5: Klauseln | AY5: Limit für DS | AZ5: Dunkelverarbeitung / Referral / KO | BA5: Refferal Triggers | BB5: KO Triggers | BC5: Zu- und Abschläge | BD5: Klauseln | BE5: Limit für DS | BF5: Dunkelverarbeitung / Referral / KO | BG5: Refferal Triggers | BH5: KO Triggers | BI5: Zu- und Abschläge | BJ5: Klauseln | BK5: Limit für DS | BL5: Dunkelverarbeitung / Referral / KO | BM5: Refferal Triggers | BN5: KO Triggers | BO5: Zu- und Abschläge | BP5: Klauseln | BQ5: Limit für DS | BR5: Fachliche Beschreibung der Referralgründe
P6: =IF(R6>0,OfferDeclined,IF(Q6>0,OfferReferral,OfferReady)) -> OFFER_REFERRAL | Q6: =COUNTIF(Q7:Q151,Referral) -> 1 | R6: =COUNTIF(R7:R151,"KO Trigger") -> 0 | S6: =SUM(S7:S151) -> 0 | T6: =CONCATENATE(T24,",",dualDefaultKlauseln) -> , | U6: =MIN(U7:U151) -> 0 | V6: =IF(X6>0,OfferDeclined,IF(W6>0,OfferReferral,OfferReady)) -> OFFER_REFERRAL | W6: =COUNTIF(W7:W151,Referral) -> 1 | X6: =COUNTIF(X7:X151,"KO Trigger") -> 0 | Y6: =SUM(Y7:Y151) -> 0 | Z6: =CONCATENATE(Z24,",",aigDefaultKlauseln) -> , | AA6: =MIN(AA7:AA151) -> 0 | AB6: =IF(AD6>0,OfferDeclined,IF(AC6>0,OfferReferral,OfferReady)) -> OFFER_REFERRAL | AC6: =COUNTIF(AC7:AC151,Referral) -> 2 | AD6: =COUNTIF(AD7:AD151,"KO Trigger") -> 0 | AE6: =SUM(AE7:AE151) -> 0 | AF6: =CONCATENATE(AF24,",",berkleyDefaultKlauseln) -> , | AG6: =MIN(AG7:AG151) -> 0 | AH6: =IF(AJ6>0,OfferDeclined,IF(AI6>0,OfferReferral,OfferReady)) -> OFFER_REFERRAL | AI6: =COUNTIF(AI7:AI151,Referral) -> 3 | AJ6: =COUNTIF(AJ7:AJ151,"KO Trigger") -> 0 | AK6: =SUM(AK7:AK151) -> 0 | AL6: =CONCATENATE(AL24,",",newlineDefaultKlauseln) -> , | AM6: =MIN(AM7:AM151) -> 0 | AN6: =IF(AP6>0,OfferDeclined,IF(AO6>0,OfferReferral,OfferReady)) -> OFFER_DECLINED | AO6: =COUNTIF(AO7:AO151,Referral) -> 2 | AP6: =COUNTIF(AP7:AP151,"KO Trigger") + IF(COUNTIF(AO53:AO59,"Referral")>1,1,0) -> 1 | AQ6: =SUM(AQ7:AQ151) -> 0 | AR6: =CONCATENATE(AR24,",",AR150,",",axaDefaultKlauseln) -> ,, | AS6: =MIN(AS7:AS151) -> 0 | AT6: =IF(AV6>0,OfferDeclined,IF(AU6>0,OfferReferral,OfferReady)) -> OFFER_REFERRAL | AU6: =COUNTIF(AU7:AU151,Referral) -> 1 | AV6: =COUNTIF(AV7:AV151,"KO Trigger") -> 0 | AW6: =SUM(AW7:AW151) -> 0 | AX6: =CONCATENATE(AX24,",",wvagDefaultKlauseln) -> , | AY6: =MIN(AY7:AY151) -> 0 | AZ6: =IF(BB6>0,OfferDeclined,IF(BA6>0,OfferReferral,OfferReady)) -> OFFER_DECLINED | BA6: =COUNTIF(BA7:BA151,Referral) -> 0 | BB6: =COUNTIF(BB7:BB151,"KO Trigger") -> 1 | BC6: =SUM(BC7:BC151) -> 0 | BD6: =CONCATENATE(BD24, ",",markelDefaultKlauseln) -> , | BE6: =MIN(BE7:BE151) -> 0 | BF6: =IF(BH6>0,OfferDeclined,IF(BG6>0,OfferReferral,OfferReady)) -> OFFER_READY_FOR_POLICY | BG6: =COUNTIF(BG7:BG151,Referral) -> 0 | BH6: =COUNTIF(BH7:BH151,"KO Trigger") -> 0 | BI6: =SUM(BI7:BI151) -> 0 | BJ6: =CONCATENATE(BJ24,",",libertyDefaultKlauseln) -> , | BK6: =MIN(BK7:BK151) -> 0 | BL6: =IF(BN6>0,OfferDeclined,IF(BM6>0,OfferReferral,OfferReady)) -> OFFER_DECLINED | BM6: =COUNTIF(BM7:BM151,Referral) -> 1 | BN6: =COUNTIF(BN7:BN151,"KO Trigger") -> 1 | BO6: =SUM(BO7:BO151) -> 0 | BP6: =CONCATENATE(BP24,BP34,",",BP149,",",ergoDefaultKlauseln) -> ,ergo_nettoisierung:group-4, | BR6: Referral | BS6: KO
A7: Risikofragen | B7: Stamm-Daten1 | C7: Stamm-Daten | D7: Name | H7: Text | M7: Text | N7: Stamm-Daten1 | P7: Dunkelverarbeitung | V7: Dunkelverarbeitung | AB7: Dunkelverarbeitung | AH7: Dunkelverarbeitung | AN7: Dunkelverarbeitung | AT7: Dunkelverarbeitung | AZ7: Dunkelverarbeitung | BF7: Dunkelverarbeitung | BL7: Dunkelverarbeitung | BS7: =BR7 -> 0
A8: Risikofragen | B8: StammDaten2 | C8: StammDaten | D8: Rechtsform | F8: =VLOOKUP(TEXT(giLegalForm,0),'Listen-Daten DigPos'!G3:H43,2,FALSE) -> andere | H8: Siehe Listen-Daten DigPos | I8: giLegalForm | J8: =VLOOKUP(F8,'Listen-Daten'!A2:B41,2,FALSE) -> #N/A | K8: =VLOOKUP(TEXT(StammDaten2,0),'Listen-Daten DigPos'!G3:H43,2,FALSE) -> andere | M8: Siehe Listen-Daten DigPos | N8: StammDaten2 | O8: =_xlfn.IFNA(VLOOKUP(K8,'Listen-Daten'!A2:B41,2,FALSE),"") | P8: Trigger | Q8: =IF(K8 ="Einzelunternehmen", Referral, Dunkelverarbeitung) -> Dunkelverarbeitung | V8: Trigger | W8: =IF(K8="Einzelunternehmen", Referral, Dunkelverarbeitung) -> Dunkelverarbeitung | AB8: Trigger | AC8: =IF(K8="Einzelunternehmen", Referral, Dunkelverarbeitung) -> Dunkelverarbeitung | AH8: Dunkelverarbeitung | AI8: =IF(OR($K$8="PartG",$K$8="GbR"), Referral, Dunkelverarbeitung) -> Dunkelverarbeitung | AN8: Trigger | AO8: =IF(K8="Einzelunternehmen", Referral, Dunkelverarbeitung) -> Dunkelverarbeitung | AT8: Trigger | AU8: =IF(OR(K8= "gGmbH",K8 ="gAG",K8 ="UG",K8 ="Einzelunternehmen"), Referral, Dunkelverarbeitung) -> Dunkelverarbeitung | AV8: =IF(K8= "GbR", "KO Trigger", Dunkelverarbeitung) -> Dunkelverarbeitung | AZ8: Trigger | BB8: =IF(OR(K8="Einzelunternehmen",K8="e.K."),KO_Trigger, Dunkelverarbeitung) -> Dunkelverarbeitung | BF8: Trigger | BG8: =IF(K8 ="Einzelunternehmen", Referral, Dunkelverarbeitung) -> Dunkelverarbeitung | BL8: Trigger | BM8: =IF(OR(K8= "LLP",K8 ="GbR",K8 ="KG",K8="OHG",K8 ="Einzelunternehmen"), Referral, Dunkelverarbeitung) -> Dunkelverarbeitung | BR8: Rechtsform | BS8: Rechtsform
A9: Risikofragen | B9: StammDaten10 | C9: StammDaten | D9: Rechtsform - Klarname | N9: StammDaten10 | P9: Dunkelverarbeitung | V9: Dunkelverarbeitung | AB9: Dunkelverarbeitung | AH9: Dunkelverarbeitung | AN9: Dunkelverarbeitung | AT9: Dunkelverarbeitung | AZ9: Dunkelverarbeitung | BF9: Dunkelverarbeitung | BL9: Dunkelverarbeitung | BS9: =BR9 -> 0
A10: Risikofragen | B10: StammDaten901 | C10: StammDaten | D10: Gemeinnützigkeit? | H10: yes / no | K10: =IF(L10="YES","ja",IF(L10="NO","nein","")) | M10: yes / no | N10: StammDaten901 | P10: Dunkelverarbeitung | V10: Dunkelverarbeitung | AB10: Dunkelverarbeitung | AH10: Dunkelverarbeitung | AN10: Dunkelverarbeitung | AT10: Dunkelverarbeitung | AZ10: Dunkelverarbeitung | BF10: Dunkelverarbeitung | BL10: Dunkelverarbeitung | BS10: =BR10 -> 0
A11: Risikofragen | B11: RisikoFragen127 | C11: RisikoFragen | D11: Wie hoch war die Bilanzsumme / das Vereinsvermögen (nur für Vereine)? | F11: =giClubRevenue -> 0 | H11: Zahlen | I11: giClubRevenue | K11: =RisikoFragen127 -> 0 | M11: Zahlen | N11: RisikoFragen127 | P11: Dunkelverarbeitung | V11: Dunkelverarbeitung | AB11: Dunkelverarbeitung | AH11: Dunkelverarbeitung | AN11: Dunkelverarbeitung | AT11: Trigger | AU11: =IF(RisikoFragen127 > 50000000,Referral,Dunkelverarbeitung) -> Dunkelverarbeitung | AV11: =IF(RisikoFragen127 > 500000000,"KO Trigger",Dunkelverarbeitung) -> Dunkelverarbeitung | AZ11: Dunkelverarbeitung | BF11: Dunkelverarbeitung | BL11: Dunkelverarbeitung | BR11: Hohe Bilanzsumme bzw. Vereinsvermöge | BS11: =BR11 -> Hohe Bilanzsumme bzw. Vereinsvermöge
A12: Risikofragen | B12: RisikoFragenVereine103 | C12: RisikoFragenVereine | D12: Betreibt die VN unmittelbar oder mittelbar durch abhängige Unternehmen lizenzabhängigen Profisport in den dazu geschaffenen Sportverbandsystem? | H12: yes / no | K12: =IF(L12="YES","ja",IF(L12="NO","nein","")) | M12: yes / no | N12: RisikoFragenVereine103 | P12: Trigger | Q12: =IF(K12=JaAntwort,Referral,Dunkelverarbeitung) -> Dunkelverarbeitung | V12: Dunkelverarbeitung | AB12: Trigger | AC12: =IF(Profisport=JaAntwort,"Referral",Dunkelverarbeitung) -> Dunkelverarbeitung | AH12: Trigger | AJ12: =IF(K12=JaAntwort,"KO Trigger",Dunkelverarbeitung) -> Dunkelverarbeitung | AN12: Trigger | AP12: =IF(Profisport=JaAntwort,"KO Trigger",Dunkelverarbeitung) -> Dunkelverarbeitung | AT12: Trigger | AV12: =IF(Profisport=JaAntwort,"KO Trigger",Dunkelverarbeitung) -> Dunkelverarbeitung | AZ12: Trigger | BA12: =IF(K12=JaAntwort,Referral,Dunkelverarbeitung) -> Dunkelverarbeitung | BF12: Trigger | BH12: =IF(Profisport=JaAntwort,"KO Trigger",Dunkelverarbeitung) -> Dunkelverarbeitung | BL12: Trigger | BN12: =IF(Profisport=JaAntwort,"KO Trigger",Dunkelverarbeitung) -> Dunkelverarbeitung | BR12: Profisport | BS12: =BR12 -> Profisport
A13: Risikofragen | B13: RisikoFragen11 | C13: RisikoFragen | D13: Branche | F13: =VLOOKUP(giBusinessCode,'Listen-Daten DigPos'!D3:E1102,2,FALSE) -> #N/A | H13: Siehe Listen-Daten DigPos | I13: giBusinessCode | K13: =IF(BusinessCode="","",VLOOKUP(BusinessCode,'Listen-Daten DigPos'!D3:E1102,2,FALSE)) | M13: Siehe Listen-Daten DigPos | N13: RisikoFragen11 | O13: =IF(K13="","",VLOOKUP(K13,'SIC-Liste'!B7:C1013,2,FALSE)) | P13: Trigger | Q13: =IF('SIC-Liste'!D3=Referral,Referral,Dunkelverarbeitung) -> Dunkelverarbeitung | R13: =IF('SIC-Liste'!D3=KO_Trigger,KO_Trigger,Dunkelverarbeitung) -> Dunkelverarbeitung | S13: ='SIC-Liste'!E3 -> 0 | V13: ??? | W13: ??? | X13: ??? | AB13: Trigger | AC13: =IF('SIC-Liste'!H3=Referral,Referral,Dunkelverarbeitung) -> Dunkelverarbeitung | AD13: =IF('SIC-Liste'!H3=KO_Trigger,KO_Trigger,Dunkelverarbeitung) -> Dunkelverarbeitung | AE13: ='SIC-Liste'!I3 -> 0 | AH13: Trigger | AI13: =IF('SIC-Liste'!F3=Referral,Referral,Dunkelverarbeitung) -> Dunkelverarbeitung | AJ13: =IF('SIC-Liste'!F3=KO_Trigger,KO_Trigger,Dunkelverarbeitung) -> Dunkelverarbeitung | AK13: ='SIC-Liste'!G3 -> 0 | AN13: Trigger | AO13: =IF('SIC-Liste'!J3=Referral,Referral,Dunkelverarbeitung) -> Dunkelverarbeitung | AP13: =IF('SIC-Liste'!J3=KO_Trigger,KO_Trigger,Dunkelverarbeitung) -> Dunkelverarbeitung | AQ13: ='SIC-Liste'!K3 -> 0 | AT13: Trigger | AU13: =IF('SIC-Liste'!L3=Referral,Referral,Dunkelverarbeitung) -> Dunkelverarbeitung | AV13: =IF('SIC-Liste'!L3=KO_Trigger,KO_Trigger,Dunkelverarbeitung) -> Dunkelverarbeitung | AW13: ='SIC-Liste'!M3 -> 0 | AZ13: Trigger | BA13: =IF('SIC-Liste'!R3=Referral,Referral,Dunkelverarbeitung) -> Dunkelverarbeitung | BB13: =IF('SIC-Liste'!R3=KO_Trigger,KO_Trigger,Dunkelverarbeitung) -> Dunkelverarbeitung | BC13: ='SIC-Liste'!S3 -> 0 | BF13: Trigger | BG13: =IF('SIC-Liste'!T2=Referral,Referral,Dunkelverarbeitung) -> Dunkelverarbeitung | BH13: =IF('SIC-Liste'!T2=KO_Trigger,KO_Trigger,Dunkelverarbeitung) -> Dunkelverarbeitung | BI13: ='SIC-Liste'!U2 -> 0 | BL13: Trigger | BM13: =IF('SIC-Liste'!X3=Referral,Referral,Dunkelverarbeitung) -> Dunkelverarbeitung | BN13: =IF('SIC-Liste'!X3=KO_Trigger,KO_Trigger,Dunkelverarbeitung) -> Dunkelverarbeitung | BO13: ='SIC-Liste'!Y3 -> 0 | BR13: Branche | BS13: =BR13 -> Branche
A14: Risikofragen | B14: RisikoFragen2 | C14: RisikoFragen | D14: Branche - Klarname | N14: RisikoFragen2 | P14: Dunkelverarbeitung | V14: Dunkelverarbeitung | AB14: Dunkelverarbeitung | AH14: Dunkelverarbeitung | AN14: Dunkelverarbeitung | AT14: Dunkelverarbeitung | AZ14: Dunkelverarbeitung | BF14: Dunkelverarbeitung | BL14: Dunkelverarbeitung | BS14: =BR14 -> 0
A15: Risikofragen | B15: RisikoFragen9 | C15: RisikoFragen | D15: Ist die Gesellschaft länger als 2 Jahre ohne Unterbrechung tätig? | H15: STARTUP / NOSTARTUP | K15: =IFERROR(VLOOKUP(L15,'Listen-Daten DigPos'!J3:K4,2,FALSE),"") | M15: STARTUP / NOSTARTUP | N15: RisikoFragen9 | O15: =K15 | P15: Trigger | Q15: =IF(RisikoFragen9="STARTUP",Referral,Dunkelverarbeitung) -> Dunkelverarbeitung | S15: =IF(K15='Listen-Daten'!F2,0.25,"") | V15: Trigger | W15: =IF(RisikoFragen9="STARTUP",Referral,Dunkelverarbeitung) -> Dunkelverarbeitung | Y15: =IF(RisikoFragen9="STARTUP",60%,"") | AA15: =IF(RisikoFragen9="STARTUP",1000000,"") | AB15: Trigger | AC15: =IF(RisikoFragen9="STARTUP",Referral,Dunkelverarbeitung) -> Dunkelverarbeitung | AE15: =IF(K15='Listen-Daten'!F2,30%,"") | AH15: Trigger | AK15: =IF(RisikoFragen9="STARTUP",0.5,0) -> 0 | AN15: Trigger | AP15: =IF(K15='Listen-Daten'!F2,"KO Trigger",Dunkelverarbeitung) -> Dunkelverarbeitung | AT15: Trigger | AU15: =IF(RisikoFragen9="STARTUP",Referral,Dunkelverarbeitung) -> Dunkelverarbeitung | AZ15: Trigger | BA15: =IF(RisikoFragen9="STARTUP",Referral,Dunkelverarbeitung) -> Dunkelverarbeitung | BE15: =IF(BA15=Referral,"1000000","") | BF15: Trigger | BH15: =IF(RisikoFragen9="STARTUP","KO Trigger",Dunkelverarbeitung) -> Dunkelverarbeitung | BL15: Trigger | BQ15: =IF(BM15=Referral,"1000000","") | BR15: Junges Unternehmen / Startup | BS15: =BR15 -> Junges Unternehmen / Startup
A16: Risikofragen | B16: Gruendungsjahr | C16: RisikoFragen | D16: Wann wurde die Firma gegründet? | K16: =L16 -> 0 | M16: Datum | N16: Gruendungsjahr | P16: Dunkelverarbeitung | V16: Dunkelverarbeitung | AB16: Dunkelverarbeitung | AH16: Dunkelverarbeitung | AN16: Dunkelverarbeitung | AT16: Dunkelverarbeitung | AZ16: Dunkelverarbeitung | BF16: Dunkelverarbeitung | BL16: Trigger | BN16: =IF(TYPE(K16)=1,IF(AND(DATEDIF(K16, TODAY(), "Y")>=2,DATEDIF(K16, TODAY(), "MD")>=0),Dunkelverarbeitung,"KO Trigger"),IF(_xlfn.NUMBERVALUE(RIGHT(K16,4))<=1900,Dunkelverarbeitung,"KO Trigger")) -> Dunkelverarbeitung | BR16: Gründungsjahr | BS16: =BR16 -> Gründungsjahr
A17: Risikofragen | B17: StammDaten3 | C17: StammDaten | D17: Land | H17: Siehe Listen-Daten DigPos | K17: =VLOOKUP(StammDaten3,'Listen-Daten'!H2:J250,3,FALSE) -> #N/A | M17: Siehe Listen-Daten DigPos | N17: StammDaten3 | P17: Trigger | R17: =IF(K17<>"Germany","KO Trigger",Dunkelverarbeitung) -> #N/A | V17: Trigger | X17: =IF(K17<>"Germany","KO Trigger",Dunkelverarbeitung) -> #N/A | AB17: Trigger | AD17: =IF(K17<>"Germany","KO Trigger",Dunkelverarbeitung) -> #N/A | AH17: Trigger | AI17: =IF(VLOOKUP(StammDaten3,'Listen-Daten'!$H$2:$K$250,4,FALSE)<>"EU",Referral,Dunkelverarbeitung) -> #N/A | AN17: Trigger | AP17: =IF(K17<>"Germany","KO Trigger",Dunkelverarbeitung) -> #N/A | AT17: Trigger | AV17: =IF(K17="Germany", Dunkelverarbeitung,"KO Trigger") -> #N/A | AZ17: Trigger | BA17: =IF(OR(K17="Germany",K17="Austria"),Dunkelverarbeitung,Referral) -> #N/A | BB17: =IF(OR(K17="Germany",K17="Austria",K17="Switzerland"),Dunkelverarbeitung,"KO Trigger") -> #N/A | BF17: Trigger | BH17: =IF(K17="Germany",Dunkelverarbeitung,"KO Trigger") -> #N/A | BL17: Trigger | BM17: =IF(K17="Germany",Dunkelverarbeitung,IF(VLOOKUP(StammDaten3,'Listen-Daten'!$H$2:$K$250,4,FALSE)="EU",Referral,"")) -> #N/A | BN17: =IF(VLOOKUP(StammDaten3,'Listen-Daten'!$H$2:$K$250,4,FALSE)<>"EU",KO_Trigger,"") -> #N/A | BR17: Land der Versicherungsnehmerin | BS17: =BR17 -> Land der Versicherungsnehmerin
A18: Risikofragen | B18: Stamm-Daten4 | C18: Stamm-Daten | D18: Strasse | H18: Text | M18: Text | N18: Stamm-Daten4 | P18: Dunkelverarbeitung | V18: Dunkelverarbeitung | AB18: Dunkelverarbeitung | AH18: Dunkelverarbeitung | AN18: Dunkelverarbeitung | AT18: Dunkelverarbeitung | AZ18: Dunkelverarbeitung | BF18: Dunkelverarbeitung | BL18: Dunkelverarbeitung | BS18: =BR18 -> 0
A19: Risikofragen | B19: Stamm-Daten5 | C19: Stamm-Daten | D19: PLZ | H19: Zahlen | M19: Zahlen | N19: Stamm-Daten5 | P19: Dunkelverarbeitung | V19: Dunkelverarbeitung | AB19: Dunkelverarbeitung | AH19: Dunkelverarbeitung | AN19: Dunkelverarbeitung | AT19: Dunkelverarbeitung | AZ19: Dunkelverarbeitung | BF19: Dunkelverarbeitung | BL19: Dunkelverarbeitung | BS19: =BR19 -> 0
A20: Risikofragen | B20: Stamm-Daten6 | C20: Stamm-Daten | D20: Stadt | H20: Text | M20: Text | N20: Stamm-Daten6 | P20: Dunkelverarbeitung | V20: Dunkelverarbeitung | AB20: Dunkelverarbeitung | AH20: Dunkelverarbeitung | AN20: Dunkelverarbeitung | AT20: Dunkelverarbeitung | AZ20: Dunkelverarbeitung | BF20: Dunkelverarbeitung | BL20: Dunkelverarbeitung | BS20: =BR20 -> 0
A21: Risikofragen | B21: RisikoFragen7 | C21: RisikoFragen | D21: Internet (webadresse) | H21: Text | K21: =IF(L21="YES","ja",IF(L21="NO","nein","")) | M21: Text | N21: RisikoFragen7 | P21: Dunkelverarbeitung | V21: Dunkelverarbeitung | AB21: Dunkelverarbeitung | AH21: Dunkelverarbeitung | AN21: Dunkelverarbeitung | AT21: Dunkelverarbeitung | AZ21: Dunkelverarbeitung | BF21: Dunkelverarbeitung | BL21: Dunkelverarbeitung | BS21: =BR21 -> 0
A22: Risikofragen | B22: RisikoFragen8 | C22: RisikoFragen | D22: Jahresabschluss Online? | H22: Text | K22: =IF(L22="YES","ja",IF(L22="NO","nein","")) | M22: Text | N22: RisikoFragen8 | P22: Dunkelverarbeitung | V22: Dunkelverarbeitung | AB22: Dunkelverarbeitung | AH22: Dunkelverarbeitung | AN22: Dunkelverarbeitung | AT22: Dunkelverarbeitung | AZ22: Dunkelverarbeitung | BF22: Dunkelverarbeitung | BL22: Dunkelverarbeitung | BS22: =BR22 -> 0
A23: Risikofragen | B23: RisikoFragen0a | C23: RisikoFragen | D23: Gewünschter Policen Beginn | E23: x | H23: Datum | K23: =RisikoFragen0a -> 0 | M23: Datum | N23: RisikoFragen0a | P23: Trigger | Q23: =IF(OR(PolicenBeginn<(TODAY()+3),PolicenBeginn>(TODAY()+90)),Referral,Dunkelverarbeitung) -> Referral | V23: Trigger | W23: =IF(PolicenBeginn<(TODAY()+3),Referral,Dunkelverarbeitung) -> Referral | AB23: Trigger | AC23: =IF(OR(PolicenBeginn<(TODAY()-30),PolicenBeginn>(TODAY()+90)),Referral,Dunkelverarbeitung) -> Referral | AH23: Trigger | AI23: =IF(OR(PolicenBeginn<(TODAY()-7),PolicenBeginn>(TODAY()+4*30)),Referral,Dunkelverarbeitung) -> Referral | AN23: Trigger | AO23: =IF(PolicenBeginn<(TODAY()+3),Referral,Dunkelverarbeitung) -> Referral | AT23: Trigger | AU23: =IF(OR(AND(Vorversicherung=JaAntwort,PolicenBeginn<(TODAY()-3*30)),AND(Vorversicherung=NeinAntwort,PolicenBeginn<(TODAY()-2*30))),Referral,Dunkelverarbeitung) -> Dunkelverarbeitung | AZ23: Trigger | BB23: =IF(OR(PolicenBeginn<(TODAY()-3*30),PolicenBeginn>(TODAY()+12*30)),"KO Trigger",Dunkelverarbeitung) -> KO Trigger | BF23: Trigger | BG23: =IF(PolicenBeginn>(EDATE(TODAY(),6)),Referral,Dunkelverarbeitung) -> Dunkelverarbeitung | BL23: Dunkelverarbeitung | BR23: Policenbeginn | BS23: =BR23 -> Policenbeginn
A24: Risikofragen | B24: RisikoFragen0b | C24: RisikoFragen | D24: Gewünschtes Policen Ende | H24: Datum | K24: =L24 -> 0 | M24: Datum | N24: RisikoFragen0b | P24: Trigger | Q24: =IF(RisikoFragen0b>DATE(YEAR(PolicenBeginn)+1,MONTH(PolicenBeginn),DAY(PolicenBeginn)),"Referral",Dunkelverarbeitung) -> Dunkelverarbeitung | T24: =IF(DAYS360(PolicenBeginn,PolicenAblauf)>=30*18,"bdv-871:group-4","") | V24: Dunkelverarbeitung | Z24: =IF(DAYS360(PolicenBeginn,PolicenAblauf)>=30*18,"bdv-811:group-4","") | AB24: Trigger | AC24: =IF(OR(DAYS360(PolicenBeginn,PolicenAblauf)<30*6,DAYS360(PolicenBeginn,PolicenAblauf)>=30*18),"Referral",Dunkelverarbeitung) -> Referral | AE24: =IF(DAYS360(PolicenBeginn,PolicenAblauf)>=30*18,0.1,0) -> 0 | AF24: =IF(DAYS360(PolicenBeginn,PolicenAblauf)>=30*18,"bdv-1351:group-4","") | AH24: Trigger | AI24: =IF(OR(DAYS360(PolicenBeginn,PolicenAblauf)<30*9,DAYS360(PolicenBeginn,PolicenAblauf)>30*24),Referral,Dunkelverarbeitung) -> Referral | AL24: =IF(DAYS360(PolicenBeginn,PolicenAblauf)>=30*18,"axa_my:group-4","") | AN24: Trigger | AP24: =IF(OR(PolicenAblauf<DATE(YEAR(PolicenBeginn)+1,MONTH(PolicenBeginn),DAY(PolicenBeginn)),PolicenAblauf>DATE(YEAR(PolicenBeginn),MONTH(PolicenBeginn)+24,DAY(PolicenBeginn))),"KO Trigger",Dunkelverarbeitung) -> KO Trigger | AR24: =IF(DAYS360(PolicenBeginn,PolicenAblauf)>=30*18,"axa_my:group-4","") | AT24: Trigger | AU24: =IF(DAYS360(PolicenBeginn,PolicenAblauf) <= 14*30,Dunkelverarbeitung,Referral) -> Dunkelverarbeitung | AX24: =IF(DAYS360(PolicenBeginn,PolicenAblauf)>=30*18,"bdv-901:group-4","") | AZ24: Trigger | BA24: =IF(DAYS360(PolicenBeginn,PolicenAblauf)<=12*30,Dunkelverarbeitung,Referral) -> Dunkelverarbeitung | BD24: =IF(DAYS360(PolicenBeginn,PolicenAblauf)>=30*18,"mk-lfv-1:group-4","") | BF24: Trigger | BG24: =IF(DAYS360(PolicenBeginn,PolicenAblauf)<=12*30,Dunkelverarbeitung,Referral) -> Dunkelverarbeitung | BJ24: =IF(DAYS360(PolicenBeginn,PolicenAblauf)>=30*18,"axa_my:group-4","") | BL24: Trigger | BN24: =IF(DAYS360(PolicenBeginn,PolicenAblauf,TRUE)<12*30,"KO Trigger",Dunkelverarbeitung) -> KO Trigger | BP24: =IF(DAYS360(PolicenBeginn,PolicenAblauf)>=30*18,"ergo-lfv-1:group-4","") | BR24: Policenende bzw. Laufzeit | BS24: =BR24 -> Policenende bzw. Laufzeit
A25: Risikofragen | B25: RisikoFragen0c | C25: RisikoFragen | D25: Deckungssumme (1) | F25: =giLimit1 -> 0 | H25: Zahlen | I25: giLimit1 | K25: =RisikoFragen0c -> 0 | M25: Zahlen | N25: RisikoFragen0c | P25: Dunkelverarbeitung | V25: Dunkelverarbeitung | AB25: Dunkelverarbeitung | AH25: Trigger --> siehe Sterne Rechner Angebot | AN25: Dunkelverarbeitung | AT25: Trigger | AZ25: Trigger | BF25: Trigger | BL25: Trigger | BS25: =BR25 -> 0
A26: Risikofragen | B26: RisikoFragen0d | C26: RisikoFragen | D26: Deckungssumme (2) | F26: =giLimit2 -> 0 | H26: Zahlen | I26: giLimit2 | K26: =RisikoFragen0d -> 0 | M26: Zahlen | N26: RisikoFragen0d | P26: Dunkelverarbeitung | V26: Dunkelverarbeitung | AB26: Dunkelverarbeitung | AH26: Trigger --> siehe Sterne Rechner Angebot | AN26: Dunkelverarbeitung | AT26: Trigger | AZ26: Trigger | BF26: Trigger | BL26: Trigger | BS26: =BR26 -> 0
A27: Risikofragen | B27: RisikoFragen0e | C27: RisikoFragen | D27: Deckungssumme (3) | F27: =giLimit3 -> 0 | H27: Zahlen | I27: giLimit3 | K27: =RisikoFragen0e -> 0 | M27: Zahlen | N27: RisikoFragen0e | P27: Dunkelverarbeitung | V27: Dunkelverarbeitung | AB27: Dunkelverarbeitung | AH27: Trigger --> siehe Sterne Rechner Angebot | AN27: Dunkelverarbeitung | AT27: Trigger | AZ27: Trigger | BF27: Trigger | BL27: Trigger | BS27: =BR27 -> 0
A28: Risikofragen | B28: RisikoFragen18 | C28: RisikoFragen | D28: Sind dem Unterzeichner Pflichtverletzungen bekannt, die zu einer Inanspruchnahme der gewünschten Deckung führen können? Wenn ja, bitte Einzelheiten angeben. | H28: yes / no | K28: =IF(L28="YES","ja",IF(L28="NO","nein","")) | M28: yes / no | N28: RisikoFragen18 | P28: Trigger | Q28: =IF(K28=JaAntwort,Referral,Dunkelverarbeitung) -> Dunkelverarbeitung | V28: Trigger | W28: =IF(K28=JaAntwort,Referral,Dunkelverarbeitung) -> Dunkelverarbeitung | AB28: Trigger | AC28: =IF(K28=JaAntwort,Referral,Dunkelverarbeitung) -> Dunkelverarbeitung | AH28: Trigger | AJ28: =IF(K28=JaAntwort,KO_Trigger,Dunkelverarbeitung) -> Dunkelverarbeitung | AN28: Trigger | AO28: =IF(K28=JaAntwort,Referral,Dunkelverarbeitung) -> Dunkelverarbeitung | AT28: Trigger | AU28: =IF(K28=JaAntwort,Referral,Dunkelverarbeitung) -> Dunkelverarbeitung | AZ28: Trigger | BA28: =IF(K28=JaAntwort,Referral,Dunkelverarbeitung) -> Dunkelverarbeitung | BF28: Trigger | BG28: =IF(K28=JaAntwort,Referral,Dunkelverarbeitung) -> Dunkelverarbeitung | BL28: Dunkelverarbeitung | BR28: Dem Unterzeichner sind Pflichtverletzungen bekannt, die zu einer Inanspruchnahme der gewünschten Deckung führen können. | BS28: =BR28 -> Dem Unterzeichner sind Pflichtverletzungen bekannt, die zu einer Inanspruchnahme der gewünschten Deckung führen können.
A29: Risikofragen | B29: RisikoFragen19 | C29: RisikoFragen | D29: Sind in der Vergangenheit Ansprüche gestellt worden, die unter die gewünschte Deckung fallen könnten? Wenn ja, bitte Einzelheiten angeben. | H29: yes / no | K29: =IF(L29="YES","ja",IF(L29="NO","nein","")) | M29: yes / no | N29: RisikoFragen19 | P29: Trigger | Q29: =IF(K29=JaAntwort,Referral,Dunkelverarbeitung) -> Dunkelverarbeitung | V29: Trigger | W29: =IF(K29=JaAntwort,Referral,Dunkelverarbeitung) -> Dunkelverarbeitung | AB29: Trigger | AC29: =IF(K29=JaAntwort,Referral,Dunkelverarbeitung) -> Dunkelverarbeitung | AH29: Trigger | AI29: =IF((AND(K29=JaAntwort,Umsatz>=100000000)),Referral,Dunkelverarbeitung) -> Dunkelverarbeitung | AJ29: =IF(AND(K29=JaAntwort,Umsatz<100000000),KO_Trigger,Dunkelverarbeitung) -> Dunkelverarbeitung | AK29: =IF(AND(K29=JaAntwort,Umsatz>=100000000),0.5,0) -> 0 | AN29: Trigger | AO29: =IF(K29=JaAntwort,Referral,Dunkelverarbeitung) -> Dunkelverarbeitung | AT29: Trigger | AU29: =IF(K29=JaAntwort,Referral,Dunkelverarbeitung) -> Dunkelverarbeitung | AZ29: Trigger | BA29: =IF(K29=JaAntwort,Referral,Dunkelverarbeitung) -> Dunkelverarbeitung | BF29: Trigger | BG29: =IF(K29=JaAntwort,Referral,Dunkelverarbeitung) -> Dunkelverarbeitung | BL29: Trigger | BM29: =IF(K29=JaAntwort,Referral,Dunkelverarbeitung) -> Dunkelverarbeitung | BR29: In der Vergangenheit sind Ansprüche gestellt worden, die unter die gewünschte Deckung fallen könnten. | BS29: =BR29 -> In der Vergangenheit sind Ansprüche gestellt worden, die unter die gewünschte Deckung fallen könnten.
A30: Risikofragen | B30: RisikoFragen20 | C30: RisikoFragen | D30: Wurden in den vergangenen drei Jahren geschäftsführende Organmitglieder im Streit abberufen? Wenn ja, bitte Einzelheiten angeben. | H30: yes / no | K30: =IF(L30="YES","ja",IF(L30="NO","nein","")) | M30: yes / no | N30: RisikoFragen20 | P30: Trigger | Q30: =IF(K30=JaAntwort,Referral,Dunkelverarbeitung) -> Dunkelverarbeitung | V30: Dunkelverarbeitung | AB30: Trigger | AC30: =IF(K30=JaAntwort,Referral,Dunkelverarbeitung) -> Dunkelverarbeitung | AH30: Trigger | AI30: =IF((AND(K30=JaAntwort,Umsatz>=100000000)),Referral,Dunkelverarbeitung) -> Dunkelverarbeitung | AJ30: =IF(AND(K30=JaAntwort,Umsatz<100000000),KO_Trigger,Dunkelverarbeitung) -> Dunkelverarbeitung | AK30: =IF(AND(K30=JaAntwort,Umsatz>=100000000),0.5,0) -> 0 | AN30: Trigger | AO30: =IF(K30=JaAntwort,Referral,Dunkelverarbeitung) -> Dunkelverarbeitung | AT30: Trigger | AU30: =IF(K30=JaAntwort,Referral,Dunkelverarbeitung) -> Dunkelverarbeitung | AZ30: Dunkelverarbeitung | BF30: Dunkelverarbeitung | BH30: =IF(K30=JaAntwort,"KO Trigger",Dunkelverarbeitung) -> Dunkelverarbeitung | BL30: Trigger | BM30: =IF(K30=JaAntwort,Referral,Dunkelverarbeitung) -> Dunkelverarbeitung | BR30: In den vergangenen drei Jahren wurden geschäftsführende Organmitglieder im Streit abberufen. | BS30: =BR30 -> In den vergangenen drei Jahren wurden geschäftsführende Organmitglieder im Streit abberufen.
A31: Risikofragen | B31: RisikoFragen21a | C31: RisikoFragen | D31: Wurde die VN innerhalb der vergangenen drei Jahre neu beherrscht? Wenn ja, bitte Einzelheiten und Datum der Neuberrschung angeben. | H31: yes / no | K31: =IF(L31="YES","ja",IF(L31="NO","nein","")) | M31: yes / no | N31: RisikoFragen21a | P31: Trigger | Q31: =IF(AND(K31=JaAntwort,Vorversicherung=JaAntwort),Referral,Dunkelverarbeitung) -> Dunkelverarbeitung | V31: Trigger | W31: Dunkelverarbeitung | Y31: =IF(Neubeherrschung="ja",0.15,"") | AB31: Trigger | AC31: =IF(K31=JaAntwort,Referral,Dunkelverarbeitung) -> Dunkelverarbeitung | AH31: Dunkelverarbeitung | AK31: =IF(K31=JaAntwort,0.2,0) -> 0 | AN31: Dunkelverarbeitung | AT31: Trigger | AU31: =IF(K31=JaAntwort,Referral,Dunkelverarbeitung) -> Dunkelverarbeitung | AZ31: Dunkelverarbeitung | BF31: Trigger | BG31: =IF(K31=JaAntwort,Referral,Dunkelverarbeitung) -> Dunkelverarbeitung | BL31: Trigger | BM31: =IF(K31=JaAntwort,Referral,Dunkelverarbeitung) -> Dunkelverarbeitung | BR31: Die Versicherungsnehmerin wurde innerhalb der vergangenen drei Jahre neu beherrscht. | BS31: =BR31 -> Die Versicherungsnehmerin wurde innerhalb der vergangenen drei Jahre neu beherrscht.
A32: Risikofragen | B32: RisikoFragen21b | C32: RisikoFragen | D32: Folgefrage: | E32: Ab wann wurde die VN neu beherrscht? | H32: Datum | K32: =RisikoFragen21b -> 0 | M32: Datum | N32: RisikoFragen21b | P32: Dunkelverarbeitung | V32: Dunkelverarbeitung | AB32: Dunkelverarbeitung | AH32: Dunkelverarbeitung | AK32: =IF(TODAY()-365<K32,0.2,"") | AN32: Dunkelverarbeitung | AT32: Trigger | AU32: =IF(K32=JaAntwort,Referral,Dunkelverarbeitung) -> Dunkelverarbeitung | AZ32: Dunkelverarbeitung | BF32: Trigger | BG32: =IF(K32=JaAntwort,Referral,Dunkelverarbeitung) -> Dunkelverarbeitung | BL32: Dunkelverarbeitung | BR32: Neubeherrschung | BS32: =BR32 -> Neubeherrschung
A33: Risikofragen | B33: RisikoFragen22 | C33: RisikoFragen | D33: Wurde innerhalb der vergangenen drei Jahre die Kapitalstruktur der VN geändert? Wenn ja, bitte Einzelheiten angeben. | H33: yes / no | K33: =IF(L33="YES","ja",IF(L33="NO","nein","")) | M33: yes / no | N33: RisikoFragen22 | P33: Trigger | Q33: =IF(K33=JaAntwort,Referral,Dunkelverarbeitung) -> Dunkelverarbeitung | V33: Trigger | W33: =IF(K33=JaAntwort,Referral,Dunkelverarbeitung) -> Dunkelverarbeitung | AB33: Trigger | AC33: =IF(K33=JaAntwort,Referral,Dunkelverarbeitung) -> Dunkelverarbeitung | AH33: Dunkelverarbeitung | AI33: =IF(K33=JaAntwort,Referral,Dunkelverarbeitung) -> Dunkelverarbeitung | AN33: Dunkelverarbeitung | AT33: Trigger | AU33: =IF(K33=JaAntwort,Referral,Dunkelverarbeitung) -> Dunkelverarbeitung | AZ33: Dunkelverarbeitung | BF33: Dunkelverarbeitung | BL33: Trigger | BM33: =IF(K33=JaAntwort,Referral,Dunkelverarbeitung) -> Dunkelverarbeitung | BR33: Innerhalb der vergangenen drei Jahre wurde die Kapitalstruktur der Versicherungsnehmerin geändert. | BS33: =BR33 -> Innerhalb der vergangenen drei Jahre wurde die Kapitalstruktur der Versicherungsnehmerin geändert.
A34: Risikofragen | B34: RisikoFragen23a | C34: RisikoFragen | D34: Besteht oder bestand für zu versichernde Personen bereits eine D&O Deckung im Sinne dieses Fragebogens? | H34: yes / no | K34: =IF(RisikoFragen23a="YES","ja",IF(RisikoFragen23a="NO","nein","")) | M34: yes / no | N34: RisikoFragen23a | P34: Dunkelverarbeitung | V34: Trigger | W34: =IF(K34=JaAntwort,Referral,Dunkelverarbeitung) -> Dunkelverarbeitung | AB34: Dunkelverarbeitung | AH34: Dunkelverarbeitung | AK34: =IF(AND(K34=JaAntwort,DATEDIF(K38,TODAY(),"y")>4),0.1,0) -> 0 | AN34: Dunkelverarbeitung | AT34: Dunkelverarbeitung | AZ34: Dunkelverarbeitung | BF34: Dunkelverarbeitung | BL34: Trigger | BP34: =IF(K34=JaAntwort,"ergo_konti:group-4","") | BR34: Es besteht oder bestand für zu versichernde Personen bereits eine D&O Deckung im Sinne dieses Fragebogens. | BS34: =BR34 -> Es besteht oder bestand für zu versichernde Personen bereits eine D&O Deckung im Sinne dieses Fragebogens.
A35: Risikofragen | B35: RisikoFragen23b | C35: RisikoFragen | D35: Höhe der Versicherungssumme: | E35: Höhe der Versicherungssumme: | H35: Text | K35: =RisikoFragen23b -> 0 | M35: Text | N35: RisikoFragen23b | P35: Dunkelverarbeitung | V35: Dunkelverarbeitung | AB35: Dunkelverarbeitung | AH35: Dunkelverarbeitung | AN35: Dunkelverarbeitung | AT35: Trigger | AU35: =IF(K35 > 7500000,Referral,Dunkelverarbeitung) -> Dunkelverarbeitung | AZ35: Trigger | BF35: Dunkelverarbeitung | BL35: Dunkelverarbeitung | BM35: =IF(K35<=5000000,Dunkelverarbeitung,Referral) -> Dunkelverarbeitung | BR35: Höhe der Versicherungssumme der Vorversicherung | BS35: =BR35 -> Höhe der Versicherungssumme der Vorversicherung
A36: Risikofragen | B36: RisikoFragen23c | C36: RisikoFragen | D36: Vorschäden? (Sind für den Vorvertrag Umstandsmeldungen oder Schäden gemeldet worden?) | E36: Vorschäden? | H36: Text | K36: =IF(L36="YES","ja",IF(L36="NO","nein","")) | M36: Text | N36: RisikoFragen23c | P36: Trigger | Q36: =IF(K36=JaAntwort,Referral,Dunkelverarbeitung) -> Dunkelverarbeitung | V36: Dunkelverarbeitung | AB36: Trigger | AC36: =IF(K36=JaAntwort,Referral,Dunkelverarbeitung) -> Dunkelverarbeitung | AH36: Trigger | AI36: =IF(K36=JaAntwort,Referral,Dunkelverarbeitung) -> Dunkelverarbeitung | AK36: =IF(K36=JaAntwort,0.1,0) -> 0 | AN36: Trigger | AO36: =IF(K36=JaAntwort,Referral,Dunkelverarbeitung) -> Dunkelverarbeitung | AT36: Trigger | AU36: =IF(K36=JaAntwort,Referral,Dunkelverarbeitung) -> Dunkelverarbeitung | AZ36: Trigger | BA36: =IF($K36=JaAntwort,Referral,Dunkelverarbeitung) -> Dunkelverarbeitung | BF36: Trigger | BH36: =IF(K36=JaAntwort,"KO Trigger",Dunkelverarbeitung) -> Dunkelverarbeitung | BL36: Trigger | BM36: =IF(K36=JaAntwort,Referral,Dunkelverarbeitung) -> Dunkelverarbeitung | BR36: Vorschäden | BS36: =BR36 -> Vorschäden
A37: Risikofragen | B37: RisikoFragen23d | C37: RisikoFragen | D37: Versicherungsscheinnummer: | E37: Versicherungsscheinnummer: | H37: Text | K37: =IF(L37="YES","ja",IF(L37="NO","nein","")) | M37: Text | N37: RisikoFragen23d | P37: Dunkelverarbeitung | V37: Dunkelverarbeitung | AB37: Dunkelverarbeitung | AH37: Dunkelverarbeitung | AN37: Dunkelverarbeitung | AT37: Dunkelverarbeitung | AZ37: Trigger | BF37: Dunkelverarbeitung | BL37: Dunkelverarbeitung | BS37: =BR37 -> 0
A38: Risikofragen | B38: RisikoFragen23e | C38: RisikoFragen | D38: Kontinuitätsdatum (Beginn Vorvertrag) | E38: Kontinuitätsdatum: | H38: Datum | K38: =RisikoFragen23e -> 0 | M38: Datum | N38: RisikoFragen23e | P38: Dunkelverarbeitung | V38: Dunkelverarbeitung | AB38: Dunkelverarbeitung | AH38: Dunkelverarbeitung | AN38: Dunkelverarbeitung | AT38: Dunkelverarbeitung | AZ38: Trigger | BF38: Dunkelverarbeitung | BL38: Dunkelverarbeitung | BR38: Kontinuität von mehr als 5 Jahre angefragt | BS38: =BR38 -> Kontinuität von mehr als 5 Jahre angefragt
A39: Risikofragen | B39: RisikoFragenVorvertragExtendedReportingPeriod | C39: RisikoFragen | D39: Gewährt der Vorversicherer eine unverfallbare Nachmeldefrist von mindestens 24 Monaten? | E39: Gewährt der Vorversicherer eine unverfallbare Nachmeldefrist von mindestens 24 Monaten? | H39: yes / no | K39: =IF(RisikoFragenVorvertragExtendedReportingPeriod="YES","ja",IF(RisikoFragenVorvertragExtendedReportingPeriod="NO","nein",IF(RisikoFragenVorvertragExtendedReportingPeriod="UNKNOWN","unbekannt",""))) | M39: yes / no | N39: RisikoFragenVorvertragExtendedReportingPeriod | P39: Trigger | Q39: =IF(OR(K39=NeinAntwort, K39="unbekannt"),Referral,Dunkelverarbeitung) -> Dunkelverarbeitung | V39: Dunkelverarbeitung | AB39: Trigger | AC39: =IF(OR(K39=NeinAntwort, K39="unbekannt"),Referral,Dunkelverarbeitung) -> Dunkelverarbeitung | AH39: Trigger | AI39: =IF(K39="unbekannt",Referral,Dunkelverarbeitung) -> Dunkelverarbeitung | AN39: Trigger | AO39: =IF(OR(K39=NeinAntwort, K39="unbekannt"),Referral,Dunkelverarbeitung) -> Dunkelverarbeitung | AT39: Trigger | AU39: =IF(OR(K39=NeinAntwort, K39="unbekannt"),Referral,Dunkelverarbeitung) -> Dunkelverarbeitung | AZ39: Trigger | BA39: =IF(OR(K39=NeinAntwort, K39="unbekannt"),Referral,Dunkelverarbeitung) -> Dunkelverarbeitung | BF39: Dunkelverarbeitung | BL39: Trigger | BM39: =IF(OR(K39=NeinAntwort, K39="unbekannt"),Referral,Dunkelverarbeitung) -> Dunkelverarbeitung | BR39: Der Vorversicherer gewährt keine unverfallbare Nachmeldefrist von mindestens 24 Monaten. | BS39: =BR39 -> Der Vorversicherer gewährt keine unverfallbare Nachmeldefrist von mindestens 24 Monaten.
A40: Risikofragen | B40: RisikoFragenVorvertragNoGapsInCoverage | C40: RisikoFragen | D40: Schließt der angefragte Vertrag ohne zeitliche Unterbrechung an den Vorvertrag an? | E40: Schließt der angefragte Vertrag ohne zeitliche Unterbrechung an den Vorvertrag an? | H40: yes / no | K40: =IF(RisikoFragenVorvertragNoGapsInCoverage="YES","ja",IF(RisikoFragenVorvertragNoGapsInCoverage="NO","nein","")) | M40: yes / no | N40: RisikoFragenVorvertragNoGapsInCoverage | P40: Trigger | Q40: =IF(K40=NeinAntwort,Referral,Dunkelverarbeitung) -> Dunkelverarbeitung | V40: Dunkelverarbeitung | AB40: Trigger | AC40: =IF(K40=NeinAntwort,Referral,Dunkelverarbeitung) -> Dunkelverarbeitung | AE40: =IF(AND(RisikoFragen23a="YES",K40=JaAntwort),15%,"") | AH40: Dunkelverarbeitung | AN40: Trigger | AO40: =IF(K40=NeinAntwort,Referral,Dunkelverarbeitung) -> Dunkelverarbeitung | AT40: Trigger | AU40: =IF(K40=NeinAntwort,Referral,Dunkelverarbeitung) -> Dunkelverarbeitung | AZ40: Trigger | BF40: Dunkelverarbeitung | BL40: Dunkelverarbeitung | BR40: Der angefragte Vertrag schließt nicht ohne zeitliche Unterbrechung an den Vorvertrag an. | BS40: =BR40 -> Der angefragte Vertrag schließt nicht ohne zeitliche Unterbrechung an den Vorvertrag an.
A41: Risikofragen | B41: RisikoFragenVorvertragClaimsForIncreasedLimit | C41: RisikoFragen | D41: Sind dem Unterzeichner Pflichtverletzungen bekannt, die zu einer Inanspruchnahme der gewünschten Deckung im Rahmen der erhöhten Deckungssumme führen können? | E41: Sind dem Unterzeichner Pflichtverletzungen bekannt, die zu einer Inanspruchnahme der gewünschten Deckung im Rahmen der erhöhten Deckungssumme führen können? | H41: yes / no | K41: =IF(RisikoFragenVorvertragClaimsForIncreasedLimit="YES","ja",IF(RisikoFragenVorvertragClaimsForIncreasedLimit="NO","nein","")) | M41: yes / no | N41: RisikoFragenVorvertragClaimsForIncreasedLimit | P41: Dunkelverarbeitung | V41: Dunkelverarbeitung | AB41: Dunkelverarbeitung | AH41: Trigger | AJ41: =IF(K41=JaAntwort,KO_Trigger,Dunkelverarbeitung) -> Dunkelverarbeitung | AN41: Dunkelverarbeitung | AT41: Trigger | AU41: =IF(K41=JaAntwort,Referral,Dunkelverarbeitung) -> Dunkelverarbeitung | AZ41: Trigger | BA41: =IF(K41=JaAntwort,Referral,Dunkelverarbeitung) -> Dunkelverarbeitung | BF41: Trigger | BH41: =IF(K41=JaAntwort,"KO Trigger",Dunkelverarbeitung) -> Dunkelverarbeitung | BL41: Trigger | BM41: =IF(K41=JaAntwort,Referral,Dunkelverarbeitung) -> Dunkelverarbeitung | BR41: Dem Unterzeichner sind Pflichtverletzungen bekannt, die zu einer Inanspruchnahme der gewünschten Deckung im Rahmen der erhöhten Deckungssumme führen können. | BS41: =BR41 -> Dem Unterzeichner sind Pflichtverletzungen bekannt, die zu einer Inanspruchnahme der gewünschten Deckung im Rahmen der erhöhten Deckungssumme führen können.
A42: Risikofragen | B42: RisikoFragenVorvertragInsurer | C42: RisikoFragen | D42: Vorversicherer | E42: Vorversicherer | H42: Text | M42: Text | N42: RisikoFragenVorvertragInsurer | P42: Trigger | Q42: =IF(OR(L42="DUAL",L42="LIBERTYMUTUAL",L42="VHV",L42="RNV",L42="AVA",L42="ARCH",L42="CHANNEL",L42="EVEREST",L42="TRAVELER"),Referral,Dunkelverarbeitung) -> Dunkelverarbeitung | V42: Dunkelverarbeitung | AB42: Trigger | AC42: =IF(OR(L42="BERKLEY",L42="CHUBBSE"),Referral,Dunkelverarbeitung) -> Dunkelverarbeitung | AH42: Trigger | AI42: =IF(L42="NEWLINE",Referral,Dunkelverarbeitung) -> Dunkelverarbeitung | AN42: Trigger | AO42: =IF(OR(L42="AXACORP",L42="AXASA",L42="AXA",L42="CATLIN",L42="XL"),Referral,Dunkelverarbeitung) -> Dunkelverarbeitung | AT42: Trigger | AU42: =IF(OR(L42="WVAG"),Referral,Dunkelverarbeitung) -> Dunkelverarbeitung | AZ42: Trigger | BA42: =IF(L42="markel",Referral,Dunkelverarbeitung) -> Dunkelverarbeitung | BF42: Trigger | BG42: =IF(K42=JaAntwort,Referral,Dunkelverarbeitung) -> Dunkelverarbeitung | BL42: Dunkelverarbeitung | BR42: Vorversicherer | BS42: =BR42 -> Vorversicherer
A43: Risikofragen | B43: RisikoFragen24 | C43: RisikoFragen | D43: Gibt es juristische Personen oder Gesellschaften, die direkt oder indirekt mehr als 50 % der Anteile der VN halten oder sie in sonstiger Weise beherrschen? Wenn ja, bitte Einzelheiten angeben. | H43: yes / no | K43: =IF(L43="YES","ja",IF(L43="NO","nein","")) | M43: yes / no | N43: RisikoFragen24 | P43: Trigger | Q43: =IF(K43=JaAntwort,Referral,Dunkelverarbeitung) -> Dunkelverarbeitung | V43: Trigger | AA43: =IF(K43=JaAntwort,5000000,"") | AB43: Trigger | AC43: =IF(K43=JaAntwort,Referral,Dunkelverarbeitung) -> Dunkelverarbeitung | AH43: Dunkelverarbeitung | AN43: Dunkelverarbeitung | AT43: Dunkelverarbeitung | AZ43: Dunkelverarbeitung | BF43: Trigger | BG43: =IF(K43=JaAntwort,Referral,Dunkelverarbeitung) -> Dunkelverarbeitung | BL43: Dunkelverarbeitung | BR43: Es gibt juristische Personen oder Gesellschaften, die direkt oder indirekt mehr als 50 % der Anteile der VN halten oder sie in sonstiger Weise beherrschen. | BS43: =BR43 -> Es gibt juristische Personen oder Gesellschaften, die direkt oder indirekt mehr als 50 % der Anteile der VN halten oder sie in sonstiger Weise beherrschen.
A44: Risikofragen | B44: RisikoFragen25 | C44: RisikoFragen | D44: Werden Anteile und/oder Anleihen der Versicherungsnehmerin, Tochtergesellschaften und/oder sonstiger mitzuversichernder Gesellschaften an einer Börse gehandelt? | H44: yes / no | K44: =IF(L44="YES","ja",IF(L44="NO","nein","")) | M44: yes / no | N44: RisikoFragen25 | P44: Trigger | Q44: =IF(K44=JaAntwort,Referral,Dunkelverarbeitung) -> Dunkelverarbeitung | V44: Dunkelverarbeitung | AB44: Trigger | AC44: =IF(K44=JaAntwort,Referral,Dunkelverarbeitung) -> Dunkelverarbeitung | AH44: Trigger | AI44: =IF(K44=JaAntwort,Referral,Dunkelverarbeitung) -> Dunkelverarbeitung | AN44: Trigger | AO44: =IF(K44=JaAntwort,Referral,Dunkelverarbeitung) -> Dunkelverarbeitung | AQ44: =IF(K44=JaAntwort,0.25,"") | AT44: Trigger | AV44: =IF(K44=JaAntwort,"KO Trigger",Dunkelverarbeitung) -> Dunkelverarbeitung | AZ44: Trigger | BA44: =IF(K44=JaAntwort,Referral,Dunkelverarbeitung) -> Dunkelverarbeitung | BF44: Trigger | BH44: =IF(K44=JaAntwort,"KO Trigger",Dunkelverarbeitung) -> Dunkelverarbeitung | BL44: Trigger | BM44: =IF(K44=JaAntwort,Referral,Dunkelverarbeitung) -> Dunkelverarbeitung | BR44: Anteile und/oder Anleihen der Versicherungsnehmerin, Tochtergesellschaften und/oder sonstiger mitzuversichernder Gesellschaften werden an einer Börse gehandelt. | BS44: =BR44 -> Anteile und/oder Anleihen der Versicherungsnehmerin, Tochtergesellschaften und/oder sonstiger mitzuversichernder Gesellschaften werden an einer Börse gehandelt.
A45: Risikofragen | B45: RisikoFragen26a | C45: RisikoFragen | D45: Gibt es Gesellschaften, die im jüngsten Geschäftsbericht der VN nicht konsolidiert sind, auf deren Organmitglieder sich der Versicherungsschutz aber dennoch erstrecken soll (z.B. Schwestergesellschaften, Joint Ventures, Pensionskassen)? Wenn ja, bitte aktuelle, konsolidierte und vollständige Geschäftsberichte dieser Gesellschaften beifügen. | H45: yes / no | K45: =IF(L45="YES","ja",IF(L45="NO","nein","")) | M45: yes / no | N45: RisikoFragen26a | P45: Trigger | Q45: =IF(K45=JaAntwort,Referral,Dunkelverarbeitung) -> Dunkelverarbeitung | V45: Dunkelverarbeitung | AB45: Trigger | AC45: =IF(K45=JaAntwort,Referral,Dunkelverarbeitung) -> Dunkelverarbeitung | AH45: Trigger | AI45: =IF(K45=JaAntwort,Referral,Dunkelverarbeitung) -> Dunkelverarbeitung | AN45: Trigger | AO45: =IF(K45=JaAntwort,Referral,Dunkelverarbeitung) -> Dunkelverarbeitung | AT45: Trigger | AU45: =IF(K45=JaAntwort,Referral,Dunkelverarbeitung) -> Dunkelverarbeitung | AZ45: Trigger | BA45: =IF(K45=JaAntwort,Referral,Dunkelverarbeitung) -> Dunkelverarbeitung | BF45: Trigger | BG45: =IF(K45=JaAntwort,Referral,Dunkelverarbeitung) -> Dunkelverarbeitung | BL45: Trigger | BM45: =IF(K45=JaAntwort,Referral,Dunkelverarbeitung) -> Dunkelverarbeitung | BR45: Es gibt Gesellschaften, die im jüngsten Geschäftsbericht der VN nicht konsolidiert sind, auf deren Organmitglieder sich der Versicherungsschutz aber dennoch erstrecken soll (z.B. Schwestergesellschaften, Joint Ventures, Pensionskassen). | BS45: =BR45 -> Es gibt Gesellschaften, die im jüngsten Geschäftsbericht der VN nicht konsolidiert sind, auf deren Organmitglieder sich der Versicherungsschutz aber dennoch erstrecken soll (z.B. Schwestergesellschaften, Joint Ventures, Pensionskassen).
A46: Risikofragen | B46: RisikoFragen26b | C46: RisikoFragen | D46: Existieren bei der VN, Tochtergesellschaften oder Gesellschaften auf denen sich der Versicherungsschutz erstrecken soll (Frage 26a) Kontrollorgane (z.B. Aufsichtsrat, Beirat, Verwaltungsrat etc.)? | H46: yes / no | K46: =IF(L46="YES","ja",IF(L46="NO","nein","")) | M46: yes / no | N46: RisikoFragen26b | P46: Trigger | Q46: =IF(K46=JaAntwort,Referral,Dunkelverarbeitung) -> Dunkelverarbeitung | V46: Dunkelverarbeitung | AB46: Dunkelverarbeitung | AH46: Dunkelverarbeitung | AN46: Dunkelverarbeitung | AT46: Trigger | AU46: =IF(K46=JaAntwort,Referral,Dunkelverarbeitung) -> Dunkelverarbeitung | AZ46: Dunkelverarbeitung | BF46: Trigger | BG46: =IF(K46=JaAntwort,Referral,Dunkelverarbeitung) -> Dunkelverarbeitung | BL46: Trigger | BM46: =IF(K46=JaAntwort,Referral,Dunkelverarbeitung) -> Dunkelverarbeitung | BR46: Bei der VN, Tochtergesellschaften oder Gesellschaften auf denen sich der Versicherungsschutz erstrecken soll existieren Kontrollorgane (z.B. Aufsichtsrat, Beirat, Verwaltungsrat etc.). | BS46: =BR46 -> Bei der VN, Tochtergesellschaften oder Gesellschaften auf denen sich der Versicherungsschutz erstrecken soll existieren Kontrollorgane (z.B. Aufsichtsrat, Beirat, Verwaltungsrat etc.).
A47: Risikofragen | B47: RisikoFragen27a | C47: RisikoFragen | D47: Soll sich der Versicherungsschutz auch auf Funktionen erstrecken, die zu versichernde Personen bzw. Arbeitnehmer (auch ausgeschiedenen) der VN oder einer Tochtergesellschaft als Mitglieder von Geschäftsführungs- oder Aufsichtsorganen bei gewinnorientierten Drittunternehmen wahrnehmen? | H47: yes / no | K47: =IF(L47="YES","ja",IF(L47="NO","nein","")) | M47: yes / no | N47: RisikoFragen27a | P47: Trigger | Q47: =IF(K47=JaAntwort,Referral,Dunkelverarbeitung) -> Dunkelverarbeitung | V47: Dunkelverarbeitung | AB47: Trigger | AC47: =IF(K47=JaAntwort,Referral,Dunkelverarbeitung) -> Dunkelverarbeitung | AH47: Dunkelverarbeitung | AN47: Dunkelverarbeitung | AT47: Trigger | AU47: =IF(K47=JaAntwort,Referral,Dunkelverarbeitung) -> Dunkelverarbeitung | AZ47: Dunkelverarbeitung | BF47: Trigger | BG47: =IF(K47=JaAntwort,Referral,Dunkelverarbeitung) -> Dunkelverarbeitung | BL47: Trigger | BM47: =IF(K47=JaAntwort,Referral,Dunkelverarbeitung) -> Dunkelverarbeitung | BR47: Der Versicherungsschutz soll sich auch auf Funktionen erstrecken, die zu versichernde Personen bzw. Arbeitnehmer (auch ausgeschiedenen) der VN oder einer Tochtergesellschaft als Mitglieder von Geschäftsführungs- oder Aufsichtsorganen bei gewinnorientierten Drittunternehmen wahrnehmen. | BS47: =BR47 -> Der Versicherungsschutz soll sich auch auf Funktionen erstrecken, die zu versichernde Personen bzw. Arbeitnehmer (auch ausgeschiedenen) der VN oder einer Tochtergesellschaft als Mitglieder von Geschäftsführungs- oder Aufsichtsorganen bei gewinnorientierten Drittunternehmen wahrnehmen.
A48: Risikofragen | B48: RisikoFragen27b | C48: RisikoFragen | D48: Folgefrage: | E48: Art des Mandats | H48: Siehe Listen-Daten DigPos | K48: =RisikoFragen27b -> 0 | M48: Siehe Listen-Daten DigPos | N48: RisikoFragen27b | P48: Dunkelverarbeitung | V48: Dunkelverarbeitung | AB48: Dunkelverarbeitung | AH48: Dunkelverarbeitung | AN48: Dunkelverarbeitung | AT48: Trigger | AZ48: Dunkelverarbeitung | BF48: Dunkelverarbeitung | BL48: Dunkelverarbeitung | BS48: =BR48 -> 0
A49: Risikofragen | B49: RisikoFragen27c | C49: RisikoFragen | D49: Folgefrage: | E49: Handelt es sich um Fremdmandate von versicherten Personen oder von Arbeitnehmern (auch ausgeschiedenen) der Versicherungsnehmerin oder einer Tochtergesellschaft? | H49: yes / no | K49: =IF(L49="YES","ja",IF(L49="NO","nein","")) | M49: yes / no | N49: RisikoFragen27c | P49: Dunkelverarbeitung | V49: Dunkelverarbeitung | AB49: Dunkelverarbeitung | AH49: Dunkelverarbeitung | AN49: Dunkelverarbeitung | AT49: Trigger | AU49: =IF(K49=JaAntwort,Referral,Dunkelverarbeitung) -> Dunkelverarbeitung | AZ49: Dunkelverarbeitung | BF49: Dunkelverarbeitung | BL49: Dunkelverarbeitung | BR49: Mandate: Fremdmandate | BS49: =BR49 -> Mandate: Fremdmandate
A50: Risikofragen | B50: RisikoFragen27d | C50: RisikoFragen | D50: Folgefrage: | E50: Erfolgt die Wahrnehmung im Interesse, auf Veranlassung, Wunsch oder Weisung der Versicherungsnehmerin oder einer Tochtergesellschaft? | H50: yes / no | K50: =IF(L50="YES","ja",IF(L50="NO","nein","")) | M50: yes / no | N50: RisikoFragen27d | P50: Dunkelverarbeitung | V50: Dunkelverarbeitung | AB50: Dunkelverarbeitung | AH50: Trigger | AI50: =IF(K50=NeinAntwort,Referral,Dunkelverarbeitung) -> Dunkelverarbeitung | AN50: Dunkelverarbeitung | AT50: Trigger | AU50: =IF(K50=JaAntwort,Referral,Dunkelverarbeitung) -> Dunkelverarbeitung | AZ50: Dunkelverarbeitung | BF50: Dunkelverarbeitung | BL50: Trigger | BM50: =IF(K50=JaAntwort,Referral,Dunkelverarbeitung) -> Dunkelverarbeitung | BR50: Mandate: Die Wahrnehmung erfolgt im Interesse, auf Veranlassung, Wunsch oder Weisung der Versicherungsnehmerin oder einer Tochtergesellschaft. | BS50: =BR50 -> Mandate: Die Wahrnehmung erfolgt im Interesse, auf Veranlassung, Wunsch oder Weisung der Versicherungsnehmerin oder einer Tochtergesellschaft.
A51: Risikofragen | B51: RisikoFragen27e | C51: RisikoFragen | D51: Folgefrage: | E51: Handelt es sich bei den Gesellschaften um börsennotierten Gesellschaften, Finanzdienstleistungsinsttitute (§1 Absatz 1a KWF), Gesellschaften mit Sitz oder Registrierung in den U.S.A, oder Gesellschaften, deren Wertpapiere an einer Börse in den U.S.A. gehandelt werden, einschließlich ADRs und Private Placement? Falls nein Themenkreis abgeschlossen ALT : Handelt es sich bei den sonstigen Gesellschaften oder juristischen Personen um: | H51: yes / no | K51: =IF(L51="YES","ja",IF(L51="NO","nein","")) | M51: yes / no | N51: RisikoFragen27e | P51: Dunkelverarbeitung | V51: Dunkelverarbeitung | AB51: Dunkelverarbeitung | AH51: Trigger | AI51: =IF(K51=JaAntwort,Referral,Dunkelverarbeitung) -> Dunkelverarbeitung | AN51: Dunkelverarbeitung | AT51: Trigger | AU51: =IF(K51=JaAntwort,Referral,Dunkelverarbeitung) -> Dunkelverarbeitung | AZ51: Trigger | BA51: =IF(K51=JaAntwort,Referral,Dunkelverarbeitung) -> Dunkelverarbeitung | BF51: Dunkelverarbeitung | BL51: Trigger | BM51: =IF(K51=JaAntwort,Referral,Dunkelverarbeitung) -> Dunkelverarbeitung | BR51: Mandate: Es handel sich bei den Gesellschaften um börsennotierten Gesellschaften, Finanzdienstleistungsinsttitute (§1 Absatz 1a KWF), Gesellschaften mit Sitz oder Registrierung in den U.S.A, oder Gesellschaften, deren Wertpapiere an einer Börse in den U.S.A. gehandelt werden, einschließlich ADRs und Private Placement. | BS51: =BR51 -> Mandate: Es handel sich bei den Gesellschaften um börsennotierten Gesellschaften, Finanzdienstleistungsinsttitute (§1 Absatz 1a KWF), Gesellschaften mit Sitz oder Registrierung in den U.S.A, oder Gesellschaften, deren Wertpapiere an einer Börse in den U.S.A. gehandelt werden, einschließlich ADRs und Private Placement.
A52: Risikofragen | B52: RisikoFragen30 | C52: RisikoFragen | D52: Existieren Tochtergesellschaften in den USA oder Kanada? Wenn ja, bitte Angabe der konsolidierten Bilanzsumme dieser Unternehmen in EURO_____________ und zusätzlich USA/Kanada Fragebogen ausfüllen. | H52: yes / no | K52: =IF(L52="YES","ja",IF(L52="NO","nein","")) | M52: yes / no | N52: RisikoFragen30 | P52: Trigger | Q52: =IF(K52=JaAntwort,Referral,Dunkelverarbeitung) -> Dunkelverarbeitung | V52: Trigger | Y52: =IF(K52="ja",0.15,"") | AB52: Trigger | AC52: =IF(K52=JaAntwort,Referral,Dunkelverarbeitung) -> Dunkelverarbeitung | AH52: Trigger | AI52: =IF(K52=JaAntwort,Referral,Dunkelverarbeitung) -> Dunkelverarbeitung | AK52: =IF(K52=JaAntwort,0.1,0) -> 0 | AL52: =IF(K52=JaAntwort,"us-selbstbehalt:group-4","") | AN52: Dunkelverarbeitung | AT52: Trigger | AU52: =IF(K52=JaAntwort,Referral,Dunkelverarbeitung) -> Dunkelverarbeitung | AZ52: Trigger | BA52: =IF(K52=JaAntwort,Referral,Dunkelverarbeitung) -> Dunkelverarbeitung | BF52: Trigger | BG52: =IF(K52=JaAntwort,Referral,Dunkelverarbeitung) -> Dunkelverarbeitung | BL52: Dunkelverarbeitung | BR52: Es existieren Tochtergesellschaften in den USA oder Kanada. | BS52: =BR52 -> Es existieren Tochtergesellschaften in den USA oder Kanada.
A53: Risikofragen | B53: RisikoFragen32 | C53: RisikoFragen | D53: Wie hoch war das Eigenkapital? | H53: Zahlen | K53: =RisikoFragen32 -> 0 | M53: Zahlen | N53: RisikoFragen32 | P53: Trigger | Q53: =IF(K53<0,Referral,Dunkelverarbeitung) -> Dunkelverarbeitung | V53: Dunkelverarbeitung | AB53: Trigger | AC53: =IF(OR(RisikoFragen35 * 15% <= K53),Dunkelverarbeitung,Referral) -> Dunkelverarbeitung | AH53: Trigger | AI53: =IF(AND(Gesellschaftsform="Unternehmen",OR(NewlineEigenkapitalquote<=0.05,K53<25000)),Referral,Dunkelverarbeitung) -> Dunkelverarbeitung | AK53: =IF(NewlineEigenkapitalquote>=0.2,-0.1,0) -> 0 | AN53: Trigger | AO53: =IF(Bilanzsumme * 17% <= K53,Dunkelverarbeitung,Referral) -> Dunkelverarbeitung | AP53: =IF(K53<0,KO_Trigger,Dunkelverarbeitung) -> Dunkelverarbeitung | AT53: Trigger | AU53: =IF(AND(Gesellschaftsform="Verein", Vereinsvermögen <= 50000000), Dunkelverarbeitung, IF(OR(RisikoFragen32<0,WVAGEigenkapitalquote<0.1),Referral,Dunkelverarbeitung)) -> Referral | AZ53: Trigger | BB53: =IF(AND(RisikoFragen32<>"",K53<=0),KO_Trigger,Dunkelverarbeitung) -> Dunkelverarbeitung | BF53: Trigger | BG53: =IF(K53<0,Referral,Dunkelverarbeitung) -> Dunkelverarbeitung | BH53: =IFERROR(IF(K53/K56<0.2,"KO Trigger",Dunkelverarbeitung),"Fehler in Berechnung") -> Fehler in Berechnung | BL53: Trigger | BM53: =IFERROR(IF(AND(K53/K56<0.2,K53/K56>=0.1),Referral,Dunkelverarbeitung),"Fehler in Berechnung") -> Fehler in Berechnung | BN53: =IFERROR(IF(K53/K56<0.1,"KO Trigger",Dunkelverarbeitung),"Fehler in Berechnung") -> Fehler in Berechnung | BR53: Eigenkapital | BS53: Eigenkapitalquote/negatives Eigenkapital
A54: Risikofragen | B54: RisikoFragen33 | C54: RisikoFragen | D54: Wie hoch war das EBIT? Berechnung EBIT: Jahresüberschuss (Gewinn) + Steueraufwand ./. Steuererträge + außerordentlicher Aufwand ./. außerordentliche Erträge + Finanzaufwand ./. Finanzerträge) | H54: Zahlen | M54: Zahlen | N54: RisikoFragen33 | AT54: Dunkelverarbeitung | AZ54: Trigger | BA54: =IF(K54<0,Referral,Dunkelverarbeitung) -> Dunkelverarbeitung | BF54: Dunkelverarbeitung | BL54: Dunkelverarbeitung | BR54: EBIT | BS54: =BR54 -> EBIT
A55: Risikofragen | B55: RisikoFragen34 | C55: RisikoFragen | D55: Wie hoch war das Jahresergebnis? | H55: Zahlen | K55: =RisikoFragen34 -> 0 | M55: Zahlen | N55: RisikoFragen34 | P55: Trigger | Q55: =IF(K55<0,Referral,Dunkelverarbeitung) -> Dunkelverarbeitung | V55: Dunkelverarbeitung | AB55: Trigger | AC55: =IF(AND(K55<=0,L55<>""),Referral,Dunkelverarbeitung) -> Dunkelverarbeitung | AH55: Trigger | AI55: =IF(AND(K55<=0,L55<>""),Referral,Dunkelverarbeitung) -> Dunkelverarbeitung | AK55: =IF(K55<0,0.15,0) -> 0 | AN55: Trigger | AP55: =IF(K55<0,KO_Trigger,Dunkelverarbeitung) -> Dunkelverarbeitung | AT55: Trigger | AU55: =IF(K55<0,Referral,Dunkelverarbeitung) -> Dunkelverarbeitung | AZ55: Trigger | BA55: =IF(K55<0,Referral,Dunkelverarbeitung) -> Dunkelverarbeitung | BF55: Trigger | BG55: =IF(K55<0,Referral,Dunkelverarbeitung) -> Dunkelverarbeitung | BL55: Trigger | BM55: =IF(K55<0,Referral,Dunkelverarbeitung) -> Dunkelverarbeitung | BR55: (negatives) Jahresergebnis | BS55: =BR55 -> (negatives) Jahresergebnis
A56: Risikofragen | B56: RisikoFragen35 | C56: RisikoFragen | D56: Wie hoch war die Bilanzsumme? | F56: =G56 -> 0 | H56: Zahlen | K56: =RisikoFragen35 -> 0 | M56: Zahlen | N56: RisikoFragen35 | P56: Dunkelverarbeitung | V56: Dunkelverarbeitung | AB56: Trigger | AC56: =IF(K56>250000000,Referral,Dunkelverarbeitung) -> Dunkelverarbeitung | AH56: Trigger | AI56: =IF(K56>200000000,Referral,Dunkelverarbeitung) -> Dunkelverarbeitung | AN56: Trigger | AO56: =IF(Außenumsatz * 20% <= K56,Dunkelverarbeitung,Referral) -> Dunkelverarbeitung | AT56: Dunkelverarbeitung | AZ56: Trigger | BA56: =IF(K56>500000000,Referral,Dunkelverarbeitung) -> Dunkelverarbeitung | BF56: Dunkelverarbeitung | BL56: Dunkelverarbeitung | BR56: Bilanzsumme | BS56: =BR56 -> Bilanzsumme
A57: Risikofragen | B57: RisikoFragen36a | C57: RisikoFragen | D57: Wie hoch war der Außenumsatz (nur für Unternehmen)? --> Non-Start-Up | F57: =MAX(giNonStartupRevenue,giStartupRevenue) -> 0 | H57: Zahlen | I57: giNonStartupRevenue | K57: =MAX(RisikoFragen36a,RisikoFragenStartUp142) -> 0 | M57: Zahlen | N57: RisikoFragen36a | P57: Dunkelverarbeitung | R57: =IF(Außenumsatz > dual_MaxUmsatz, "KO Trigger", Dunkelverarbeitung) -> Dunkelverarbeitung | V57: Dunkelverarbeitung | X57: =IF(Außenumsatz > aig_MaxUmsatz, "KO Trigger", Dunkelverarbeitung) -> Dunkelverarbeitung | AB57: Trigger | AD57: =IF(Außenumsatz>berkley_MaxUmsatz,"KO Trigger",Dunkelverarbeitung) -> Dunkelverarbeitung | AH57: Trigger | AJ57: =IF(Außenumsatz>newline_MaxUmsatz,"KO Trigger",Dunkelverarbeitung) -> Dunkelverarbeitung | AN57: Dunkelverarbeitung | AP57: =IF(Außenumsatz > axa_MaxUmsatz, "KO Trigger", Dunkelverarbeitung) -> Dunkelverarbeitung | AT57: Trigger | AV57: =IF(Außenumsatz>wvag_MaxUmsatz,"KO Trigger",Dunkelverarbeitung) -> Dunkelverarbeitung | AZ57: Trigger | BB57: =IF(Außenumsatz>markel_MaxUmsatz,"KO Trigger",Dunkelverarbeitung) -> Dunkelverarbeitung | BF57: Dunkelverarbeitung | BH57: =IF(Außenumsatz > liberty_MaxUmsatz, "KO Trigger", Dunkelverarbeitung) -> Dunkelverarbeitung | BL57: Dunkelverarbeitung | BN57: =IF(Außenumsatz > ergo_MaxUmsatz, "KO Trigger", Dunkelverarbeitung) -> Dunkelverarbeitung | BR57: Der letzte konsolidierte Umsatz der Versicherungsnehmerin liegt über der maximalen Höhe des hinterlegten Tarifes. | BS57: =BR57 -> Der letzte konsolidierte Umsatz der Versicherungsnehmerin liegt über der maximalen Höhe des hinterlegten Tarifes.
A58: Risikofragen | B58: RisikoFragen36b | C58: RisikoFragen | D58: Wie hoch war der Außenumsatz (nur für Unternehmen)?--> Start-Up (wird nicht für Berechnungen herangezogen | H58: Zahlen | I58: giStartupRevenue | M58: Zahlen | N58: RisikoFragen36b | P58: Dunkelverarbeitung | V58: Dunkelverarbeitung | AB58: Trigger | AC58: =IF(K58>250000000,Referral,Dunkelverarbeitung) -> Dunkelverarbeitung | AH58: Trigger | AJ58: =IF(Außenumsatz>newline_MaxUmsatz,"KO Trigger",Dunkelverarbeitung) -> Dunkelverarbeitung | AN58: Dunkelverarbeitung | AT58: Dunkelverarbeitung | AZ58: Trigger | BA58: =IF(K58>250000000,Referral,Dunkelverarbeitung) -> Dunkelverarbeitung | BF58: Dunkelverarbeitung | BL58: Dunkelverarbeitung | BR58: Außenumsatz | BS58: =BR58 -> Außenumsatz
A59: Risikofragen | B59: RisikoFragen37 | C59: RisikoFragen | D59: Wie hoch war der Außenumsatz von Tochtergesellschaften, die in Common Law-Ländern (Großbritannien, Irland, Australien, Neuseeland, Südafrika, Indien, Singapur, Hongkong) ansässig sind? | H59: Zahlen | K59: =RisikoFragen37 -> 0 | M59: Zahlen | N59: RisikoFragen37 | P59: Dunkelverarbeitung | V59: Dunkelverarbeitung | AB59: Dunkelverarbeitung | AH59: Dunkelverarbeitung | AN59: Dunkelverarbeitung | AT59: Dunkelverarbeitung | AZ59: Dunkelverarbeitung | BF59: Dunkelverarbeitung | BL59: Dunkelverarbeitung | BS59: =BR59 -> 0
A60: Risikofragen | B60: RisikoFragen39 | C60: RisikoFragen | D60: War das Umlaufvermögen größer als die kurzfristigen Verbindlichkeiten? | H60: yes / no | K60: =IF(L60="YES","ja",IF(L60="NO","nein","")) | M60: yes / no | N60: RisikoFragen39 | P60: Trigger | Q60: =IF(K60=NeinAntwort,Referral,Dunkelverarbeitung) -> Dunkelverarbeitung | V60: Dunkelverarbeitung | AB60: Trigger | AC60: =IF(K60=NeinAntwort,Referral,Dunkelverarbeitung) -> Dunkelverarbeitung | AH60: Trigger | AI60: =IF(K60=NeinAntwort,Referral,Dunkelverarbeitung) -> Dunkelverarbeitung | AK60: =IF(K60=NeinAntwort,0.15,0) -> 0 | AN60: Trigger | AO60: =IF(K60=NeinAntwort,Referral,Dunkelverarbeitung) -> Dunkelverarbeitung | AT60: Trigger | AU60: =IF(K60=NeinAntwort,Referral,Dunkelverarbeitung) -> Dunkelverarbeitung | AZ60: Trigger | BA60: =IF(K60=NeinAntwort,Referral,Dunkelverarbeitung) -> Dunkelverarbeitung | BF60: Dunkelverarbeitung | BG60: =IF(K60=NeinAntwort,Referral,Dunkelverarbeitung) -> Dunkelverarbeitung | BL60: Trigger | BM60: =IF(K60=NeinAntwort,Referral,Dunkelverarbeitung) -> Dunkelverarbeitung | BR60: Umlaufvermögen und kurzfristige Verbindlichkeiten | BS60: =BR60 -> Umlaufvermögen und kurzfristige Verbindlichkeiten
A61: Risikofragen | B61: RisikoFragenAIGFacility40 | C61: RisikoFragenAIGFacility | D61: Werden Anteile und/oder Anleihen der Versicherungsnehmerin, Tochtergesellschaften und/oder sonstiger mitzuversichernder Gesellschaften an einer Börse gehandelt? | H61: yes / no | K61: =IF(L61="YES","ja",IF(L61="NO","nein","")) | M61: yes / no | N61: RisikoFragenAIGFacility40 | P61: Dunkelverarbeitung | V61: Dunkelverarbeitung | AB61: Trigger | AC61: =IF(K61=JaAntwort,Referral,Dunkelverarbeitung) -> Dunkelverarbeitung | AH61: Trigger | AI61: =IF(K61=JaAntwort,Referral,Dunkelverarbeitung) -> Dunkelverarbeitung | AN61: Trigger | AO61: =IF(K61=JaAntwort,Referral,Dunkelverarbeitung) -> Dunkelverarbeitung | AT61: Trigger | AV61: =IF(K61=JaAntwort,"KO Trigger",Dunkelverarbeitung) -> Dunkelverarbeitung | AZ61: Trigger | BA61: =IF(K61=JaAntwort,Referral,Dunkelverarbeitung) -> Dunkelverarbeitung | BF61: Trigger | BH61: =IF(K61=JaAntwort,"KO Trigger",Dunkelverarbeitung) -> Dunkelverarbeitung | BL61: Trigger | BM61: =IF(K61=JaAntwort,Referral,Dunkelverarbeitung) -> Dunkelverarbeitung | BR61: Anteile und/oder Anleihen der Versicherungsnehmerin, Tochtergesellschaften und/oder sonstiger mitzuversichernder Gesellschaften werden an einer Börse gehandelt. | BS61: =BR61 -> Anteile und/oder Anleihen der Versicherungsnehmerin, Tochtergesellschaften und/oder sonstiger mitzuversichernder Gesellschaften werden an einer Börse gehandelt.
A62: Risikofragen | B62: RisikoFragenAIGFacility41 | C62: RisikoFragenAIGFacility | D62: Ist die Versicherungsnehmerin, Tochtergesellschaften und/oder sonstige mitzuversichernde Unternehmen ein Kreditinstitut, eine Versicherung oder ein Finanzdienstleistungsinstitut im Sinne von § 1 Abs. 1 und 1a KWG (Kreditwesengesetz), § 1 VAG (Versicherungsaufsichtsgesetz) oder ein Wertpapierinstitut im Sinne von § 2 WpIG (Wertpapierinstitutsgesetz)? | H62: yes / no | K62: =IF(L62="YES","ja",IF(L62="NO","nein","")) | M62: yes / no | N62: RisikoFragenAIGFacility41 | P62: Dunkelverarbeitung | V62: Dunkelverarbeitung | AB62: Trigger | AC62: =IF(K62=JaAntwort,Referral,Dunkelverarbeitung) -> Dunkelverarbeitung | AH62: Trigger | AI62: =IF(K62=JaAntwort,Referral,Dunkelverarbeitung) -> Dunkelverarbeitung | AN62: Trigger | AP62: =IF(K62=JaAntwort,"KO Trigger",Dunkelverarbeitung) -> Dunkelverarbeitung | AT62: Trigger | AV62: =IF(K62=JaAntwort,"KO Trigger",Dunkelverarbeitung) -> Dunkelverarbeitung | AZ62: Trigger | BA62: =IF(K62=JaAntwort,Referral,Dunkelverarbeitung) -> Dunkelverarbeitung | BF62: Trigger | BH62: =IF(K62=JaAntwort,"KO Trigger",Dunkelverarbeitung) -> Dunkelverarbeitung | BL62: Trigger | BM62: =IF(K62=JaAntwort,Referral,Dunkelverarbeitung) -> Dunkelverarbeitung | BR62: Die Versicherungsnehmerin ist ein Kreditinstitut oder ein Finanzdienstleistungsinstitut im Sinne von § 1 Abs. 1 und 1a KWG (Kreditwesengesetz) oder ein Wertpapierinstitute im Sinne von § 2 WpIG (Wertpapierinstitutsgesetz). | BS62: =BR62 -> Die Versicherungsnehmerin ist ein Kreditinstitut oder ein Finanzdienstleistungsinstitut im Sinne von § 1 Abs. 1 und 1a KWG (Kreditwesengesetz) oder ein Wertpapierinstitute im Sinne von § 2 WpIG (Wertpapierinstitutsgesetz).
A63: Risikofragen | B63: RisikoFragenAIGFacility42 | C63: RisikoFragenAIGFacility | D63: Wird eine Deckungssumme von mehr als EUR 10,0 Mio. gewünscht? | H63: yes / no | K63: =IF(L63="YES","ja",IF(L63="NO","nein","")) | M63: yes / no | N63: RisikoFragenAIGFacility42 | P63: Dunkelverarbeitung | V63: Dunkelverarbeitung | AB63: Trigger | AC63: =IF(K63=JaAntwort,Referral,Dunkelverarbeitung) -> Dunkelverarbeitung | AH63: Trigger | AI63: =IF(K63=JaAntwort,Referral,Dunkelverarbeitung) -> Dunkelverarbeitung | AN63: Trigger | AO63: =IF(K63=JaAntwort,Referral,Dunkelverarbeitung) -> Dunkelverarbeitung | AT63: Trigger | AV63: =IF(K63=JaAntwort,"KO Trigger",Dunkelverarbeitung) -> Dunkelverarbeitung | AZ63: Trigger | BA63: =IF(K63=JaAntwort,Referral,Dunkelverarbeitung) -> Dunkelverarbeitung | BF63: Trigger | BG63: =IF(K63=JaAntwort,Referral,Dunkelverarbeitung) -> Dunkelverarbeitung | BL63: Trigger | BM63: =IF(K63=JaAntwort,Referral,Dunkelverarbeitung) -> Dunkelverarbeitung | BR63: Deckungssumme mehr als 10 Mio. EUR | BS63: =BR63 -> Deckungssumme mehr als 10 Mio. EUR
A64: Risikofragen | B64: RisikoFragenAIGFacility43 | C64: RisikoFragenAIGFacility | D64: Ist die Versicherungsnehmerin eine Gewerkschaft oder ein Spitzenverband ? | H64: yes / no | K64: =IF(L64="YES","ja",IF(L64="NO","nein","")) | M64: yes / no | N64: RisikoFragenAIGFacility43 | P64: Dunkelverarbeitung | V64: Dunkelverarbeitung | AB64: Trigger | AC64: =IF(K64=JaAntwort,Referral,Dunkelverarbeitung) -> Dunkelverarbeitung | AH64: Trigger | AI64: =IF(K64=JaAntwort,Referral,Dunkelverarbeitung) -> Dunkelverarbeitung | AN64: Trigger | AP64: =IF(K64=JaAntwort,"KO Trigger",Dunkelverarbeitung) -> Dunkelverarbeitung | AT64: Trigger | AV64: =IF(K64=JaAntwort,"KO Trigger",Dunkelverarbeitung) -> Dunkelverarbeitung | AZ64: Trigger | BA64: =IF(K64=JaAntwort,Referral,Dunkelverarbeitung) -> Dunkelverarbeitung | BF64: Trigger | BH64: =IF(K64=JaAntwort,"KO Trigger",Dunkelverarbeitung) -> Dunkelverarbeitung | BL64: Trigger | BN64: =IF(K64=JaAntwort,"KO Trigger",Dunkelverarbeitung) -> Dunkelverarbeitung | BR64: Die Versicherungsnehmerin ist eine Gewerkschaft oder ein Spitzenverband. | BS64: =BR64 -> Die Versicherungsnehmerin ist eine Gewerkschaft oder ein Spitzenverband.
A65: Risikofragen | B65: RisikoFragenAIGFacility44 | C65: RisikoFragenAIGFacility | D65: Liegt der letzte konsolidierte Umsatz der Versicherungsnehmerin über EUR 150 Mio.? | H65: yes / no | K65: =IF(L65="YES","ja",IF(L65="NO","nein","")) | M65: yes / no | N65: RisikoFragenAIGFacility44 | P65: Dunkelverarbeitung | V65: Dunkelverarbeitung | AB65: Dunkelverarbeitung | AH65: Dunkelverarbeitung | AN65: Dunkelverarbeitung | AT65: Dunkelverarbeitung | AZ65: Dunkelverarbeitung | BF65: Dunkelverarbeitung | BL65: Dunkelverarbeitung | BR65: Der letzte konsolidierte Umsatz der Versicherungsnehmerin liegt über EUR 150 Mio. EUR. | BS65: =BR65 -> Der letzte konsolidierte Umsatz der Versicherungsnehmerin liegt über EUR 150 Mio. EUR.
A66: Risikofragen | B66: RisikoFragenAIGFacility45 | C66: RisikoFragenAIGFacility | D66: Wurde die Versicherungsnehmerin in den vergangenen zwei Jahren gegründet (Wenn ja bitte Businessplan und Finanzierungsplan einreichen)? | H66: yes / no | K66: =IF(L66="YES","ja",IF(L66="NO","nein","")) | M66: yes / no | N66: RisikoFragenAIGFacility45 | P66: Dunkelverarbeitung | V66: Dunkelverarbeitung | AB66: Trigger | AC66: =IF(K66=JaAntwort,Referral,Dunkelverarbeitung) -> Dunkelverarbeitung | AH66: Trigger | AI66: =IF(K66=JaAntwort,Referral,Dunkelverarbeitung) -> Dunkelverarbeitung | AN66: Dunkelverarbeitung | AT66: Dunkelverarbeitung | AU66: =IF(K66=JaAntwort,Referral,Dunkelverarbeitung) -> Dunkelverarbeitung | AZ66: Trigger | BA66: =IF(K66=JaAntwort,Referral,Dunkelverarbeitung) -> Dunkelverarbeitung | BF66: Trigger | BH66: =IF(K66=JaAntwort,"KO Trigger",Dunkelverarbeitung) -> Dunkelverarbeitung | BL66: Dunkelverarbeitung | BR66: Die Versicherungsnehmerin wurde in den vergangenen zwei Jahren gegründet. | BS66: =BR66 -> Die Versicherungsnehmerin wurde in den vergangenen zwei Jahren gegründet.
A67: Risikofragen | B67: RisikoFragenAIGFacility46 | C67: RisikoFragenAIGFacility | D67: Befindet sich die Versicherungsnehmerin und/oder eine Tochtergesellschaft in einem Insolvenzverfahren? | H67: yes / no | K67: =IF(L67="YES","ja",IF(L67="NO","nein","")) | M67: yes / no | N67: RisikoFragenAIGFacility46 | P67: Trigger | Q67: =IF(K67=JaAntwort,Referral,Dunkelverarbeitung) -> Dunkelverarbeitung | V67: Trigger | W67: =IF(K67=JaAntwort,Referral,Dunkelverarbeitung) -> Dunkelverarbeitung | AB67: Trigger | AC67: =IF(K67=JaAntwort,Referral,Dunkelverarbeitung) -> Dunkelverarbeitung | AH67: Trigger | AJ67: =(IF(K67=JaAntwort,"KO Trigger",Dunkelverarbeitung)) -> Dunkelverarbeitung | AN67: Trigger | AP67: =IF(K67=JaAntwort,"KO Trigger",Dunkelverarbeitung) -> Dunkelverarbeitung | AT67: Trigger | AU67: =IF(K67=JaAntwort,Referral,Dunkelverarbeitung) -> Dunkelverarbeitung | AZ67: Trigger | BB67: =IF(K67=JaAntwort,"KO Trigger",Dunkelverarbeitung) -> Dunkelverarbeitung | BF67: Trigger | BH67: =IF(K67=JaAntwort,"KO Trigger",Dunkelverarbeitung) -> Dunkelverarbeitung | BL67: Trigger | BM67: =IF(K67=JaAntwort,Referral,Dunkelverarbeitung) -> Dunkelverarbeitung | BR67: Die Versicherungsnehmerin und/oder eine Tochtergesellschaft befindet sich in einem Insolvenzverfahren. | BS67: =BR67 -> Die Versicherungsnehmerin und/oder eine Tochtergesellschaft befindet sich in einem Insolvenzverfahren.
A68: Risikofragen | B68: RisikoFragenAIGFacility47 | C68: RisikoFragenAIGFacility | D68: Wurde der Bestätigungsvermerk im aktuellen Geschäftsbericht nicht oder nur eingeschränkt erteilt? | H68: yes / no | K68: =IF(L68="YES","ja",IF(L68="NO","nein","")) | M68: yes / no | N68: RisikoFragenAIGFacility47 | P68: Dunkelverarbeitung | V68: Trigger | W68: =IF(K68=JaAntwort,Referral,Dunkelverarbeitung) -> Dunkelverarbeitung | AB68: Trigger | AC68: =IF(K68=JaAntwort,Referral,Dunkelverarbeitung) -> Dunkelverarbeitung | AH68: Trigger | AI68: =IF(K68=JaAntwort,Referral,Dunkelverarbeitung) -> Dunkelverarbeitung | AN68: Trigger | AO68: =IF(K68=JaAntwort,Referral,Dunkelverarbeitung) -> Dunkelverarbeitung | AT68: Trigger | AU68: =IF(K68=JaAntwort,Referral,Dunkelverarbeitung) -> Dunkelverarbeitung | AZ68: Trigger | BA68: =IF(K68=JaAntwort,Referral,Dunkelverarbeitung) -> Dunkelverarbeitung | BF68: Trigger | BH68: =IF(K68=JaAntwort,"KO Trigger",Dunkelverarbeitung) -> Dunkelverarbeitung | BL68: Trigger | BM68: =IF(K68=JaAntwort,Referral,Dunkelverarbeitung) -> Dunkelverarbeitung | BR68: Es wurde der Bestätigungsvermerk im aktuellen Geschäftsbericht nicht oder nur eingeschränkt erteilt. | BS68: =BR68 -> Es wurde der Bestätigungsvermerk im aktuellen Geschäftsbericht nicht oder nur eingeschränkt erteilt.
A69: Risikofragen | B69: RisikoFragenAIGFacility48 | C69: RisikoFragenAIGFacility | D69: Ist das konsolidierte Eigenkapital der Versicherungsnehmerin negativ? | H69: yes / no | K69: =IF(L69="YES","ja",IF(L69="NO","nein","")) | M69: yes / no | N69: RisikoFragenAIGFacility48 | P69: Dunkelverarbeitung | V69: Trigger | W69: =IF(K69=JaAntwort,Referral,Dunkelverarbeitung) -> Dunkelverarbeitung | AB69: Trigger | AD69: =IF(K69=JaAntwort,"KO Trigger",Dunkelverarbeitung) -> Dunkelverarbeitung | AH69: Trigger | AJ69: =(IF(K69=JaAntwort,"KO Trigger",Dunkelverarbeitung)) -> Dunkelverarbeitung | AN69: Trigger | AO69: =IF(K69=JaAntwort,Referral,Dunkelverarbeitung) -> Dunkelverarbeitung | AT69: Dunkelverarbeitung | AV69: =IF(K69=JaAntwort,"KO Trigger",Dunkelverarbeitung) -> Dunkelverarbeitung | AZ69: Trigger | BB69: =IF(K69=JaAntwort,"KO Trigger",Dunkelverarbeitung) -> Dunkelverarbeitung | BF69: Trigger | BH69: =IF(K69=JaAntwort,"KO Trigger",Dunkelverarbeitung) -> Dunkelverarbeitung | BL69: Trigger | BN69: =IF(K69=JaAntwort,"KO Trigger",Dunkelverarbeitung) -> Dunkelverarbeitung | BR69: Negatives Eigenkapital | BS69: =BR69 -> Negatives Eigenkapital
A70: Risikofragen | B70: RisikoFragenAIGFacility49 | C70: RisikoFragenAIGFacility | D70: War das letzte konsolidierte Jahresergebnis der Versicherungsnehmerin negativ? | H70: yes / no | K70: =IF(L70="YES","ja",IF(L70="NO","nein","")) | M70: yes / no | N70: RisikoFragenAIGFacility49 | P70: Dunkelverarbeitung | V70: Dunkelverarbeitung | AB70: Dunkelverarbeitung | AH70: Trigger | AI70: =IF(K70=JaAntwort,Referral,Dunkelverarbeitung) -> Dunkelverarbeitung | AK70: =IF(K70=JaAntwort,0.15,0) -> 0 | AN70: Trigger | AO70: =IF(K70=JaAntwort,Referral,Dunkelverarbeitung) -> Dunkelverarbeitung | AT70: Dunkelverarbeitung | AU70: =IF(K70=JaAntwort,Referral,Dunkelverarbeitung) -> Dunkelverarbeitung | AZ70: Trigger | BA70: =IF(K70=JaAntwort,Referral,Dunkelverarbeitung) -> Dunkelverarbeitung | BF70: Trigger | BH70: =IF(K70=JaAntwort,"KO Trigger",Dunkelverarbeitung) -> Dunkelverarbeitung | BL70: Trigger | BM70: =IF(K70=JaAntwort,Referral,Dunkelverarbeitung) -> Dunkelverarbeitung | BR70: Negatives Jahresergebnis | BS70: =BR70 -> Negatives Jahresergebnis
A71: Risikofragen | B71: RisikoFragenStartUp92 | C71: RisikoFragenStartUp | D71: Sind in den nächsten 2 Jahren Fusionen geplant oder ist eine Fremdbeherrschung der Versicherungsnehmerin möglich? Wenn ja, bitte Einzelheiten / Gründe angeben. | H71: yes / no | K71: =IF(L71="YES","ja",IF(L71="NO","nein","")) | M71: yes / no | N71: RisikoFragenStartUp92 | P71: Trigger | Q71: =IF(K71=JaAntwort,Referral,Dunkelverarbeitung) -> Dunkelverarbeitung | V71: Dunkelverarbeitung | AB71: Trigger | AC71: =IF(K71=JaAntwort,Referral,Dunkelverarbeitung) -> Dunkelverarbeitung | AH71: Trigger | AI71: =IF(K71=JaAntwort,Referral,Dunkelverarbeitung) -> Dunkelverarbeitung | AK71: =IF(K71=JaAntwort,0.25,0) -> 0 | AN71: Dunkelverarbeitung | AT71: Trigger | AU71: =IF(K71=JaAntwort,Referral,Dunkelverarbeitung) -> Dunkelverarbeitung | AZ71: Trigger | BA71: =IF(K71=JaAntwort,Referral,Dunkelverarbeitung) -> Dunkelverarbeitung | BF71: Trigger | BH71: =IF(K71=JaAntwort,"KO Trigger",Dunkelverarbeitung) -> Dunkelverarbeitung | BL71: Trigger | BM71: =IF(K71=JaAntwort,Referral,Dunkelverarbeitung) -> Dunkelverarbeitung | BR71: In den nächsten 2 Jahren sind Fusionen geplant oder es ist eine Fremdbeherrschung der Versicherungsnehmerin möglich. | BS71: =BR71 -> In den nächsten 2 Jahren sind Fusionen geplant oder es ist eine Fremdbeherrschung der Versicherungsnehmerin möglich.
A72: Risikofragen | B72: RisikoFragenStartUp93 | C72: RisikoFragenStartUp | D72: Hat eine Versicherungsgesellschaft einen Antrag auf diese Deckungsform abgelehnt? Wenn ja, bitte Einzelheiten / Gründe angeben. | H72: yes / no | K72: =IF(L72="YES","ja",IF(L72="NO","nein","")) | M72: yes / no | N72: RisikoFragenStartUp93 | P72: Trigger | Q72: =IF(K72=JaAntwort,Referral,Dunkelverarbeitung) -> Dunkelverarbeitung | V72: Dunkelverarbeitung | AB72: Dunkelverarbeitung | AH72: Dunkelverarbeitung | AN72: Dunkelverarbeitung | AT72: Trigger | AU72: =IF(K72=JaAntwort,Referral,Dunkelverarbeitung) -> Dunkelverarbeitung | AZ72: Trigger | BA72: =IF(K72=JaAntwort,Referral,Dunkelverarbeitung) -> Dunkelverarbeitung | BF72: Trigger | BH72: =IF(K72=JaAntwort,"KO Trigger",Dunkelverarbeitung) -> Dunkelverarbeitung | BL72: Trigger | BM72: =IF(K72=JaAntwort,Referral,Dunkelverarbeitung) -> Dunkelverarbeitung | BR72: Es hat eine Versicherungsgesellschaft einen Antrag auf diese Deckungsform abgelehnt. | BS72: =BR72 -> Es hat eine Versicherungsgesellschaft einen Antrag auf diese Deckungsform abgelehnt.
A73: Risikofragen | B73: RisikoFragenStartUp94 | C73: RisikoFragenStartUp | D73: Hat eine Versicherungsgesellschaft eine bestehende Police gekündigt oder deren Verlängerung abgelehnt? Wenn ja, bitte Einzelheiten / Gründe angeben. | H73: yes / no | K73: =IF(L73="YES","ja",IF(L73="NO","nein","")) | M73: yes / no | N73: RisikoFragenStartUp94 | P73: Trigger | Q73: =IF(K73=JaAntwort,Referral,Dunkelverarbeitung) -> Dunkelverarbeitung | V73: Dunkelverarbeitung | AB73: Trigger | AC73: =IF(K73=JaAntwort,Referral,Dunkelverarbeitung) -> Dunkelverarbeitung | AH73: Dunkelverarbeitung | AN73: Dunkelverarbeitung | AT73: Trigger | AU73: =IF(K73=JaAntwort,Referral,Dunkelverarbeitung) -> Dunkelverarbeitung | AZ73: Trigger | BA73: =IF(K73=JaAntwort,Referral,Dunkelverarbeitung) -> Dunkelverarbeitung | BF73: Trigger | BH73: =IF(K73=JaAntwort,"KO Trigger",Dunkelverarbeitung) -> Dunkelverarbeitung | BL73: Trigger | BM73: =IF(K73=JaAntwort,Referral,Dunkelverarbeitung) -> Dunkelverarbeitung | BR73: Es hat eine Versicherungsgesellschaft eine bestehende Police gekündigt oder deren Verlängerung abgelehnt. | BS73: =BR73 -> Es hat eine Versicherungsgesellschaft eine bestehende Police gekündigt oder deren Verlängerung abgelehnt.
A74: Risikofragen | B74: RisikoFragen95a | C74: RisikoFragen | D74: Anzahl aller mitversicherte Unternehmen und Personen | H74: Text | K74: =IF(L74="YES","ja",IF(L74="NO","nein","")) | M74: Text | N74: RisikoFragen95a | P74: Dunkelverarbeitung | V74: Dunkelverarbeitung | AB74: Trigger | AC74: =IF(K74=JaAntwort,Referral,Dunkelverarbeitung) -> Dunkelverarbeitung | AH74: Trigger | AI74: =IF(K74<>"",Referral,Dunkelverarbeitung) -> Dunkelverarbeitung | AN74: Dunkelverarbeitung | AT74: Trigger | AU74: =IF(K74> JaAntwort, Referral, Dunkelverarbeitung) -> Dunkelverarbeitung | AZ74: Dunkelverarbeitung | BF74: Trigger | BL74: Trigger | BR74: Anzahl aller mitversicherte Unternehmen und Personen | BS74: =BR74 -> Anzahl aller mitversicherte Unternehmen und Personen
A75: Risikofragen | B75: RisikoFragen95b | C75: RisikoFragen | D75: Einschluss-Datum | H75: Datum | M75: Datum | N75: RisikoFragen95b | P75: Dunkelverarbeitung | V75: Dunkelverarbeitung | AB75: Dunkelverarbeitung | AH75: Dunkelverarbeitung | AN75: Dunkelverarbeitung | AT75: Dunkelverarbeitung | AZ75: Dunkelverarbeitung | BF75: Dunkelverarbeitung | BL75: Dunkelverarbeitung | BS75: =BR75 -> 0
A76: Risikofragen | B76: RisikoFragen95c | C76: RisikoFragen | D76: Sublimit der mitversicherten Unternehmen | H76: Zahlen | M76: Zahlen | N76: RisikoFragen95c | P76: Dunkelverarbeitung | V76: Dunkelverarbeitung | AB76: Dunkelverarbeitung | AH76: Dunkelverarbeitung | AN76: Dunkelverarbeitung | AT76: Dunkelverarbeitung | AZ76: Dunkelverarbeitung | BF76: Dunkelverarbeitung | BL76: Dunkelverarbeitung | BS76: =BR76 -> 0
A77: Risikofragen | B77: RisikoFragen95d | C77: RisikoFragen | D77: Name des mitversicherten Unternehmens | H77: Text | M77: Text | N77: RisikoFragen95d | P77: Dunkelverarbeitung | V77: Dunkelverarbeitung | AB77: Dunkelverarbeitung | AH77: Dunkelverarbeitung | AN77: Dunkelverarbeitung | AT77: Dunkelverarbeitung | AZ77: Dunkelverarbeitung | BF77: Dunkelverarbeitung | BL77: Dunkelverarbeitung | BS77: =BR77 -> 0
A78: Risikofragen | B78: RisikoFragen95e | C78: RisikoFragen | D78: Adresse | H78: Text | M78: Text | N78: RisikoFragen95e | P78: Dunkelverarbeitung | V78: Dunkelverarbeitung | AB78: Dunkelverarbeitung | AH78: Dunkelverarbeitung | AN78: Dunkelverarbeitung | AT78: Dunkelverarbeitung | AZ78: Dunkelverarbeitung | BF78: Dunkelverarbeitung | BL78: Dunkelverarbeitung | BS78: =BR78 -> 0
A79: Risikofragen | B79: RisikoFragen96 | C79: RisikoFragen | D79: Anzahl aller ausgeschlossenen Unternehmen und Personen | H79: Text | M79: Text | N79: RisikoFragen96 | P79: Dunkelverarbeitung | V79: Dunkelverarbeitung | AB79: Dunkelverarbeitung | AH79: Dunkelverarbeitung | AN79: Dunkelverarbeitung | AT79: Trigger | AU79: =IF(K79> JaAntwort, Referral, Dunkelverarbeitung) -> Dunkelverarbeitung | AZ79: Dunkelverarbeitung | BF79: Dunkelverarbeitung | BL79: Trigger | BS79: =BR79 -> 0
A80: Risikofragen | B80: RisikoFragen97a | C80: RisikoFragen | D80: Mitversicherte Personen | H80: Text | M80: Text | N80: RisikoFragen97a | P80: Dunkelverarbeitung | V80: Dunkelverarbeitung | AB80: Trigger | AC80: =IF(K80=JaAntwort,Referral,Dunkelverarbeitung) -> Dunkelverarbeitung | AH80: Dunkelverarbeitung | AN80: Dunkelverarbeitung | AT80: Trigger | AU80: =IF(K80> JaAntwort, Referral, Dunkelverarbeitung) -> Dunkelverarbeitung | AZ80: Dunkelverarbeitung | BF80: Dunkelverarbeitung | BL80: Trigger | BR80: Mitversicherte Personen | BS80: =BR80 -> Mitversicherte Personen
A81: Risikofragen | B81: RisikoFragen97b | C81: RisikoFragen | D81: Einschluss-Datum | H81: Datum | M81: Datum | N81: RisikoFragen97b | P81: Dunkelverarbeitung | V81: Dunkelverarbeitung | AB81: Dunkelverarbeitung | AH81: Dunkelverarbeitung | AN81: Dunkelverarbeitung | AT81: Dunkelverarbeitung | AZ81: Dunkelverarbeitung | BF81: Dunkelverarbeitung | BL81: Dunkelverarbeitung | BS81: =BR81 -> 0
A82: Risikofragen | B82: RisikoFragen97c | C82: RisikoFragen | D82: Sublimit der mitversicherten Person | H82: Zahlen | M82: Zahlen | N82: RisikoFragen97c | P82: Dunkelverarbeitung | V82: Dunkelverarbeitung | AB82: Dunkelverarbeitung | AH82: Dunkelverarbeitung | AN82: Dunkelverarbeitung | AT82: Dunkelverarbeitung | AZ82: Dunkelverarbeitung | BF82: Dunkelverarbeitung | BL82: Dunkelverarbeitung | BS82: =BR82 -> 0
A83: Risikofragen | B83: RisikoFragen97d | C83: RisikoFragen | D83: Name des mitversicherten Person | H83: Text | M83: Text | N83: RisikoFragen97d | P83: Dunkelverarbeitung | V83: Dunkelverarbeitung | AB83: Dunkelverarbeitung | AH83: Dunkelverarbeitung | AN83: Dunkelverarbeitung | AT83: Dunkelverarbeitung | AZ83: Dunkelverarbeitung | BF83: Dunkelverarbeitung | BL83: Dunkelverarbeitung | BS83: =BR83 -> 0
A84: Risikofragen | B84: RisikoFragen97e | C84: RisikoFragen | D84: Adresse | H84: Text | M84: Text | N84: RisikoFragen97e | P84: Dunkelverarbeitung | V84: Dunkelverarbeitung | AB84: Dunkelverarbeitung | AH84: Dunkelverarbeitung | AN84: Dunkelverarbeitung | AT84: Dunkelverarbeitung | AZ84: Dunkelverarbeitung | BF84: Dunkelverarbeitung | BL84: Dunkelverarbeitung | BS84: =BR84 -> 0
A85: Risikofragen | B85: RisikoFragen98 | C85: RisikoFragen | D85: Ausgeschlossene Personen | H85: Text | M85: Text | N85: RisikoFragen98 | P85: Dunkelverarbeitung | V85: Dunkelverarbeitung | AB85: Dunkelverarbeitung | AH85: Dunkelverarbeitung | AN85: Dunkelverarbeitung | AT85: Dunkelverarbeitung | AZ85: Dunkelverarbeitung | BF85: Dunkelverarbeitung | BL85: Dunkelverarbeitung | BS85: =BR85 -> 0
A86: Risikofragen | B86: RisikoFragen99 | C86: RisikoFragen | D86: Zwei- Fach Maximierung gewünscht | H86: yes / no | K86: =IF(L86="YES","ja",IF(L86="NO","nein","")) | M86: yes / no | N86: RisikoFragen99 | P86: Dunkelverarbeitung | V86: Dunkelverarbeitung | AB86: Dunkelverarbeitung | AH86: Dunkelverarbeitung | AN86: Dunkelverarbeitung | AT86: Dunkelverarbeitung | AZ86: Dunkelverarbeitung | BF86: Dunkelverarbeitung | BL86: Dunkelverarbeitung | BS86: =BR86 -> 0
A87: Risikofragen | B87: RisikoFragenVereine100 | C87: RisikoFragenVereine | D87: Beträgt die Bilanzsumme der VN weniger als 50 Mio. Euro? | H87: yes / no | K87: =IF(L87="YES","ja",IF(L87="NO","nein","")) | M87: yes / no | N87: RisikoFragenVereine100 | P87: Dunkelverarbeitung | V87: Dunkelverarbeitung | AB87: Dunkelverarbeitung | AH87: Dunkelverarbeitung | AN87: Dunkelverarbeitung | AT87: Dunkelverarbeitung | AZ87: Dunkelverarbeitung | BF87: Dunkelverarbeitung | BL87: Dunkelverarbeitung | BS87: =BR87 -> 0
A88: Risikofragen | B88: RisikoFragenVereine101 | C88: RisikoFragenVereine | D88: Ist das Eigenkapital der VN positiv? | H88: yes / no | K88: =IF(L88="YES","ja",IF(L88="NO","nein","")) | M88: yes / no | N88: RisikoFragenVereine101 | P88: Trigger | Q88: =IF(K88=NeinAntwort,Referral,Dunkelverarbeitung) -> Dunkelverarbeitung | V88: Dunkelverarbeitung | AB88: Trigger | AC88: =IF(K88=NeinAntwort,Referral,Dunkelverarbeitung) -> Dunkelverarbeitung | AH88: Trigger | AJ88: =IF(K88=NeinAntwort,"KO Trigger",Dunkelverarbeitung) -> Dunkelverarbeitung | AN88: Trigger | AO88: =IF(K88=NeinAntwort,Referral,Dunkelverarbeitung) -> Dunkelverarbeitung | AT88: Trigger | AV88: =IF(K88=NeinAntwort,"KO Trigger",Dunkelverarbeitung) -> Dunkelverarbeitung | AZ88: Trigger | BA88: =IF(K88=NeinAntwort,Referral,Dunkelverarbeitung) -> Dunkelverarbeitung | BF88: Trigger | BH88: =IF(K88=NeinAntwort,"KO Trigger",Dunkelverarbeitung) -> Dunkelverarbeitung | BL88: Trigger | BN88: =IF(K88=NeinAntwort,"KO Trigger",Dunkelverarbeitung) -> Dunkelverarbeitung | BR88: Negatives Eigenkapital | BS88: =BR88 -> Negatives Eigenkapital
A89: Risikofragen | B89: RisikoFragenVereine102 | C89: RisikoFragenVereine | D89: Besteht der satzungsmäßige oder tatsächliche Zweck der VN in der Familienvermögenverwaltung, der Erbringung von rechts-, steuerberatenden oder wirtschaftsprüfenden Dienstleistungen, der Verwaltung von Vermögen oder Kassen zur Altersversorge oder Gewinerzielung? | H89: yes / no | K89: =IF(L89="YES","ja",IF(L89="NO","nein","")) | M89: yes / no | N89: RisikoFragenVereine102 | P89: Trigger | Q89: =IF(K89=JaAntwort,Referral,Dunkelverarbeitung) -> Dunkelverarbeitung | V89: Dunkelverarbeitung | AB89: Trigger | AC89: =IF(K89=JaAntwort,Referral,Dunkelverarbeitung) -> Dunkelverarbeitung | AH89: Trigger | AI89: =IF(K89=JaAntwort,Referral,Dunkelverarbeitung) -> Dunkelverarbeitung | AN89: Trigger | AO89: =IF(K89=JaAntwort,Referral,Dunkelverarbeitung) -> Dunkelverarbeitung | AT89: Trigger | AU89: =IF(K89=JaAntwort,Referral,Dunkelverarbeitung) -> Dunkelverarbeitung | AZ89: Trigger | BA89: =IF(K89=JaAntwort,Referral,Dunkelverarbeitung) -> Dunkelverarbeitung | BD89: Dienstleistungsausschluss | BF89: Trigger | BH89: =IF(K89=JaAntwort,"KO Trigger",Dunkelverarbeitung) -> Dunkelverarbeitung | BL89: Trigger | BM89: =IF(K89=JaAntwort,Referral,Dunkelverarbeitung) -> Dunkelverarbeitung | BR89: Der satzungsmäßige oder tatsächliche Zweck der VN besteht in der Familienvermögenverwaltung, der Erbringung von rechts-, steuerberatenden oder wirtschaftsprüfenden Dienstleistungen, der Verwaltung von Vermögen oder Kassen zur Altersversorge oder Gewinnerzielung. | BS89: =BR89 -> Der satzungsmäßige oder tatsächliche Zweck der VN besteht in der Familienvermögenverwaltung, der Erbringung von rechts-, steuerberatenden oder wirtschaftsprüfenden Dienstleistungen, der Verwaltung von Vermögen oder Kassen zur Altersversorge oder Gewinnerzielung.
A90: Risikofragen | B90: RisikoFragenVereine104 | C90: RisikoFragenVereine | D90: Erfolgt die Rechnungslegung der VN nach den für sie geltenden gesetzlichen Bestimmungen? | H90: yes / no | K90: =IF(L90="YES","ja",IF(L90="NO","nein","")) | M90: yes / no | N90: RisikoFragenVereine104 | P90: Trigger | Q90: =IF(K90=NeinAntwort,Referral,Dunkelverarbeitung) -> Dunkelverarbeitung | V90: Dunkelverarbeitung | AB90: Dunkelverarbeitung | AH90: Trigger | AJ90: =IF(K90=NeinAntwort,"KO Trigger",Dunkelverarbeitung) -> Dunkelverarbeitung | AN90: Trigger | AO90: =IF(K90=NeinAntwort,Referral,Dunkelverarbeitung) -> Dunkelverarbeitung | AT90: Dunkelverarbeitung | AU90: =IF(K90=NeinAntwort,Referral,Dunkelverarbeitung) -> Dunkelverarbeitung | AZ90: Dunkelverarbeitung | BF90: Trigger | BH90: =IF(K90=NeinAntwort,"KO Trigger",Dunkelverarbeitung) -> Dunkelverarbeitung | BL90: Trigger | BN90: =IF(K90=NeinAntwort,"KO Trigger",Dunkelverarbeitung) -> Dunkelverarbeitung | BR90: Die Rechnungslegung der VN erfolgt nicht nach den für sie geltenden gesetzlichen Bestimmungen. | BS90: =BR90 -> Die Rechnungslegung der VN erfolgt nicht nach den für sie geltenden gesetzlichen Bestimmungen.
A91: Risikofragen | B91: RisikoFragenVereine105 | C91: RisikoFragenVereine | D91: Ist die VN seit mehr als drei Jahren mit dem gleichen Zweck tätig? | H91: yes / no | K91: =IF(L91="YES","ja",IF(L91="NO","nein","")) | M91: yes / no | N91: RisikoFragenVereine105 | P91: Trigger | Q91: =IF( AND(K91=NeinAntwort,OR(K8="gGMBH",K8="e.V.",K8="Stiftung döR")),Referral,Dunkelverarbeitung) -> Dunkelverarbeitung | V91: Dunkelverarbeitung | W91: =IF( AND(K91=NeinAntwort,OR(K8="gGMBH",K8="e.V.",K8="Stiftung döR")),Referral,Dunkelverarbeitung) -> Dunkelverarbeitung | AB91: Dunkelverarbeitung | AC91: =IF( AND(K91=NeinAntwort,OR(K8="gGMBH",K8="e.V.",K8="Stiftung döR")),Referral,Dunkelverarbeitung) -> Dunkelverarbeitung | AH91: Dunkelverarbeitung | AI91: =IF(K91=NeinAntwort,Referral,Dunkelverarbeitung) -> Dunkelverarbeitung | AN91: Trigger | AO91: =IF( AND(K91=NeinAntwort,OR(K8="gGMBH",K8="e.V.",K8="Stiftung döR")),Referral,Dunkelverarbeitung) -> Dunkelverarbeitung | AT91: Dunkelverarbeitung | AZ91: Dunkelverarbeitung | BF91: Trigger | BH91: =IF(K91=NeinAntwort,"KO Trigger",Dunkelverarbeitung) -> Dunkelverarbeitung | BL91: Trigger | BM91: =IF(K91=NeinAntwort,Referral,Dunkelverarbeitung) -> Dunkelverarbeitung | BR91: Die VN ist nicht seit mehr als drei Jahren mit dem gleichen Zweck tätig. | BS91: =BR91 -> Die VN ist nicht seit mehr als drei Jahren mit dem gleichen Zweck tätig.
A92: Risikofragen | B92: RisikoFragenUSACAN106 | C92: RisikoFragenUSACAN | D92: Wie groß sind die gesamten Aktiva aller Beteiligungsgesellschaften/ Tochtergesellschaften in Nordamerika? | H92: Zahlen | M92: Zahlen | N92: RisikoFragenUSACAN106 | P92: Dunkelverarbeitung | V92: Dunkelverarbeitung | AB92: Trigger | AC92: =IF(K92<>"",Referral,Dunkelverarbeitung) -> Dunkelverarbeitung | AH92: Dunkelverarbeitung | AN92: Dunkelverarbeitung | AT92: Dunkelverarbeitung | AZ92: Dunkelverarbeitung | BF92: Dunkelverarbeitung | BL92: Trigger | BM92: =IF(K92<>"",Referral,Dunkelverarbeitung) -> Dunkelverarbeitung | BR92: Aktiva aller Beteiligungsgesellschaften/ Tochtergesellschaften in Nordamerika | BS92: =BR92 -> Aktiva aller Beteiligungsgesellschaften/ Tochtergesellschaften in Nordamerika
A93: Risikofragen | B93: RisikoFragenUSACAN107 | C93: RisikoFragenUSACAN | D93: Wie viele Mitarbeiter sind in Nordamerika beschäftigt? | H93: Zahlen | M93: Zahlen | N93: RisikoFragenUSACAN107 | P93: Dunkelverarbeitung | V93: Dunkelverarbeitung | AB93: Trigger | AC93: =IF(K93<>"",Referral,Dunkelverarbeitung) -> Dunkelverarbeitung | AH93: Dunkelverarbeitung | AN93: Dunkelverarbeitung | AT93: Dunkelverarbeitung | AZ93: Dunkelverarbeitung | BF93: Dunkelverarbeitung | BL93: Trigger | BM93: =IF(K93<>"",Referral,Dunkelverarbeitung) -> Dunkelverarbeitung | BR93: Mitarbeiter in Nordamerika | BS93: =BR93 -> Mitarbeiter in Nordamerika
A94: Risikofragen | B94: RisikoFragenUSACAN108 | C94: RisikoFragenUSACAN | D94: Bitte nennen Sie die Beteiligungsgesellschaften/Tochtergesellschaften in Nordamerika. | H94: Text | M94: Text | N94: RisikoFragenUSACAN108 | P94: Dunkelverarbeitung | V94: Dunkelverarbeitung | AB94: Trigger | AC94: =IF(K94<>"",Referral,Dunkelverarbeitung) -> Dunkelverarbeitung | AH94: Dunkelverarbeitung | AN94: Dunkelverarbeitung | AT94: Dunkelverarbeitung | AZ94: Dunkelverarbeitung | BF94: Dunkelverarbeitung | BL94: Trigger | BM94: =IF(K94<>"",Referral,Dunkelverarbeitung) -> Dunkelverarbeitung | BR94: Beteiligungsgesellschaften/Tochtergesellschaften in Nordamerika | BS94: =BR94 -> Beteiligungsgesellschaften/Tochtergesellschaften in Nordamerika
A95: Risikofragen | B95: RisikoFragenUSACAN109 | C95: RisikoFragenUSACAN | D95: Bitte nennen Sie den Prozentsatz der Beteiligungen. | H95: %-Wert | M95: %-Wert | N95: RisikoFragenUSACAN109 | P95: Dunkelverarbeitung | V95: Dunkelverarbeitung | AB95: Trigger | AC95: =IF(K95<>"",Referral,Dunkelverarbeitung) -> Dunkelverarbeitung | AH95: Dunkelverarbeitung | AN95: Dunkelverarbeitung | AT95: Dunkelverarbeitung | AZ95: Dunkelverarbeitung | BF95: Dunkelverarbeitung | BL95: Trigger | BM95: =IF(K95<>"",Referral,Dunkelverarbeitung) -> Dunkelverarbeitung | BR95: Beteiligungsgesellschaften/Tochtergesellschaften in Nordamerika | BS95: =BR95 -> Beteiligungsgesellschaften/Tochtergesellschaften in Nordamerika
A96: Risikofragen | B96: RisikoFragenUSACAN110 | C96: RisikoFragenUSACAN | D96: Bitte nennen Sie die Namen der übrigen Anteilseigner, die mehr als 5 % halten. | H96: Text | M96: Text | N96: RisikoFragenUSACAN110 | P96: Dunkelverarbeitung | V96: Dunkelverarbeitung | AB96: Dunkelverarbeitung | AH96: Dunkelverarbeitung | AN96: Dunkelverarbeitung | AT96: Dunkelverarbeitung | AZ96: Dunkelverarbeitung | BF96: Dunkelverarbeitung | BL96: Trigger | BM96: =IF(K96<>"",Referral,Dunkelverarbeitung) -> Dunkelverarbeitung | BR96: Beteiligungsgesellschaften/Tochtergesellschaften in Nordamerika | BS96: =BR96 -> Beteiligungsgesellschaften/Tochtergesellschaften in Nordamerika
A97: Risikofragen | B97: RisikoFragenUSACAN111 | C97: RisikoFragenUSACAN | D97: Ist mindestens eines dieser Unternehmen börsennotiert | H97: yes / no | K97: =RisikoFragenUSACAN111 -> 0 | M97: yes / no | N97: RisikoFragenUSACAN111 | P97: Dunkelverarbeitung | V97: Dunkelverarbeitung | AB97: Dunkelverarbeitung | AH97: Trigger | AJ97: =IF(K97=JaAntwort,"KO Trigger",Dunkelverarbeitung) -> Dunkelverarbeitung | AN97: Trigger | AP97: =IF(K97=JaAntwort,"KO Trigger",Dunkelverarbeitung) -> Dunkelverarbeitung | AT97: Trigger | AU97: =IF(K97=JaAntwort,Referral,Dunkelverarbeitung) -> Dunkelverarbeitung | AZ97: Dunkelverarbeitung | BF97: Dunkelverarbeitung | BL97: Trigger | BM97: =IF(K97=JaAntwort,Referral,Dunkelverarbeitung) -> Dunkelverarbeitung | BR97: Nordamerika: Börsennotierung: Wann wurde zuletzt angeboten/aufgelegt? | BS97: =BR97 -> Nordamerika: Börsennotierung: Wann wurde zuletzt angeboten/aufgelegt?
A98: Risikofragen | B98: RisikoFragenUSACAN112 | C98: RisikoFragenUSACAN | D98: Unterlag das Angebot dem "The United States Security Act of 1933"/"The Securities Exchange Act of 1934"? | H98: yes / no | M98: yes / no | N98: RisikoFragenUSACAN112 | P98: Dunkelverarbeitung | V98: Dunkelverarbeitung | AB98: Dunkelverarbeitung | AH98: Dunkelverarbeitung | AN98: Dunkelverarbeitung | AT98: Trigger | AU98: =IF(K98=JaAntwort,Referral,Dunkelverarbeitung) -> Dunkelverarbeitung | AZ98: Dunkelverarbeitung | BF98: Dunkelverarbeitung | BL98: Trigger | BM98: =IF(K98=JaAntwort,Referral,Dunkelverarbeitung) -> Dunkelverarbeitung | BR98: Unterlag das Angebot dem "The United States Security Act of 1933"/"The Securities Exchange Act of 1934" | BS98: =BR98 -> Unterlag das Angebot dem "The United States Security Act of 1933"/"The Securities Exchange Act of 1934"
A99: Risikofragen | B99: RisikoFragenUSACAN113 | C99: RisikoFragenUSACAN | D99: Werden in Nordamerika Anteile der Gesellschaft in Form von ADRs (American Despository Receipts) gehandelt? (Falls zutreffend, unterliegt der Handel der ADRs der amerikanischen Börsenaufsicht (SEC)?) | H99: yes / no | K99: =IF(RisikoFragenUSACAN113="YES",JaAntwort,IF(RisikoFragenUSACAN113="NO",NeinAntwort,"")) | M99: yes / no | N99: RisikoFragenUSACAN113 | P99: Dunkelverarbeitung | V99: Dunkelverarbeitung | AB99: Trigger | AC99: =IF(K99<>"",Referral,Dunkelverarbeitung) -> Dunkelverarbeitung | AH99: Trigger | AI99: =IF(K99=JaAntwort,Referral,Dunkelverarbeitung) -> Dunkelverarbeitung | AN99: Trigger | AO99: =IF(K99=JaAntwort,Referral,Dunkelverarbeitung) -> Dunkelverarbeitung | AT99: Trigger | AU99: =IF(K99=JaAntwort,Referral,Dunkelverarbeitung) -> Dunkelverarbeitung | AZ99: Trigger | BA99: =IF(K99=JaAntwort,Referral,Dunkelverarbeitung) -> Dunkelverarbeitung | BF99: Dunkelverarbeitung | BL99: Trigger | BM99: =IF(K99=JaAntwort,Referral,Dunkelverarbeitung) -> Dunkelverarbeitung | BR99: Nordamerika: Anteile der Gesellschaft werden in Form von ADRs (American Despository Receipts) gehandelt | BS99: =BR99 -> Nordamerika: Anteile der Gesellschaft werden in Form von ADRs (American Despository Receipts) gehandelt
A100: Risikofragen | B100: RisikoFragenUSACAN114 | C100: RisikoFragenUSACAN | D100: Bitte fügen Sie Kopie der letzten 20 F-Meldung an die US-Aufsichtsbehörde bei. (Wenn nicht zutreffend, bitte bestätigen) | H100: yes / no | K100: =IF(RisikoFragenUSACAN114="YES",JaAntwort,IF(RisikoFragenUSACAN114="NO",NeinAntwort,"")) | M100: yes / no | N100: RisikoFragenUSACAN114 | P100: Dunkelverarbeitung | V100: Dunkelverarbeitung | AB100: Trigger | AC100: =IF(K100<>"",Referral,Dunkelverarbeitung) -> Dunkelverarbeitung | AH100: Dunkelverarbeitung | AN100: Trigger | AO100: =IF(K100=JaAntwort,Referral,Dunkelverarbeitung) -> Dunkelverarbeitung | AT100: Trigger | AU100: =IF(K100=JaAntwort,Referral,Dunkelverarbeitung) -> Dunkelverarbeitung | AZ100: Trigger | BA100: =IF(K100=JaAntwort,Referral,Dunkelverarbeitung) -> Dunkelverarbeitung | BF100: Dunkelverarbeitung | BL100: Trigger | BM100: =IF(K100=JaAntwort,Referral,Dunkelverarbeitung) -> Dunkelverarbeitung | BR100: Nordamerika: letzten 20 F-Meldung an die US-Aufsichtsbehörde | BS100: =BR100 -> Nordamerika: letzten 20 F-Meldung an die US-Aufsichtsbehörde
...

Sheet Daten-Abzug
I1: Grobindikation Light DS
D2: Angebot | I2: Sterne | J2: DS 1 | K2: DS 2 | L2: DS 3
D3: DS 1 | E3: DS 2 | F3: DS 3 | I3: Versicherer | J3: =IFERROR('Sterne-Rechner - GI'!V39,"") -> Kein Angebot möglich! | K3: =IFERROR('Sterne-Rechner - GI'!V40,"") -> Kein Angebot möglich! | L3: =IFERROR('Sterne-Rechner - GI'!V41,"") -> Kein Angebot möglich!
C4: Angefragte Deckungssumme | D4: =Deckungssumme1 -> 0 | E4: =Deckungssumme2 -> 0 | F4: =Deckungssumme3 -> 0 | I4: Preis | J4: =IFERROR(ROUND('Sterne-Rechner - GI'!X39,2),"") | K4: =IFERROR(ROUND('Sterne-Rechner - GI'!X40,2),"") | L4: =IFERROR(ROUND('Sterne-Rechner - GI'!X41,2),"")
B5: WVAG | C5: Sterne | D5: =TEXT('Sterne-Rechner - Angebot'!Y4,"0") | E5: =TEXT('Sterne-Rechner - Angebot'!Y5,"0") | F5: =TEXT('Sterne-Rechner - Angebot'!Y6,"0") | I5: Angebotene Deckungssumme | J5: =IFERROR(ROUND('Sterne-Rechner - GI'!W39,0),"") | K5: =IFERROR(ROUND('Sterne-Rechner - GI'!W40,0),"") | L5: =IFERROR(ROUND('Sterne-Rechner - GI'!W41,0),"")
C6: Bewertungsfaktor | D6: ='Sterne-Rechner - Angebot'!Q4 -> 75 | E6: ='Sterne-Rechner - Angebot'!Q5 -> 75 | F6: ='Sterne-Rechner - Angebot'!Q6 -> 75
C7: Angebotene Deckungssumme | D7: ='Sterne-Rechner - Angebot'!AD4 -> 0 | E7: ='Sterne-Rechner - Angebot'!AD5 -> 0 | F7: ='Sterne-Rechner - Angebot'!AD6 -> 0
C8: Nettoisierte Jahresnettoprämie | D8: ='Sterne-Rechner - Angebot'!AC4 | E8: ='Sterne-Rechner - Angebot'!AC5 | F8: ='Sterne-Rechner - Angebot'!AC6
C9: Provision Howden | D9: ='Preisrechner Alle Tarife'!R34 -> 0 | E9: ='Preisrechner Alle Tarife'!S34 -> 0 | F9: ='Preisrechner Alle Tarife'!T34 -> 0
C10: Provision Coop-Makler | D10: ='Preisrechner Alle Tarife'!V34 -> 0 | E10: ='Preisrechner Alle Tarife'!W34 -> 0 | F10: ='Preisrechner Alle Tarife'!X34 -> 0
C11: Zusätzliche gewählte Deckungsoptionen
C12: Klauseln | D12: =wvagUsedClauses -> , | E12: =wvagUsedClauses -> , | F12: =wvagUsedClauses -> ,
C13: Status | D13: ='Sterne-Rechner - Angebot'!AE4 -> OFFER_DECLINED | E13: ='Sterne-Rechner - Angebot'!AE5 -> OFFER_DECLINED | F13: ='Sterne-Rechner - Angebot'!AE6 -> OFFER_DECLINED
C14: Axa Facility (wahr) / Axa MMC (falsch) | D14: =IF(AXAFacilityKriterien="Kriterien erfüllt",TRUE,FALSE) -> FALSE
B15: AXA | C15: Sterne | D15: =TEXT('Sterne-Rechner - Angebot'!Y7,"0") | E15: =TEXT('Sterne-Rechner - Angebot'!Y8,"0") | F15: =TEXT('Sterne-Rechner - Angebot'!Y9,"0")
C16: Bewertungsfaktor | D16: ='Sterne-Rechner - Angebot'!Q7 -> 95 | E16: ='Sterne-Rechner - Angebot'!Q8 -> 95 | F16: ='Sterne-Rechner - Angebot'!Q9 -> 95
C17: Angebotene Deckungssumme | D17: ='Sterne-Rechner - Angebot'!AD7 -> 0 | E17: ='Sterne-Rechner - Angebot'!AD8 -> 0 | F17: ='Sterne-Rechner - Angebot'!AD9 -> 0
C18: Nettoisierte Jahresnettoprämie | D18: ='Sterne-Rechner - Angebot'!AC7 | E18: ='Sterne-Rechner - Angebot'!AC8 | F18: ='Sterne-Rechner - Angebot'!AC9
C19: Provision Howden | D19: ='Preisrechner Alle Tarife'!R35 -> 0 | E19: ='Preisrechner Alle Tarife'!S35 -> 0 | F19: ='Preisrechner Alle Tarife'!T35 -> 0
C20: Provision Coop-Makler | D20: ='Preisrechner Alle Tarife'!V35 -> 0 | E20: ='Preisrechner Alle Tarife'!W35 -> 0 | F20: ='Preisrechner Alle Tarife'!X35 -> 0
C21: Zusätzliche gewählte Deckungsoptionen | D21: =IF(AND(OR(Fragenkatalog!K8="AG",Fragenkatalog!K8="SE",Fragenkatalog!K8="Versicherungsverein aG",Fragenkatalog!K8="e.G."),Außenumsatz>150000000,Branche="FI"),"WpHG,","") | E21: =IF(AND(OR(Fragenkatalog!K8="AG",Fragenkatalog!K8="SE",Fragenkatalog!K8="Versicherungsverein aG",Fragenkatalog!K8="e.G."),Außenumsatz>150000000,Branche="FI"),"WpHG,","") | F21: =IF(AND(OR(Fragenkatalog!K8="AG",Fragenkatalog!K8="SE",Fragenkatalog!K8="Versicherungsverein aG",Fragenkatalog!K8="e.G."),Außenumsatz>150000000,Branche="FI"),"WpHG,","")
C22: Klauseln | D22: =axaUsedClauses -> ,, | E22: =axaUsedClauses -> ,, | F22: =axaUsedClauses -> ,,
C23: Status | D23: ='Sterne-Rechner - Angebot'!AE7 -> OFFER_DECLINED | E23: ='Sterne-Rechner - Angebot'!AE8 -> OFFER_DECLINED | F23: ='Sterne-Rechner - Angebot'!AE9 -> OFFER_DECLINED
B24: =IF('Sterne-Rechner - Angebot'!C13=OfferReady,"AIG Facility","AIG") -> AIG | C24: Facility ja / nein | D24: =IF(AIGFacilityKriterien="Kriterien erfüllt",TRUE,FALSE) -> FALSE
C25: Sterne | D25: =TEXT(IF(D24=TRUE,'Sterne-Rechner - Angebot'!Y13,'Sterne-Rechner - Angebot'!Y10),"0") | E25: =TEXT(IF(D24=TRUE,'Sterne-Rechner - Angebot'!Y14,'Sterne-Rechner - Angebot'!Y11),"0") | F25: =TEXT(IF(D24=TRUE,'Sterne-Rechner - Angebot'!Y15,'Sterne-Rechner - Angebot'!Y12),"0")
C26: Bewertungsfaktor | D26: 0 | E26: 0 | F26: 0
C27: Angebotene Deckungssumme | D27: =IF(aigFacilityYesNo=TRUE,'Sterne-Rechner - Angebot'!AD13,'Sterne-Rechner - Angebot'!AD10) -> 0 | E27: =IF(aigFacilityYesNo=TRUE,'Sterne-Rechner - Angebot'!AD14,'Sterne-Rechner - Angebot'!AD11) -> 0 | F27: =IF(aigFacilityYesNo=TRUE,'Sterne-Rechner - Angebot'!AD15,'Sterne-Rechner - Angebot'!AD12) -> 0
C28: Nettoisierte Jahresnettoprämie | D28: =IF(aigFacilityYesNo=TRUE,'Sterne-Rechner - Angebot'!AC13,'Sterne-Rechner - Angebot'!AC10) | E28: =IF(aigFacilityYesNo=TRUE,'Sterne-Rechner - Angebot'!AC14,'Sterne-Rechner - Angebot'!AC11) | F28: =IF(aigFacilityYesNo=TRUE,'Sterne-Rechner - Angebot'!AC15,'Sterne-Rechner - Angebot'!AC12)
C29: Provision Howden | D29: =IF(aigFacilityYesNo=TRUE,'Preisrechner Alle Tarife'!U8,'Preisrechner Alle Tarife'!U7) -> 0 | E29: =IF(aigFacilityYesNo=TRUE,'Preisrechner Alle Tarife'!V8,'Preisrechner Alle Tarife'!V7) -> 0 | F29: =IF(aigFacilityYesNo=TRUE,'Preisrechner Alle Tarife'!W8,'Preisrechner Alle Tarife'!W7) -> 0
C30: Provision Coop-Makler | D30: =IF(aigFacilityYesNo=TRUE,'Preisrechner Alle Tarife'!Y8,'Preisrechner Alle Tarife'!Y7) -> 0
C31: Zusätzliche gewählte Deckungsoptionen
C32: Klauseln | D32: =aigUsedClauses -> , | E32: =aigUsedClauses -> , | F32: =aigUsedClauses -> ,
C33: Status | D33: =IF(aigFacilityYesNo=TRUE,'Sterne-Rechner - Angebot'!AE13,'Sterne-Rechner - Angebot'!AE10) -> OFFER_DECLINED | E33: =IF(aigFacilityYesNo=TRUE,'Sterne-Rechner - Angebot'!AE14,'Sterne-Rechner - Angebot'!AE11) -> OFFER_DECLINED | F33: =IF(aigFacilityYesNo=TRUE,'Sterne-Rechner - Angebot'!AE15,'Sterne-Rechner - Angebot'!AE12) -> OFFER_DECLINED
B34: DUAL | C34: Sterne | D34: =TEXT('Sterne-Rechner - Angebot'!Y16,"0") | E34: =TEXT('Sterne-Rechner - Angebot'!Y17,"0") | F34: =TEXT('Sterne-Rechner - Angebot'!Y18,"0")
C35: Bewertungsfaktor | D35: ='Sterne-Rechner - Angebot'!Q16 -> 10 | E35: ='Sterne-Rechner - Angebot'!Q17 -> 10 | F35: ='Sterne-Rechner - Angebot'!Q18 -> 10
C36: Angebotene Deckungssumme | D36: ='Sterne-Rechner - Angebot'!AD16 -> 0 | E36: ='Sterne-Rechner - Angebot'!AD17 -> 0 | F36: ='Sterne-Rechner - Angebot'!AD18 -> 0
C37: Nettoisierte Jahresnettoprämie | D37: ='Sterne-Rechner - Angebot'!AC16 | E37: ='Sterne-Rechner - Angebot'!AC17 | F37: ='Sterne-Rechner - Angebot'!AC18
C38: Provision Howden | D38: ='Preisrechner Alle Tarife'!R38 -> 0 | E38: ='Preisrechner Alle Tarife'!S38 -> 0 | F38: ='Preisrechner Alle Tarife'!T38 -> 0
C39: Provision Coop-Makler | D39: ='Preisrechner Alle Tarife'!V38 -> 0 | E39: ='Preisrechner Alle Tarife'!W38 -> 0 | F39: ='Preisrechner Alle Tarife'!X38 -> 0
C40: Zusätzliche gewählte Deckungsoptionen
C41: Klauseln | D41: =dualUsedClauses -> , | E41: =dualUsedClauses -> , | F41: =dualUsedClauses -> ,
C42: Status | D42: ='Sterne-Rechner - Angebot'!AE16 -> OFFER_DECLINED | E42: ='Sterne-Rechner - Angebot'!AE17 -> OFFER_DECLINED | F42: ='Sterne-Rechner - Angebot'!AE18 -> OFFER_DECLINED
B43: Newline | C43: Sterne | D43: =TEXT('Sterne-Rechner - Angebot'!Y19,"0") | E43: =TEXT('Sterne-Rechner - Angebot'!Y20,"0") | F43: =TEXT('Sterne-Rechner - Angebot'!Y21,"0")
C44: Bewertungsfaktor | D44: ='Sterne-Rechner - Angebot'!Q19 -> 75 | E44: ='Sterne-Rechner - Angebot'!Q20 -> 75 | F44: ='Sterne-Rechner - Angebot'!Q21 -> 75
C45: Angebotene Deckungssumme | D45: ='Sterne-Rechner - Angebot'!AD19 -> 0 | E45: ='Sterne-Rechner - Angebot'!AD20 -> 0 | F45: ='Sterne-Rechner - Angebot'!AD21 -> 0
C46: Nettoisierte Jahresnettoprämie | D46: ='Sterne-Rechner - Angebot'!AC19 | E46: ='Sterne-Rechner - Angebot'!AC20 | F46: ='Sterne-Rechner - Angebot'!AC21
C47: Provision Howden | D47: ='Preisrechner Alle Tarife'!R39 -> 0 | E47: ='Preisrechner Alle Tarife'!S39 -> 0 | F47: ='Preisrechner Alle Tarife'!T39 -> 0
C48: Provision Coop-Makler | D48: ='Preisrechner Alle Tarife'!V39 -> 0 | E48: ='Preisrechner Alle Tarife'!W39 -> 0 | F48: ='Preisrechner Alle Tarife'!X39 -> 0
C49: Zusätzliche gewählte Deckungsoptionen | D49: =IF(OR(Fragenkatalog!K8="AG",Fragenkatalog!K8="SE",Fragenkatalog!K8="Versicherungsverein aG",Fragenkatalog!K8="e.G."),"WpHG,","") | E49: =IF(OR(Fragenkatalog!K8="AG",Fragenkatalog!K8="SE",Fragenkatalog!K8="Versicherungsverein aG",Fragenkatalog!K8="e.G."),"WpHG,","") | F49: =IF(OR(Fragenkatalog!K8="AG",Fragenkatalog!K8="SE",Fragenkatalog!K8="Versicherungsverein aG",Fragenkatalog!K8="e.G."),"WpHG,","")
C50: Klauseln | D50: =newlineUsedClauses -> , | E50: =newlineUsedClauses -> , | F50: =newlineUsedClauses -> ,
C51: Status | D51: ='Sterne-Rechner - Angebot'!AE19 -> OFFER_DECLINED | E51: ='Sterne-Rechner - Angebot'!AE20 -> OFFER_DECLINED | F51: ='Sterne-Rechner - Angebot'!AE21 -> OFFER_DECLINED
B52: Berkley | C52: Sterne | D52: =TEXT('Sterne-Rechner - Angebot'!Y22,"0") | E52: =TEXT('Sterne-Rechner - Angebot'!Y23,"0") | F52: =TEXT('Sterne-Rechner - Angebot'!Y24,"0")
C53: Bewertungsfaktor | D53: ='Sterne-Rechner - Angebot'!Q22 -> 25 | E53: ='Sterne-Rechner - Angebot'!Q23 -> 25 | F53: ='Sterne-Rechner - Angebot'!Q24 -> 25
C54: Angebotene Deckungssumme | D54: ='Sterne-Rechner - Angebot'!AD22 -> 0 | E54: ='Sterne-Rechner - Angebot'!AD23 -> 0 | F54: ='Sterne-Rechner - Angebot'!AD24 -> 0
C55: Nettoisierte Jahresnettoprämie | D55: ='Sterne-Rechner - Angebot'!AC22 | E55: ='Sterne-Rechner - Angebot'!AC23 | F55: ='Sterne-Rechner - Angebot'!AC24
C56: Provision Howden | D56: ='Preisrechner Alle Tarife'!R40 -> 0 | E56: ='Preisrechner Alle Tarife'!S40 -> 0 | F56: ='Preisrechner Alle Tarife'!T40 -> 0
C57: Provision Coop-Makler | D57: ='Preisrechner Alle Tarife'!V40 -> 0 | E57: ='Preisrechner Alle Tarife'!W40 -> 0 | F57: ='Preisrechner Alle Tarife'!X40 -> 0
C58: Zusätzliche gewählte Deckungsoptionen | D58: =IF(OR(Fragenkatalog!K8="AG",Fragenkatalog!K8="SE",Fragenkatalog!K8="Versicherungsverein aG",Fragenkatalog!K8="e.G."),"WpHG,","") | E58: =IF(OR(Fragenkatalog!K8="AG",Fragenkatalog!K8="SE",Fragenkatalog!K8="Versicherungsverein aG",Fragenkatalog!K8="e.G."),"WpHG,","") | F58: =IF(OR(Fragenkatalog!K8="AG",Fragenkatalog!K8="SE",Fragenkatalog!K8="Versicherungsverein aG",Fragenkatalog!K8="e.G."),"WpHG,","")
C59: Klauseln | D59: =berkleyUsedClauses -> , | E59: =berkleyUsedClauses -> , | F59: =berkleyUsedClauses -> ,
C60: Status | D60: ='Sterne-Rechner - Angebot'!AE22 -> OFFER_DECLINED | E60: ='Sterne-Rechner - Angebot'!AE23 -> OFFER_DECLINED | F60: ='Sterne-Rechner - Angebot'!AE24 -> OFFER_DECLINED
B61: Markel | C61: Sterne | D61: =TEXT('Sterne-Rechner - Angebot'!Y25,"0") | E61: =TEXT('Sterne-Rechner - Angebot'!Y26,"0") | F61: =TEXT('Sterne-Rechner - Angebot'!Y27,"0")
C62: Bewertungsfaktor | D62: ='Sterne-Rechner - Angebot'!Q25 -> 75 | E62: ='Sterne-Rechner - Angebot'!Q26 -> 75 | F62: ='Sterne-Rechner - Angebot'!Q27 -> 75
C63: Angebotene Deckungssumme | D63: ='Sterne-Rechner - Angebot'!AD25 -> 0 | E63: ='Sterne-Rechner - Angebot'!AD26 -> 0 | F63: ='Sterne-Rechner - Angebot'!AD27 -> 0
C64: Nettoisierte Jahresnettoprämie | D64: ='Sterne-Rechner - Angebot'!AC25 | E64: ='Sterne-Rechner - Angebot'!AC26 | F64: ='Sterne-Rechner - Angebot'!AC27
C65: Provision Howden | D65: ='Preisrechner Alle Tarife'!R41 -> 0 | E65: ='Preisrechner Alle Tarife'!S41 -> 0 | F65: ='Preisrechner Alle Tarife'!T41 -> 0
C66: Provision Coop-Makler | D66: ='Preisrechner Alle Tarife'!V41 -> 0 | E66: ='Preisrechner Alle Tarife'!W41 -> 0 | F66: ='Preisrechner Alle Tarife'!X41 -> 0
C67: Zusätzliche gewählte Deckungsoptionen
C68: Klauseln | D68: =markelUsedClauses -> , | E68: =markelUsedClauses -> , | F68: =markelUsedClauses -> ,
C69: Status | D69: ='Sterne-Rechner - Angebot'!AE25 -> OFFER_DECLINED | E69: ='Sterne-Rechner - Angebot'!AE26 -> OFFER_DECLINED | F69: ='Sterne-Rechner - Angebot'!AE27 -> OFFER_DECLINED
B70: Liberty | C70: Sterne | D70: =TEXT('Sterne-Rechner - Angebot'!Y28,"0") | E70: =TEXT('Sterne-Rechner - Angebot'!Y29,"0") | F70: =TEXT('Sterne-Rechner - Angebot'!Y30,"0")
C71: Bewertungsfaktor | D71: ='Sterne-Rechner - Angebot'!Q28 -> 95 | E71: ='Sterne-Rechner - Angebot'!Q29 -> 95 | F71: ='Sterne-Rechner - Angebot'!Q30 -> 95
C72: Angebotene Deckungssumme | D72: ='Sterne-Rechner - Angebot'!AD28 -> 0 | E72: ='Sterne-Rechner - Angebot'!AD29 -> 0 | F72: ='Sterne-Rechner - Angebot'!AD30 -> 0
C73: Nettoisierte Jahresnettoprämie | D73: ='Sterne-Rechner - Angebot'!$AC28 | E73: ='Sterne-Rechner - Angebot'!$AC29 | F73: ='Sterne-Rechner - Angebot'!$AC30
C74: Provision Howden | D74: ='Preisrechner Alle Tarife'!R42 -> 0 | E74: ='Preisrechner Alle Tarife'!S42 -> 0 | F74: ='Preisrechner Alle Tarife'!T42 -> 0
C75: Provision Coop-Makler | D75: ='Preisrechner Alle Tarife'!V42 -> 0 | E75: ='Preisrechner Alle Tarife'!W42 -> 0 | F75: ='Preisrechner Alle Tarife'!X42 -> 0
C76: Zusätzliche gewählte Deckungsoptionen
C77: Klauseln | D77: =libertyUsedClauses -> , | E77: =libertyUsedClauses -> , | F77: =libertyUsedClauses -> ,
C78: Status | D78: ='Sterne-Rechner - Angebot'!$AE28 -> OFFER_DECLINED | E78: ='Sterne-Rechner - Angebot'!$AE29 -> OFFER_DECLINED | F78: ='Sterne-Rechner - Angebot'!$AE30 -> OFFER_DECLINED
B79: Ergo | C79: Sterne | D79: =TEXT('Sterne-Rechner - Angebot'!Y31,"0") | E79: =TEXT('Sterne-Rechner - Angebot'!Y32,"0") | F79: =TEXT('Sterne-Rechner - Angebot'!Y33,"0")
C80: Bewertungsfaktor | D80: ='Sterne-Rechner - Angebot'!Q31 -> 50 | E80: ='Sterne-Rechner - Angebot'!Q32 -> 50 | F80: ='Sterne-Rechner - Angebot'!Q33 -> 50
C81: Angebotene Deckungssumme | D81: ='Sterne-Rechner - Angebot'!AD31 -> 0 | E81: ='Sterne-Rechner - Angebot'!AD32 -> 0 | F81: ='Sterne-Rechner - Angebot'!AD33 -> 0
C82: Nettoisierte Jahresnettoprämie | D82: ='Sterne-Rechner - Angebot'!$AC31 | E82: ='Sterne-Rechner - Angebot'!$AC32 | F82: ='Sterne-Rechner - Angebot'!$AC33
C83: Provision Howden | D83: ='Preisrechner Alle Tarife'!R43 -> 0 | E83: ='Preisrechner Alle Tarife'!S43 -> 0 | F83: ='Preisrechner Alle Tarife'!T43 -> 0
C84: Provision Coop-Makler | D84: ='Preisrechner Alle Tarife'!V43 -> 0 | E84: ='Preisrechner Alle Tarife'!W43 -> 0 | F84: ='Preisrechner Alle Tarife'!X43 -> 0
C85: Zusätzliche gewählte Deckungsoptionen
C86: Klauseln | D86: =ergoUsedClauses -> ,ergo_nettoisierung:group-4, | E86: =ergoUsedClauses -> ,ergo_nettoisierung:group-4, | F86: =ergoUsedClauses -> ,ergo_nettoisierung:group-4,
C87: Status | D87: ='Sterne-Rechner - Angebot'!$AE31 -> OFFER_DECLINED | E87: ='Sterne-Rechner - Angebot'!$AE32 -> OFFER_DECLINED | F87: ='Sterne-Rechner - Angebot'!$AE33 -> OFFER_DECLINED

Sheet Deckungsoptionen
A1: Deckungsoptionen Defaults:
A3: Diese Werte sind Default-Werte. Hier keine Berechnungen mit anderen Felder ausführen!
A5: Zweifachmaximierung | B5: AIG | C5: AXA XL - Facility | D5: AXA XL - MMC | E5: DUAL | F5: Newline | G5: Berkley | H5: WVAG | I5: Markel | J5: Liberty | K5: Ergo
A6: Option gewählt | B6: TRUE | C6: TRUE | D6: TRUE | E6: TRUE | F6: TRUE | G6: TRUE | H6: TRUE | I6: TRUE | J6: TRUE | K6: TRUE
A7: Prämienneutral | B7: FALSE | C7: FALSE | D7: FALSE | E7: FALSE | F7: FALSE | G7: FALSE | H7: FALSE | I7: FALSE | J7: FALSE | K7: FALSE
A8: Prozentsatz | B8: 15 | C8: 20 | D8: 20 | E8: 25 | F8: 15 | G8: 15 | H8: 15 | I8: 10 | J8: 20 | K8: 20
A10: Schiedsgericht (ARIAS) | B10: AIG | C10: AXA XL - Facility | D10: AXA XL - MMC | E10: DUAL | F10: Newline | G10: Berkley | H10: WVAG | I10: Markel | J10: Liberty | K10: Ergo | M10: ARIAS Included | N10: Manche neue Bedingungswerke haben die Schiedsgerichtklausel immer mit drin (Liberty,Axa MMC ab 2024, Ergo ab 2024, Newline ab 2024). Option muss immer Prämienneutral angewählt sein
A11: Option gewählt | B11: TRUE | C11: TRUE | D11: =includedArbitrationCourtSelected -> TRUE | E11: =noOptionSelected -> FALSE | F11: =includedArbitrationCourtSelected -> TRUE | G11: =noOptionSelected -> FALSE | H11: =noOptionSelected -> FALSE | I11: =includedArbitrationCourtSelected -> TRUE | J11: =includedArbitrationCourtSelected -> TRUE | K11: =includedArbitrationCourtSelected -> TRUE | M11: TRUE
A12: Prämienneutral | B12: FALSE | C12: TRUE | D12: =includedArbitrationCourtPremiumNeutral -> TRUE | E12: =noOptionPremiumNeutral -> FALSE | F12: =includedArbitrationCourtPremiumNeutral -> TRUE | G12: =noOptionPremiumNeutral -> FALSE | H12: =noOptionPremiumNeutral -> FALSE | I12: =includedArbitrationCourtPremiumNeutral -> TRUE | J12: =includedArbitrationCourtPremiumNeutral -> TRUE | K12: =includedArbitrationCourtPremiumNeutral -> TRUE | M12: TRUE
A13: Prozentsatz | B13: 20 | C13: 0 | D13: =includedArbitrationCourtPercentage -> 0 | E13: =noOptionPercentage -> 0 | F13: =includedArbitrationCourtPercentage -> 0 | G13: =noOptionPercentage -> 0 | H13: =noOptionPercentage -> 0 | I13: =includedArbitrationCourtPercentage -> 0 | J13: =includedArbitrationCourtPercentage -> 0 | K13: =includedArbitrationCourtPercentage -> 0 | M13: 0
A15: WpHG | B15: AIG | C15: AXA XL - Facility | D15: AXA XL - MMC | E15: DUAL | F15: Newline | G15: Berkley | H15: WVAG | I15: Markel | J15: Liberty | K15: Ergo
A16: Option gewählt | B16: TRUE | C16: FALSE | D16: =noOptionSelected -> FALSE | E16: =noOptionSelected -> FALSE | F16: FALSE | G16: FALSE | H16: =noOptionSelected -> FALSE | I16: FALSE | J16: =noOptionSelected -> FALSE | K16: =noOptionSelected -> FALSE
A17: Prämienneutral | B17: FALSE | C17: FALSE | D17: =noOptionPremiumNeutral -> FALSE | E17: =noOptionPremiumNeutral -> FALSE | F17: FALSE | G17: FALSE | H17: =noOptionPremiumNeutral -> FALSE | I17: FALSE | J17: =noOptionPremiumNeutral -> FALSE | K17: =noOptionPremiumNeutral -> FALSE
A18: Prozentsatz | B18: 10 | C18: 10 | D18: =noOptionPercentage -> 0 | E18: =noOptionPercentage -> 0 | F18: 10 | G18: 10 | H18: =noOptionPercentage -> 0 | I18: 10 | J18: =noOptionPercentage -> 0 | K18: =noOptionPercentage -> 0
A20: Format zeigt, dass Versicherer | B20: FALSE
A21: die Option nicht anbietet | B21: FALSE
B22: 0

Sheet Referral Stati
B1: AGCS | D1: Württembergische | F1: AXA Facility | H1: AIG | J1: AIG Facility | L1: DUAL | N1: Newline | P1: Berkley | R1: Markel | T1: Liberty | V1: ERGO
A2: Trigger | B2: Referral | C2: KO | D2: Referral | E2: KO | F2: Referral | G2: KO | H2: Referral | I2: KO | J2: Referral | K2: KO | L2: Referral | M2: KO | N2: Referral | O2: KO | P2: Referral | Q2: KO | R2: Referral | S2: KO | T2: Referral | U2: KO | V2: Referral | W2: KO
A3: 1 | B3: {=IFERROR(IF(ROW(A1)>COUNTA(B$20:B$162),"",INDEX(B:B,SMALL(IF(B$20:B$162<>"", ROW($20:$162)),ROW(A1)))),"")} | C3: {=IFERROR(IF(ROW(A1)>COUNTA(C$20:C$162),"",INDEX(C:C,SMALL(IF(C$20:C$162<>"", ROW($20:$162)),ROW(A1)))),"")} | D3: {=IFERROR(INDEX(D:D,SMALL(IF(D$20:D$177<>"", ROW($20:$177)),$A3)),"")} -> Eigenkapital | E3: {=IFERROR(INDEX(E:E,SMALL(IF(E$20:E$177<>"", ROW($20:$177)),$A3)),"")} | F3: {=IFERROR(INDEX(F:F,SMALL(IF(F$20:F$177<>"", ROW($20:$177)),$A3)),"")} -> Policenbeginn | G3: {=IFERROR(INDEX(G:G,SMALL(IF(G$20:G$177<>"", ROW($20:$177)),$A3)),"")} -> Policenende bzw. Laufzeit | H3: {=IFERROR(IF(ROW(D1)>COUNTA(H$20:H$162),"",INDEX(H:H,SMALL(IF(H$20:H$162<>"", ROW($20:$162)),ROW($A$1)))),"")} | I3: {=IFERROR(IF(ROW(E1)>COUNTA(I$20:I$162),"",INDEX(I:I,SMALL(IF(I$20:I$162<>"", ROW($20:$162)),ROW($A$1)))),"")} | J3: {=IFERROR(IF(ROW(F1)>COUNTA(J$20:J$162),"",INDEX(J:J,SMALL(IF(J$20:J$162<>"", ROW($20:$162)),ROW($A$1)))),"")} -> Policenbeginn | K3: {=IFERROR(IF(ROW(G1)>COUNTA(K$20:K$162),"",INDEX(K:K,SMALL(IF(K$20:K$162<>"", ROW($20:$162)),ROW($A$1)))),"")} | L3: {=IFERROR(INDEX(L:L,SMALL(IF(L$20:L$177<>"", ROW($20:$177)),$A3)),"")} -> Policenbeginn | M3: {=IFERROR(INDEX(M:M,SMALL(IF(M$20:M$177<>"", ROW($20:$177)),$A3)),"")} -> Manueller Backstop | N3: {=IFERROR(INDEX(N:N,SMALL(IF(N$20:N$177<>"", ROW($20:$177)),$A3)),"")} -> Policenbeginn | O3: {=IFERROR(INDEX(O:O,SMALL(IF(O$20:O$177<>"", ROW($20:$177)),$A3)),"")} | P3: {=IFERROR(INDEX(P:P,SMALL(IF(P$20:P$177<>"", ROW($20:$177)),$A3)),"")} -> Policenbeginn | Q3: {=IFERROR(INDEX(Q:Q,SMALL(IF(Q$20:Q$177<>"", ROW($20:$177)),$A3)),"")} | R3: {=IFERROR(INDEX(R:R,SMALL(IF(R$20:R$177<>"", ROW($20:$177)),$A3)),"")} | S3: {=IFERROR(INDEX(S:S,SMALL(IF(S$20:S$177<>"", ROW($20:$177)),$A3)),"")} -> Policenbeginn | T3: {=IFERROR(INDEX(T:T,SMALL(IF(T$20:T$177<>"", ROW($20:$177)),$A3)),"")} | U3: {=IFERROR(INDEX(U:U,SMALL(IF(U$20:U$177<>"", ROW($20:$177)),$A3)),"")} | V3: {=IFERROR(INDEX(V:V,SMALL(IF(V$20:V$177<>"", ROW($20:$177)),$A3)),"")} -> Nettoisierung | W3: {=IFERROR(INDEX(W:W,SMALL(IF(W$20:W$177<>"", ROW($20:$177)),$A3)),"")} -> Policenende bzw. Laufzeit
A4: =A3+1 -> 2 | B4: {=IFERROR(IF(ROW(A2)>COUNTA(B$20:B$162),"",INDEX(B:B,SMALL(IF(B$20:B$162<>"", ROW($20:$162)),ROW(A2)))),"")} | C4: {=IFERROR(IF(ROW(A2)>COUNTA(C$20:C$162),"",INDEX(C:C,SMALL(IF(C$20:C$162<>"", ROW($20:$162)),ROW(A2)))),"")} | D4: {=IFERROR(INDEX(D:D,SMALL(IF(D$20:D$177<>"", ROW($20:$177)),$A4)),"")} | E4: {=IFERROR(INDEX(E:E,SMALL(IF(E$20:E$177<>"", ROW($20:$177)),$A4)),"")} | F4: {=IFERROR(INDEX(F:F,SMALL(IF(F$20:F$177<>"", ROW($20:$177)),$A4)),"")} -> Nettoisierung | G4: {=IFERROR(INDEX(G:G,SMALL(IF(G$20:G$177<>"", ROW($20:$177)),$A4)),"")} | H4: {=IFERROR(IF(ROW(D2)>COUNTA(H$20:H$162),"",INDEX(H:H,SMALL(IF(H$20:H$162<>"", ROW($20:$162)),ROW(C2)))),"")} | I4: {=IFERROR(IF(ROW(E2)>COUNTA(I$20:I$162),"",INDEX(I:I,SMALL(IF(I$20:I$162<>"", ROW($20:$162)),ROW(D2)))),"")} | J4: {=IFERROR(IF(ROW(F2)>COUNTA(J$20:J$162),"",INDEX(J:J,SMALL(IF(J$20:J$162<>"", ROW($20:$162)),ROW(E2)))),"")} | K4: {=IFERROR(IF(ROW(G2)>COUNTA(K$20:K$162),"",INDEX(K:K,SMALL(IF(K$20:K$162<>"", ROW($20:$162)),ROW(F2)))),"")} | L4: {=IFERROR(INDEX(L:L,SMALL(IF(L$20:L$177<>"", ROW($20:$177)),$A4)),"")} | M4: {=IFERROR(INDEX(M:M,SMALL(IF(M$20:M$177<>"", ROW($20:$177)),$A4)),"")} | N4: {=IFERROR(INDEX(N:N,SMALL(IF(N$20:N$177<>"", ROW($20:$177)),$A4)),"")} -> Policenende bzw. Laufzeit | O4: {=IFERROR(INDEX(O:O,SMALL(IF(O$20:O$177<>"", ROW($20:$177)),$A4)),"")} | P4: {=IFERROR(INDEX(P:P,SMALL(IF(P$20:P$177<>"", ROW($20:$177)),$A4)),"")} -> Policenende bzw. Laufzeit | Q4: {=IFERROR(INDEX(Q:Q,SMALL(IF(Q$20:Q$177<>"", ROW($20:$177)),$A4)),"")} | R4: {=IFERROR(INDEX(R:R,SMALL(IF(R$20:R$177<>"", ROW($20:$177)),$A4)),"")} | S4: {=IFERROR(INDEX(S:S,SMALL(IF(S$20:S$177<>"", ROW($20:$177)),$A4)),"")} | T4: {=IFERROR(INDEX(T:T,SMALL(IF(T$20:T$177<>"", ROW($20:$177)),$A4)),"")} | U4: {=IFERROR(INDEX(U:U,SMALL(IF(U$20:U$177<>"", ROW($20:$177)),$A4)),"")} | V4: {=IFERROR(INDEX(V:V,SMALL(IF(V$20:V$177<>"", ROW($20:$177)),$A4)),"")} | W4: {=IFERROR(INDEX(W:W,SMALL(IF(W$20:W$177<>"", ROW($20:$177)),$A4)),"")}
A5: =A4+1 -> 3 | B5: {=IFERROR(IF(ROW(A3)>COUNTA(B$20:B$162),"",INDEX(B:B,SMALL(IF(B$20:B$162<>"", ROW($20:$162)),ROW(A3)))),"")} | C5: {=IFERROR(IF(ROW(A3)>COUNTA(C$20:C$162),"",INDEX(C:C,SMALL(IF(C$20:C$162<>"", ROW($20:$162)),ROW(A3)))),"")} | D5: {=IFERROR(INDEX(D:D,SMALL(IF(D$20:D$177<>"", ROW($20:$177)),$A5)),"")} | E5: {=IFERROR(INDEX(E:E,SMALL(IF(E$20:E$177<>"", ROW($20:$177)),$A5)),"")} | F5: {=IFERROR(INDEX(F:F,SMALL(IF(F$20:F$177<>"", ROW($20:$177)),$A5)),"")} | G5: {=IFERROR(INDEX(G:G,SMALL(IF(G$20:G$177<>"", ROW($20:$177)),$A5)),"")} | H5: {=IFERROR(IF(ROW(D3)>COUNTA(H$20:H$162),"",INDEX(H:H,SMALL(IF(H$20:H$162<>"", ROW($20:$162)),ROW(C3)))),"")} | I5: {=IFERROR(IF(ROW(E3)>COUNTA(I$20:I$162),"",INDEX(I:I,SMALL(IF(I$20:I$162<>"", ROW($20:$162)),ROW(D3)))),"")} | J5: {=IFERROR(IF(ROW(F3)>COUNTA(J$20:J$162),"",INDEX(J:J,SMALL(IF(J$20:J$162<>"", ROW($20:$162)),ROW(E3)))),"")} | K5: {=IFERROR(IF(ROW(G3)>COUNTA(K$20:K$162),"",INDEX(K:K,SMALL(IF(K$20:K$162<>"", ROW($20:$162)),ROW(F3)))),"")} | L5: {=IFERROR(INDEX(L:L,SMALL(IF(L$20:L$177<>"", ROW($20:$177)),$A5)),"")} | M5: {=IFERROR(INDEX(M:M,SMALL(IF(M$20:M$177<>"", ROW($20:$177)),$A5)),"")} | N5: {=IFERROR(INDEX(N:N,SMALL(IF(N$20:N$177<>"", ROW($20:$177)),$A5)),"")} -> Nettoisierung | O5: {=IFERROR(INDEX(O:O,SMALL(IF(O$20:O$177<>"", ROW($20:$177)),$A5)),"")} | P5: {=IFERROR(INDEX(P:P,SMALL(IF(P$20:P$177<>"", ROW($20:$177)),$A5)),"")} | Q5: {=IFERROR(INDEX(Q:Q,SMALL(IF(Q$20:Q$177<>"", ROW($20:$177)),$A5)),"")} | R5: {=IFERROR(INDEX(R:R,SMALL(IF(R$20:R$177<>"", ROW($20:$177)),$A5)),"")} | S5: {=IFERROR(INDEX(S:S,SMALL(IF(S$20:S$177<>"", ROW($20:$177)),$A5)),"")} | T5: {=IFERROR(INDEX(T:T,SMALL(IF(T$20:T$177<>"", ROW($20:$177)),$A5)),"")} | U5: {=IFERROR(INDEX(U:U,SMALL(IF(U$20:U$177<>"", ROW($20:$177)),$A5)),"")} | V5: {=IFERROR(INDEX(V:V,SMALL(IF(V$20:V$177<>"", ROW($20:$177)),$A5)),"")} | W5: {=IFERROR(INDEX(W:W,SMALL(IF(W$20:W$177<>"", ROW($20:$177)),$A5)),"")}
A6: =A5+1 -> 4 | B6: {=IFERROR(IF(ROW(A4)>COUNTA(B$20:B$162),"",INDEX(B:B,SMALL(IF(B$20:B$162<>"", ROW($20:$162)),ROW(A4)))),"")} | C6: {=IFERROR(IF(ROW(A4)>COUNTA(C$20:C$162),"",INDEX(C:C,SMALL(IF(C$20:C$162<>"", ROW($20:$162)),ROW(A4)))),"")} | D6: {=IFERROR(INDEX(D:D,SMALL(IF(D$20:D$177<>"", ROW($20:$177)),$A6)),"")} | E6: {=IFERROR(INDEX(E:E,SMALL(IF(E$20:E$177<>"", ROW($20:$177)),$A6)),"")} | F6: {=IFERROR(INDEX(F:F,SMALL(IF(F$20:F$177<>"", ROW($20:$177)),$A6)),"")} | G6: {=IFERROR(INDEX(G:G,SMALL(IF(G$20:G$177<>"", ROW($20:$177)),$A6)),"")} | H6: {=IFERROR(IF(ROW(D4)>COUNTA(H$20:H$162),"",INDEX(H:H,SMALL(IF(H$20:H$162<>"", ROW($20:$162)),ROW(C4)))),"")} | I6: {=IFERROR(IF(ROW(E4)>COUNTA(I$20:I$162),"",INDEX(I:I,SMALL(IF(I$20:I$162<>"", ROW($20:$162)),ROW(D4)))),"")} | J6: {=IFERROR(IF(ROW(F4)>COUNTA(J$20:J$162),"",INDEX(J:J,SMALL(IF(J$20:J$162<>"", ROW($20:$162)),ROW(E4)))),"")} | K6: {=IFERROR(IF(ROW(G4)>COUNTA(K$20:K$162),"",INDEX(K:K,SMALL(IF(K$20:K$162<>"", ROW($20:$162)),ROW(F4)))),"")} | L6: {=IFERROR(INDEX(L:L,SMALL(IF(L$20:L$177<>"", ROW($20:$177)),$A6)),"")} | M6: {=IFERROR(INDEX(M:M,SMALL(IF(M$20:M$177<>"", ROW($20:$177)),$A6)),"")} | N6: {=IFERROR(INDEX(N:N,SMALL(IF(N$20:N$177<>"", ROW($20:$177)),$A6)),"")} -> Manueller Backstop | O6: {=IFERROR(INDEX(O:O,SMALL(IF(O$20:O$177<>"", ROW($20:$177)),$A6)),"")} | P6: {=IFERROR(INDEX(P:P,SMALL(IF(P$20:P$177<>"", ROW($20:$177)),$A6)),"")} | Q6: {=IFERROR(INDEX(Q:Q,SMALL(IF(Q$20:Q$177<>"", ROW($20:$177)),$A6)),"")} | R6: {=IFERROR(INDEX(R:R,SMALL(IF(R$20:R$177<>"", ROW($20:$177)),$A6)),"")} | S6: {=IFERROR(INDEX(S:S,SMALL(IF(S$20:S$177<>"", ROW($20:$177)),$A6)),"")} | T6: {=IFERROR(INDEX(T:T,SMALL(IF(T$20:T$177<>"", ROW($20:$177)),$A6)),"")} | U6: {=IFERROR(INDEX(U:U,SMALL(IF(U$20:U$177<>"", ROW($20:$177)),$A6)),"")} | V6: {=IFERROR(INDEX(V:V,SMALL(IF(V$20:V$177<>"", ROW($20:$177)),$A6)),"")} | W6: {=IFERROR(INDEX(W:W,SMALL(IF(W$20:W$177<>"", ROW($20:$177)),$A6)),"")}
A7: =A6+1 -> 5 | B7: {=IFERROR(IF(ROW(A5)>COUNTA(B$20:B$162),"",INDEX(B:B,SMALL(IF(B$20:B$162<>"", ROW($20:$162)),ROW(A5)))),"")} | C7: {=IFERROR(IF(ROW(A5)>COUNTA(C$20:C$162),"",INDEX(C:C,SMALL(IF(C$20:C$162<>"", ROW($20:$162)),ROW(A5)))),"")} | D7: {=IFERROR(INDEX(D:D,SMALL(IF(D$20:D$177<>"", ROW($20:$177)),$A7)),"")} | E7: {=IFERROR(INDEX(E:E,SMALL(IF(E$20:E$177<>"", ROW($20:$177)),$A7)),"")} | F7: {=IFERROR(INDEX(F:F,SMALL(IF(F$20:F$177<>"", ROW($20:$177)),$A7)),"")} | G7: {=IFERROR(INDEX(G:G,SMALL(IF(G$20:G$177<>"", ROW($20:$177)),$A7)),"")} | H7: {=IFERROR(IF(ROW(D5)>COUNTA(H$20:H$162),"",INDEX(H:H,SMALL(IF(H$20:H$162<>"", ROW($20:$162)),ROW(C5)))),"")} | I7: {=IFERROR(IF(ROW(E5)>COUNTA(I$20:I$162),"",INDEX(I:I,SMALL(IF(I$20:I$162<>"", ROW($20:$162)),ROW(D5)))),"")} | J7: {=IFERROR(IF(ROW(F5)>COUNTA(J$20:J$162),"",INDEX(J:J,SMALL(IF(J$20:J$162<>"", ROW($20:$162)),ROW(E5)))),"")} | K7: {=IFERROR(IF(ROW(G5)>COUNTA(K$20:K$162),"",INDEX(K:K,SMALL(IF(K$20:K$162<>"", ROW($20:$162)),ROW(F5)))),"")} | L7: {=IFERROR(INDEX(L:L,SMALL(IF(L$20:L$177<>"", ROW($20:$177)),$A7)),"")} | M7: {=IFERROR(INDEX(M:M,SMALL(IF(M$20:M$177<>"", ROW($20:$177)),$A7)),"")} | N7: {=IFERROR(INDEX(N:N,SMALL(IF(N$20:N$177<>"", ROW($20:$177)),$A7)),"")} | O7: {=IFERROR(INDEX(O:O,SMALL(IF(O$20:O$177<>"", ROW($20:$177)),$A7)),"")} | P7: {=IFERROR(INDEX(P:P,SMALL(IF(P$20:P$177<>"", ROW($20:$177)),$A7)),"")} | Q7: {=IFERROR(INDEX(Q:Q,SMALL(IF(Q$20:Q$177<>"", ROW($20:$177)),$A7)),"")} | R7: {=IFERROR(INDEX(R:R,SMALL(IF(R$20:R$177<>"", ROW($20:$177)),$A7)),"")} | S7: {=IFERROR(INDEX(S:S,SMALL(IF(S$20:S$177<>"", ROW($20:$177)),$A7)),"")} | T7: {=IFERROR(INDEX(T:T,SMALL(IF(T$20:T$177<>"", ROW($20:$177)),$A7)),"")} | U7: {=IFERROR(INDEX(U:U,SMALL(IF(U$20:U$177<>"", ROW($20:$177)),$A7)),"")} | V7: {=IFERROR(INDEX(V:V,SMALL(IF(V$20:V$177<>"", ROW($20:$177)),$A7)),"")} | W7: {=IFERROR(INDEX(W:W,SMALL(IF(W$20:W$177<>"", ROW($20:$177)),$A7)),"")}
A8: =A7+1 -> 6 | B8: {=IFERROR(IF(ROW(A6)>COUNTA(B$20:B$162),"",INDEX(B:B,SMALL(IF(B$20:B$162<>"", ROW($20:$162)),ROW(A6)))),"")} | C8: {=IFERROR(IF(ROW(A6)>COUNTA(C$20:C$162),"",INDEX(C:C,SMALL(IF(C$20:C$162<>"", ROW($20:$162)),ROW(A6)))),"")} | D8: {=IFERROR(INDEX(D:D,SMALL(IF(D$20:D$177<>"", ROW($20:$177)),$A8)),"")} | E8: {=IFERROR(INDEX(E:E,SMALL(IF(E$20:E$177<>"", ROW($20:$177)),$A8)),"")} | F8: {=IFERROR(INDEX(F:F,SMALL(IF(F$20:F$177<>"", ROW($20:$177)),$A8)),"")} | G8: {=IFERROR(INDEX(G:G,SMALL(IF(G$20:G$177<>"", ROW($20:$177)),$A8)),"")} | H8: {=IFERROR(IF(ROW(D6)>COUNTA(H$20:H$162),"",INDEX(H:H,SMALL(IF(H$20:H$162<>"", ROW($20:$162)),ROW(C6)))),"")} | I8: {=IFERROR(IF(ROW(E6)>COUNTA(I$20:I$162),"",INDEX(I:I,SMALL(IF(I$20:I$162<>"", ROW($20:$162)),ROW(D6)))),"")} | J8: {=IFERROR(IF(ROW(F6)>COUNTA(J$20:J$162),"",INDEX(J:J,SMALL(IF(J$20:J$162<>"", ROW($20:$162)),ROW(E6)))),"")} | K8: {=IFERROR(IF(ROW(G6)>COUNTA(K$20:K$162),"",INDEX(K:K,SMALL(IF(K$20:K$162<>"", ROW($20:$162)),ROW(F6)))),"")} | L8: {=IFERROR(INDEX(L:L,SMALL(IF(L$20:L$177<>"", ROW($20:$177)),$A8)),"")} | M8: {=IFERROR(INDEX(M:M,SMALL(IF(M$20:M$177<>"", ROW($20:$177)),$A8)),"")} | N8: {=IFERROR(INDEX(N:N,SMALL(IF(N$20:N$177<>"", ROW($20:$177)),$A8)),"")} | O8: {=IFERROR(INDEX(O:O,SMALL(IF(O$20:O$177<>"", ROW($20:$177)),$A8)),"")} | P8: {=IFERROR(INDEX(P:P,SMALL(IF(P$20:P$177<>"", ROW($20:$177)),$A8)),"")} | Q8: {=IFERROR(INDEX(Q:Q,SMALL(IF(Q$20:Q$177<>"", ROW($20:$177)),$A8)),"")} | R8: {=IFERROR(INDEX(R:R,SMALL(IF(R$20:R$177<>"", ROW($20:$177)),$A8)),"")} | S8: {=IFERROR(INDEX(S:S,SMALL(IF(S$20:S$177<>"", ROW($20:$177)),$A8)),"")} | T8: {=IFERROR(INDEX(T:T,SMALL(IF(T$20:T$177<>"", ROW($20:$177)),$A8)),"")} | U8: {=IFERROR(INDEX(U:U,SMALL(IF(U$20:U$177<>"", ROW($20:$177)),$A8)),"")} | V8: {=IFERROR(INDEX(V:V,SMALL(IF(V$20:V$177<>"", ROW($20:$177)),$A8)),"")} | W8: {=IFERROR(INDEX(W:W,SMALL(IF(W$20:W$177<>"", ROW($20:$177)),$A8)),"")}
A9: =A8+1 -> 7 | B9: {=IFERROR(IF(ROW(A7)>COUNTA(B$20:B$162),"",INDEX(B:B,SMALL(IF(B$20:B$162<>"", ROW($20:$162)),ROW(A7)))),"")} | C9: {=IFERROR(IF(ROW(A7)>COUNTA(C$20:C$162),"",INDEX(C:C,SMALL(IF(C$20:C$162<>"", ROW($20:$162)),ROW(A7)))),"")} | D9: {=IFERROR(INDEX(D:D,SMALL(IF(D$20:D$177<>"", ROW($20:$177)),$A9)),"")} | E9: {=IFERROR(INDEX(E:E,SMALL(IF(E$20:E$177<>"", ROW($20:$177)),$A9)),"")} | F9: {=IFERROR(INDEX(F:F,SMALL(IF(F$20:F$177<>"", ROW($20:$177)),$A9)),"")} | G9: {=IFERROR(INDEX(G:G,SMALL(IF(G$20:G$177<>"", ROW($20:$177)),$A9)),"")} | H9: {=IFERROR(IF(ROW(D7)>COUNTA(H$20:H$162),"",INDEX(H:H,SMALL(IF(H$20:H$162<>"", ROW($20:$162)),ROW(C7)))),"")} | I9: {=IFERROR(IF(ROW(E7)>COUNTA(I$20:I$162),"",INDEX(I:I,SMALL(IF(I$20:I$162<>"", ROW($20:$162)),ROW(D7)))),"")} | J9: {=IFERROR(IF(ROW(F7)>COUNTA(J$20:J$162),"",INDEX(J:J,SMALL(IF(J$20:J$162<>"", ROW($20:$162)),ROW(E7)))),"")} | K9: {=IFERROR(IF(ROW(G7)>COUNTA(K$20:K$162),"",INDEX(K:K,SMALL(IF(K$20:K$162<>"", ROW($20:$162)),ROW(F7)))),"")} | L9: {=IFERROR(INDEX(L:L,SMALL(IF(L$20:L$177<>"", ROW($20:$177)),$A9)),"")} | M9: {=IFERROR(INDEX(M:M,SMALL(IF(M$20:M$177<>"", ROW($20:$177)),$A9)),"")} | N9: {=IFERROR(INDEX(N:N,SMALL(IF(N$20:N$177<>"", ROW($20:$177)),$A9)),"")} | O9: {=IFERROR(INDEX(O:O,SMALL(IF(O$20:O$177<>"", ROW($20:$177)),$A9)),"")} | P9: {=IFERROR(INDEX(P:P,SMALL(IF(P$20:P$177<>"", ROW($20:$177)),$A9)),"")} | Q9: {=IFERROR(INDEX(Q:Q,SMALL(IF(Q$20:Q$177<>"", ROW($20:$177)),$A9)),"")} | R9: {=IFERROR(INDEX(R:R,SMALL(IF(R$20:R$177<>"", ROW($20:$177)),$A9)),"")} | S9: {=IFERROR(INDEX(S:S,SMALL(IF(S$20:S$177<>"", ROW($20:$177)),$A9)),"")} | T9: {=IFERROR(INDEX(T:T,SMALL(IF(T$20:T$177<>"", ROW($20:$177)),$A9)),"")} | U9: {=IFERROR(INDEX(U:U,SMALL(IF(U$20:U$177<>"", ROW($20:$177)),$A9)),"")} | V9: {=IFERROR(INDEX(V:V,SMALL(IF(V$20:V$177<>"", ROW($20:$177)),$A9)),"")} | W9: {=IFERROR(INDEX(W:W,SMALL(IF(W$20:W$177<>"", ROW($20:$177)),$A9)),"")}
A10: =A9+1 -> 8 | B10: {=IFERROR(IF(ROW(A8)>COUNTA(B$20:B$162),"",INDEX(B:B,SMALL(IF(B$20:B$162<>"", ROW($20:$162)),ROW(A8)))),"")} | C10: {=IFERROR(IF(ROW(A8)>COUNTA(C$20:C$162),"",INDEX(C:C,SMALL(IF(C$20:C$162<>"", ROW($20:$162)),ROW(A8)))),"")} | D10: {=IFERROR(INDEX(D:D,SMALL(IF(D$20:D$177<>"", ROW($20:$177)),$A10)),"")} | E10: {=IFERROR(INDEX(E:E,SMALL(IF(E$20:E$177<>"", ROW($20:$177)),$A10)),"")} | F10: {=IFERROR(INDEX(F:F,SMALL(IF(F$20:F$177<>"", ROW($20:$177)),$A10)),"")} | G10: {=IFERROR(INDEX(G:G,SMALL(IF(G$20:G$177<>"", ROW($20:$177)),$A10)),"")} | H10: {=IFERROR(IF(ROW(D8)>COUNTA(H$20:H$162),"",INDEX(H:H,SMALL(IF(H$20:H$162<>"", ROW($20:$162)),ROW(C8)))),"")} | I10: {=IFERROR(IF(ROW(E8)>COUNTA(I$20:I$162),"",INDEX(I:I,SMALL(IF(I$20:I$162<>"", ROW($20:$162)),ROW(D8)))),"")} | J10: {=IFERROR(IF(ROW(F8)>COUNTA(J$20:J$162),"",INDEX(J:J,SMALL(IF(J$20:J$162<>"", ROW($20:$162)),ROW(E8)))),"")} | K10: {=IFERROR(IF(ROW(G8)>COUNTA(K$20:K$162),"",INDEX(K:K,SMALL(IF(K$20:K$162<>"", ROW($20:$162)),ROW(F8)))),"")} | L10: {=IFERROR(INDEX(L:L,SMALL(IF(L$20:L$177<>"", ROW($20:$177)),$A10)),"")} | M10: {=IFERROR(INDEX(M:M,SMALL(IF(M$20:M$177<>"", ROW($20:$177)),$A10)),"")} | N10: {=IFERROR(INDEX(N:N,SMALL(IF(N$20:N$177<>"", ROW($20:$177)),$A10)),"")} | O10: {=IFERROR(INDEX(O:O,SMALL(IF(O$20:O$177<>"", ROW($20:$177)),$A10)),"")} | P10: {=IFERROR(INDEX(P:P,SMALL(IF(P$20:P$177<>"", ROW($20:$177)),$A10)),"")} | Q10: {=IFERROR(INDEX(Q:Q,SMALL(IF(Q$20:Q$177<>"", ROW($20:$177)),$A10)),"")} | R10: {=IFERROR(INDEX(R:R,SMALL(IF(R$20:R$177<>"", ROW($20:$177)),$A10)),"")} | S10: {=IFERROR(INDEX(S:S,SMALL(IF(S$20:S$177<>"", ROW($20:$177)),$A10)),"")} | T10: {=IFERROR(INDEX(T:T,SMALL(IF(T$20:T$177<>"", ROW($20:$177)),$A10)),"")} | U10: {=IFERROR(INDEX(U:U,SMALL(IF(U$20:U$177<>"", ROW($20:$177)),$A10)),"")} | V10: {=IFERROR(INDEX(V:V,SMALL(IF(V$20:V$177<>"", ROW($20:$177)),$A10)),"")} | W10: {=IFERROR(INDEX(W:W,SMALL(IF(W$20:W$177<>"", ROW($20:$177)),$A10)),"")}
A11: =A10+1 -> 9 | B11: {=IFERROR(IF(ROW(A9)>COUNTA(B$20:B$162),"",INDEX(B:B,SMALL(IF(B$20:B$162<>"", ROW($20:$162)),ROW(A9)))),"")} | C11: {=IFERROR(IF(ROW(A9)>COUNTA(C$20:C$162),"",INDEX(C:C,SMALL(IF(C$20:C$162<>"", ROW($20:$162)),ROW(A9)))),"")} | D11: {=IFERROR(INDEX(D:D,SMALL(IF(D$20:D$177<>"", ROW($20:$177)),$A11)),"")} | E11: {=IFERROR(INDEX(E:E,SMALL(IF(E$20:E$177<>"", ROW($20:$177)),$A11)),"")} | F11: {=IFERROR(INDEX(F:F,SMALL(IF(F$20:F$177<>"", ROW($20:$177)),$A11)),"")} | G11: {=IFERROR(INDEX(G:G,SMALL(IF(G$20:G$177<>"", ROW($20:$177)),$A11)),"")} | H11: {=IFERROR(IF(ROW(D9)>COUNTA(H$20:H$162),"",INDEX(H:H,SMALL(IF(H$20:H$162<>"", ROW($20:$162)),ROW(C9)))),"")} | I11: {=IFERROR(IF(ROW(E9)>COUNTA(I$20:I$162),"",INDEX(I:I,SMALL(IF(I$20:I$162<>"", ROW($20:$162)),ROW(D9)))),"")} | J11: {=IFERROR(IF(ROW(F9)>COUNTA(J$20:J$162),"",INDEX(J:J,SMALL(IF(J$20:J$162<>"", ROW($20:$162)),ROW(E9)))),"")} | K11: {=IFERROR(IF(ROW(G9)>COUNTA(K$20:K$162),"",INDEX(K:K,SMALL(IF(K$20:K$162<>"", ROW($20:$162)),ROW(F9)))),"")} | L11: {=IFERROR(INDEX(L:L,SMALL(IF(L$20:L$177<>"", ROW($20:$177)),$A11)),"")} | M11: {=IFERROR(INDEX(M:M,SMALL(IF(M$20:M$177<>"", ROW($20:$177)),$A11)),"")} | N11: {=IFERROR(INDEX(N:N,SMALL(IF(N$20:N$177<>"", ROW($20:$177)),$A11)),"")} | O11: {=IFERROR(INDEX(O:O,SMALL(IF(O$20:O$177<>"", ROW($20:$177)),$A11)),"")} | P11: {=IFERROR(INDEX(P:P,SMALL(IF(P$20:P$177<>"", ROW($20:$177)),$A11)),"")} | Q11: {=IFERROR(INDEX(Q:Q,SMALL(IF(Q$20:Q$177<>"", ROW($20:$177)),$A11)),"")} | R11: {=IFERROR(INDEX(R:R,SMALL(IF(R$20:R$177<>"", ROW($20:$177)),$A11)),"")} | S11: {=IFERROR(INDEX(S:S,SMALL(IF(S$20:S$177<>"", ROW($20:$177)),$A11)),"")} | T11: {=IFERROR(INDEX(T:T,SMALL(IF(T$20:T$177<>"", ROW($20:$177)),$A11)),"")} | U11: {=IFERROR(INDEX(U:U,SMALL(IF(U$20:U$177<>"", ROW($20:$177)),$A11)),"")} | V11: {=IFERROR(INDEX(V:V,SMALL(IF(V$20:V$177<>"", ROW($20:$177)),$A11)),"")} | W11: {=IFERROR(INDEX(W:W,SMALL(IF(W$20:W$177<>"", ROW($20:$177)),$A11)),"")}
A12: =A11+1 -> 10 | B12: {=IFERROR(IF(ROW(A10)>COUNTA(B$20:B$162),"",INDEX(B:B,SMALL(IF(B$20:B$162<>"", ROW($20:$162)),ROW(A10)))),"")} | C12: {=IFERROR(IF(ROW(A10)>COUNTA(C$20:C$162),"",INDEX(C:C,SMALL(IF(C$20:C$162<>"", ROW($20:$162)),ROW(A10)))),"")} | D12: {=IFERROR(INDEX(D:D,SMALL(IF(D$20:D$177<>"", ROW($20:$177)),$A12)),"")} | E12: {=IFERROR(INDEX(E:E,SMALL(IF(E$20:E$177<>"", ROW($20:$177)),$A12)),"")} | F12: {=IFERROR(INDEX(F:F,SMALL(IF(F$20:F$177<>"", ROW($20:$177)),$A12)),"")} | G12: {=IFERROR(INDEX(G:G,SMALL(IF(G$20:G$177<>"", ROW($20:$177)),$A12)),"")} | H12: {=IFERROR(IF(ROW(D10)>COUNTA(H$20:H$162),"",INDEX(H:H,SMALL(IF(H$20:H$162<>"", ROW($20:$162)),ROW(C10)))),"")} | I12: {=IFERROR(IF(ROW(E10)>COUNTA(I$20:I$162),"",INDEX(I:I,SMALL(IF(I$20:I$162<>"", ROW($20:$162)),ROW(D10)))),"")} | J12: {=IFERROR(IF(ROW(F10)>COUNTA(J$20:J$162),"",INDEX(J:J,SMALL(IF(J$20:J$162<>"", ROW($20:$162)),ROW(E10)))),"")} | K12: {=IFERROR(IF(ROW(G10)>COUNTA(K$20:K$162),"",INDEX(K:K,SMALL(IF(K$20:K$162<>"", ROW($20:$162)),ROW(F10)))),"")} | L12: {=IFERROR(INDEX(L:L,SMALL(IF(L$20:L$177<>"", ROW($20:$177)),$A12)),"")} | M12: {=IFERROR(INDEX(M:M,SMALL(IF(M$20:M$177<>"", ROW($20:$177)),$A12)),"")} | N12: {=IFERROR(INDEX(N:N,SMALL(IF(N$20:N$177<>"", ROW($20:$177)),$A12)),"")} | O12: {=IFERROR(INDEX(O:O,SMALL(IF(O$20:O$177<>"", ROW($20:$177)),$A12)),"")} | P12: {=IFERROR(INDEX(P:P,SMALL(IF(P$20:P$177<>"", ROW($20:$177)),$A12)),"")} | Q12: {=IFERROR(INDEX(Q:Q,SMALL(IF(Q$20:Q$177<>"", ROW($20:$177)),$A12)),"")} | R12: {=IFERROR(INDEX(R:R,SMALL(IF(R$20:R$177<>"", ROW($20:$177)),$A12)),"")} | S12: {=IFERROR(INDEX(S:S,SMALL(IF(S$20:S$177<>"", ROW($20:$177)),$A12)),"")} | T12: {=IFERROR(INDEX(T:T,SMALL(IF(T$20:T$177<>"", ROW($20:$177)),$A12)),"")} | U12: {=IFERROR(INDEX(U:U,SMALL(IF(U$20:U$177<>"", ROW($20:$177)),$A12)),"")} | V12: {=IFERROR(INDEX(V:V,SMALL(IF(V$20:V$177<>"", ROW($20:$177)),$A12)),"")} | W12: {=IFERROR(INDEX(W:W,SMALL(IF(W$20:W$177<>"", ROW($20:$177)),$A12)),"")}
A13: =A12+1 -> 11 | D13: {=IFERROR(INDEX(D:D,SMALL(IF(D$20:D$177<>"", ROW($20:$177)),$A13)),"")} | E13: {=IFERROR(INDEX(E:E,SMALL(IF(E$20:E$177<>"", ROW($20:$177)),$A13)),"")} | F13: {=IFERROR(INDEX(F:F,SMALL(IF(F$20:F$177<>"", ROW($20:$177)),$A13)),"")} | G13: {=IFERROR(INDEX(G:G,SMALL(IF(G$20:G$177<>"", ROW($20:$177)),$A13)),"")} | L13: {=IFERROR(INDEX(L:L,SMALL(IF(L$20:L$177<>"", ROW($20:$177)),$A13)),"")} | M13: {=IFERROR(INDEX(M:M,SMALL(IF(M$20:M$177<>"", ROW($20:$177)),$A13)),"")} | N13: {=IFERROR(INDEX(N:N,SMALL(IF(N$20:N$177<>"", ROW($20:$177)),$A13)),"")} | O13: {=IFERROR(INDEX(O:O,SMALL(IF(O$20:O$177<>"", ROW($20:$177)),$A13)),"")} | P13: {=IFERROR(INDEX(P:P,SMALL(IF(P$20:P$177<>"", ROW($20:$177)),$A13)),"")} | Q13: {=IFERROR(INDEX(Q:Q,SMALL(IF(Q$20:Q$177<>"", ROW($20:$177)),$A13)),"")} | R13: {=IFERROR(INDEX(R:R,SMALL(IF(R$20:R$177<>"", ROW($20:$177)),$A13)),"")} | S13: {=IFERROR(INDEX(S:S,SMALL(IF(S$20:S$177<>"", ROW($20:$177)),$A13)),"")} | T13: {=IFERROR(INDEX(T:T,SMALL(IF(T$20:T$177<>"", ROW($20:$177)),$A13)),"")} | U13: {=IFERROR(INDEX(U:U,SMALL(IF(U$20:U$177<>"", ROW($20:$177)),$A13)),"")} | V13: {=IFERROR(INDEX(V:V,SMALL(IF(V$20:V$177<>"", ROW($20:$177)),$A13)),"")} | W13: {=IFERROR(INDEX(W:W,SMALL(IF(W$20:W$177<>"", ROW($20:$177)),$A13)),"")}
A14: =A13+1 -> 12 | D14: {=IFERROR(INDEX(D:D,SMALL(IF(D$20:D$177<>"", ROW($20:$177)),$A14)),"")} | E14: {=IFERROR(INDEX(E:E,SMALL(IF(E$20:E$177<>"", ROW($20:$177)),$A14)),"")} | F14: {=IFERROR(INDEX(F:F,SMALL(IF(F$20:F$177<>"", ROW($20:$177)),$A14)),"")} | G14: {=IFERROR(INDEX(G:G,SMALL(IF(G$20:G$177<>"", ROW($20:$177)),$A14)),"")} | L14: {=IFERROR(INDEX(L:L,SMALL(IF(L$20:L$177<>"", ROW($20:$177)),$A14)),"")} | M14: {=IFERROR(INDEX(M:M,SMALL(IF(M$20:M$177<>"", ROW($20:$177)),$A14)),"")} | N14: {=IFERROR(INDEX(N:N,SMALL(IF(N$20:N$177<>"", ROW($20:$177)),$A14)),"")} | O14: {=IFERROR(INDEX(O:O,SMALL(IF(O$20:O$177<>"", ROW($20:$177)),$A14)),"")} | P14: {=IFERROR(INDEX(P:P,SMALL(IF(P$20:P$177<>"", ROW($20:$177)),$A14)),"")} | Q14: {=IFERROR(INDEX(Q:Q,SMALL(IF(Q$20:Q$177<>"", ROW($20:$177)),$A14)),"")} | R14: {=IFERROR(INDEX(R:R,SMALL(IF(R$20:R$177<>"", ROW($20:$177)),$A14)),"")} | S14: {=IFERROR(INDEX(S:S,SMALL(IF(S$20:S$177<>"", ROW($20:$177)),$A14)),"")} | T14: {=IFERROR(INDEX(T:T,SMALL(IF(T$20:T$177<>"", ROW($20:$177)),$A14)),"")} | U14: {=IFERROR(INDEX(U:U,SMALL(IF(U$20:U$177<>"", ROW($20:$177)),$A14)),"")} | V14: {=IFERROR(INDEX(V:V,SMALL(IF(V$20:V$177<>"", ROW($20:$177)),$A14)),"")} | W14: {=IFERROR(INDEX(W:W,SMALL(IF(W$20:W$177<>"", ROW($20:$177)),$A14)),"")}
A15: =A14+1 -> 13 | D15: {=IFERROR(INDEX(D:D,SMALL(IF(D$20:D$177<>"", ROW($20:$177)),$A15)),"")} | E15: {=IFERROR(INDEX(E:E,SMALL(IF(E$20:E$177<>"", ROW($20:$177)),$A15)),"")} | F15: {=IFERROR(INDEX(F:F,SMALL(IF(F$20:F$177<>"", ROW($20:$177)),$A15)),"")} | G15: {=IFERROR(INDEX(G:G,SMALL(IF(G$20:G$177<>"", ROW($20:$177)),$A15)),"")} | L15: {=IFERROR(INDEX(L:L,SMALL(IF(L$20:L$177<>"", ROW($20:$177)),$A15)),"")} | M15: {=IFERROR(INDEX(M:M,SMALL(IF(M$20:M$177<>"", ROW($20:$177)),$A15)),"")} | N15: {=IFERROR(INDEX(N:N,SMALL(IF(N$20:N$177<>"", ROW($20:$177)),$A15)),"")} | O15: {=IFERROR(INDEX(O:O,SMALL(IF(O$20:O$177<>"", ROW($20:$177)),$A15)),"")} | P15: {=IFERROR(INDEX(P:P,SMALL(IF(P$20:P$177<>"", ROW($20:$177)),$A15)),"")} | Q15: {=IFERROR(INDEX(Q:Q,SMALL(IF(Q$20:Q$177<>"", ROW($20:$177)),$A15)),"")} | R15: {=IFERROR(INDEX(R:R,SMALL(IF(R$20:R$177<>"", ROW($20:$177)),$A15)),"")} | S15: {=IFERROR(INDEX(S:S,SMALL(IF(S$20:S$177<>"", ROW($20:$177)),$A15)),"")} | T15: {=IFERROR(INDEX(T:T,SMALL(IF(T$20:T$177<>"", ROW($20:$177)),$A15)),"")} | U15: {=IFERROR(INDEX(U:U,SMALL(IF(U$20:U$177<>"", ROW($20:$177)),$A15)),"")} | V15: {=IFERROR(INDEX(V:V,SMALL(IF(V$20:V$177<>"", ROW($20:$177)),$A15)),"")} | W15: {=IFERROR(INDEX(W:W,SMALL(IF(W$20:W$177<>"", ROW($20:$177)),$A15)),"")}
A16: =A15+1 -> 14 | D16: {=IFERROR(INDEX(D:D,SMALL(IF(D$20:D$177<>"", ROW($20:$177)),$A16)),"")} | E16: {=IFERROR(INDEX(E:E,SMALL(IF(E$20:E$177<>"", ROW($20:$177)),$A16)),"")} | F16: {=IFERROR(INDEX(F:F,SMALL(IF(F$20:F$177<>"", ROW($20:$177)),$A16)),"")} | G16: {=IFERROR(INDEX(G:G,SMALL(IF(G$20:G$177<>"", ROW($20:$177)),$A16)),"")} | L16: {=IFERROR(INDEX(L:L,SMALL(IF(L$20:L$177<>"", ROW($20:$177)),$A16)),"")} | M16: {=IFERROR(INDEX(M:M,SMALL(IF(M$20:M$177<>"", ROW($20:$177)),$A16)),"")} | N16: {=IFERROR(INDEX(N:N,SMALL(IF(N$20:N$177<>"", ROW($20:$177)),$A16)),"")} | O16: {=IFERROR(INDEX(O:O,SMALL(IF(O$20:O$177<>"", ROW($20:$177)),$A16)),"")} | P16: {=IFERROR(INDEX(P:P,SMALL(IF(P$20:P$177<>"", ROW($20:$177)),$A16)),"")} | Q16: {=IFERROR(INDEX(Q:Q,SMALL(IF(Q$20:Q$177<>"", ROW($20:$177)),$A16)),"")} | R16: {=IFERROR(INDEX(R:R,SMALL(IF(R$20:R$177<>"", ROW($20:$177)),$A16)),"")} | S16: {=IFERROR(INDEX(S:S,SMALL(IF(S$20:S$177<>"", ROW($20:$177)),$A16)),"")} | T16: {=IFERROR(INDEX(T:T,SMALL(IF(T$20:T$177<>"", ROW($20:$177)),$A16)),"")} | U16: {=IFERROR(INDEX(U:U,SMALL(IF(U$20:U$177<>"", ROW($20:$177)),$A16)),"")} | V16: {=IFERROR(INDEX(V:V,SMALL(IF(V$20:V$177<>"", ROW($20:$177)),$A16)),"")} | W16: {=IFERROR(INDEX(W:W,SMALL(IF(W$20:W$177<>"", ROW($20:$177)),$A16)),"")}
A17: =A16+1 -> 15 | D17: {=IFERROR(INDEX(D:D,SMALL(IF(D$20:D$177<>"", ROW($20:$177)),$A17)),"")} | E17: {=IFERROR(INDEX(E:E,SMALL(IF(E$20:E$177<>"", ROW($20:$177)),$A17)),"")} | F17: {=IFERROR(INDEX(F:F,SMALL(IF(F$20:F$177<>"", ROW($20:$177)),$A17)),"")} | G17: {=IFERROR(INDEX(G:G,SMALL(IF(G$20:G$177<>"", ROW($20:$177)),$A17)),"")} | L17: {=IFERROR(INDEX(L:L,SMALL(IF(L$20:L$177<>"", ROW($20:$177)),$A17)),"")} | M17: {=IFERROR(INDEX(M:M,SMALL(IF(M$20:M$177<>"", ROW($20:$177)),$A17)),"")} | N17: {=IFERROR(INDEX(N:N,SMALL(IF(N$20:N$177<>"", ROW($20:$177)),$A17)),"")} | O17: {=IFERROR(INDEX(O:O,SMALL(IF(O$20:O$177<>"", ROW($20:$177)),$A17)),"")} | P17: {=IFERROR(INDEX(P:P,SMALL(IF(P$20:P$177<>"", ROW($20:$177)),$A17)),"")} | Q17: {=IFERROR(INDEX(Q:Q,SMALL(IF(Q$20:Q$177<>"", ROW($20:$177)),$A17)),"")} | R17: {=IFERROR(INDEX(R:R,SMALL(IF(R$20:R$177<>"", ROW($20:$177)),$A17)),"")} | S17: {=IFERROR(INDEX(S:S,SMALL(IF(S$20:S$177<>"", ROW($20:$177)),$A17)),"")} | T17: {=IFERROR(INDEX(T:T,SMALL(IF(T$20:T$177<>"", ROW($20:$177)),$A17)),"")} | U17: {=IFERROR(INDEX(U:U,SMALL(IF(U$20:U$177<>"", ROW($20:$177)),$A17)),"")} | V17: {=IFERROR(INDEX(V:V,SMALL(IF(V$20:V$177<>"", ROW($20:$177)),$A17)),"")} | W17: {=IFERROR(INDEX(W:W,SMALL(IF(W$20:W$177<>"", ROW($20:$177)),$A17)),"")}
B19: Referral | C19: KO Trigger | D19: Referral | E19: KO Trigger | F19: Referral | G19: KO Trigger | H19: Referral | I19: KO Trigger | J19: Referral | K19: KO Trigger | L19: Referral | M19: KO Trigger | N19: Referral | O19: KO Trigger | P19: Referral | Q19: KO Trigger | R19: Referral | S19: KO Trigger | T19: Referral | U19: KO Trigger | V19: Referral | W19: KO Trigger
A20: =Fragenkatalog!B7 -> Stamm-Daten1 | D20: =LEFT(IFERROR(INDEX(Fragenkatalog!$BR7,MATCH('Referral Stati'!$D$19,Fragenkatalog!AU7,0)),""),250) | E20: =LEFT(IFERROR(INDEX(Fragenkatalog!$BR7,MATCH('Referral Stati'!$E$19,Fragenkatalog!AV7,0)),""),250) | F20: =LEFT(IFERROR(INDEX(Fragenkatalog!$BR7,MATCH('Referral Stati'!$F$19,Fragenkatalog!AO7,0)),""),250) | G20: =LEFT(IFERROR(INDEX(Fragenkatalog!$BR7,MATCH('Referral Stati'!$G$19,Fragenkatalog!AP7,0)),""),250) | J20: {=LEFT(IFERROR(INDEX(Fragenkatalog!BR7,MATCH('Referral Stati'!$J$19,Fragenkatalog!W7,0)),""),250)} | K20: {=LEFT(IFERROR(INDEX(Fragenkatalog!BR7,MATCH('Referral Stati'!$K$19,Fragenkatalog!X7,0)),""),250)} | L20: =LEFT(IFERROR(INDEX(Fragenkatalog!$BR7,MATCH('Referral Stati'!$L$19,Fragenkatalog!Q7,0)),""),250) | M20: =LEFT(IFERROR(INDEX(Fragenkatalog!$BR7,MATCH('Referral Stati'!$M$19,Fragenkatalog!R7,0)),""),250) | N20: =LEFT(IFERROR(INDEX(Fragenkatalog!$BR7,MATCH('Referral Stati'!$N$19,Fragenkatalog!AI7,0)),""),250) | O20: =LEFT(IFERROR(INDEX(Fragenkatalog!$BR7,MATCH('Referral Stati'!$O$19,Fragenkatalog!AJ7,0)),""),250) | P20: =LEFT(IFERROR(INDEX(Fragenkatalog!$BR7,MATCH('Referral Stati'!$P$19,Fragenkatalog!AC7,0)),""),250) | Q20: =LEFT(IFERROR(INDEX(Fragenkatalog!$BR7,MATCH('Referral Stati'!$Q$19,Fragenkatalog!AD7,0)),""),250) | R20: =LEFT(IFERROR(INDEX(Fragenkatalog!$BR7,MATCH('Referral Stati'!$R$19,Fragenkatalog!BA7,0)),""),250) | S20: =LEFT(IFERROR(INDEX(Fragenkatalog!$BR7,MATCH('Referral Stati'!$S$19,Fragenkatalog!BB7,0)),""),250) | T20: =LEFT(IFERROR(INDEX(Fragenkatalog!$BR7,MATCH('Referral Stati'!$T$19,Fragenkatalog!BG7,0)),""),250) | U20: =LEFT(IFERROR(INDEX(Fragenkatalog!$BR7,MATCH('Referral Stati'!$U$19,Fragenkatalog!BH7,0)),""),250) | V20: =LEFT(IFERROR(INDEX(Fragenkatalog!$BR7,MATCH('Referral Stati'!$V$19,Fragenkatalog!BM7,0)),""),250) | W20: =LEFT(IFERROR(INDEX(Fragenkatalog!$BR7,MATCH('Referral Stati'!$U$19,Fragenkatalog!BN7,0)),""),250)
A21: =Fragenkatalog!B8 -> StammDaten2 | D21: =LEFT(IFERROR(INDEX(Fragenkatalog!$BR8,MATCH('Referral Stati'!$D$19,Fragenkatalog!AU8,0)),""),250) | E21: =LEFT(IFERROR(INDEX(Fragenkatalog!$BR8,MATCH('Referral Stati'!$E$19,Fragenkatalog!AV8,0)),""),250) | F21: =LEFT(IFERROR(INDEX(Fragenkatalog!$BR8,MATCH('Referral Stati'!$F$19,Fragenkatalog!AO8,0)),""),250) | G21: =LEFT(IFERROR(INDEX(Fragenkatalog!$BR8,MATCH('Referral Stati'!$G$19,Fragenkatalog!AP8,0)),""),250) | J21: {=LEFT(IFERROR(INDEX(Fragenkatalog!BR8,MATCH('Referral Stati'!$J$19,Fragenkatalog!W8,0)),""),250)} | K21: {=LEFT(IFERROR(INDEX(Fragenkatalog!BR8,MATCH('Referral Stati'!$K$19,Fragenkatalog!X8,0)),""),250)} | L21: =LEFT(IFERROR(INDEX(Fragenkatalog!$BR8,MATCH('Referral Stati'!$L$19,Fragenkatalog!Q8,0)),""),250) | M21: =LEFT(IFERROR(INDEX(Fragenkatalog!$BR8,MATCH('Referral Stati'!$M$19,Fragenkatalog!R8,0)),""),250) | N21: =LEFT(IFERROR(INDEX(Fragenkatalog!$BR8,MATCH('Referral Stati'!$N$19,Fragenkatalog!AI8,0)),""),250) | O21: =LEFT(IFERROR(INDEX(Fragenkatalog!$BR8,MATCH('Referral Stati'!$O$19,Fragenkatalog!AJ8,0)),""),250) | P21: =LEFT(IFERROR(INDEX(Fragenkatalog!$BR8,MATCH('Referral Stati'!$P$19,Fragenkatalog!AC8,0)),""),250) | Q21: =LEFT(IFERROR(INDEX(Fragenkatalog!$BR8,MATCH('Referral Stati'!$Q$19,Fragenkatalog!AD8,0)),""),250) | R21: =LEFT(IFERROR(INDEX(Fragenkatalog!$BR8,MATCH('Referral Stati'!$R$19,Fragenkatalog!BA8,0)),""),250) | S21: =LEFT(IFERROR(INDEX(Fragenkatalog!$BR8,MATCH('Referral Stati'!$S$19,Fragenkatalog!BB8,0)),""),250) | T21: =LEFT(IFERROR(INDEX(Fragenkatalog!$BR8,MATCH('Referral Stati'!$T$19,Fragenkatalog!BG8,0)),""),250) | U21: =LEFT(IFERROR(INDEX(Fragenkatalog!$BR8,MATCH('Referral Stati'!$U$19,Fragenkatalog!BH8,0)),""),250) | V21: =LEFT(IFERROR(INDEX(Fragenkatalog!$BR8,MATCH('Referral Stati'!$V$19,Fragenkatalog!BM8,0)),""),250) | W21: =LEFT(IFERROR(INDEX(Fragenkatalog!$BR8,MATCH('Referral Stati'!$U$19,Fragenkatalog!BN8,0)),""),250)
A22: =Fragenkatalog!B9 -> StammDaten10 | D22: =LEFT(IFERROR(INDEX(Fragenkatalog!$BR9,MATCH('Referral Stati'!$D$19,Fragenkatalog!AU9,0)),""),250) | E22: =LEFT(IFERROR(INDEX(Fragenkatalog!$BR9,MATCH('Referral Stati'!$E$19,Fragenkatalog!AV9,0)),""),250) | F22: =LEFT(IFERROR(INDEX(Fragenkatalog!$BR9,MATCH('Referral Stati'!$F$19,Fragenkatalog!AO9,0)),""),250) | G22: =LEFT(IFERROR(INDEX(Fragenkatalog!$BR9,MATCH('Referral Stati'!$G$19,Fragenkatalog!AP9,0)),""),250) | J22: {=LEFT(IFERROR(INDEX(Fragenkatalog!BR9,MATCH('Referral Stati'!$J$19,Fragenkatalog!W9,0)),""),250)} | K22: {=LEFT(IFERROR(INDEX(Fragenkatalog!BR9,MATCH('Referral Stati'!$K$19,Fragenkatalog!X9,0)),""),250)} | L22: =LEFT(IFERROR(INDEX(Fragenkatalog!$BR9,MATCH('Referral Stati'!$L$19,Fragenkatalog!Q9,0)),""),250) | M22: =LEFT(IFERROR(INDEX(Fragenkatalog!$BR9,MATCH('Referral Stati'!$M$19,Fragenkatalog!R9,0)),""),250) | N22: =LEFT(IFERROR(INDEX(Fragenkatalog!$BR9,MATCH('Referral Stati'!$N$19,Fragenkatalog!AI9,0)),""),250) | O22: =LEFT(IFERROR(INDEX(Fragenkatalog!$BR9,MATCH('Referral Stati'!$O$19,Fragenkatalog!AJ9,0)),""),250) | P22: =LEFT(IFERROR(INDEX(Fragenkatalog!$BR9,MATCH('Referral Stati'!$P$19,Fragenkatalog!AC9,0)),""),250) | Q22: =LEFT(IFERROR(INDEX(Fragenkatalog!$BR9,MATCH('Referral Stati'!$Q$19,Fragenkatalog!AD9,0)),""),250) | R22: =LEFT(IFERROR(INDEX(Fragenkatalog!$BR9,MATCH('Referral Stati'!$R$19,Fragenkatalog!BA9,0)),""),250) | S22: =LEFT(IFERROR(INDEX(Fragenkatalog!$BR9,MATCH('Referral Stati'!$S$19,Fragenkatalog!BB9,0)),""),250) | T22: =LEFT(IFERROR(INDEX(Fragenkatalog!$BR9,MATCH('Referral Stati'!$T$19,Fragenkatalog!BG9,0)),""),250) | U22: =LEFT(IFERROR(INDEX(Fragenkatalog!$BR9,MATCH('Referral Stati'!$U$19,Fragenkatalog!BH9,0)),""),250) | V22: =LEFT(IFERROR(INDEX(Fragenkatalog!$BR9,MATCH('Referral Stati'!$V$19,Fragenkatalog!BM9,0)),""),250) | W22: =LEFT(IFERROR(INDEX(Fragenkatalog!$BR9,MATCH('Referral Stati'!$U$19,Fragenkatalog!BN9,0)),""),250)
A23: =Fragenkatalog!B10 -> StammDaten901 | D23: =LEFT(IFERROR(INDEX(Fragenkatalog!$BR10,MATCH('Referral Stati'!$D$19,Fragenkatalog!AU10,0)),""),250) | E23: =LEFT(IFERROR(INDEX(Fragenkatalog!$BR10,MATCH('Referral Stati'!$E$19,Fragenkatalog!AV10,0)),""),250) | F23: =LEFT(IFERROR(INDEX(Fragenkatalog!$BR10,MATCH('Referral Stati'!$F$19,Fragenkatalog!AO10,0)),""),250) | G23: =LEFT(IFERROR(INDEX(Fragenkatalog!$BR10,MATCH('Referral Stati'!$G$19,Fragenkatalog!AP10,0)),""),250) | J23: {=LEFT(IFERROR(INDEX(Fragenkatalog!BR10,MATCH('Referral Stati'!$J$19,Fragenkatalog!W10,0)),""),250)} | K23: {=LEFT(IFERROR(INDEX(Fragenkatalog!BR10,MATCH('Referral Stati'!$K$19,Fragenkatalog!X10,0)),""),250)} | L23: =LEFT(IFERROR(INDEX(Fragenkatalog!$BR10,MATCH('Referral Stati'!$L$19,Fragenkatalog!Q10,0)),""),250) | M23: =LEFT(IFERROR(INDEX(Fragenkatalog!$BR10,MATCH('Referral Stati'!$M$19,Fragenkatalog!R10,0)),""),250) | N23: =LEFT(IFERROR(INDEX(Fragenkatalog!$BR10,MATCH('Referral Stati'!$N$19,Fragenkatalog!AI10,0)),""),250) | O23: =LEFT(IFERROR(INDEX(Fragenkatalog!$BR10,MATCH('Referral Stati'!$O$19,Fragenkatalog!AJ10,0)),""),250) | P23: =LEFT(IFERROR(INDEX(Fragenkatalog!$BR10,MATCH('Referral Stati'!$P$19,Fragenkatalog!AC10,0)),""),250) | Q23: =LEFT(IFERROR(INDEX(Fragenkatalog!$BR10,MATCH('Referral Stati'!$Q$19,Fragenkatalog!AD10,0)),""),250) | R23: =LEFT(IFERROR(INDEX(Fragenkatalog!$BR10,MATCH('Referral Stati'!$R$19,Fragenkatalog!BA10,0)),""),250) | S23: =LEFT(IFERROR(INDEX(Fragenkatalog!$BR10,MATCH('Referral Stati'!$S$19,Fragenkatalog!BB10,0)),""),250) | T23: =LEFT(IFERROR(INDEX(Fragenkatalog!$BR10,MATCH('Referral Stati'!$T$19,Fragenkatalog!BG10,0)),""),250) | U23: =LEFT(IFERROR(INDEX(Fragenkatalog!$BR10,MATCH('Referral Stati'!$U$19,Fragenkatalog!BH10,0)),""),250) | V23: =LEFT(IFERROR(INDEX(Fragenkatalog!$BR10,MATCH('Referral Stati'!$V$19,Fragenkatalog!BM10,0)),""),250) | W23: =LEFT(IFERROR(INDEX(Fragenkatalog!$BR10,MATCH('Referral Stati'!$U$19,Fragenkatalog!BN10,0)),""),250)
A24: =Fragenkatalog!B11 -> RisikoFragen127 | D24: =LEFT(IFERROR(INDEX(Fragenkatalog!$BR11,MATCH('Referral Stati'!$D$19,Fragenkatalog!AU11,0)),""),250) | E24: =LEFT(IFERROR(INDEX(Fragenkatalog!$BR11,MATCH('Referral Stati'!$E$19,Fragenkatalog!AV11,0)),""),250) | F24: =LEFT(IFERROR(INDEX(Fragenkatalog!$BR11,MATCH('Referral Stati'!$F$19,Fragenkatalog!AO11,0)),""),250) | G24: =LEFT(IFERROR(INDEX(Fragenkatalog!$BR11,MATCH('Referral Stati'!$G$19,Fragenkatalog!AP11,0)),""),250) | J24: {=LEFT(IFERROR(INDEX(Fragenkatalog!BR11,MATCH('Referral Stati'!$J$19,Fragenkatalog!W11,0)),""),250)} | K24: {=LEFT(IFERROR(INDEX(Fragenkatalog!BR11,MATCH('Referral Stati'!$K$19,Fragenkatalog!X11,0)),""),250)} | L24: =LEFT(IFERROR(INDEX(Fragenkatalog!$BR11,MATCH('Referral Stati'!$L$19,Fragenkatalog!Q11,0)),""),250) | M24: =LEFT(IFERROR(INDEX(Fragenkatalog!$BR11,MATCH('Referral Stati'!$M$19,Fragenkatalog!R11,0)),""),250) | N24: =LEFT(IFERROR(INDEX(Fragenkatalog!$BR11,MATCH('Referral Stati'!$N$19,Fragenkatalog!AI11,0)),""),250) | O24: =LEFT(IFERROR(INDEX(Fragenkatalog!$BR11,MATCH('Referral Stati'!$O$19,Fragenkatalog!AJ11,0)),""),250) | P24: =LEFT(IFERROR(INDEX(Fragenkatalog!$BR11,MATCH('Referral Stati'!$P$19,Fragenkatalog!AC11,0)),""),250) | Q24: =LEFT(IFERROR(INDEX(Fragenkatalog!$BR11,MATCH('Referral Stati'!$Q$19,Fragenkatalog!AD11,0)),""),250) | R24: =LEFT(IFERROR(INDEX(Fragenkatalog!$BR11,MATCH('Referral Stati'!$R$19,Fragenkatalog!BA11,0)),""),250) | S24: =LEFT(IFERROR(INDEX(Fragenkatalog!$BR11,MATCH('Referral Stati'!$S$19,Fragenkatalog!BB11,0)),""),250) | T24: =LEFT(IFERROR(INDEX(Fragenkatalog!$BR11,MATCH('Referral Stati'!$T$19,Fragenkatalog!BG11,0)),""),250) | U24: =LEFT(IFERROR(INDEX(Fragenkatalog!$BR11,MATCH('Referral Stati'!$U$19,Fragenkatalog!BH11,0)),""),250) | V24: =LEFT(IFERROR(INDEX(Fragenkatalog!$BR11,MATCH('Referral Stati'!$V$19,Fragenkatalog!BM11,0)),""),250) | W24: =LEFT(IFERROR(INDEX(Fragenkatalog!$BR11,MATCH('Referral Stati'!$U$19,Fragenkatalog!BN11,0)),""),250)
A25: =Fragenkatalog!B12 -> RisikoFragenVereine103 | D25: =LEFT(IFERROR(INDEX(Fragenkatalog!$BR12,MATCH('Referral Stati'!$D$19,Fragenkatalog!AU12,0)),""),250) | E25: =LEFT(IFERROR(INDEX(Fragenkatalog!$BR12,MATCH('Referral Stati'!$E$19,Fragenkatalog!AV12,0)),""),250) | F25: =LEFT(IFERROR(INDEX(Fragenkatalog!$BR12,MATCH('Referral Stati'!$F$19,Fragenkatalog!AO12,0)),""),250) | G25: =LEFT(IFERROR(INDEX(Fragenkatalog!$BR12,MATCH('Referral Stati'!$G$19,Fragenkatalog!AP12,0)),""),250) | J25: {=LEFT(IFERROR(INDEX(Fragenkatalog!BR12,MATCH('Referral Stati'!$J$19,Fragenkatalog!W12,0)),""),250)} | K25: {=LEFT(IFERROR(INDEX(Fragenkatalog!BR12,MATCH('Referral Stati'!$K$19,Fragenkatalog!X12,0)),""),250)} | L25: =LEFT(IFERROR(INDEX(Fragenkatalog!$BR12,MATCH('Referral Stati'!$L$19,Fragenkatalog!Q12,0)),""),250) | M25: =LEFT(IFERROR(INDEX(Fragenkatalog!$BR12,MATCH('Referral Stati'!$M$19,Fragenkatalog!R12,0)),""),250) | N25: =LEFT(IFERROR(INDEX(Fragenkatalog!$BR12,MATCH('Referral Stati'!$N$19,Fragenkatalog!AI12,0)),""),250) | O25: =LEFT(IFERROR(INDEX(Fragenkatalog!$BR12,MATCH('Referral Stati'!$O$19,Fragenkatalog!AJ12,0)),""),250) | P25: =LEFT(IFERROR(INDEX(Fragenkatalog!$BR12,MATCH('Referral Stati'!$P$19,Fragenkatalog!AC12,0)),""),250) | Q25: =LEFT(IFERROR(INDEX(Fragenkatalog!$BR12,MATCH('Referral Stati'!$Q$19,Fragenkatalog!AD12,0)),""),250) | R25: =LEFT(IFERROR(INDEX(Fragenkatalog!$BR12,MATCH('Referral Stati'!$R$19,Fragenkatalog!BA12,0)),""),250) | S25: =LEFT(IFERROR(INDEX(Fragenkatalog!$BR12,MATCH('Referral Stati'!$S$19,Fragenkatalog!BB12,0)),""),250) | T25: =LEFT(IFERROR(INDEX(Fragenkatalog!$BR12,MATCH('Referral Stati'!$T$19,Fragenkatalog!BG12,0)),""),250) | U25: =LEFT(IFERROR(INDEX(Fragenkatalog!$BR12,MATCH('Referral Stati'!$U$19,Fragenkatalog!BH12,0)),""),250) | V25: =LEFT(IFERROR(INDEX(Fragenkatalog!$BR12,MATCH('Referral Stati'!$V$19,Fragenkatalog!BM12,0)),""),250) | W25: =LEFT(IFERROR(INDEX(Fragenkatalog!$BR12,MATCH('Referral Stati'!$U$19,Fragenkatalog!BN12,0)),""),250)
A26: =Fragenkatalog!B13 -> RisikoFragen11 | D26: =LEFT(IFERROR(INDEX(Fragenkatalog!$BR13,MATCH('Referral Stati'!$D$19,Fragenkatalog!AU13,0)),""),250) | E26: =LEFT(IFERROR(INDEX(Fragenkatalog!$BR13,MATCH('Referral Stati'!$E$19,Fragenkatalog!AV13,0)),""),250) | F26: =LEFT(IFERROR(INDEX(Fragenkatalog!$BR13,MATCH('Referral Stati'!$F$19,Fragenkatalog!AO13,0)),""),250) | G26: =LEFT(IFERROR(INDEX(Fragenkatalog!$BR13,MATCH('Referral Stati'!$G$19,Fragenkatalog!AP13,0)),""),250) | J26: {=LEFT(IFERROR(INDEX(Fragenkatalog!BR13,MATCH('Referral Stati'!$J$19,Fragenkatalog!W13,0)),""),250)} | K26: {=LEFT(IFERROR(INDEX(Fragenkatalog!BR13,MATCH('Referral Stati'!$K$19,Fragenkatalog!X13,0)),""),250)} | L26: =LEFT(IFERROR(INDEX(Fragenkatalog!$BR13,MATCH('Referral Stati'!$L$19,Fragenkatalog!Q13,0)),""),250) | M26: =LEFT(IFERROR(INDEX(Fragenkatalog!$BR13,MATCH('Referral Stati'!$M$19,Fragenkatalog!R13,0)),""),250) | N26: =LEFT(IFERROR(INDEX(Fragenkatalog!$BR13,MATCH('Referral Stati'!$N$19,Fragenkatalog!AI13,0)),""),250) | O26: =LEFT(IFERROR(INDEX(Fragenkatalog!$BR13,MATCH('Referral Stati'!$O$19,Fragenkatalog!AJ13,0)),""),250) | P26: =LEFT(IFERROR(INDEX(Fragenkatalog!$BR13,MATCH('Referral Stati'!$P$19,Fragenkatalog!AC13,0)),""),250) | Q26: =LEFT(IFERROR(INDEX(Fragenkatalog!$BR13,MATCH('Referral Stati'!$Q$19,Fragenkatalog!AD13,0)),""),250) | R26: =LEFT(IFERROR(INDEX(Fragenkatalog!$BR13,MATCH('Referral Stati'!$R$19,Fragenkatalog!BA13,0)),""),250) | S26: =LEFT(IFERROR(INDEX(Fragenkatalog!$BR13,MATCH('Referral Stati'!$S$19,Fragenkatalog!BB13,0)),""),250) | T26: =LEFT(IFERROR(INDEX(Fragenkatalog!$BR13,MATCH('Referral Stati'!$T$19,Fragenkatalog!BG13,0)),""),250) | U26: =LEFT(IFERROR(INDEX(Fragenkatalog!$BR13,MATCH('Referral Stati'!$U$19,Fragenkatalog!BH13,0)),""),250) | V26: =LEFT(IFERROR(INDEX(Fragenkatalog!$BR13,MATCH('Referral Stati'!$V$19,Fragenkatalog!BM13,0)),""),250) | W26: =LEFT(IFERROR(INDEX(Fragenkatalog!$BR13,MATCH('Referral Stati'!$U$19,Fragenkatalog!BN13,0)),""),250)
A27: =Fragenkatalog!B14 -> RisikoFragen2 | D27: =LEFT(IFERROR(INDEX(Fragenkatalog!$BR14,MATCH('Referral Stati'!$D$19,Fragenkatalog!AU14,0)),""),250) | E27: =LEFT(IFERROR(INDEX(Fragenkatalog!$BR14,MATCH('Referral Stati'!$E$19,Fragenkatalog!AV14,0)),""),250) | F27: =LEFT(IFERROR(INDEX(Fragenkatalog!$BR14,MATCH('Referral Stati'!$F$19,Fragenkatalog!AO14,0)),""),250) | G27: =LEFT(IFERROR(INDEX(Fragenkatalog!$BR14,MATCH('Referral Stati'!$G$19,Fragenkatalog!AP14,0)),""),250) | J27: {=LEFT(IFERROR(INDEX(Fragenkatalog!BR14,MATCH('Referral Stati'!$J$19,Fragenkatalog!W14,0)),""),250)} | K27: {=LEFT(IFERROR(INDEX(Fragenkatalog!BR14,MATCH('Referral Stati'!$K$19,Fragenkatalog!X14,0)),""),250)} | L27: =LEFT(IFERROR(INDEX(Fragenkatalog!$BR14,MATCH('Referral Stati'!$L$19,Fragenkatalog!Q14,0)),""),250) | M27: =LEFT(IFERROR(INDEX(Fragenkatalog!$BR14,MATCH('Referral Stati'!$M$19,Fragenkatalog!R14,0)),""),250) | N27: =LEFT(IFERROR(INDEX(Fragenkatalog!$BR14,MATCH('Referral Stati'!$N$19,Fragenkatalog!AI14,0)),""),250) | O27: =LEFT(IFERROR(INDEX(Fragenkatalog!$BR14,MATCH('Referral Stati'!$O$19,Fragenkatalog!AJ14,0)),""),250) | P27: =LEFT(IFERROR(INDEX(Fragenkatalog!$BR14,MATCH('Referral Stati'!$P$19,Fragenkatalog!AC14,0)),""),250) | Q27: =LEFT(IFERROR(INDEX(Fragenkatalog!$BR14,MATCH('Referral Stati'!$Q$19,Fragenkatalog!AD14,0)),""),250) | R27: =LEFT(IFERROR(INDEX(Fragenkatalog!$BR14,MATCH('Referral Stati'!$R$19,Fragenkatalog!BA14,0)),""),250) | S27: =LEFT(IFERROR(INDEX(Fragenkatalog!$BR14,MATCH('Referral Stati'!$S$19,Fragenkatalog!BB14,0)),""),250) | T27: =LEFT(IFERROR(INDEX(Fragenkatalog!$BR14,MATCH('Referral Stati'!$T$19,Fragenkatalog!BG14,0)),""),250) | U27: =LEFT(IFERROR(INDEX(Fragenkatalog!$BR14,MATCH('Referral Stati'!$U$19,Fragenkatalog!BH14,0)),""),250) | V27: =LEFT(IFERROR(INDEX(Fragenkatalog!$BR14,MATCH('Referral Stati'!$V$19,Fragenkatalog!BM14,0)),""),250) | W27: =LEFT(IFERROR(INDEX(Fragenkatalog!$BR14,MATCH('Referral Stati'!$U$19,Fragenkatalog!BN14,0)),""),250)
A28: =Fragenkatalog!B15 -> RisikoFragen9 | D28: =LEFT(IFERROR(INDEX(Fragenkatalog!$BR15,MATCH('Referral Stati'!$D$19,Fragenkatalog!AU15,0)),""),250) | E28: =LEFT(IFERROR(INDEX(Fragenkatalog!$BR15,MATCH('Referral Stati'!$E$19,Fragenkatalog!AV15,0)),""),250) | F28: =LEFT(IFERROR(INDEX(Fragenkatalog!$BR15,MATCH('Referral Stati'!$F$19,Fragenkatalog!AO15,0)),""),250) | G28: =LEFT(IFERROR(INDEX(Fragenkatalog!$BR15,MATCH('Referral Stati'!$G$19,Fragenkatalog!AP15,0)),""),250) | J28: {=LEFT(IFERROR(INDEX(Fragenkatalog!BR15,MATCH('Referral Stati'!$J$19,Fragenkatalog!W15,0)),""),250)} | K28: {=LEFT(IFERROR(INDEX(Fragenkatalog!BR15,MATCH('Referral Stati'!$K$19,Fragenkatalog!X15,0)),""),250)} | L28: =LEFT(IFERROR(INDEX(Fragenkatalog!$BR15,MATCH('Referral Stati'!$L$19,Fragenkatalog!Q15,0)),""),250) | M28: =LEFT(IFERROR(INDEX(Fragenkatalog!$BR15,MATCH('Referral Stati'!$M$19,Fragenkatalog!R15,0)),""),250) | N28: =LEFT(IFERROR(INDEX(Fragenkatalog!$BR15,MATCH('Referral Stati'!$N$19,Fragenkatalog!AI15,0)),""),250) | O28: =LEFT(IFERROR(INDEX(Fragenkatalog!$BR15,MATCH('Referral Stati'!$O$19,Fragenkatalog!AJ15,0)),""),250) | P28: =LEFT(IFERROR(INDEX(Fragenkatalog!$BR15,MATCH('Referral Stati'!$P$19,Fragenkatalog!AC15,0)),""),250) | Q28: =LEFT(IFERROR(INDEX(Fragenkatalog!$BR15,MATCH('Referral Stati'!$Q$19,Fragenkatalog!AD15,0)),""),250) | R28: =LEFT(IFERROR(INDEX(Fragenkatalog!$BR15,MATCH('Referral Stati'!$R$19,Fragenkatalog!BA15,0)),""),250) | S28: =LEFT(IFERROR(INDEX(Fragenkatalog!$BR15,MATCH('Referral Stati'!$S$19,Fragenkatalog!BB15,0)),""),250) | T28: =LEFT(IFERROR(INDEX(Fragenkatalog!$BR15,MATCH('Referral Stati'!$T$19,Fragenkatalog!BG15,0)),""),250) | U28: =LEFT(IFERROR(INDEX(Fragenkatalog!$BR15,MATCH('Referral Stati'!$U$19,Fragenkatalog!BH15,0)),""),250) | V28: =LEFT(IFERROR(INDEX(Fragenkatalog!$BR15,MATCH('Referral Stati'!$V$19,Fragenkatalog!BM15,0)),""),250) | W28: =LEFT(IFERROR(INDEX(Fragenkatalog!$BR15,MATCH('Referral Stati'!$U$19,Fragenkatalog!BN15,0)),""),250)
A29: Gruendungsjahr | D29: =LEFT(IFERROR(INDEX(Fragenkatalog!$BR16,MATCH('Referral Stati'!$D$19,Fragenkatalog!AU16,0)),""),250) | E29: =LEFT(IFERROR(INDEX(Fragenkatalog!$BR16,MATCH('Referral Stati'!$E$19,Fragenkatalog!AV16,0)),""),250) | F29: =LEFT(IFERROR(INDEX(Fragenkatalog!$BR16,MATCH('Referral Stati'!$F$19,Fragenkatalog!AO16,0)),""),250) | G29: =LEFT(IFERROR(INDEX(Fragenkatalog!$BR16,MATCH('Referral Stati'!$G$19,Fragenkatalog!AP16,0)),""),250) | L29: =LEFT(IFERROR(INDEX(Fragenkatalog!$BR16,MATCH('Referral Stati'!$L$19,Fragenkatalog!Q16,0)),""),250) | M29: =LEFT(IFERROR(INDEX(Fragenkatalog!$BR16,MATCH('Referral Stati'!$M$19,Fragenkatalog!R16,0)),""),250) | N29: =LEFT(IFERROR(INDEX(Fragenkatalog!$BR16,MATCH('Referral Stati'!$N$19,Fragenkatalog!AI16,0)),""),250) | O29: =LEFT(IFERROR(INDEX(Fragenkatalog!$BR16,MATCH('Referral Stati'!$O$19,Fragenkatalog!AJ16,0)),""),250) | P29: =LEFT(IFERROR(INDEX(Fragenkatalog!$BR16,MATCH('Referral Stati'!$P$19,Fragenkatalog!AC16,0)),""),250) | Q29: =LEFT(IFERROR(INDEX(Fragenkatalog!$BR16,MATCH('Referral Stati'!$Q$19,Fragenkatalog!AD16,0)),""),250) | R29: =LEFT(IFERROR(INDEX(Fragenkatalog!$BR16,MATCH('Referral Stati'!$R$19,Fragenkatalog!BA16,0)),""),250) | S29: =LEFT(IFERROR(INDEX(Fragenkatalog!$BR16,MATCH('Referral Stati'!$S$19,Fragenkatalog!BB16,0)),""),250) | T29: =LEFT(IFERROR(INDEX(Fragenkatalog!$BR16,MATCH('Referral Stati'!$T$19,Fragenkatalog!BG16,0)),""),250) | U29: =LEFT(IFERROR(INDEX(Fragenkatalog!$BR16,MATCH('Referral Stati'!$U$19,Fragenkatalog!BH16,0)),""),250) | V29: =LEFT(IFERROR(INDEX(Fragenkatalog!$BR16,MATCH('Referral Stati'!$V$19,Fragenkatalog!BM16,0)),""),250) | W29: =LEFT(IFERROR(INDEX(Fragenkatalog!$BR16,MATCH('Referral Stati'!$U$19,Fragenkatalog!BN16,0)),""),250)
A30: =Fragenkatalog!B17 -> StammDaten3 | D30: =LEFT(IFERROR(INDEX(Fragenkatalog!$BR17,MATCH('Referral Stati'!$D$19,Fragenkatalog!AU17,0)),""),250) | E30: =LEFT(IFERROR(INDEX(Fragenkatalog!$BR17,MATCH('Referral Stati'!$E$19,Fragenkatalog!AV17,0)),""),250) | F30: =LEFT(IFERROR(INDEX(Fragenkatalog!$BR17,MATCH('Referral Stati'!$F$19,Fragenkatalog!AO17,0)),""),250) | G30: =LEFT(IFERROR(INDEX(Fragenkatalog!$BR17,MATCH('Referral Stati'!$G$19,Fragenkatalog!AP17,0)),""),250) | J30: {=LEFT(IFERROR(INDEX(Fragenkatalog!BR17,MATCH('Referral Stati'!$J$19,Fragenkatalog!W17,0)),""),250)} | K30: {=LEFT(IFERROR(INDEX(Fragenkatalog!BR17,MATCH('Referral Stati'!$K$19,Fragenkatalog!X17,0)),""),250)} | L30: =LEFT(IFERROR(INDEX(Fragenkatalog!$BR17,MATCH('Referral Stati'!$L$19,Fragenkatalog!Q17,0)),""),250) | M30: =LEFT(IFERROR(INDEX(Fragenkatalog!$BR17,MATCH('Referral Stati'!$M$19,Fragenkatalog!R17,0)),""),250) | N30: =LEFT(IFERROR(INDEX(Fragenkatalog!$BR17,MATCH('Referral Stati'!$N$19,Fragenkatalog!AI17,0)),""),250) | O30: =LEFT(IFERROR(INDEX(Fragenkatalog!$BR17,MATCH('Referral Stati'!$O$19,Fragenkatalog!AJ17,0)),""),250) | P30: =LEFT(IFERROR(INDEX(Fragenkatalog!$BR17,MATCH('Referral Stati'!$P$19,Fragenkatalog!AC17,0)),""),250) | Q30: =LEFT(IFERROR(INDEX(Fragenkatalog!$BR17,MATCH('Referral Stati'!$Q$19,Fragenkatalog!AD17,0)),""),250) | R30: =LEFT(IFERROR(INDEX(Fragenkatalog!$BR17,MATCH('Referral Stati'!$R$19,Fragenkatalog!BA17,0)),""),250) | S30: =LEFT(IFERROR(INDEX(Fragenkatalog!$BR17,MATCH('Referral Stati'!$S$19,Fragenkatalog!BB17,0)),""),250) | T30: =LEFT(IFERROR(INDEX(Fragenkatalog!$BR17,MATCH('Referral Stati'!$T$19,Fragenkatalog!BG17,0)),""),250) | U30: =LEFT(IFERROR(INDEX(Fragenkatalog!$BR17,MATCH('Referral Stati'!$U$19,Fragenkatalog!BH17,0)),""),250) | V30: =LEFT(IFERROR(INDEX(Fragenkatalog!$BR17,MATCH('Referral Stati'!$V$19,Fragenkatalog!BN17,0)),""),250) | W30: =LEFT(IFERROR(INDEX(Fragenkatalog!$BR17,MATCH('Referral Stati'!$U$19,Fragenkatalog!#REF!,0)),""),250)
A31: =Fragenkatalog!B18 -> Stamm-Daten4 | D31: =LEFT(IFERROR(INDEX(Fragenkatalog!$BR18,MATCH('Referral Stati'!$D$19,Fragenkatalog!AU18,0)),""),250) | E31: =LEFT(IFERROR(INDEX(Fragenkatalog!$BR18,MATCH('Referral Stati'!$E$19,Fragenkatalog!AV18,0)),""),250) | F31: =LEFT(IFERROR(INDEX(Fragenkatalog!$BR18,MATCH('Referral Stati'!$F$19,Fragenkatalog!AO18,0)),""),250) | G31: =LEFT(IFERROR(INDEX(Fragenkatalog!$BR18,MATCH('Referral Stati'!$G$19,Fragenkatalog!AP18,0)),""),250) | J31: {=LEFT(IFERROR(INDEX(Fragenkatalog!BR18,MATCH('Referral Stati'!$J$19,Fragenkatalog!W18,0)),""),250)} | K31: {=LEFT(IFERROR(INDEX(Fragenkatalog!BR18,MATCH('Referral Stati'!$K$19,Fragenkatalog!X18,0)),""),250)} | L31: =LEFT(IFERROR(INDEX(Fragenkatalog!$BR18,MATCH('Referral Stati'!$L$19,Fragenkatalog!Q18,0)),""),250) | M31: =LEFT(IFERROR(INDEX(Fragenkatalog!$BR18,MATCH('Referral Stati'!$M$19,Fragenkatalog!R18,0)),""),250) | N31: =LEFT(IFERROR(INDEX(Fragenkatalog!$BR18,MATCH('Referral Stati'!$N$19,Fragenkatalog!AI18,0)),""),250) | O31: =LEFT(IFERROR(INDEX(Fragenkatalog!$BR18,MATCH('Referral Stati'!$O$19,Fragenkatalog!AJ18,0)),""),250) | P31: =LEFT(IFERROR(INDEX(Fragenkatalog!$BR18,MATCH('Referral Stati'!$P$19,Fragenkatalog!AC18,0)),""),250) | Q31: =LEFT(IFERROR(INDEX(Fragenkatalog!$BR18,MATCH('Referral Stati'!$Q$19,Fragenkatalog!AD18,0)),""),250) | R31: =LEFT(IFERROR(INDEX(Fragenkatalog!$BR18,MATCH('Referral Stati'!$R$19,Fragenkatalog!BA18,0)),""),250) | S31: =LEFT(IFERROR(INDEX(Fragenkatalog!$BR18,MATCH('Referral Stati'!$S$19,Fragenkatalog!BB18,0)),""),250) | T31: =LEFT(IFERROR(INDEX(Fragenkatalog!$BR18,MATCH('Referral Stati'!$T$19,Fragenkatalog!BG18,0)),""),250) | U31: =LEFT(IFERROR(INDEX(Fragenkatalog!$BR18,MATCH('Referral Stati'!$U$19,Fragenkatalog!BH18,0)),""),250) | V31: =LEFT(IFERROR(INDEX(Fragenkatalog!$BR18,MATCH('Referral Stati'!$V$19,Fragenkatalog!BM18,0)),""),250) | W31: =LEFT(IFERROR(INDEX(Fragenkatalog!$BR18,MATCH('Referral Stati'!$U$19,Fragenkatalog!BN18,0)),""),250)
A32: =Fragenkatalog!B19 -> Stamm-Daten5 | D32: =LEFT(IFERROR(INDEX(Fragenkatalog!$BR19,MATCH('Referral Stati'!$D$19,Fragenkatalog!AU19,0)),""),250) | E32: =LEFT(IFERROR(INDEX(Fragenkatalog!$BR19,MATCH('Referral Stati'!$E$19,Fragenkatalog!AV19,0)),""),250) | F32: =LEFT(IFERROR(INDEX(Fragenkatalog!$BR19,MATCH('Referral Stati'!$F$19,Fragenkatalog!AO19,0)),""),250) | G32: =LEFT(IFERROR(INDEX(Fragenkatalog!$BR19,MATCH('Referral Stati'!$G$19,Fragenkatalog!AP19,0)),""),250) | J32: {=LEFT(IFERROR(INDEX(Fragenkatalog!BR19,MATCH('Referral Stati'!$J$19,Fragenkatalog!W19,0)),""),250)} | K32: {=LEFT(IFERROR(INDEX(Fragenkatalog!BR19,MATCH('Referral Stati'!$K$19,Fragenkatalog!X19,0)),""),250)} | L32: =LEFT(IFERROR(INDEX(Fragenkatalog!$BR19,MATCH('Referral Stati'!$L$19,Fragenkatalog!Q19,0)),""),250) | M32: =LEFT(IFERROR(INDEX(Fragenkatalog!$BR19,MATCH('Referral Stati'!$M$19,Fragenkatalog!R19,0)),""),250) | N32: =LEFT(IFERROR(INDEX(Fragenkatalog!$BR19,MATCH('Referral Stati'!$N$19,Fragenkatalog!AI19,0)),""),250) | O32: =LEFT(IFERROR(INDEX(Fragenkatalog!$BR19,MATCH('Referral Stati'!$O$19,Fragenkatalog!AJ19,0)),""),250) | P32: =LEFT(IFERROR(INDEX(Fragenkatalog!$BR19,MATCH('Referral Stati'!$P$19,Fragenkatalog!AC19,0)),""),250) | Q32: =LEFT(IFERROR(INDEX(Fragenkatalog!$BR19,MATCH('Referral Stati'!$Q$19,Fragenkatalog!AD19,0)),""),250) | R32: =LEFT(IFERROR(INDEX(Fragenkatalog!$BR19,MATCH('Referral Stati'!$R$19,Fragenkatalog!BA19,0)),""),250) | S32: =LEFT(IFERROR(INDEX(Fragenkatalog!$BR19,MATCH('Referral Stati'!$S$19,Fragenkatalog!BB19,0)),""),250) | T32: =LEFT(IFERROR(INDEX(Fragenkatalog!$BR19,MATCH('Referral Stati'!$T$19,Fragenkatalog!BG19,0)),""),250) | U32: =LEFT(IFERROR(INDEX(Fragenkatalog!$BR19,MATCH('Referral Stati'!$U$19,Fragenkatalog!BH19,0)),""),250) | V32: =LEFT(IFERROR(INDEX(Fragenkatalog!$BR19,MATCH('Referral Stati'!$V$19,Fragenkatalog!BM19,0)),""),250) | W32: =LEFT(IFERROR(INDEX(Fragenkatalog!$BR19,MATCH('Referral Stati'!$U$19,Fragenkatalog!BN19,0)),""),250)
A33: =Fragenkatalog!B20 -> Stamm-Daten6 | D33: =LEFT(IFERROR(INDEX(Fragenkatalog!$BR20,MATCH('Referral Stati'!$D$19,Fragenkatalog!AU20,0)),""),250) | E33: =LEFT(IFERROR(INDEX(Fragenkatalog!$BR20,MATCH('Referral Stati'!$E$19,Fragenkatalog!AV20,0)),""),250) | F33: =LEFT(IFERROR(INDEX(Fragenkatalog!$BR20,MATCH('Referral Stati'!$F$19,Fragenkatalog!AO20,0)),""),250) | G33: =LEFT(IFERROR(INDEX(Fragenkatalog!$BR20,MATCH('Referral Stati'!$G$19,Fragenkatalog!AP20,0)),""),250) | J33: {=LEFT(IFERROR(INDEX(Fragenkatalog!BR20,MATCH('Referral Stati'!$J$19,Fragenkatalog!W20,0)),""),250)} | K33: {=LEFT(IFERROR(INDEX(Fragenkatalog!BR20,MATCH('Referral Stati'!$K$19,Fragenkatalog!X20,0)),""),250)} | L33: =LEFT(IFERROR(INDEX(Fragenkatalog!$BR20,MATCH('Referral Stati'!$L$19,Fragenkatalog!Q20,0)),""),250) | M33: =LEFT(IFERROR(INDEX(Fragenkatalog!$BR20,MATCH('Referral Stati'!$M$19,Fragenkatalog!R20,0)),""),250) | N33: =LEFT(IFERROR(INDEX(Fragenkatalog!$BR20,MATCH('Referral Stati'!$N$19,Fragenkatalog!AI20,0)),""),250) | O33: =LEFT(IFERROR(INDEX(Fragenkatalog!$BR20,MATCH('Referral Stati'!$O$19,Fragenkatalog!AJ20,0)),""),250) | P33: =LEFT(IFERROR(INDEX(Fragenkatalog!$BR20,MATCH('Referral Stati'!$P$19,Fragenkatalog!AC20,0)),""),250) | Q33: =LEFT(IFERROR(INDEX(Fragenkatalog!$BR20,MATCH('Referral Stati'!$Q$19,Fragenkatalog!AD20,0)),""),250) | R33: =LEFT(IFERROR(INDEX(Fragenkatalog!$BR20,MATCH('Referral Stati'!$R$19,Fragenkatalog!BA20,0)),""),250) | S33: =LEFT(IFERROR(INDEX(Fragenkatalog!$BR20,MATCH('Referral Stati'!$S$19,Fragenkatalog!BB20,0)),""),250) | T33: =LEFT(IFERROR(INDEX(Fragenkatalog!$BR20,MATCH('Referral Stati'!$T$19,Fragenkatalog!BG20,0)),""),250) | U33: =LEFT(IFERROR(INDEX(Fragenkatalog!$BR20,MATCH('Referral Stati'!$U$19,Fragenkatalog!BH20,0)),""),250) | V33: =LEFT(IFERROR(INDEX(Fragenkatalog!$BR20,MATCH('Referral Stati'!$V$19,Fragenkatalog!BM20,0)),""),250) | W33: =LEFT(IFERROR(INDEX(Fragenkatalog!$BR20,MATCH('Referral Stati'!$U$19,Fragenkatalog!BN20,0)),""),250)
A34: =Fragenkatalog!B21 -> RisikoFragen7 | D34: =LEFT(IFERROR(INDEX(Fragenkatalog!$BR21,MATCH('Referral Stati'!$D$19,Fragenkatalog!AU21,0)),""),250) | E34: =LEFT(IFERROR(INDEX(Fragenkatalog!$BR21,MATCH('Referral Stati'!$E$19,Fragenkatalog!AV21,0)),""),250) | F34: =LEFT(IFERROR(INDEX(Fragenkatalog!$BR21,MATCH('Referral Stati'!$F$19,Fragenkatalog!AO21,0)),""),250) | G34: =LEFT(IFERROR(INDEX(Fragenkatalog!$BR21,MATCH('Referral Stati'!$G$19,Fragenkatalog!AP21,0)),""),250) | J34: {=LEFT(IFERROR(INDEX(Fragenkatalog!BR21,MATCH('Referral Stati'!$J$19,Fragenkatalog!W21,0)),""),250)} | K34: {=LEFT(IFERROR(INDEX(Fragenkatalog!BR21,MATCH('Referral Stati'!$K$19,Fragenkatalog!X21,0)),""),250)} | L34: =LEFT(IFERROR(INDEX(Fragenkatalog!$BR21,MATCH('Referral Stati'!$L$19,Fragenkatalog!Q21,0)),""),250) | M34: =LEFT(IFERROR(INDEX(Fragenkatalog!$BR21,MATCH('Referral Stati'!$M$19,Fragenkatalog!R21,0)),""),250) | N34: =LEFT(IFERROR(INDEX(Fragenkatalog!$BR21,MATCH('Referral Stati'!$N$19,Fragenkatalog!AI21,0)),""),250) | O34: =LEFT(IFERROR(INDEX(Fragenkatalog!$BR21,MATCH('Referral Stati'!$O$19,Fragenkatalog!AJ21,0)),""),250) | P34: =LEFT(IFERROR(INDEX(Fragenkatalog!$BR21,MATCH('Referral Stati'!$P$19,Fragenkatalog!AC21,0)),""),250) | Q34: =LEFT(IFERROR(INDEX(Fragenkatalog!$BR21,MATCH('Referral Stati'!$Q$19,Fragenkatalog!AD21,0)),""),250) | R34: =LEFT(IFERROR(INDEX(Fragenkatalog!$BR21,MATCH('Referral Stati'!$R$19,Fragenkatalog!BA21,0)),""),250) | S34: =LEFT(IFERROR(INDEX(Fragenkatalog!$BR21,MATCH('Referral Stati'!$S$19,Fragenkatalog!BB21,0)),""),250) | T34: =LEFT(IFERROR(INDEX(Fragenkatalog!$BR21,MATCH('Referral Stati'!$T$19,Fragenkatalog!BG21,0)),""),250) | U34: =LEFT(IFERROR(INDEX(Fragenkatalog!$BR21,MATCH('Referral Stati'!$U$19,Fragenkatalog!BH21,0)),""),250) | V34: =LEFT(IFERROR(INDEX(Fragenkatalog!$BR21,MATCH('Referral Stati'!$V$19,Fragenkatalog!BM21,0)),""),250) | W34: =LEFT(IFERROR(INDEX(Fragenkatalog!$BR21,MATCH('Referral Stati'!$U$19,Fragenkatalog!BN21,0)),""),250)
A35: =Fragenkatalog!B22 -> RisikoFragen8 | D35: =LEFT(IFERROR(INDEX(Fragenkatalog!$BR22,MATCH('Referral Stati'!$D$19,Fragenkatalog!AU22,0)),""),250) | E35: =LEFT(IFERROR(INDEX(Fragenkatalog!$BR22,MATCH('Referral Stati'!$E$19,Fragenkatalog!AV22,0)),""),250) | F35: =LEFT(IFERROR(INDEX(Fragenkatalog!$BR22,MATCH('Referral Stati'!$F$19,Fragenkatalog!AO22,0)),""),250) | G35: =LEFT(IFERROR(INDEX(Fragenkatalog!$BR22,MATCH('Referral Stati'!$G$19,Fragenkatalog!AP22,0)),""),250) | J35: {=LEFT(IFERROR(INDEX(Fragenkatalog!BR22,MATCH('Referral Stati'!$J$19,Fragenkatalog!W22,0)),""),250)} | K35: {=LEFT(IFERROR(INDEX(Fragenkatalog!BR22,MATCH('Referral Stati'!$K$19,Fragenkatalog!X22,0)),""),250)} | L35: =LEFT(IFERROR(INDEX(Fragenkatalog!$BR22,MATCH('Referral Stati'!$L$19,Fragenkatalog!Q22,0)),""),250) | M35: =LEFT(IFERROR(INDEX(Fragenkatalog!$BR22,MATCH('Referral Stati'!$M$19,Fragenkatalog!R22,0)),""),250) | N35: =LEFT(IFERROR(INDEX(Fragenkatalog!$BR22,MATCH('Referral Stati'!$N$19,Fragenkatalog!AI22,0)),""),250) | O35: =LEFT(IFERROR(INDEX(Fragenkatalog!$BR22,MATCH('Referral Stati'!$O$19,Fragenkatalog!AJ22,0)),""),250) | P35: =LEFT(IFERROR(INDEX(Fragenkatalog!$BR22,MATCH('Referral Stati'!$P$19,Fragenkatalog!AC22,0)),""),250) | Q35: =LEFT(IFERROR(INDEX(Fragenkatalog!$BR22,MATCH('Referral Stati'!$Q$19,Fragenkatalog!AD22,0)),""),250) | R35: =LEFT(IFERROR(INDEX(Fragenkatalog!$BR22,MATCH('Referral Stati'!$R$19,Fragenkatalog!BA22,0)),""),250) | S35: =LEFT(IFERROR(INDEX(Fragenkatalog!$BR22,MATCH('Referral Stati'!$S$19,Fragenkatalog!BB22,0)),""),250) | T35: =LEFT(IFERROR(INDEX(Fragenkatalog!$BR22,MATCH('Referral Stati'!$T$19,Fragenkatalog!BG22,0)),""),250) | U35: =LEFT(IFERROR(INDEX(Fragenkatalog!$BR22,MATCH('Referral Stati'!$U$19,Fragenkatalog!BH22,0)),""),250) | V35: =LEFT(IFERROR(INDEX(Fragenkatalog!$BR22,MATCH('Referral Stati'!$V$19,Fragenkatalog!BM22,0)),""),250) | W35: =LEFT(IFERROR(INDEX(Fragenkatalog!$BR22,MATCH('Referral Stati'!$U$19,Fragenkatalog!BN22,0)),""),250)
A36: =Fragenkatalog!B23 -> RisikoFragen0a | D36: =LEFT(IFERROR(INDEX(Fragenkatalog!$BR23,MATCH('Referral Stati'!$D$19,Fragenkatalog!AU23,0)),""),250) | E36: =LEFT(IFERROR(INDEX(Fragenkatalog!$BR23,MATCH('Referral Stati'!$E$19,Fragenkatalog!AV23,0)),""),250) | F36: =LEFT(IFERROR(INDEX(Fragenkatalog!$BR23,MATCH('Referral Stati'!$F$19,Fragenkatalog!AO23,0)),""),250) -> Policenbeginn | G36: =LEFT(IFERROR(INDEX(Fragenkatalog!$BR23,MATCH('Referral Stati'!$G$19,Fragenkatalog!AP23,0)),""),250) | J36: {=LEFT(IFERROR(INDEX(Fragenkatalog!BR23,MATCH('Referral Stati'!$J$19,Fragenkatalog!W23,0)),""),250)} -> Policenbeginn | K36: {=LEFT(IFERROR(INDEX(Fragenkatalog!BR23,MATCH('Referral Stati'!$K$19,Fragenkatalog!X23,0)),""),250)} | L36: =LEFT(IFERROR(INDEX(Fragenkatalog!$BR23,MATCH('Referral Stati'!$L$19,Fragenkatalog!Q23,0)),""),250) -> Policenbeginn | M36: =LEFT(IFERROR(INDEX(Fragenkatalog!$BR23,MATCH('Referral Stati'!$M$19,Fragenkatalog!R23,0)),""),250) | N36: =LEFT(IFERROR(INDEX(Fragenkatalog!$BR23,MATCH('Referral Stati'!$N$19,Fragenkatalog!AI23,0)),""),250) -> Policenbeginn | O36: =LEFT(IFERROR(INDEX(Fragenkatalog!$BR23,MATCH('Referral Stati'!$O$19,Fragenkatalog!AJ23,0)),""),250) | P36: =LEFT(IFERROR(INDEX(Fragenkatalog!$BR23,MATCH('Referral Stati'!$P$19,Fragenkatalog!AC23,0)),""),250) -> Policenbeginn | Q36: =LEFT(IFERROR(INDEX(Fragenkatalog!$BR23,MATCH('Referral Stati'!$Q$19,Fragenkatalog!AD23,0)),""),250) | R36: =LEFT(IFERROR(INDEX(Fragenkatalog!$BR23,MATCH('Referral Stati'!$R$19,Fragenkatalog!BA23,0)),""),250) | S36: =LEFT(IFERROR(INDEX(Fragenkatalog!$BR23,MATCH('Referral Stati'!$S$19,Fragenkatalog!BB23,0)),""),250) -> Policenbeginn | T36: =LEFT(IFERROR(INDEX(Fragenkatalog!$BR23,MATCH('Referral Stati'!$T$19,Fragenkatalog!BG23,0)),""),250) | U36: =LEFT(IFERROR(INDEX(Fragenkatalog!$BR23,MATCH('Referral Stati'!$U$19,Fragenkatalog!BH23,0)),""),250) | V36: =LEFT(IFERROR(INDEX(Fragenkatalog!$BR23,MATCH('Referral Stati'!$V$19,Fragenkatalog!BM23,0)),""),250) | W36: =LEFT(IFERROR(INDEX(Fragenkatalog!$BR23,MATCH('Referral Stati'!$U$19,Fragenkatalog!BN23,0)),""),250)
A37: =Fragenkatalog!B24 -> RisikoFragen0b | D37: =LEFT(IFERROR(INDEX(Fragenkatalog!$BR24,MATCH('Referral Stati'!$D$19,Fragenkatalog!AU24,0)),""),250) | E37: =LEFT(IFERROR(INDEX(Fragenkatalog!$BR24,MATCH('Referral Stati'!$E$19,Fragenkatalog!AV24,0)),""),250) | F37: =LEFT(IFERROR(INDEX(Fragenkatalog!$BR24,MATCH('Referral Stati'!$F$19,Fragenkatalog!AO24,0)),""),250) | G37: =LEFT(IFERROR(INDEX(Fragenkatalog!$BR24,MATCH('Referral Stati'!$G$19,Fragenkatalog!AP24,0)),""),250) -> Policenende bzw. Laufzeit | J37: {=LEFT(IFERROR(INDEX(Fragenkatalog!BR24,MATCH('Referral Stati'!$J$19,Fragenkatalog!W24,0)),""),250)} | K37: {=LEFT(IFERROR(INDEX(Fragenkatalog!BR24,MATCH('Referral Stati'!$K$19,Fragenkatalog!X24,0)),""),250)} | L37: =LEFT(IFERROR(INDEX(Fragenkatalog!$BR24,MATCH('Referral Stati'!$L$19,Fragenkatalog!Q24,0)),""),250) | M37: =LEFT(IFERROR(INDEX(Fragenkatalog!$BR24,MATCH('Referral Stati'!$M$19,Fragenkatalog!R24,0)),""),250) | N37: =LEFT(IFERROR(INDEX(Fragenkatalog!$BR24,MATCH('Referral Stati'!$N$19,Fragenkatalog!AI24,0)),""),250) -> Policenende bzw. Laufzeit | O37: =LEFT(IFERROR(INDEX(Fragenkatalog!$BR24,MATCH('Referral Stati'!$O$19,Fragenkatalog!AJ24,0)),""),250) | P37: =LEFT(IFERROR(INDEX(Fragenkatalog!$BR24,MATCH('Referral Stati'!$P$19,Fragenkatalog!AC24,0)),""),250) -> Policenende bzw. Laufzeit | Q37: =LEFT(IFERROR(INDEX(Fragenkatalog!$BR24,MATCH('Referral Stati'!$Q$19,Fragenkatalog!AD24,0)),""),250) | R37: =LEFT(IFERROR(INDEX(Fragenkatalog!$BR24,MATCH('Referral Stati'!$R$19,Fragenkatalog!BA24,0)),""),250) | S37: =LEFT(IFERROR(INDEX(Fragenkatalog!$BR24,MATCH('Referral Stati'!$S$19,Fragenkatalog!BB24,0)),""),250) | T37: =LEFT(IFERROR(INDEX(Fragenkatalog!$BR24,MATCH('Referral Stati'!$T$19,Fragenkatalog!BG24,0)),""),250) | U37: =LEFT(IFERROR(INDEX(Fragenkatalog!$BR24,MATCH('Referral Stati'!$U$19,Fragenkatalog!BH24,0)),""),250) | V37: =LEFT(IFERROR(INDEX(Fragenkatalog!$BR24,MATCH('Referral Stati'!$V$19,Fragenkatalog!BM24,0)),""),250) | W37: =LEFT(IFERROR(INDEX(Fragenkatalog!$BR24,MATCH('Referral Stati'!$U$19,Fragenkatalog!BN24,0)),""),250) -> Policenende bzw. Laufzeit
A38: =Fragenkatalog!B25 -> RisikoFragen0c | D38: =LEFT(IFERROR(INDEX(Fragenkatalog!$BR25,MATCH('Referral Stati'!$D$19,Fragenkatalog!AU25,0)),""),250) | E38: =LEFT(IFERROR(INDEX(Fragenkatalog!$BR25,MATCH('Referral Stati'!$E$19,Fragenkatalog!AV25,0)),""),250) | F38: =LEFT(IFERROR(INDEX(Fragenkatalog!$BR25,MATCH('Referral Stati'!$F$19,Fragenkatalog!AO25,0)),""),250) | G38: =LEFT(IFERROR(INDEX(Fragenkatalog!$BR25,MATCH('Referral Stati'!$G$19,Fragenkatalog!AP25,0)),""),250) | J38: {=LEFT(IFERROR(INDEX(Fragenkatalog!BR25,MATCH('Referral Stati'!$J$19,Fragenkatalog!W25,0)),""),250)} | K38: {=LEFT(IFERROR(INDEX(Fragenkatalog!BR25,MATCH('Referral Stati'!$K$19,Fragenkatalog!X25,0)),""),250)} | L38: =LEFT(IFERROR(INDEX(Fragenkatalog!$BR25,MATCH('Referral Stati'!$L$19,Fragenkatalog!Q25,0)),""),250) | M38: =LEFT(IFERROR(INDEX(Fragenkatalog!$BR25,MATCH('Referral Stati'!$M$19,Fragenkatalog!R25,0)),""),250) | N38: =LEFT(IFERROR(INDEX(Fragenkatalog!$BR25,MATCH('Referral Stati'!$N$19,Fragenkatalog!AI25,0)),""),250) | O38: =LEFT(IFERROR(INDEX(Fragenkatalog!$BR25,MATCH('Referral Stati'!$O$19,Fragenkatalog!AJ25,0)),""),250) | P38: =LEFT(IFERROR(INDEX(Fragenkatalog!$BR25,MATCH('Referral Stati'!$P$19,Fragenkatalog!AC25,0)),""),250) | Q38: =LEFT(IFERROR(INDEX(Fragenkatalog!$BR25,MATCH('Referral Stati'!$Q$19,Fragenkatalog!AD25,0)),""),250) | R38: =LEFT(IFERROR(INDEX(Fragenkatalog!$BR25,MATCH('Referral Stati'!$R$19,Fragenkatalog!BA25,0)),""),250) | S38: =LEFT(IFERROR(INDEX(Fragenkatalog!$BR25,MATCH('Referral Stati'!$S$19,Fragenkatalog!BB25,0)),""),250) | T38: =LEFT(IFERROR(INDEX(Fragenkatalog!$BR25,MATCH('Referral Stati'!$T$19,Fragenkatalog!BG25,0)),""),250) | U38: =LEFT(IFERROR(INDEX(Fragenkatalog!$BR25,MATCH('Referral Stati'!$U$19,Fragenkatalog!BH25,0)),""),250) | V38: =LEFT(IFERROR(INDEX(Fragenkatalog!$BR25,MATCH('Referral Stati'!$V$19,Fragenkatalog!BM25,0)),""),250) | W38: =LEFT(IFERROR(INDEX(Fragenkatalog!$BR25,MATCH('Referral Stati'!$U$19,Fragenkatalog!BN25,0)),""),250)
A39: =Fragenkatalog!B26 -> RisikoFragen0d | D39: =LEFT(IFERROR(INDEX(Fragenkatalog!$BR26,MATCH('Referral Stati'!$D$19,Fragenkatalog!AU26,0)),""),250) | E39: =LEFT(IFERROR(INDEX(Fragenkatalog!$BR26,MATCH('Referral Stati'!$E$19,Fragenkatalog!AV26,0)),""),250) | F39: =LEFT(IFERROR(INDEX(Fragenkatalog!$BR26,MATCH('Referral Stati'!$F$19,Fragenkatalog!AO26,0)),""),250) | G39: =LEFT(IFERROR(INDEX(Fragenkatalog!$BR26,MATCH('Referral Stati'!$G$19,Fragenkatalog!AP26,0)),""),250) | J39: {=LEFT(IFERROR(INDEX(Fragenkatalog!BR26,MATCH('Referral Stati'!$J$19,Fragenkatalog!W26,0)),""),250)} | K39: {=LEFT(IFERROR(INDEX(Fragenkatalog!BR26,MATCH('Referral Stati'!$K$19,Fragenkatalog!X26,0)),""),250)} | L39: =LEFT(IFERROR(INDEX(Fragenkatalog!$BR26,MATCH('Referral Stati'!$L$19,Fragenkatalog!Q26,0)),""),250) | M39: =LEFT(IFERROR(INDEX(Fragenkatalog!$BR26,MATCH('Referral Stati'!$M$19,Fragenkatalog!R26,0)),""),250) | N39: =LEFT(IFERROR(INDEX(Fragenkatalog!$BR26,MATCH('Referral Stati'!$N$19,Fragenkatalog!AI26,0)),""),250) | O39: =LEFT(IFERROR(INDEX(Fragenkatalog!$BR26,MATCH('Referral Stati'!$O$19,Fragenkatalog!AJ26,0)),""),250) | P39: =LEFT(IFERROR(INDEX(Fragenkatalog!$BR26,MATCH('Referral Stati'!$P$19,Fragenkatalog!AC26,0)),""),250) | Q39: =LEFT(IFERROR(INDEX(Fragenkatalog!$BR26,MATCH('Referral Stati'!$Q$19,Fragenkatalog!AD26,0)),""),250) | R39: =LEFT(IFERROR(INDEX(Fragenkatalog!$BR26,MATCH('Referral Stati'!$R$19,Fragenkatalog!BA26,0)),""),250) | S39: =LEFT(IFERROR(INDEX(Fragenkatalog!$BR26,MATCH('Referral Stati'!$S$19,Fragenkatalog!BB26,0)),""),250) | T39: =LEFT(IFERROR(INDEX(Fragenkatalog!$BR26,MATCH('Referral Stati'!$T$19,Fragenkatalog!BG26,0)),""),250) | U39: =LEFT(IFERROR(INDEX(Fragenkatalog!$BR26,MATCH('Referral Stati'!$U$19,Fragenkatalog!BH26,0)),""),250) | V39: =LEFT(IFERROR(INDEX(Fragenkatalog!$BR26,MATCH('Referral Stati'!$V$19,Fragenkatalog!BM26,0)),""),250) | W39: =LEFT(IFERROR(INDEX(Fragenkatalog!$BR26,MATCH('Referral Stati'!$U$19,Fragenkatalog!BN26,0)),""),250)
A40: =Fragenkatalog!B27 -> RisikoFragen0e | D40: =LEFT(IFERROR(INDEX(Fragenkatalog!$BR27,MATCH('Referral Stati'!$D$19,Fragenkatalog!AU27,0)),""),250) | E40: =LEFT(IFERROR(INDEX(Fragenkatalog!$BR27,MATCH('Referral Stati'!$E$19,Fragenkatalog!AV27,0)),""),250) | F40: =LEFT(IFERROR(INDEX(Fragenkatalog!$BR27,MATCH('Referral Stati'!$F$19,Fragenkatalog!AO27,0)),""),250) | G40: =LEFT(IFERROR(INDEX(Fragenkatalog!$BR27,MATCH('Referral Stati'!$G$19,Fragenkatalog!AP27,0)),""),250) | J40: {=LEFT(IFERROR(INDEX(Fragenkatalog!BR27,MATCH('Referral Stati'!$J$19,Fragenkatalog!W27,0)),""),250)} | K40: {=LEFT(IFERROR(INDEX(Fragenkatalog!BR27,MATCH('Referral Stati'!$K$19,Fragenkatalog!X27,0)),""),250)} | L40: =LEFT(IFERROR(INDEX(Fragenkatalog!$BR27,MATCH('Referral Stati'!$L$19,Fragenkatalog!Q27,0)),""),250) | M40: =LEFT(IFERROR(INDEX(Fragenkatalog!$BR27,MATCH('Referral Stati'!$M$19,Fragenkatalog!R27,0)),""),250) | N40: =LEFT(IFERROR(INDEX(Fragenkatalog!$BR27,MATCH('Referral Stati'!$N$19,Fragenkatalog!AI27,0)),""),250) | O40: =LEFT(IFERROR(INDEX(Fragenkatalog!$BR27,MATCH('Referral Stati'!$O$19,Fragenkatalog!AJ27,0)),""),250) | P40: =LEFT(IFERROR(INDEX(Fragenkatalog!$BR27,MATCH('Referral Stati'!$P$19,Fragenkatalog!AC27,0)),""),250) | Q40: =LEFT(IFERROR(INDEX(Fragenkatalog!$BR27,MATCH('Referral Stati'!$Q$19,Fragenkatalog!AD27,0)),""),250) | R40: =LEFT(IFERROR(INDEX(Fragenkatalog!$BR27,MATCH('Referral Stati'!$R$19,Fragenkatalog!BA27,0)),""),250) | S40: =LEFT(IFERROR(INDEX(Fragenkatalog!$BR27,MATCH('Referral Stati'!$S$19,Fragenkatalog!BB27,0)),""),250) | T40: =LEFT(IFERROR(INDEX(Fragenkatalog!$BR27,MATCH('Referral Stati'!$T$19,Fragenkatalog!BG27,0)),""),250) | U40: =LEFT(IFERROR(INDEX(Fragenkatalog!$BR27,MATCH('Referral Stati'!$U$19,Fragenkatalog!BH27,0)),""),250) | V40: =LEFT(IFERROR(INDEX(Fragenkatalog!$BR27,MATCH('Referral Stati'!$V$19,Fragenkatalog!BM27,0)),""),250) | W40: =LEFT(IFERROR(INDEX(Fragenkatalog!$BR27,MATCH('Referral Stati'!$U$19,Fragenkatalog!BN27,0)),""),250)
A41: =Fragenkatalog!B28 -> RisikoFragen18 | D41: =LEFT(IFERROR(INDEX(Fragenkatalog!$BR28,MATCH('Referral Stati'!$D$19,Fragenkatalog!AU28,0)),""),250) | E41: =LEFT(IFERROR(INDEX(Fragenkatalog!$BR28,MATCH('Referral Stati'!$E$19,Fragenkatalog!AV28,0)),""),250) | F41: =LEFT(IFERROR(INDEX(Fragenkatalog!$BR28,MATCH('Referral Stati'!$F$19,Fragenkatalog!AO28,0)),""),250) | G41: =LEFT(IFERROR(INDEX(Fragenkatalog!$BR28,MATCH('Referral Stati'!$G$19,Fragenkatalog!AP28,0)),""),250) | J41: {=LEFT(IFERROR(INDEX(Fragenkatalog!BR28,MATCH('Referral Stati'!$J$19,Fragenkatalog!W28,0)),""),250)} | K41: {=LEFT(IFERROR(INDEX(Fragenkatalog!BR28,MATCH('Referral Stati'!$K$19,Fragenkatalog!X28,0)),""),250)} | L41: =LEFT(IFERROR(INDEX(Fragenkatalog!$BR28,MATCH('Referral Stati'!$L$19,Fragenkatalog!Q28,0)),""),250) | M41: =LEFT(IFERROR(INDEX(Fragenkatalog!$BR28,MATCH('Referral Stati'!$M$19,Fragenkatalog!R28,0)),""),250) | N41: =LEFT(IFERROR(INDEX(Fragenkatalog!$BR28,MATCH('Referral Stati'!$N$19,Fragenkatalog!AI28,0)),""),250) | O41: =LEFT(IFERROR(INDEX(Fragenkatalog!$BR28,MATCH('Referral Stati'!$O$19,Fragenkatalog!AJ28,0)),""),250) | P41: =LEFT(IFERROR(INDEX(Fragenkatalog!$BR28,MATCH('Referral Stati'!$P$19,Fragenkatalog!AC28,0)),""),250) | Q41: =LEFT(IFERROR(INDEX(Fragenkatalog!$BR28,MATCH('Referral Stati'!$Q$19,Fragenkatalog!AD28,0)),""),250) | R41: =LEFT(IFERROR(INDEX(Fragenkatalog!$BR28,MATCH('Referral Stati'!$R$19,Fragenkatalog!BA28,0)),""),250) | S41: =LEFT(IFERROR(INDEX(Fragenkatalog!$BR28,MATCH('Referral Stati'!$S$19,Fragenkatalog!BB28,0)),""),250) | T41: =LEFT(IFERROR(INDEX(Fragenkatalog!$BR28,MATCH('Referral Stati'!$T$19,Fragenkatalog!BG28,0)),""),250) | U41: =LEFT(IFERROR(INDEX(Fragenkatalog!$BR28,MATCH('Referral Stati'!$U$19,Fragenkatalog!BH28,0)),""),250) | V41: =LEFT(IFERROR(INDEX(Fragenkatalog!$BR28,MATCH('Referral Stati'!$V$19,Fragenkatalog!BM28,0)),""),250) | W41: =LEFT(IFERROR(INDEX(Fragenkatalog!$BR28,MATCH('Referral Stati'!$U$19,Fragenkatalog!BN28,0)),""),250)
A42: =Fragenkatalog!B29 -> RisikoFragen19 | D42: =LEFT(IFERROR(INDEX(Fragenkatalog!$BR29,MATCH('Referral Stati'!$D$19,Fragenkatalog!AU29,0)),""),250) | E42: =LEFT(IFERROR(INDEX(Fragenkatalog!$BR29,MATCH('Referral Stati'!$E$19,Fragenkatalog!AV29,0)),""),250) | F42: =LEFT(IFERROR(INDEX(Fragenkatalog!$BR29,MATCH('Referral Stati'!$F$19,Fragenkatalog!AO29,0)),""),250) | G42: =LEFT(IFERROR(INDEX(Fragenkatalog!$BR29,MATCH('Referral Stati'!$G$19,Fragenkatalog!AP29,0)),""),250) | J42: {=LEFT(IFERROR(INDEX(Fragenkatalog!BR29,MATCH('Referral Stati'!$J$19,Fragenkatalog!W29,0)),""),250)} | K42: {=LEFT(IFERROR(INDEX(Fragenkatalog!BR29,MATCH('Referral Stati'!$K$19,Fragenkatalog!X29,0)),""),250)} | L42: =LEFT(IFERROR(INDEX(Fragenkatalog!$BR29,MATCH('Referral Stati'!$L$19,Fragenkatalog!Q29,0)),""),250) | M42: =LEFT(IFERROR(INDEX(Fragenkatalog!$BR29,MATCH('Referral Stati'!$M$19,Fragenkatalog!R29,0)),""),250) | N42: =LEFT(IFERROR(INDEX(Fragenkatalog!$BR29,MATCH('Referral Stati'!$N$19,Fragenkatalog!AI29,0)),""),250) | O42: =LEFT(IFERROR(INDEX(Fragenkatalog!$BR29,MATCH('Referral Stati'!$O$19,Fragenkatalog!AJ29,0)),""),250) | P42: =LEFT(IFERROR(INDEX(Fragenkatalog!$BR29,MATCH('Referral Stati'!$P$19,Fragenkatalog!AC29,0)),""),250) | Q42: =LEFT(IFERROR(INDEX(Fragenkatalog!$BR29,MATCH('Referral Stati'!$Q$19,Fragenkatalog!AD29,0)),""),250) | R42: =LEFT(IFERROR(INDEX(Fragenkatalog!$BR29,MATCH('Referral Stati'!$R$19,Fragenkatalog!BA29,0)),""),250) | S42: =LEFT(IFERROR(INDEX(Fragenkatalog!$BR29,MATCH('Referral Stati'!$S$19,Fragenkatalog!BB29,0)),""),250) | T42: =LEFT(IFERROR(INDEX(Fragenkatalog!$BR29,MATCH('Referral Stati'!$T$19,Fragenkatalog!BG29,0)),""),250) | U42: =LEFT(IFERROR(INDEX(Fragenkatalog!$BR29,MATCH('Referral Stati'!$U$19,Fragenkatalog!BH29,0)),""),250) | V42: =LEFT(IFERROR(INDEX(Fragenkatalog!$BR29,MATCH('Referral Stati'!$V$19,Fragenkatalog!BM29,0)),""),250) | W42: =LEFT(IFERROR(INDEX(Fragenkatalog!$BR29,MATCH('Referral Stati'!$U$19,Fragenkatalog!BN29,0)),""),250)
... A51: =Fragenkatalog!B38 -> RisikoFragen23e | D51: =LEFT(IFERROR(INDEX(Fragenkatalog!$BR38,MATCH('Referral Stati'!$D$19,Fragenkatalog!AU38,0)),""),250) | E51: =LEFT(IFERROR(INDEX(Fragenkatalog!$BR38,MATCH('Referral Stati'!$E$19,Fragenkatalog!AV38,0)),""),250) | F51: =LEFT(IFERROR(INDEX(Fragenkatalog!$BR38,MATCH('Referral Stati'!$F$19,Fragenkatalog!AO38,0)),""),250) | G51: =LEFT(IFERROR(INDEX(Fragenkatalog!$BR38,MATCH('Referral Stati'!$G$19,Fragenkatalog!AP38,0)),""),250) | J51: {=LEFT(IFERROR(INDEX(Fragenkatalog!BR38,MATCH('Referral Stati'!$J$19,Fragenkatalog!W38,0)),""),250)} | K51: {=LEFT(IFERROR(INDEX(Fragenkatalog!BR38,MATCH('Referral Stati'!$K$19,Fragenkatalog!X38,0)),""),250)} | L51: =LEFT(IFERROR(INDEX(Fragenkatalog!$BR38,MATCH('Referral Stati'!$L$19,Fragenkatalog!Q38,0)),""),250) | M51: =LEFT(IFERROR(INDEX(Fragenkatalog!$BR38,MATCH('Referral Stati'!$M$19,Fragenkatalog!R38,0)),""),250) | N51: =LEFT(IFERROR(INDEX(Fragenkatalog!$BR38,MATCH('Referral Stati'!$N$19,Fragenkatalog!AI38,0)),""),250) | O51: =LEFT(IFERROR(INDEX(Fragenkatalog!$BR38,MATCH('Referral Stati'!$O$19,Fragenkatalog!AJ38,0)),""),250) | P51: =LEFT(IFERROR(INDEX(Fragenkatalog!$BR38,MATCH('Referral Stati'!$P$19,Fragenkatalog!AC38,0)),""),250) | Q51: =LEFT(IFERROR(INDEX(Fragenkatalog!$BR38,MATCH('Referral Stati'!$Q$19,Fragenkatalog!AD38,0)),""),250) | R51: =LEFT(IFERROR(INDEX(Fragenkatalog!$BR38,MATCH('Referral Stati'!$R$19,Fragenkatalog!BA38,0)),""),250) | S51: =LEFT(IFERROR(INDEX(Fragenkatalog!$BR38,MATCH('Referral Stati'!$S$19,Fragenkatalog!BB38,0)),""),250) | T51: =LEFT(IFERROR(INDEX(Fragenkatalog!$BR38,MATCH('Referral Stati'!$T$19,Fragenkatalog!BG38,0)),""),250) | U51: =LEFT(IFERROR(INDEX(Fragenkatalog!$BR38,MATCH('Referral Stati'!$U$19,Fragenkatalog!BH38,0)),""),250) | V51: =LEFT(IFERROR(INDEX(Fragenkatalog!$BR38,MATCH('Referral Stati'!$V$19,Fragenkatalog!BM38,0)),""),250) | W51: =LEFT(IFERROR(INDEX(Fragenkatalog!$BR38,MATCH('Referral Stati'!$U$19,Fragenkatalog!BN38,0)),""),250)
A52: RisikoFragenVorvertragExtendedReportingPeriod | D52: =LEFT(IFERROR(INDEX(Fragenkatalog!$BR39,MATCH('Referral Stati'!$D$19,Fragenkatalog!AU39,0)),""),250) | E52: =LEFT(IFERROR(INDEX(Fragenkatalog!$BR39,MATCH('Referral Stati'!$E$19,Fragenkatalog!AV39,0)),""),250) | F52: =LEFT(IFERROR(INDEX(Fragenkatalog!$BR39,MATCH('Referral Stati'!$F$19,Fragenkatalog!AO39,0)),""),250) | G52: =LEFT(IFERROR(INDEX(Fragenkatalog!$BR39,MATCH('Referral Stati'!$G$19,Fragenkatalog!AP39,0)),""),250) | J52: {=LEFT(IFERROR(INDEX(Fragenkatalog!BR39,MATCH('Referral Stati'!$J$19,Fragenkatalog!W39,0)),""),250)} | K52: {=LEFT(IFERROR(INDEX(Fragenkatalog!BR39,MATCH('Referral Stati'!$K$19,Fragenkatalog!X39,0)),""),250)} | L52: =LEFT(IFERROR(INDEX(Fragenkatalog!$BR39,MATCH('Referral Stati'!$L$19,Fragenkatalog!Q39,0)),""),250) | M52: =LEFT(IFERROR(INDEX(Fragenkatalog!$BR39,MATCH('Referral Stati'!$M$19,Fragenkatalog!R39,0)),""),250) | N52: =LEFT(IFERROR(INDEX(Fragenkatalog!$BR39,MATCH('Referral Stati'!$N$19,Fragenkatalog!AI39,0)),""),250) | O52: =LEFT(IFERROR(INDEX(Fragenkatalog!$BR39,MATCH('Referral Stati'!$O$19,Fragenkatalog!AJ39,0)),""),250) | P52: =LEFT(IFERROR(INDEX(Fragenkatalog!$BR39,MATCH('Referral Stati'!$P$19,Fragenkatalog!AC39,0)),""),250) | Q52: =LEFT(IFERROR(INDEX(Fragenkatalog!$BR39,MATCH('Referral Stati'!$Q$19,Fragenkatalog!AD39,0)),""),250) | R52: =LEFT(IFERROR(INDEX(Fragenkatalog!$BR39,MATCH('Referral Stati'!$R$19,Fragenkatalog!BA39,0)),""),250) | S52: =LEFT(IFERROR(INDEX(Fragenkatalog!$BR39,MATCH('Referral Stati'!$S$19,Fragenkatalog!BB39,0)),""),250) | T52: =LEFT(IFERROR(INDEX(Fragenkatalog!$BR39,MATCH('Referral Stati'!$T$19,Fragenkatalog!BG39,0)),""),250) | U52: =LEFT(IFERROR(INDEX(Fragenkatalog!$BR39,MATCH('Referral Stati'!$U$19,Fragenkatalog!BH39,0)),""),250) | V52: =LEFT(IFERROR(INDEX(Fragenkatalog!$BR39,MATCH('Referral Stati'!$V$19,Fragenkatalog!BM39,0)),""),250) | W52: =LEFT(IFERROR(INDEX(Fragenkatalog!$BR39,MATCH('Referral Stati'!$U$19,Fragenkatalog!BN39,0)),""),250)
A53: RisikoFragenVorvertragNoGapsInCoverage | D53: =LEFT(IFERROR(INDEX(Fragenkatalog!$BR40,MATCH('Referral Stati'!$D$19,Fragenkatalog!AU40,0)),""),250) | E53: =LEFT(IFERROR(INDEX(Fragenkatalog!$BR40,MATCH('Referral Stati'!$E$19,Fragenkatalog!AV40,0)),""),250) | F53: =LEFT(IFERROR(INDEX(Fragenkatalog!$BR40,MATCH('Referral Stati'!$F$19,Fragenkatalog!AO40,0)),""),250) | G53: =LEFT(IFERROR(INDEX(Fragenkatalog!$BR40,MATCH('Referral Stati'!$G$19,Fragenkatalog!AP40,0)),""),250) | J53: {=LEFT(IFERROR(INDEX(Fragenkatalog!BR40,MATCH('Referral Stati'!$J$19,Fragenkatalog!W40,0)),""),250)} | K53: {=LEFT(IFERROR(INDEX(Fragenkatalog!BR40,MATCH('Referral Stati'!$K$19,Fragenkatalog!X40,0)),""),250)} | L53: =LEFT(IFERROR(INDEX(Fragenkatalog!$BR40,MATCH('Referral Stati'!$L$19,Fragenkatalog!Q40,0)),""),250) | M53: =LEFT(IFERROR(INDEX(Fragenkatalog!$BR40,MATCH('Referral Stati'!$M$19,Fragenkatalog!R40,0)),""),250) | N53: =LEFT(IFERROR(INDEX(Fragenkatalog!$BR40,MATCH('Referral Stati'!$N$19,Fragenkatalog!AI40,0)),""),250) | O53: =LEFT(IFERROR(INDEX(Fragenkatalog!$BR40,MATCH('Referral Stati'!$O$19,Fragenkatalog!AJ40,0)),""),250) | P53: =LEFT(IFERROR(INDEX(Fragenkatalog!$BR40,MATCH('Referral Stati'!$P$19,Fragenkatalog!AC40,0)),""),250) | Q53: =LEFT(IFERROR(INDEX(Fragenkatalog!$BR40,MATCH('Referral Stati'!$Q$19,Fragenkatalog!AD40,0)),""),250) | R53: =LEFT(IFERROR(INDEX(Fragenkatalog!$BR40,MATCH('Referral Stati'!$R$19,Fragenkatalog!BA40,0)),""),250) | S53: =LEFT(IFERROR(INDEX(Fragenkatalog!$BR40,MATCH('Referral Stati'!$S$19,Fragenkatalog!BB40,0)),""),250) | T53: =LEFT(IFERROR(INDEX(Fragenkatalog!$BR40,MATCH('Referral Stati'!$T$19,Fragenkatalog!BG40,0)),""),250) | U53: =LEFT(IFERROR(INDEX(Fragenkatalog!$BR40,MATCH('Referral Stati'!$U$19,Fragenkatalog!BH40,0)),""),250) | V53: =LEFT(IFERROR(INDEX(Fragenkatalog!$BR40,MATCH('Referral Stati'!$V$19,Fragenkatalog!BM40,0)),""),250) | W53: =LEFT(IFERROR(INDEX(Fragenkatalog!$BR40,MATCH('Referral Stati'!$U$19,Fragenkatalog!BN40,0)),""),250)
A54: RisikoFragenVorvertragClaimsForIncreasedLimit | D54: =LEFT(IFERROR(INDEX(Fragenkatalog!$BR41,MATCH('Referral Stati'!$D$19,Fragenkatalog!AU41,0)),""),250) | E54: =LEFT(IFERROR(INDEX(Fragenkatalog!$BR41,MATCH('Referral Stati'!$E$19,Fragenkatalog!AV41,0)),""),250) | F54: =LEFT(IFERROR(INDEX(Fragenkatalog!$BR41,MATCH('Referral Stati'!$F$19,Fragenkatalog!AO41,0)),""),250) | G54: =LEFT(IFERROR(INDEX(Fragenkatalog!$BR41,MATCH('Referral Stati'!$G$19,Fragenkatalog!AP41,0)),""),250) | J54: {=LEFT(IFERROR(INDEX(Fragenkatalog!BR41,MATCH('Referral Stati'!$J$19,Fragenkatalog!W41,0)),""),250)} | K54: {=LEFT(IFERROR(INDEX(Fragenkatalog!BR41,MATCH('Referral Stati'!$K$19,Fragenkatalog!X41,0)),""),250)} | L54: =LEFT(IFERROR(INDEX(Fragenkatalog!$BR41,MATCH('Referral Stati'!$L$19,Fragenkatalog!Q41,0)),""),250) | M54: =LEFT(IFERROR(INDEX(Fragenkatalog!$BR41,MATCH('Referral Stati'!$M$19,Fragenkatalog!R41,0)),""),250) | N54: =LEFT(IFERROR(INDEX(Fragenkatalog!$BR41,MATCH('Referral Stati'!$N$19,Fragenkatalog!AI41,0)),""),250) | O54: =LEFT(IFERROR(INDEX(Fragenkatalog!$BR41,MATCH('Referral Stati'!$O$19,Fragenkatalog!AJ41,0)),""),250) | P54: =LEFT(IFERROR(INDEX(Fragenkatalog!$BR41,MATCH('Referral Stati'!$P$19,Fragenkatalog!AC41,0)),""),250) | Q54: =LEFT(IFERROR(INDEX(Fragenkatalog!$BR41,MATCH('Referral Stati'!$Q$19,Fragenkatalog!AD41,0)),""),250) | R54: =LEFT(IFERROR(INDEX(Fragenkatalog!$BR41,MATCH('Referral Stati'!$R$19,Fragenkatalog!BA41,0)),""),250) | S54: =LEFT(IFERROR(INDEX(Fragenkatalog!$BR41,MATCH('Referral Stati'!$S$19,Fragenkatalog!BB41,0)),""),250) | T54: =LEFT(IFERROR(INDEX(Fragenkatalog!$BR41,MATCH('Referral Stati'!$T$19,Fragenkatalog!BG41,0)),""),250) | U54: =LEFT(IFERROR(INDEX(Fragenkatalog!$BR41,MATCH('Referral Stati'!$U$19,Fragenkatalog!BH41,0)),""),250) | V54: =LEFT(IFERROR(INDEX(Fragenkatalog!$BR41,MATCH('Referral Stati'!$V$19,Fragenkatalog!BM41,0)),""),250) | W54: =LEFT(IFERROR(INDEX(Fragenkatalog!$BR41,MATCH('Referral Stati'!$U$19,Fragenkatalog!BN41,0)),""),250)
A55: RisikoFragenVorvertragInsurer | D55: =LEFT(IFERROR(INDEX(Fragenkatalog!$BR42,MATCH('Referral Stati'!$D$19,Fragenkatalog!AU42,0)),""),250) | E55: =LEFT(IFERROR(INDEX(Fragenkatalog!$BR42,MATCH('Referral Stati'!$E$19,Fragenkatalog!AV42,0)),""),250) | F55: =LEFT(IFERROR(INDEX(Fragenkatalog!$BR42,MATCH('Referral Stati'!$F$19,Fragenkatalog!AO42,0)),""),250) | G55: =LEFT(IFERROR(INDEX(Fragenkatalog!$BR42,MATCH('Referral Stati'!$G$19,Fragenkatalog!AP42,0)),""),250) | J55: {=LEFT(IFERROR(INDEX(Fragenkatalog!BR42,MATCH('Referral Stati'!$J$19,Fragenkatalog!W42,0)),""),250)} | K55: {=LEFT(IFERROR(INDEX(Fragenkatalog!BR42,MATCH('Referral Stati'!$K$19,Fragenkatalog!X42,0)),""),250)} | L55: =LEFT(IFERROR(INDEX(Fragenkatalog!$BR42,MATCH('Referral Stati'!$L$19,Fragenkatalog!Q42,0)),""),250) | M55: =LEFT(IFERROR(INDEX(Fragenkatalog!$BR42,MATCH('Referral Stati'!$M$19,Fragenkatalog!R42,0)),""),250) | N55: =LEFT(IFERROR(INDEX(Fragenkatalog!$BR42,MATCH('Referral Stati'!$N$19,Fragenkatalog!AI42,0)),""),250) | O55: =LEFT(IFERROR(INDEX(Fragenkatalog!$BR42,MATCH('Referral Stati'!$O$19,Fragenkatalog!AJ42,0)),""),250) | P55: =LEFT(IFERROR(INDEX(Fragenkatalog!$BR42,MATCH('Referral Stati'!$P$19,Fragenkatalog!AC42,0)),""),250) | Q55: =LEFT(IFERROR(INDEX(Fragenkatalog!$BR42,MATCH('Referral Stati'!$Q$19,Fragenkatalog!AD42,0)),""),250) | R55: =LEFT(IFERROR(INDEX(Fragenkatalog!$BR42,MATCH('Referral Stati'!$R$19,Fragenkatalog!BA42,0)),""),250) | S55: =LEFT(IFERROR(INDEX(Fragenkatalog!$BR42,MATCH('Referral Stati'!$S$19,Fragenkatalog!BB42,0)),""),250) | T55: =LEFT(IFERROR(INDEX(Fragenkatalog!$BR42,MATCH('Referral Stati'!$T$19,Fragenkatalog!BG42,0)),""),250) | U55: =LEFT(IFERROR(INDEX(Fragenkatalog!$BR42,MATCH('Referral Stati'!$U$19,Fragenkatalog!BH42,0)),""),250) | V55: =LEFT(IFERROR(INDEX(Fragenkatalog!$BR42,MATCH('Referral Stati'!$V$19,Fragenkatalog!BM42,0)),""),250) | W55: =LEFT(IFERROR(INDEX(Fragenkatalog!$BR42,MATCH('Referral Stati'!$U$19,Fragenkatalog!BN42,0)),""),250)
