Workbook
Name anzahlMitarbeiterGesamt: Referrals!$B$13
Name anzahlMitarbeiterGF: Fragenkatalog!$B$15
Name anzahlMitarbeiterTZ: Fragenkatalog!$B$14
Name anzahlMitarbeiterVZ: Fragenkatalog!$B$13
Name arag_PremiumAdjustment: 'SIC-TAW-Codes'!$T$6
Name arag_Referral: 'SIC-TAW-Codes'!$S$6
Name aragLimit1CoopBrokerNetProvision: Datenabzug!$I$17
Name aragLimit1EmployeeGraduation: Datenabzug!$N$17
Name aragLimit1HowdenNetProvision: Datenabzug!$H$17
Name aragLimit1MinimumPremium: Datenabzug!$L$17
Name aragLimit1Offered: Datenabzug!$C$17
Name aragLimit1Premium: Datenabzug!$E$17
Name aragLimit1PremiumPerEmployee: Datenabzug!$K$17
Name aragLimit1PremiumType: Datenabzug!$M$17
Name aragLimit1Stars: Datenabzug!$F$17
Name aragLimit1Status: Datenabzug!$G$17
Name aragLimit1SublimitOffered: Datenabzug!$D$17
Name aragLimit1UsedClauses: Datenabzug!$J$17
Name aragLimit2CoopBrokerNetProvision: Datenabzug!$I$18
Name aragLimit2EmployeeGraduation: Datenabzug!$N$18
Name aragLimit2HowdenNetProvision: Datenabzug!$H$18
Name aragLimit2MinimumPremium: Datenabzug!$L$18
Name aragLimit2Offered: Datenabzug!$C$18
Name aragLimit2Premium: Datenabzug!$E$18
Name aragLimit2PremiumPerEmployee: Datenabzug!$K$18
Name aragLimit2PremiumType: Datenabzug!$M$18
Name aragLimit2Stars: Datenabzug!$F$18
Name aragLimit2Status: Datenabzug!$G$18
Name aragLimit2SublimitOffered: Datenabzug!$D$18
Name aragLimit2UsedClauses: Datenabzug!$J$18
Name aragLimit3CoopBrokerNetProvision: Datenabzug!$I$19
Name aragLimit3EmployeeGraduation: Datenabzug!$N$19
Name aragLimit3HowdenNetProvision: Datenabzug!$H$19
Name aragLimit3MinimumPremium: Datenabzug!$L$19
Name aragLimit3Offered: Datenabzug!$C$19
Name aragLimit3Premium: Datenabzug!$E$19
Name aragLimit3PremiumPerEmployee: Datenabzug!$K$19
Name aragLimit3PremiumType: Datenabzug!$M$19
Name aragLimit3Stars: Datenabzug!$F$19
Name aragLimit3Status: Datenabzug!$G$19
Name aragLimit3SublimitOffered: Datenabzug!$D$19
Name aragLimit3UsedClauses: Datenabzug!$J$19
Name aragLimit4CoopBrokerNetProvision: Datenabzug!$I$20
Name aragLimit4EmployeeGraduation: Datenabzug!$N$20
Name aragLimit4HowdenNetProvision: Datenabzug!$H$20
Name aragLimit4MinimumPremium: Datenabzug!$L$20
Name aragLimit4Offered: Datenabzug!$C$20
Name aragLimit4Premium: Datenabzug!$E$20
Name aragLimit4PremiumPerEmployee: Datenabzug!$K$20
Name aragLimit4PremiumType: Datenabzug!$M$20
Name aragLimit4Stars: Datenabzug!$F$20
Name aragLimit4Status: Datenabzug!$G$20
Name aragLimit4SublimitOffered: Datenabzug!$D$20
Name aragLimit4UsedClauses: Datenabzug!$J$20
Name aragLimit5CoopBrokerNetProvision: Datenabzug!$I$21
Name aragLimit5EmployeeGraduation: Datenabzug!$N$21
Name aragLimit5HowdenNetProvision: Datenabzug!$H$21
Name aragLimit5MinimumPremium: Datenabzug!$L$21
Name aragLimit5Offered: Datenabzug!$C$21
Name aragLimit5Premium: Datenabzug!$E$21

Sheet Fragenkatalog
A1: Fragebogen / Tasks | B1: Antwort / Wert | C1: Formatierte Darstellung
A2: Land des Versicherungsnehmers | C2: =LOOKUP(StammDaten3,'Listen-Daten'!E2:G250,'Listen-Daten'!G2:G250) -> #N/A
A3: Gewünschter Policen Beginn | C3: =RisikoFragen0a -> 0
A4: Gewünschtes Policen Ende | C4: =RisikoFragen0b -> 0
A5: Deckungssumme (1) | C5: =limit1 -> 0
A6: Sublimit Kartellrecht (1) | C6: =sublimit1 -> 0
A7: Deckungssumme (2) | C7: =limit2 -> 0
A8: Sublimit Kartellrecht (2) | C8: =sublimit2 -> 0
A9: Deckungssumme (3) | C9: =limit3 -> 0
A10: Sublimit Kartellrecht (3) | C10: =sublimit3 -> 0
A11: Branche (SIC-Codes) | C11: =VLOOKUP(B11,'Listen-Daten'!K:L,2) -> #N/A
A12: Rechtsform | C12: =IF(StammDaten2="",'Listen-Daten'!B2,VLOOKUP(StammDaten2,'Listen-Daten'!A:B,2,0)) -> andere
A13: Anzahl Vollzeit Beschäftigte | C13: =B13 & " FTE" -> FTE
A14: Anzahl Teilzeit Beschäftigte | C14: =B14 & " FTE" -> FTE
A15: Anzahl geringfügig Beschäftigte | C15: =B15 & " FTE" -> FTE
A16: Tochtergesellschaften und mitversicherte Unternehmen | C16: =DaughterAndCoInsuredCompanies -> 0
A17: Geltungsbereich | C17: =LOOKUP(geltungsbereich,'Listen-Daten'!N2:O3,'Listen-Daten'!O2:O3) -> #N/A
A18: Nettoisierung | C18: =B18 -> 0
A19: Provision Koopmakler | C19: =coopbrokerCourtageHPST -> 0
A20: Besteht oder bestand für zu versichernde Unternehmen bereits eine Rechtsschutzversicherung im Sinne dieser HPST-Ausschreibung? | C20: =vorvertrag -> 0
A21: Versicherungsgesellschaft des Vorvertrags | C21: =VLOOKUP(B21,'Listen-Daten'!X:Y,2) -> #N/A
A22: Wurde dem Vorvertrag ein Hendricks und Partner Bedingungswerk zugrunde gelegt? | C22: =RisikoFrageClaims1c -> 0
A23: Versicherungsscheinnummer | C23: =versicherungsscheinnummer -> 0
A24: Deckungssumme des Vorvertrags | C24: =deckungssummevorversicherer -> 0
A25: Haben sich im Rahmen einer Vorversicherung bei einem anderen Versicherer für das beantragte Risiko Schadenfälle ereignet? | C25: =RisikoFrageClaims1a -> 0
A26: Wurde der Vertrag vom Vorversicherer gekündigt oder wurden Sanierungsmaßnahmen eingeleitet oder angekündigt? | C26: =RisikoFrageClaims1b -> 0
A27: Wurden in den letzten 2 Jahren außerhalb des Straßenverkehrs Straf- oder Ordnungswidrigkeitenverfahren gegen den Versicherungsnehmer, das Unternehmen oder einzelne Mitarbeiter durchgeführt? | C27: =RisikoFrageQ2a -> 0
A28: Sind solche Verfahren anhängig? | C28: =RisikoFrageQ2b -> 0
A29: Sind Umstände bekannt, die auf ein anstehendes Ermittlungs- oder Strafverfahren hinweisen? | C29: =RisikoFrageQ3a -> 0
A30: Vom Antragssteller bzw. im Konzern der Versicherungsnehmerin wird eine Tätigkeit gemäß § 1 (1) KWG oder § 1 VAG (Bank- oder Versicherungsgeschäfte oder sonstige Finanzdienstleistungen) erbracht. | C30: =RisikoFrageQ5a -> 0
A31: Ist eines der zu versichernden Unternehmen in einer oder mehrerer der folgenden Branchen tätig? | C31: =RisikoFrageQ5b -> 0
A32: Wird Gefahrgut transportiert oder gelagert? | C32: =RisikoFrageQ6 -> 0
A33: Sind Umstände bekannt, die auf die Einleitung von Verfahren aufgrund von Preis - und/oder Ausschreibungsabsprachen hindeuten? | C33: =RisikoFrageQ4a -> 0
A34: Wurden in den letzten zwei Jahren Verfahren gegen den Versicherungsnehmer, das Unternehmen (auch Tochter- und Beteiligungsunternehmen) oder einzelne Mitarbeiter aufgrund von Preis - und/oder Ausschreibungsabsprachen eingeleitet? | C34: =RisikoFrageQ4b -> 0
A35: Hat der Versicherungsnehmer Tochtergesellschaften in den USA, China, Indien, Südkorea, Brasilien, Südafrika, Japan, Australien oder in der Schweiz? | C35: =RisikoFrageQ4c -> 0
A36: Es gibt MVU | C36: =CoInsuredCompaniesExist -> 0

Sheet Datenabzug
B1: Versicherer | C1: Deckungssumme | D1: Sublimit Kartell | E1: Prämie | F1: Bewertung | G1: Status | H1: Provision Hendricks | I1: Provision Makler | J1: Klauseln
A2: DS1 inkl. Sublimit | B2: ROLAND | C2: ='Prämie - Roland'!B25 -> 0 | D2: ='Prämie - Roland'!C25 | E2: =IF(G2<>OfferReferralNoPremium,IF(ISNUMBER('Prämie - Roland'!D25),ROUND('Prämie - Roland'!D25,2),""),"") | F2: =TEXT(5,"5") -> 5 | G2: =Referrals!G40 -> OFFER_REFERRAL_NO_PREMIUM | H2: =ROUND('Prämie - Roland'!E25,2) -> 0.4 | I2: =ROUND('Prämie - Roland'!F25,2) -> 0 | J2: =Referrals!F$37 -> ,hpst_geltungsbereich_2:hpst_rol-2,hpst_kartellrecht:group-hpst-1
A3: DS1 | B3: ROLAND | C3: ='Prämie - Roland'!B25 -> 0 | E3: =IF(G3<>OfferReferralNoPremium,IF(ISNUMBER('Prämie - Roland'!D26),ROUND('Prämie - Roland'!D26,2),""),"") | F3: =TEXT(5,"5") -> 5 | G3: =Referrals!G41 -> OFFER_REFERRAL_NO_PREMIUM | H3: =ROUND('Prämie - Roland'!E26,2) -> 0.4 | I3: =ROUND('Prämie - Roland'!F26,2) -> 0 | J3: =Referrals!F$37 -> ,hpst_geltungsbereich_2:hpst_rol-2,hpst_kartellrecht:group-hpst-1
A4: DS2 inkl. Sublimit | B4: ROLAND | C4: ='Prämie - Roland'!B27 -> 0 | D4: ='Prämie - Roland'!C27 | E4: =IF(G4<>OfferReferralNoPremium,IF(ISNUMBER('Prämie - Roland'!D27),ROUND('Prämie - Roland'!D27,2),""),"") | F4: =TEXT(5,"5") -> 5 | G4: =Referrals!G42 -> OFFER_REFERRAL_NO_PREMIUM | H4: =ROUND('Prämie - Roland'!E27,2) -> 0.4 | I4: =ROUND('Prämie - Roland'!F27,2) -> 0 | J4: =Referrals!F$37 -> ,hpst_geltungsbereich_2:hpst_rol-2,hpst_kartellrecht:group-hpst-1
A5: DS2 | B5: ROLAND | C5: ='Prämie - Roland'!B27 -> 0 | E5: =IF(G5<>OfferReferralNoPremium,IF(ISNUMBER('Prämie - Roland'!D28),ROUND('Prämie - Roland'!D28,2),""),"") | F5: =TEXT(5,"5") -> 5 | G5: =Referrals!G43 -> OFFER_REFERRAL_NO_PREMIUM | H5: =ROUND('Prämie - Roland'!E28,2) -> 0.4 | I5: =ROUND('Prämie - Roland'!F28,2) -> 0 | J5: =Referrals!F$37 -> ,hpst_geltungsbereich_2:hpst_rol-2,hpst_kartellrecht:group-hpst-1
A6: DS3 inkl. Sublimit | B6: ROLAND | C6: ='Prämie - Roland'!B29 -> 0 | D6: ='Prämie - Roland'!C29 | E6: =IF(G6<>OfferReferralNoPremium,IF(ISNUMBER('Prämie - Roland'!D29),ROUND('Prämie - Roland'!D29,2),""),"") | F6: =TEXT(5,"5") -> 5 | G6: =Referrals!G44 -> OFFER_REFERRAL_NO_PREMIUM | H6: =ROUND('Prämie - Roland'!E29,2) -> 0.4 | I6: =ROUND('Prämie - Roland'!F29,2) -> 0 | J6: =Referrals!F$37 -> ,hpst_geltungsbereich_2:hpst_rol-2,hpst_kartellrecht:group-hpst-1
A7: DS3 | B7: ROLAND | C7: ='Prämie - Roland'!B29 -> 0 | E7: =IF(G7<>OfferReferralNoPremium,IF(ISNUMBER('Prämie - Roland'!D30),ROUND('Prämie - Roland'!D30,2),""),"") | F7: =TEXT(5,"5") -> 5 | G7: =Referrals!G45 -> OFFER_REFERRAL_NO_PREMIUM | H7: =ROUND('Prämie - Roland'!E30,2) -> 0.4 | I7: =ROUND('Prämie - Roland'!F30,2) -> 0 | J7: =Referrals!F$37 -> ,hpst_geltungsbereich_2:hpst_rol-2,hpst_kartellrecht:group-hpst-1
A9: Grobindikation TAW Code
A10: Grobindikation TAW Description
A11: TAW Code | B11: =IFERROR(VLOOKUP(Referrals!B7,'SIC-TAW-Codes'!A:C,3,FALSE),"0002") -> 0002
A12: TAW Description | B12: =VLOOKUP(B11,'SIC-TAW-Codes'!C:D,2,FALSE) -> Anfrage
A13: TAW Code Roland | B13: =IFERROR(VLOOKUP(Referrals!B7,'SIC-TAW-Codes'!A:F,6,FALSE),"0002") -> 0002
A14: TAW Description | B14: =VLOOKUP(B13,'SIC-TAW-Codes'!F:G,2,FALSE) -> Anfrage
B16: Versicherer | C16: Deckungssumme | D16: Sublimit Kartell | E16: Prämie | F16: Bewertung | G16: Status | H16: Provision Hendricks | I16: Provision Makler | J16: Klauseln | K16: Prämie Pro Mitarbeiter | L16: Mindest-Prämie | M16: Prämien-Art | N16: Staffelung
A17: DS1 inkl. Sublimit | B17: ARAG | C17: ='Prämie - Arag'!B25 -> 0 | D17: ='Prämie - Arag'!C25 | E17: =IF(D17="",IF(ISNUMBER('Prämie - Arag'!D25),ROUND('Prämie - Arag'!D25,2),""),"") | F17: =TEXT(4,"4") -> 4 | G17: =Referrals!L40 -> OFFER_REFERRAL | H17: =ROUND('Prämie - Arag'!E25,2) -> 0.4 | I17: =ROUND('Prämie - Arag'!F25,2) -> 0 | J17: =CONCATENATE(Referrals!K40,Referrals!K$37) | K17: =IF(ISNUMBER('Arag-Tarif'!D21), 'Arag-Tarif'!D21,"") | L17: =IF(ISNUMBER('Arag-Tarif'!E21), 'Arag-Tarif'!E21,"") | M17: =IF(ISERROR('Arag-Tarif'!F21),"",'Arag-Tarif'!F21) | N17: =IF(ISERROR('Arag-Tarif'!B14),"",'Arag-Tarif'!B14) -> 0 - 10
A18: DS1 | B18: ARAG | C18: ='Prämie - Arag'!B26 -> 0 | E18: =IF(D18="",IF(ISNUMBER('Prämie - Arag'!D26),ROUND('Prämie - Arag'!D26,2),""),"") | F18: =TEXT(4,"4") -> 4 | G18: =Referrals!L41 -> OFFER_REFERRAL | H18: =ROUND('Prämie - Arag'!E26,2) -> 0.4 | I18: =ROUND('Prämie - Arag'!F26,2) -> 0 | J18: =CONCATENATE(Referrals!K41,Referrals!K$37) | K18: =IF(ISNUMBER('Arag-Tarif'!D22), 'Arag-Tarif'!D22,"") | L18: =IF(ISNUMBER('Arag-Tarif'!E22), 'Arag-Tarif'!E22,"") | M18: =IF(ISERROR('Arag-Tarif'!F22),"",'Arag-Tarif'!F22) | N18: =IF(ISERROR('Arag-Tarif'!B14),"",'Arag-Tarif'!B14) -> 0 - 10
A19: DS2 inkl. Sublimit | B19: ARAG | C19: ='Prämie - Arag'!B27 -> 0 | D19: ='Prämie - Arag'!C27 | E19: =IF(D19="",IF(ISNUMBER('Prämie - Arag'!D27),ROUND('Prämie - Arag'!D27,2),""),"") | F19: =TEXT(4,"4") -> 4 | G19: =Referrals!L42 -> OFFER_REFERRAL | H19: =ROUND('Prämie - Arag'!E27,2) -> 0.4 | I19: =ROUND('Prämie - Arag'!F27,2) -> 0 | J19: =CONCATENATE(Referrals!K42,Referrals!K$37) | K19: =IF(ISNUMBER('Arag-Tarif'!D23), 'Arag-Tarif'!D23,"") | L19: =IF(ISNUMBER('Arag-Tarif'!E23), 'Arag-Tarif'!E23,"") | M19: =IF(ISERROR('Arag-Tarif'!F23),"",'Arag-Tarif'!F23) | N19: =IF(ISERROR('Arag-Tarif'!B14),"",'Arag-Tarif'!B14) -> 0 - 10
A20: DS2 | B20: ARAG | C20: ='Prämie - Arag'!B28 -> 0 | E20: =IF(D20="",IF(ISNUMBER('Prämie - Arag'!D28),ROUND('Prämie - Arag'!D28,2),""),"") | F20: =TEXT(4,"4") -> 4 | G20: =Referrals!L43 -> OFFER_REFERRAL | H20: =ROUND('Prämie - Arag'!E28,2) -> 0.4 | I20: =ROUND('Prämie - Arag'!F28,2) -> 0 | J20: =CONCATENATE(Referrals!K43,Referrals!K$37) | K20: =IF(ISNUMBER('Arag-Tarif'!D24), 'Arag-Tarif'!D24,"") | L20: =IF(ISNUMBER('Arag-Tarif'!E24), 'Arag-Tarif'!E24,"") | M20: =IF(ISERROR('Arag-Tarif'!F24),"",'Arag-Tarif'!F24) | N20: =IF(ISERROR('Arag-Tarif'!B14),"",'Arag-Tarif'!B14) -> 0 - 10
A21: DS3 inkl. Sublimit | B21: ARAG | C21: ='Prämie - Arag'!B29 -> 0 | D21: ='Prämie - Arag'!C29 | E21: =IF(D21="",IF(ISNUMBER('Prämie - Arag'!D29),ROUND('Prämie - Arag'!D29,2),""),"") | F21: =TEXT(4,"4") -> 4 | G21: =Referrals!L44 -> OFFER_REFERRAL | H21: =ROUND('Prämie - Arag'!E29,2) -> 0.4 | I21: =ROUND('Prämie - Arag'!F29,2) -> 0 | J21: =CONCATENATE(Referrals!K44,Referrals!K$37) | K21: =IF(ISNUMBER('Arag-Tarif'!D25), 'Arag-Tarif'!D25,"") | L21: =IF(ISNUMBER('Arag-Tarif'!E25), 'Arag-Tarif'!E25,"") | M21: =IF(ISERROR('Arag-Tarif'!F25),"",'Arag-Tarif'!F25) | N21: =IF(ISERROR('Arag-Tarif'!B14),"",'Arag-Tarif'!B14) -> 0 - 10
A22: DS3 | B22: ARAG | C22: ='Prämie - Arag'!B30 -> 0 | E22: =IF(D22="",IF(ISNUMBER('Prämie - Arag'!D30),ROUND('Prämie - Arag'!D30,2),""),"") | F22: =TEXT(4,"4") -> 4 | G22: =Referrals!L45 -> OFFER_REFERRAL | H22: =ROUND('Prämie - Arag'!E30,2) -> 0.4 | I22: =ROUND('Prämie - Arag'!F30,2) -> 0 | J22: =CONCATENATE(Referrals!K45,Referrals!K$37) | K22: =IF(ISNUMBER('Arag-Tarif'!D26), 'Arag-Tarif'!D26,"") | L22: =IF(ISNUMBER('Arag-Tarif'!E26), 'Arag-Tarif'!E26,"") | M22: =IF(ISERROR('Arag-Tarif'!F26),"",'Arag-Tarif'!F26) | N22: =IF(ISERROR('Arag-Tarif'!B14),"",'Arag-Tarif'!B14) -> 0 - 10

Sheet Referrals
C1: ROLAND | H1: ARAG
A2: Fragebogen / Tasks | B2: Antwort / Wert | C2: Refferal Triggers | D2: Referral nur bei Kartellrecht | E2: Zu- und Abschläge | F2: Klauseln | H2: Refferal Triggers | I2: Referral nur bei Kartellrecht | J2: Zu- und Abschläge | K2: Klauseln | N2: Formulierung Referraltrigger in den Mails | O2: Formulierung Trigger Referral Kartellrecht
A3: =Fragenkatalog!A2 -> Land des Versicherungsnehmers | B3: =Fragenkatalog!B2 -> 0 | C3: =IF($B$3 = "DE",OfferReady,OfferReferral) -> OFFER_REFERRAL | H3: =IF($B$3 = "DE",OfferReady,OfferReferral) -> OFFER_REFERRAL | N3: Land des VN
A4: =Fragenkatalog!A3 -> Gewünschter Policen Beginn | B4: =Fragenkatalog!B3 -> 0 | C4: =IF($B$4<TODAY(),OfferReferral,OfferReady) -> OFFER_REFERRAL | H4: =IF($B$4<TODAY(),OfferReferral,OfferReady) -> OFFER_REFERRAL | N4: Policenbeginn
A5: =Fragenkatalog!A4 -> Gewünschtes Policen Ende | B5: =Fragenkatalog!B4 -> 0
A6: Laufzeit (Moante) | B6: =DAYS360(B4,B5) -> 0 | C6: =IF($B$6>1080,OfferReferral,OfferReady) -> OFFER_READY_FOR_POLICY | H6: =IF(OR($B$6>360,$B$6<360),OfferReferral,OfferReady) -> OFFER_REFERRAL | N6: Laufzeit
A7: =Fragenkatalog!A11 -> Branche (SIC-Codes) | B7: =Fragenkatalog!B11 -> 0 | H7: =VLOOKUP(arag_Referral,'Listen-Daten'!$T$2:$U$4,2,FALSE) -> #N/A
A8: TAW-Code | B8: =IFERROR(VLOOKUP(B7,'SIC-TAW-Codes'!A:C,3,FALSE),"0002") -> 0002 | C8: =IF(OR(B8="7000",B8="7005",B8="7021",B8="8838",B8="7020",B8="7008",B8="8839",B8="7027",B8="7019",B8="7023",B8="6700",B8="0002"),OfferReferralNoPremium,IF(ISNUMBER(MATCH(B8,'SIC-TAW-Codes'!N:N,0)),OfferReferral,OfferReady)) -> OFFER_REFERRAL_NO_PREMIUM | E8: =IF(ISNUMBER(MATCH(B8,'SIC-TAW-Codes'!K:K,0)),30,0) -> 0 | N8: Branche
A9: =Fragenkatalog!A12 -> Rechtsform | B9: =Fragenkatalog!C12 -> andere | H9: =IF(VLOOKUP($B$9,'Listen-Daten'!B:C,2,0)=OfferReady,"",VLOOKUP($B$9,'Listen-Daten'!B:C,2,0)) -> OFFER_REFERRAL | N9: Rechtsform
A10: =Fragenkatalog!A13 -> Anzahl Vollzeit Beschäftigte | B10: =Fragenkatalog!B13 -> 0
A11: =Fragenkatalog!A14 -> Anzahl Teilzeit Beschäftigte | B11: =Fragenkatalog!B14 -> 0
A12: =Fragenkatalog!A15 -> Anzahl geringfügig Beschäftigte | B12: =Fragenkatalog!B15 -> 0
A13: Gesamtzahl Beschäftigte | B13: =B10+ROUNDUP(B11/2+B12/4,0) -> 0 | C13: =IF(anzahlMitarbeiterGesamt>1500,OfferReferral,OfferReady) -> OFFER_READY_FOR_POLICY | H13: =IF(anzahlMitarbeiterGesamt>100,OfferReferral,OfferReady) -> OFFER_READY_FOR_POLICY | N13: Gesamtzahl MA
A14: Tochtergesellschaften und mitversicherte Unternehmen | B14: =DaughterAndCoInsuredCompanies -> 0 | C14: =IF($B$14="WORLD",OfferReferral,OfferReady) -> OFFER_READY_FOR_POLICY | H14: =IF($B$14="WORLD",OfferReferral,OfferReady) -> OFFER_READY_FOR_POLICY | N14: TU / MVU außerhalb EWR
A15: =Fragenkatalog!A17 -> Geltungsbereich | B15: =Fragenkatalog!B17 -> 0 | E15: s. Prämie-Roland | F15: =IF(geltungsbereich="EU",",hpst_geltungsbereich_1:hpst_rol-2",",hpst_geltungsbereich_2:hpst_rol-2") -> ,hpst_geltungsbereich_2:hpst_rol-2 | J15: s. Prämie-Arag
A16: =Fragenkatalog!A18 -> Nettoisierung | B16: =Fragenkatalog!B18 -> 0
A17: =Fragenkatalog!A19 -> Provision Koopmakler | B17: =Fragenkatalog!B19 -> 0
A18: =Fragenkatalog!A20 -> Besteht oder bestand für zu versichernde Unternehmen bereits eine Rechtsschutzversicherung im Sinne dieser HPST-Ausschreibung? | B18: =Fragenkatalog!B20 -> 0 | C18: =IF(AND(B18="YES",OR(B19="5807",B19="5528")),OfferReferral,OfferReady) -> OFFER_READY_FOR_POLICY | H18: =IF(B18="YES",OfferReferral,OfferReady) -> OFFER_READY_FOR_POLICY | N18: Existierender Vorvertrag
A19: Versicherungsgesellschaft des Vorvertrags | B19: =Fragenkatalog!B21 -> 0
A20: =Fragenkatalog!A22 -> Wurde dem Vorvertrag ein Hendricks und Partner Bedingungswerk zugrunde gelegt? | B20: =Fragenkatalog!B22 -> 0 | F20: =IF(AND(B18="YES",RisikoFrageClaims1c="NO"),",hpst-anz-obl:group-hpst-1","")
A21: =Fragenkatalog!A23 -> Versicherungsscheinnummer | B21: =Fragenkatalog!B23 -> 0
A22: =Fragenkatalog!A24 -> Deckungssumme des Vorvertrags | B22: =Fragenkatalog!B24 -> 0
A23: =Fragenkatalog!A25 -> Haben sich im Rahmen einer Vorversicherung bei einem anderen Versicherer für das beantragte Risiko Schadenfälle ereignet? | B23: =Fragenkatalog!B25 -> 0 | C23: =IF($B$23="YES",OfferReferral,OfferReady) -> OFFER_READY_FOR_POLICY | H23: =IF($B$23="YES",OfferReferral,OfferReady) -> OFFER_READY_FOR_POLICY | N23: Schäden Vorvertrag
A24: =Fragenkatalog!A26 -> Wurde der Vertrag vom Vorversicherer gekündigt oder wurden Sanierungsmaßnahmen eingeleitet oder angekündigt? | B24: =Fragenkatalog!B26 -> 0 | C24: =IF($B$24="YES",OfferReferral,OfferReady) -> OFFER_READY_FOR_POLICY | H24: =IF($B$24="YES",OfferReferral,OfferReady) -> OFFER_READY_FOR_POLICY | N24: Kündigung Vorvertrag
A25: =Fragenkatalog!A27 -> Wurden in den letzten 2 Jahren außerhalb des Straßenverkehrs Straf- oder Ordnungswidrigkeitenverfahren gegen den Versicherungsnehmer, das Unternehmen oder einzelne Mitarbeiter durchgeführt? | B25: =Fragenkatalog!B27 -> 0 | C25: =IF($B$25="YES",OfferReferral,OfferReady) -> OFFER_READY_FOR_POLICY | H25: =IF($B$25="YES",OfferReferral,OfferReady) -> OFFER_READY_FOR_POLICY | N25: Verfahren letzte 2 Jahre
A26: =Fragenkatalog!A28 -> Sind solche Verfahren anhängig? | B26: =Fragenkatalog!B28 -> 0 | C26: =IF($B$26="YES",OfferReferral,OfferReady) -> OFFER_READY_FOR_POLICY | H26: =IF($B$26="YES",OfferReferral,OfferReady) -> OFFER_READY_FOR_POLICY | N26: Anhängige Verfahren
A27: =Fragenkatalog!A29 -> Sind Umstände bekannt, die auf ein anstehendes Ermittlungs- oder Strafverfahren hinweisen? | B27: =Fragenkatalog!B29 -> 0 | C27: =IF($B$27="YES",OfferReferral,OfferReady) -> OFFER_READY_FOR_POLICY | H27: =IF($B$27="YES",OfferReferral,OfferReady) -> OFFER_READY_FOR_POLICY | N27: Anstehende Verfahren
A28: =Fragenkatalog!A30 -> Vom Antragssteller bzw. im Konzern der Versicherungsnehmerin wird eine Tätigkeit gemäß § 1 (1) KWG oder § 1 VAG (Bank- oder Versicherungsgeschäfte oder sonstige Finanzdienstleistungen) erbracht. | B28: =RisikoFrageQ5a -> 0 | C28: =IF($B$28="YES",OfferReferral,OfferReady) -> OFFER_READY_FOR_POLICY | F28: =IF($B$28="YES",",CumEx:group-hpst-rol","") | H28: =IF($B$28="YES",OfferReferral,OfferReady) -> OFFER_READY_FOR_POLICY | N28: Tätig nach KWG oder VAG
A29: =Fragenkatalog!A31 -> Ist eines der zu versichernden Unternehmen in einer oder mehrerer der folgenden Branchen tätig? | B29: =RisikoFrageQ5b -> 0 | C29: =IF($B$29="YES",OfferReferral,OfferReady) -> OFFER_READY_FOR_POLICY | H29: =IF($B$29="YES",OfferReferral,OfferReady) -> OFFER_READY_FOR_POLICY | N29: Tätig in Ausschlussbranche
A30: =Fragenkatalog!A32 -> Wird Gefahrgut transportiert oder gelagert? | B30: =RisikoFrageQ6 -> 0 | E30: =IF(B30="YES",30,0) -> 0
A31: =Fragenkatalog!A33 -> Sind Umstände bekannt, die auf die Einleitung von Verfahren aufgrund von Preis - und/oder Ausschreibungsabsprachen hindeuten? | B31: =Fragenkatalog!B33 -> 0 | D31: =IF(B31="YES",OfferReferral,OfferReady) -> OFFER_READY_FOR_POLICY | O31: Hinweise auf Kartellrechtsverfahren
A32: =Fragenkatalog!A34 -> Wurden in den letzten zwei Jahren Verfahren gegen den Versicherungsnehmer, das Unternehmen (auch Tochter- und Beteiligungsunternehmen) oder einzelne Mitarbeiter aufgrund von Preis - und/oder Ausschreibungsabsprachen eingeleitet? | B32: =Fragenkatalog!B34 -> 0 | D32: =IF(B32="YES",OfferReferral,OfferReady) -> OFFER_READY_FOR_POLICY | O32: Kartellrechtsverfahren letzte zwei Jahre
A33: =Fragenkatalog!A35 -> Hat der Versicherungsnehmer Tochtergesellschaften in den USA, China, Indien, Südkorea, Brasilien, Südafrika, Japan, Australien oder in der Schweiz? | B33: =Fragenkatalog!B35 -> 0 | D33: =IF(B33="YES",OfferReferral,OfferReady) -> OFFER_READY_FOR_POLICY | O33: TU in Problemstaaten
A34: Es gibt MVU | B34: {=CoInsuredCompaniesExist} -> 0 | C34: =IF(AND($B$14="EWR",$B$34=TRUE),OfferReferral,OfferReady) -> OFFER_READY_FOR_POLICY | F34: =IF($B$34=TRUE,",hpst_mitversicherte_unternehmen:group-hpst-1","") | H34: =IF(AND($B$14="EWR",$B$34=TRUE),OfferReferral,OfferReady) -> OFFER_READY_FOR_POLICY | N34: MVU im EWR
A35: Globaler Status | C35: =VLOOKUP(rolandRiskManagerGlobalState,'Listen-Daten'!$Q$2:$R$4,2,0) -> #N/A | H35: =VLOOKUP(aragRiskManagerGlobalState,'Listen-Daten'!$Q$2:$R$4,2,0) -> #N/A | N35: Globaler Status
A36: Default | F36: ,hpst_kartellrecht:group-hpst-1
C37: =IF(COUNTIF(C3:C35,OfferDeclined), OfferDeclined,IF(COUNTIF(C3:C35,OfferReferralNoPremium),OfferReferralNoPremium,IF(COUNTIF(C3:C35,OfferReferral),OfferReferral,OfferReady))) -> OFFER_REFERRAL_NO_PREMIUM | D37: =IF(COUNTIF(D3:D33,OfferReferralNoPremium),OfferReferralNoPremium,IF(COUNTIF(D3:D33,OfferReferral),OfferReferral,OfferReady)) -> OFFER_READY_FOR_POLICY | E37: =(100+$E$8)*(100+$E$30)/10000 -> 1 | F37: =CONCATENATE(F15,F20,F28,F34,F36) -> ,hpst_geltungsbereich_2:hpst_rol-2,hpst_kartellrecht:group-hpst-1 | H37: =IF(COUNTIF(H3:H35,OfferDeclined), OfferDeclined,IF(COUNTIF(H3:H35,OfferReferral),OfferReferral,OfferReady)) -> OFFER_REFERRAL | I37: =IF(COUNTIF(I3:I33,OfferReferral),OfferReferral,OfferReady) -> OFFER_READY_FOR_POLICY | J37: =(100+$J$8)*(100+$J$30)/10000 -> 1
B38: =Fragenkatalog!B23 -> 0
C39: Deckungssumme | D39: Sublimit Kartell | E39: Mit / ohne Tarifprämie | F39: Klauseln | G39: Gesatmstatus | H39: Deckungssumme | I39: Sublimit Kartell | J39: Mit / ohne Tarifprämie | K39: Klauseln | L39: Gesatmstatus
A40: DS1 inkl. Sublimit | B40: =CONCATENATE(limit1, " / ", sublimit1) -> / | C40: =IF(limit1>2000000,OfferReferral,OfferReady) -> OFFER_READY_FOR_POLICY | D40: =IF(AND(sublimit1>0, ISNUMBER(MATCH(B8,'SIC-TAW-Codes'!Q:Q,0))),OfferReferralNoPremium,IF(sublimit1>150000,OfferReferral,D37)) -> OFFER_READY_FOR_POLICY | E40: =IF(ISNUMBER('Prämie - Roland'!D25),OfferReady,OfferReferralNoPremium) -> OFFER_REFERRAL_NO_PREMIUM | G40: =IF(OR(C$37=OfferDeclined,C40=OfferDeclined,D40=OfferDeclined,E40=OfferDeclined),OfferDeclined,IF(OR(C$37=OfferReferralNoPremium,C40=OfferReferralNoPremium,D40=OfferReferralNoPremium,E40=OfferReferralNoPremium),OfferReferralNoPremium,IF(OR(C$37=OfferReferral,C40=OfferReferral,D40=OfferReferral,E40=OfferReferral),OfferReferral,OfferReady))) -> OFFER_REFERRAL_NO_PREMIUM | H40: =IF(limit1>1500000,OfferReferral,OfferReady) -> OFFER_READY_FOR_POLICY | I40: =IF(sublimit1>0,OfferReferral,OfferReady) -> OFFER_READY_FOR_POLICY | J40: =IF(ISNUMBER('Prämie - Arag'!D25),OfferReady,OfferReferral) -> OFFER_REFERRAL | K40: =IF(limit1>2000000,",hpst_arag_ZweifachMaximierung:group-hpst-1","") | L40: =IF(OR(H$37=OfferDeclined,H40=OfferDeclined,I40=OfferDeclined,J40=OfferDeclined),OfferDeclined,IF(OR(H$37=OfferReferral,H40=OfferReferral,I40=OfferReferral,J40=OfferReferral),OfferReferral,OfferReady)) -> OFFER_REFERRAL
A41: DS1 | B41: =CONCATENATE(limit1) | C41: =IF(limit1>2000000,OfferReferral,OfferReady) -> OFFER_READY_FOR_POLICY | E41: =IF(ISNUMBER('Prämie - Roland'!D26),OfferReady,OfferReferralNoPremium) -> OFFER_REFERRAL_NO_PREMIUM | G41: =IF(OR(C$37=OfferDeclined,C40=OfferDeclined,D40=OfferDeclined,E40=OfferDeclined),OfferDeclined,IF(OR(C$37=OfferReferralNoPremium,C41=OfferReferralNoPremium,D41=OfferReferralNoPremium,E41=OfferReferralNoPremium),OfferReferralNoPremium,IF(OR(C$37=OfferReferral,C41=OfferReferral,D41=OfferReferral,E41=OfferReferral),OfferReferral,OfferReady))) -> OFFER_REFERRAL_NO_PREMIUM | H41: =IF(limit1>1500000,OfferReferral,OfferReady) -> OFFER_READY_FOR_POLICY | J41: =IF(ISNUMBER('Prämie - Arag'!D26),OfferReady,OfferReferral) -> OFFER_REFERRAL | K41: =IF(limit1>2000000,",hpst_arag_ZweifachMaximierung:group-hpst-1","") | L41: =IF(OR(H$37=OfferDeclined,H41=OfferDeclined,I41=OfferDeclined,J41=OfferDeclined),OfferDeclined,IF(OR(H$37=OfferReferral,H41=OfferReferral,I41=OfferReferral,J41=OfferReferral),OfferReferral,OfferReady)) -> OFFER_REFERRAL
A42: DS2 inkl. Sublimit | B42: =CONCATENATE(limit2, " / ", sublimit2) -> / | C42: =IF(limit2>2000000,OfferReferral,OfferReady) -> OFFER_READY_FOR_POLICY | D42: =IF(AND(sublimit2>0, ISNUMBER(MATCH(B8,'SIC-TAW-Codes'!Q:Q,0))),OfferReferralNoPremium,IF(sublimit2>150000,OfferReferral,D37)) -> OFFER_READY_FOR_POLICY | E42: =IF(ISNUMBER('Prämie - Roland'!D27),OfferReady,OfferReferralNoPremium) -> OFFER_REFERRAL_NO_PREMIUM | G42: =IF(OR(C$37=OfferDeclined,C40=OfferDeclined,D40=OfferDeclined,E40=OfferDeclined),OfferDeclined,IF(OR(C$37=OfferReferralNoPremium,C42=OfferReferralNoPremium,D42=OfferReferralNoPremium,E42=OfferReferralNoPremium),OfferReferralNoPremium,IF(OR(C$37=OfferReferral,C42=OfferReferral,D42=OfferReferral,E42=OfferReferral),OfferReferral,OfferReady))) -> OFFER_REFERRAL_NO_PREMIUM | H42: =IF(limit2>1500000,OfferReferral,OfferReady) -> OFFER_READY_FOR_POLICY | I42: =IF(sublimit2>0,OfferReferral,OfferReady) -> OFFER_READY_FOR_POLICY | J42: =IF(ISNUMBER('Prämie - Arag'!D27),OfferReady,OfferReferral) -> OFFER_REFERRAL | K42: =IF(limit2>2000000,",hpst_arag_ZweifachMaximierung:group-hpst-1","") | L42: =IF(OR(H$37=OfferDeclined,H42=OfferDeclined,I42=OfferDeclined,J42=OfferDeclined),OfferDeclined,IF(OR(H$37=OfferReferral,H42=OfferReferral,I42=OfferReferral,J42=OfferReferral),OfferReferral,OfferReady)) -> OFFER_REFERRAL
A43: DS2 | B43: =CONCATENATE(limit2) | C43: =IF(limit2>2000000,OfferReferral,OfferReady) -> OFFER_READY_FOR_POLICY | E43: =IF(ISNUMBER('Prämie - Roland'!D28),OfferReady,OfferReferralNoPremium) -> OFFER_REFERRAL_NO_PREMIUM | G43: =IF(OR(C$37=OfferDeclined,C40=OfferDeclined,D40=OfferDeclined,E40=OfferDeclined),OfferDeclined,IF(OR(C$37=OfferReferralNoPremium,C43=OfferReferralNoPremium,D43=OfferReferralNoPremium,E43=OfferReferralNoPremium),OfferReferralNoPremium,IF(OR(C$37=OfferReferral,C43=OfferReferral,D43=OfferReferral,E43=OfferReferral),OfferReferral,OfferReady))) -> OFFER_REFERRAL_NO_PREMIUM | H43: =IF(limit2>1500000,OfferReferral,OfferReady) -> OFFER_READY_FOR_POLICY | J43: =IF(ISNUMBER('Prämie - Arag'!D28),OfferReady,OfferReferral) -> OFFER_REFERRAL | K43: =IF(limit2>2000000,",hpst_arag_ZweifachMaximierung:group-hpst-1","") | L43: =IF(OR(H$37=OfferDeclined,H43=OfferDeclined,I43=OfferDeclined,J43=OfferDeclined),OfferDeclined,IF(OR(H$37=OfferReferral,H43=OfferReferral,I43=OfferReferral,J43=OfferReferral),OfferReferral,OfferReady)) -> OFFER_REFERRAL
A44: DS3 inkl. Sublimit | B44: =CONCATENATE(limit3, " / ", sublimit3) -> / | C44: =IF(limit3>2000000,OfferReferral,OfferReady) -> OFFER_READY_FOR_POLICY | D44: =IF(AND(sublimit3>0, ISNUMBER(MATCH(B8,'SIC-TAW-Codes'!Q:Q,0))),OfferReferralNoPremium,IF(sublimit3>150000,OfferReferral,D37)) -> OFFER_READY_FOR_POLICY | E44: =IF(ISNUMBER('Prämie - Roland'!D29),OfferReady,OfferReferralNoPremium) -> OFFER_REFERRAL_NO_PREMIUM | G44: =IF(OR(C$37=OfferDeclined,C40=OfferDeclined,D40=OfferDeclined,E40=OfferDeclined),OfferDeclined,IF(OR(C$37=OfferReferralNoPremium,C44=OfferReferralNoPremium,D44=OfferReferralNoPremium,E44=OfferReferralNoPremium),OfferReferralNoPremium,IF(OR(C$37=OfferReferral,C44=OfferReferral,D44=OfferReferral,F44=OfferReferral),OfferReferral,OfferReady))) -> OFFER_REFERRAL_NO_PREMIUM | H44: =IF(limit3>1500000,OfferReferral,OfferReady) -> OFFER_READY_FOR_POLICY | I44: =IF(sublimit3>0,OfferReferral,OfferReady) -> OFFER_READY_FOR_POLICY | J44: =IF(ISNUMBER('Prämie - Arag'!D29),OfferReady,OfferReferral) -> OFFER_REFERRAL | K44: =IF(limit3>2000000,",hpst_arag_ZweifachMaximierung:group-hpst-1","") | L44: =IF(OR(H$37=OfferDeclined,H44=OfferDeclined,I44=OfferDeclined,J44=OfferDeclined),OfferDeclined,IF(OR(H$37=OfferReferral,H44=OfferReferral,I44=OfferReferral,J44=OfferReferral),OfferReferral,OfferReady)) -> OFFER_REFERRAL
A45: DS3 | B45: =CONCATENATE(limit3) | C45: =IF(limit3>2000000,OfferReferral,OfferReady) -> OFFER_READY_FOR_POLICY | E45: =IF(ISNUMBER('Prämie - Roland'!D30),OfferReady,OfferReferralNoPremium) -> OFFER_REFERRAL_NO_PREMIUM | G45: =IF(OR(C$37=OfferDeclined,C40=OfferDeclined,D40=OfferDeclined,E40=OfferDeclined),OfferDeclined,IF(OR(C$37=OfferReferralNoPremium,C45=OfferReferralNoPremium,D45=OfferReferralNoPremium,E45=OfferReferralNoPremium),OfferReferralNoPremium,IF(OR(C$37=OfferReferral,C45=OfferReferral,D45=OfferReferral,E45=OfferReferral),OfferReferral,OfferReady))) -> OFFER_REFERRAL_NO_PREMIUM | H45: =IF(limit3>1500000,OfferReferral,OfferReady) -> OFFER_READY_FOR_POLICY | J45: =IF(ISNUMBER('Prämie - Arag'!D30),OfferReady,OfferReferral) -> OFFER_REFERRAL | K45: =IF(limit3>2000000,",hpst_arag_ZweifachMaximierung:group-hpst-1","") | L45: =IF(OR(H$37=OfferDeclined,H45=OfferDeclined,I45=OfferDeclined,J45=OfferDeclined),OfferDeclined,IF(OR(H$37=OfferReferral,H45=OfferReferral,I45=OfferReferral,J45=OfferReferral),OfferReferral,OfferReady)) -> OFFER_REFERRAL
B47: Gründe Referral | C47: Limit größer 2 Millionen Euro | D47: Sublimit größer 150,000 Euro oder Ausschlußbranche | E47: Außerhalb Tarif | H47: Limit größer 1,5 Millionen Euro | I47: Es existiert ein Sublimit | J47: Außerhalb Tarif
A48: Ausschlussbranche Sublimit Kartellrecht | B48: =IF(AND(OR(sublimit1>0,sublimit2>0,sublimit3>0),ISNUMBER(MATCH(B8,'SIC-TAW-Codes'!Q:Q,0))),"YES","NO") -> NO

Sheet Listen-Daten
A1: Rechtsform | C1: Status ARAG Referral | E1: Länder | I1: Status Angebot | K1: SIC-4-Code | L1: Branche | N1: Geltungsbereich Cosmo | O1: Roland Tarif | Q1: Globaler Status | R1: Status Angebot | T1: Arag Status | U1: Status Angebot | X1: Nummer | Y1: Versicherer
A2: 0 | B2: andere | C2: OFFER_REFERRAL | E2: AD | F2: 1 | G2: Andorra | I2: OFFER_READY_FOR_POLICY | K2: 0111 | L2: 0111 - Landwirtschaft Anbau - Weizen | N2: EU | O2: Europaweit | Q2: KO | R2: OFFER_DECLINED | T2: KO Trigger | U2: OFFER_DECLINED | X2: 5036 | Y2: SV Sparkassen Versicherung
A3: 1 | B3: LLC | C3: OFFER_DECLINED | E3: AE | F3: 2 | G3: United Arab Emirates | I3: OFFER_DECLINED | K3: 0112 | L3: 0112 - Landwirtschaft Anbau - Reis | N3: WORLD | O3: Weltweit | Q3: referral | R3: OFFER_REFERRAL | T3: Referral | U3: OFFER_REFERRAL | X3: 5052 | Y3: AXA Alternative
A4: 2 | B4: Corp. | C4: OFFER_DECLINED | E4: AF | F4: 3 | G4: Afghanistan | I4: OFFER_REFERRAL | K4: 0115 | L4: 0115 - Landwirtschaft Anbau - Mais | Q4: green | R4: OFFER_READY_FOR_POLICY | T4: Dunkelverarbeitung | U4: OFFER_READY_FOR_POLICY | X4: 5055 | Y4: DirectLine
A5: 3 | B5: Inc. | C5: OFFER_DECLINED | E5: AG | F5: 4 | G5: Antigua and Barbuda | I5: OFFER_REFERRAL_NO_PREMIUM | K5: 0116 | L5: 0116 - Landwirtschaft Anbau - Soyabohnen | X5: 5057 | Y5: Interlloyd VERSICHERUNGS-AG
A6: 4 | B6: LLP | C6: OFFER_DECLINED | E6: AI | F6: 5 | G6: Anguilla | K6: 0119 | L6: 0119 - Landwirtschaft Anbau - Sonstige Getreide | X6: 5061 | Y6: Mannheimer Versicherungen Holding AG
A7: 5 | B7: Plc | C7: OFFER_DECLINED | E7: AL | F7: 6 | G7: Albania | K7: 0131 | L7: 0131 - Landwirtschaft Anbau - Baumwolle | X7: 5079 | Y7: Hiscox AG - Niederlassung für die Bundesrepublik Deutschland
A8: 6 | B8: S.A.R.L. | C8: OFFER_DECLINED | E8: AM | F8: 7 | G8: Armenia | K8: 0132 | L8: 0132 - Landwirtschaft Anbau - Tabak | X8: 5080 | Y8: KRAVAG-ALLGEMEINE Versicherungs-Aktiengesellschaft
A9: 7 | B9: SA | C9: OFFER_DECLINED | E9: AO | F9: 8 | G9: Angola | K9: 0133 | L9: 0133 - Landwirtschaft Anbau - Zuckerpflanzen (-rohr, -rüben) | X9: 5084 | Y9: Deutsche Internet
A10: 8 | B10: PartGmbB | C10: OFFER_REFERRAL | E10: AQ | F10: 9 | G10: Antarctica | K10: 0134 | L10: 0134 - Landwirtschaft Anbau - Kartoffeln | X10: 5085 | Y10: HDI Privat Versicherung AG
A11: 9 | B11: PartG | C11: OFFER_REFERRAL | E11: AR | F11: 10 | G11: Argentina | K11: 0139 | L11: 0139 - Landwirtschaft Anbau - Sonstige Feldfrüchte, außer Getreide | X11: 5086 | Y11: HUK 24 AG
A12: 10 | B12: AG | C12: OFFER_READY_FOR_POLICY | E12: AS | F12: 11 | G12: American Samoa | K12: 0161 | L12: 0161 - Landwirtschaft Anbau - Gemüse u. Melonen | X12: 5093 | Y12: Westfälische Provinzial Versicherung AG
A13: 11 | B13: SE | C13: OFFER_READY_FOR_POLICY | E13: AT | F13: 12 | G13: Austria | K13: 0171 | L13: 0171 - Landwirtschaft Anbau - Beerenfrüchte | X13: 5095 | Y13: Provinzial Versicherungsanstalt der Rheinprovinz
A14: 12 | B14: Behörde | C14: OFFER_REFERRAL | E14: AU | F14: 13 | G14: Australia | K14: 0172 | L14: 0172 - Landwirtschaft Anbau - Weintrauben | X14: 5129 | Y14: Deutsche Familienversicherung
A15: 13 | B15: e.G. | C15: OFFER_DECLINED | E15: AW | F15: 14 | G15: Aruba | K15: 0173 | L15: 0173 - Landwirtschaft Anbau - Nüsse | X15: 5142 | Y15: Chubb European Group Limited - Direktion für Deutschland
A16: 14 | B16: e.K. | C16: OFFER_DECLINED | E16: AX | F16: 15 | G16: Åland Islands | K16: 0174 | L16: 0174 - Landwirtschaft Anbau - Zitrusfrüchte | X16: 5151 | Y16: Zürich Versicherung AG
A17: 15 | B17: e.V. | C17: OFFER_REFERRAL | E17: AZ | F17: 16 | G17: Azerbaijan | K17: 0175 | L17: 0175 - Landwirtschaft Anbau - Jährliche Baumfrüchte | X17: 5310 | Y17: Bayerische Beamten
... A42: 40 | B42: Einzelunternehmen | C42: OFFER_REFERRAL | E42: CF | F42: 41 | G42: Central African Republic | K42: 0723 | L42: 0723 - Landwirtschaftl. Dienstleistungen - Feldfruchtpräparation z. Verkauf, außer Baumwollentkörnung | X42: 5405 | Y42: Alte Leipziger
E43: CG | F43: 42 | G43: Congo | K43: 0724 | L43: 0724 - Landwirtschaftl. Dienstleistungen - Baumwollentkörnung | X43: 5412 | Y43: Mecklenburgische Versicherungsgruppe Direktion
E44: CH | F44: 43 | G44: Switzerland | K44: 0741 | L44: 0741 - Landwirtschaftl. Dienstleistungen - Veterinärdienst f. lebend. Vieh, einschl. Tierpraxen u. -krankenhäuser | X44: 5414 | Y44: Münchener Verein Allgemeine Versicherung-AG
E45: CI | F45: 44 | G45: Côte d'Ivoire | K45: 0742 | L45: 0742 - Landwirtschaftl. Dienstleistungen - Veterinärdienst f. Spezial- u. Haustiere | X45: 5426 | Y45: Nürnberger Allgemeine Versicherungs-Aktiengesellschaft
E46: CK | F46: 45 | G46: Cook Islands | K46: 0751 | L46: 0751 - Landwirtschaftl. Dienstleistungen - Viehzucht, Medizin, Betreuung, Qualitätsprüfung | X46: 5430 | Y46: Oldenburgische Landesbrandkasse
E47: CL | F47: 46 | G47: Chile | K47: 0761 | L47: 0761 - Landwirtschaftl. Dienstleistungen - Arbeitstrupps u. Mannschaftsführer für die Landwirtschaft | X47: 5441 | Y47: Vereinte Spezial Versicherung AG
E48: CM | F48: 47 | G48: Cameroon | K48: 0762 | L48: 0762 - Landwirtschaftl. Dienstleistungen - Verwaltung, Landwirtschaftl. Betrieb, Landwirtschaftl. Organisationsdienst | X48: 5448 | Y48: SCHWEIZER-NATIONAL
E49: CN | F49: 48 | G49: China | K49: 0781 | L49: 0781 - Landwirtschaftl. Dienstleistungen - Landschaftsarchitektur, -beratung u. -planung | X49: 5450 | Y49: Basler Securitas
E50: CO | F50: 49 | G50: Colombia | K50: 0782 | L50: 0782 - Landwirtschaftl. Dienstleistungen - Rasen- u. Gartenpflege | X50: 5456 | Y50: Generali Versicherungs AG
E51: CR | F51: 50 | G51: Costa Rica | K51: 0783 | L51: 0783 - Landwirtschaftl. Dienstleistungen - Zierbäume u. Sträucher | X51: 5458 | Y51: Transatlantische Allgemeine Versicherung AG
E52: CU | F52: 51 | G52: Cuba | K52: 0811 | L52: 0811 - Landwirtschaftl. Dienstleistungen - Nutzholzanbau | X52: 5459 | Y52: Uelzener Allgemeine Versicherung-Ges.aG
E53: CV | F53: 52 | G53: Cabo Verde | K53: 0831 | L53: 0831 - Forstwirtschaft - Baumschulen und Forstprodukte | X53: 5466 | Y53: Provinzial Brandkasse Versicherungsanstalt Schleswig-Holstein
E54: CW | F54: 53 | G54: Curaçao | K54: 0851 | L54: 0851 - Forstwirtschaft - Forstwirtschaftl. Dienste | X54: 5473 | Y54: Volksfürsorge Deutsche Lebensversicherung AG
... E124: KW | F124: 123 | G124: Kuwait | K124: 2026 | L124: 2026 - Lebensmittel- und verwandte Produkte - Milch (außer Trockenmilch) | X124: OTHER | Y124: Anderer
E125: KY | F125: 124 | G125: Cayman Islands | K125: 2032 | L125: 2032 - Lebensmittel- und verwandte Produkte - Konservenspezialitäten
E126: KZ | F126: 125 | G126: Kazakhstan | K126: 2033 | L126: 2033 - Lebensmittel- und verwandte Produkte - Obst- u. Gemüsekonserven, Marmeladen, Gelees
E127: LA | F127: 126 | G127: Lao People's Democratic Republic | K127: 2034 | L127: 2034 - Lebensmittel- und verwandte Produkte - Trockengemüse u. -früchte, Trockensuppen
E128: LB | F128: 127 | G128: Lebanon | K128: 2035 | L128: 2035 - Lebensmittel- und verwandte Produkte - Essigfrüchte u. -gemüse, Gemüsesaucen, Gewürze, Salatsaucen
E129: LC | F129: 128 | G129: Saint Lucia | K129: 2037 | L129: 2037 - Lebensmittel- und verwandte Produkte - Tiefgefrorenes Obst u. Gemüse, Fruchtsäfte
E130: LI | F130: 129 | G130: Liechtenstein | K130: 2038 | L130: 2038 - Lebensmittel- und verwandte Produkte - Sonstige Tiefkühlspezialitäten
E131: LK | F131: 130 | G131: Sri Lanka | K131: 2041 | L131: 2041 - Lebensmittel- und verwandte Produkte - Mehl- u. andere Mühlenprodukte
E132: LR | F132: 131 | G132: Liberia | K132: 2043 | L132: 2043 - Lebensmittel- und verwandte Produkte - Getreideflocken
E133: LS | F133: 132 | G133: Lesotho | K133: 2044 | L133: 2044 - Lebensmittel- und verwandte Produkte - Reisprodukte
E134: LT | F134: 133 | G134: Lithuania | K134: 2045 | L134: 2045 - Lebensmittel- und verwandte Produkte - Backmischungen und Teige
E135: LU | F135: 134 | G135: Luxembourg | K135: 2046 | L135: 2046 - Lebensmittel- und verwandte Produkte - Naßgetreidemühlen
E136: LV | F136: 135 | G136: Latvia | K136: 2047 | L136: 2047 - Lebensmittel- und verwandte Produkte - Hunde- und Katzenfutter
... E250: ZW | F250: 249 | G250: Zimbabwe | K250: 2541 | L250: 2541 - Möbel und Einrichtungsgegenstände - Holztrennwände, Regale, Büro- u. Lagereinrichtungen
K251: 2542 | L251: 2542 - Möbel und Einrichtungsgegenstände - Trennwände, Regale, Büro- u. Lagereinrichtungen (außer Holz)
K252: 2591 | L252: 2591 - Möbel und Einrichtungsgegenstände - Metallwaren für Innenausstattung
K253: 2599 | L253: 2599 - Möbel und Einrichtungsgegenstände - Sonstige Möbel- u. Einrichtungsgegenstände
K254: 2611 | L254: 2611 - Papier und verwandte Produkte - Papiermassehersteller, Altpapieraufbereitung
K255: 2621 | L255: 2621 - Papier und verwandte Produkte - Papierfabriken
K256: 2631 | L256: 2631 - Papier und verwandte Produkte - Kartonagenfabriken
K257: 2652 | L257: 2652 - Papier und verwandte Produkte - Zusammensetzbare Kartons
K258: 2653 | L258: 2653 - Papier und verwandte Produkte - Hartfaserplattenschachteln u. Wellpappkartons
K259: 2655 | L259: 2655 - Papier und verwandte Produkte - Faserstoffbecher, Dosen, Trommeln etc.
K260: 2656 | L260: 2656 - Papier und verwandte Produkte - Hygienische Lebensmittelbehälter (außer faltbare)
K261: 2657 | L261: 2657 - Papier und verwandte Produkte - Faltkartons (auch für Lebensmittel)
K262: 2671 | L262: 2671 - Papier und verwandte Produkte - Packpapier u. Plastikfolie, beschichtet
... K1001: 9999 | L1001: 9999 - Nicht klassifizierbare Einrichtungen - Nicht klassifizierbare Einrichtungen

Sheet SIC-TAW-Codes
A1: Code | B1: Klarname | C1: Zuordnung ROLAND TAW-Code | D1: Branche | E1: Zusatz | F1: Zuordnung ROLAND TAW-Code | G1: Branche | J1: Zuschlags-Branchen Straf | M1: Ausschluss-Branchen Straf | P1: Ausschluss-Branchen Kartell | S1: Die gelbmarkierten Felder werden aus den versichererspezifischen Branchen-Excels befüllt!
A2: 01 - 09 | B2: 01 - 09 Land- und Forstwirtschaft | J2: TAW_BEZEICHNUNG | K2: TAW_CODE | M2: TAW_BEZEICHNUNG | N2: TAW_CODE | P2: TAW_BEZEICHNUNG | Q2: TAW_CODE
A3: 0100 | B3: 0100 --- Landwirtschaft Anbau --- | J3: Abfallwirtschaft - Sammlung, Transport | K3: 6006 | M3: Anfrage | N3: 0001 | P3: Abfallwirtschaft - Atommüll | Q3: 6008
A4: 0111 | B4: 0111 Weizen | C4: 9333 | D4: Landwirtschaftlicher Betrieb | F4: 9333 | G4: Landwirtschaftlicher Betrieb | J4: Abfallwirtschaft - Verwertung (Recycling), Deponie | K4: 6007 | M4: Abfallwirtschaft - Atommüll | N4: 6008 | P4: Abfallwirtschaft - Sammlung, Transport | Q4: 6006 | S4: ARAG
A5: 0112 | B5: 0112 Reis | C5: 9333 | D5: Landwirtschaftlicher Betrieb | F5: 9333 | G5: Landwirtschaftlicher Betrieb | J5: Abwasserbeseitigung | K5: 6004 | M5: Ambulanter Pflegedienst/Altenpflegedienst | N5: 5467 | P5: Abfallwirtschaft - Verwertung (Recycling), Deponie | Q5: 6007 | S5: Referral | T5: Prämien-Anpassungen
A6: 0115 | B6: 0115 Mais | C6: 9333 | D6: Landwirtschaftlicher Betrieb | F6: 9333 | G6: Landwirtschaftlicher Betrieb | J6: Arzneimittelherstellung | K6: 2460 | M6: Anlagenberatungsbüro | N6: 7001 | P6: Abwasserbeseitigung | Q6: 6004
A7: 0116 | B7: 0116 Soyabohnen | C7: 9333 | D7: Landwirtschaftlicher Betrieb | F7: 9333 | G7: Landwirtschaftlicher Betrieb | J7: Asbestbe- und -verarbeitung | K7: 9651 | M7: Arzneimittelgroßhandel | N7: 5405 | P7: Anlagenberatungsbüro | Q7: 7001
A8: 0119 | B8: 0119 Sonstige Getreide | C8: 9333 | D8: Landwirtschaftlicher Betrieb | F8: 9333 | G8: Landwirtschaftlicher Betrieb | J8: Klärwerk | K8: 8418 | M8: Asset Management (Vermögensverwaltung, Anlageberatung) | N8: 7022 | P8: Anlagenreinigung | Q8: 8012
A9: 0131 | B9: 0131 Baumwolle | C9: 9333 | D9: Landwirtschaftlicher Betrieb | F9: 9333 | G9: Landwirtschaftlicher Betrieb | J9: Kraftfahrzeug-Verwertung | K9: 4211 | M9: Bank/Sparkasse | N9: 7000 | P9: Arzneimittelherstellung | Q9: 2460
A10: 0132 | B10: 0132 Tabak | C10: 9333 | D10: Landwirtschaftlicher Betrieb | F10: 9333 | G10: Landwirtschaftlicher Betrieb | J10: Lagerhaus/Lagereibetrieb - mit Gefahrgut | K10: 6614 | M10: Containerdienst | N10: 8842 | P10: Asset Management (Vermögensverwaltung, Anlageberatung) | Q10: 7022
A11: 0133 | B11: 0133 Zuckerpflanzen (-rohr, -rüben) | C11: 9333 | D11: Landwirtschaftlicher Betrieb | F11: 9333 | G11: Landwirtschaftlicher Betrieb | J11: Pharmazeutische Artikelherstellung | K11: 2461 | M11: Entsorgung | N11: 1552 | P11: Bank/Sparkasse | Q11: 7000
A12: 0134 | B12: 0134 Kartoffeln | C12: 9333 | D12: Landwirtschaftlicher Betrieb | F12: 9333 | G12: Landwirtschaftlicher Betrieb | J12: Recyclingunternehmen | K12: 1554 | M12: Finanzberater/Finanzkaufmann | N12: 7005 | P12: Bauausführung/Bauhauptgewerbe | Q12: 7403
A13: 0139 | B13: 0139 Sonstige Feldfrüchte, außer Getreide | C13: 9333 | D13: Landwirtschaftlicher Betrieb | F13: 9333 | G13: Landwirtschaftlicher Betrieb | J13: Spedition/Fuhrunternehmen - mit Gefahrgut/-lager | K13: 6641 | M13: Finanzvermittlungsbüro | N13: 7021 | P13: Baumarkt | Q13: 8048
A14: 0161 | B14: 0161 Gemüse u. Melonen | C14: 9333 | D14: Landwirtschaftlicher Betrieb | F14: 9333 | G14: Landwirtschaftlicher Betrieb | J14: Transportunternehmen mit Gefahrgut | K14: 8811 | M14: Flughafen (Personenbeförderung) | N14: 1458 | P14: Baunebengewerbe | Q14: 7406
A15: 0171 | B15: 0171 Beerenfrüchte | C15: 9333 | D15: Landwirtschaftlicher Betrieb | F15: 9333 | G15: Landwirtschaftlicher Betrieb | M15: Fondsgesellschaften (z.B. Immobilienfonds) | N15: 8838 | P15: Baustoffhandel | Q15: 7421
A16: 0172 | B16: 0172 Weintrauben | C16: 9333 | D16: Landwirtschaftlicher Betrieb | F16: 9333 | G16: Landwirtschaftlicher Betrieb | M16: Heizölhandel | N16: 8331 | P16: Baustoffherstellung | Q16: 9619
A17: 0173 | B17: 0173 Nüsse | C17: 9333 | D17: Landwirtschaftlicher Betrieb | F17: 9333 | G17: Landwirtschaftlicher Betrieb | M17: Investmentfonds | N17: 7020 | P17: Bauunternehmen | Q17: 7410
A18: 0174 | B18: 0174 Zitrusfrüchte | C18: 9333 | D18: Landwirtschaftlicher Betrieb | F18: 9333 | G18: Landwirtschaftlicher Betrieb | M18: Investmentgesellschaft | N18: 7008 | P18: Betonwerk | Q18: 9645
A19: 0175 | B19: 0175 Jährliche Baumfrüchte | C19: 9333 | D19: Landwirtschaftlicher Betrieb | F19: 9333 | G19: Landwirtschaftlicher Betrieb | M19: Kapitalanlagegesellschaft | N19: 8839 | P19: Brauerei | Q19: 2106
A20: 0179 | B20: 0179 Sonstiges Obst und Nüsse | C20: 9333 | D20: Landwirtschaftlicher Betrieb | F20: 9333 | G20: Landwirtschaftlicher Betrieb | M20: Kommunen | N20: 8840 | P20: Brennerei | Q20: 2107
A21: 0181 | B21: 0181 Gartengestaltung und Baumschulenerzeugnisse | C21: 9315 | D21: Garten-und Landschaftsbau | F21: 9315 | G21: Garten-und Landschaftsbau | M21: Konkurs-/Insolvenzverwaltung | N21: 7010 | P21: Brennerei | Q21: 2107
A22: 0182 | B22: 0182 Feldfrüchte aus Treibhaus und Mistbeet | C22: 9333 | D22: Landwirtschaftlicher Betrieb | F22: 9333 | G22: Landwirtschaftlicher Betrieb | M22: Kraftstoffhandel/Brennstoffhandel | N22: 4250 | P22: Chemikalienhandel | Q22: 2455
A23: 0191 | B23: 0191 Allgem. Landwirtschaft, Anbau | C23: 9333 | D23: Landwirtschaftlicher Betrieb | F23: 9333 | G23: Landwirtschaftlicher Betrieb | M23: Kraftstoffherstellung | N23: 1537 | P23: Chemikalienherstellung | Q23: 2454
A24: 0192 | B24: 0192 Gartenbauspezialitäten | C24: 9315 | D24: Garten-und Landschaftsbau | F24: 9315 | G24: Garten-und Landschaftsbau | M24: Kraftwerk | N24: 1001 | P24: Containerdienst | Q24: 8842
A25: 0200 | B25: 0200 --- Landwirtschaft Viehzucht --- | M25: Krankenhaus | N25: 5450 | P25: Drogerie | Q25: 5404
A26: 0211 | B26: 0211 Rindvieh und Weidewirtschaft | C26: 9351 | D26: Tierzucht (Landwirt / Großbetriebe) | F26: 9351 | G26: Tierzucht (Landwirt / Großbetriebe) | M26: Krankenkasse | N26: 7099 | P26: e-Commerce (Internet-Handel) | Q26: 8141
A27: 0212 | B27: 0212 Rindvieh, ohne Weiden | C27: 9351 | D27: Tierzucht (Landwirt / Großbetriebe) | F27: 9351 | G27: Tierzucht (Landwirt / Großbetriebe) | M27: Mineralölhandel | N27: 4249 | P27: Einkaufszentrum/-markt oder Supermarkt | Q27: 8146
A28: 0213 | B28: 0213 Schweinezucht | C28: 9351 | D28: Tierzucht (Landwirt / Großbetriebe) | F28: 9351 | G28: Tierzucht (Landwirt / Großbetriebe) | M28: Pharmazeutischer Handel | N28: 2463 | P28: Einrichtungshaus | Q28: 8147
A29: 0214 | B29: 0214 Schaf- und Ziegenzucht | C29: 9351 | D29: Tierzucht (Landwirt / Großbetriebe) | F29: 9351 | G29: Tierzucht (Landwirt / Großbetriebe) | M29: Postagentur/Postbankagentur | N29: 8612 | P29: Einzelhandelsgeschäft | Q29: 8148
A30: 0219 | B30: 0219 Viehzucht allgemein, außer Geflügel, Milchwirtschaft | C30: 9351 | D30: Tierzucht (Landwirt / Großbetriebe) | F30: 9351 | G30: Tierzucht (Landwirt / Großbetriebe) | M30: Rechtsanwalt (mit Strafrecht) | N30: 7024 | P30: Eisenwarenhandel | Q30: 8153
A31: 0241 | B31: 0241 Milchwirtschaft | C31: 9351 | D31: Tierzucht (Landwirt / Großbetriebe) | F31: 9351 | G31: Tierzucht (Landwirt / Großbetriebe) | M31: Schwer- und Leichtathletik Verein | N31: B0007 | P31: Elektronische Bauelementehandel | Q31: 8160
A32: 0251 | B32: 0251 Brat-, Grill- und Masthähnchen | C32: 9351 | D32: Tierzucht (Landwirt / Großbetriebe) | F32: 9351 | G32: Tierzucht (Landwirt / Großbetriebe) | M32: Sportvereine ( Profis ) | N32: 7469 | P32: Elektrowarenherstellung | Q32: 1590
A33: 0252 | B33: 0252 Hühnereier | C33: 9351 | D33: Tierzucht (Landwirt / Großbetriebe) | F33: 9351 | G33: Tierzucht (Landwirt / Großbetriebe) | M33: Unternehmensberatung mit Finanzierungsberatung | N33: 7027 | P33: Energie-Erzeuger (Strom, Gas, Wasser) | Q33: 1007
A34: 0253 | B34: 0253 Puten und Puteneier | C34: 9351 | D34: Tierzucht (Landwirt / Großbetriebe) | F34: 9351 | G34: Tierzucht (Landwirt / Großbetriebe) | M34: Vermögensberatung | N34: 7019 | P34: Energie-Versorger (Strom, Gas, Wasser) | Q34: 1008
A35: 0254 | B35: 0254 Geflügelzucht und Brüterei | C35: 9351 | D35: Tierzucht (Landwirt / Großbetriebe) | F35: 9351 | G35: Tierzucht (Landwirt / Großbetriebe) | M35: Vermögensverwaltung | N35: 7023 | P35: Entsorgung | Q35: 1552
A36: 0259 | B36: 0259 Sonstige Geflügel und Eier | C36: 9351 | D36: Tierzucht (Landwirt / Großbetriebe) | F36: 9351 | G36: Tierzucht (Landwirt / Großbetriebe) | M36: Versicherung | N36: 7100 | P36: Fassaden/Wandverkleidungen | Q36: 1214
A37: 0271 | B37: 0271 Pelztiere und Kaninchen | C37: 9351 | D37: Tierzucht (Landwirt / Großbetriebe) | F37: 9351 | G37: Tierzucht (Landwirt / Großbetriebe) | M37: Versicherungsagentur | N37: 7101 | P37: Feinkostgeschäft | Q37: 8183
... A41: 0291 | B41: 0291 Allgemeine Landwirtschaft, hauptsächl. Viehzucht | C41: 9351 | D41: Tierzucht (Landwirt / Großbetriebe) | F41: 9351 | G41: Tierzucht (Landwirt / Großbetriebe) | M41: Wettbüro | N41: 8880 | P41: Finanzberater/Finanzkaufmann | Q41: 7005
A42: 0700 | B42: 0700 --- Landwirtschaftl. Dienstleistungen --- | M42: Anfrage | N42: 0002 | P42: Finanzvermittlungsbüro | Q42: 7021
A43: 0711 | B43: 0711 Bodenvorbereitungsdienste | C43: 9315 | D43: Garten-und Landschaftsbau | F43: 9315 | G43: Garten-und Landschaftsbau | M43: Versicherte Branche gem. Antrag RKL 2 USRU | N43: 1033 | P43: Fondsgesellschaften (z.B. Immobilienfonds) | Q43: 8838
A44: 0721 | B44: 0721 Anbau, Kultur u. Pflanzenschutz | C44: 9315 | D44: Garten-und Landschaftsbau | F44: 9315 | G44: Garten-und Landschaftsbau | P44: Förderanlagen/Aufzugherstellung | Q44: 1568
A45: 0722 | B45: 0722 Ernte, hauptsächl. maschinell | C45: 9333 | D45: Landwirtschaftlicher Betrieb | F45: 9333 | G45: Landwirtschaftlicher Betrieb | P45: Funktelefonhandel | Q45: 8240
A46: 0723 | B46: 0723 Feldfruchtpräparation z. Verkauf, außer Baumwollentkörnung | C46: 9333 | D46: Landwirtschaftlicher Betrieb | F46: 9333 | G46: Landwirtschaftlicher Betrieb | P46: Futtermittelherstellung | Q46: 9360
A47: 0724 | B47: 0724 Baumwollentkörnung | C47: 9333 | D47: Landwirtschaftlicher Betrieb | F47: 9333 | G47: Landwirtschaftlicher Betrieb | P47: Futtermittelherstellung | Q47: 9360
A48: 0741 | B48: 0741 Veterinärdienst f. lebend. Vieh, einschl. Tierpraxen u. -krankenhäuser | C48: 6469 | D48: Tierarzt | F48: 6469 | G48: Tierarzt | P48: Getränke-Herstellung | Q48: 2163
A49: 0742 | B49: 0742 Veterinärdienst f. Spezial- u. Haustiere | C49: 6469 | D49: Tierarzt | F49: 6469 | G49: Tierarzt | P49: Glasbearbeitung/Glasverarbeitung | Q49: 9626
A50: 0751 | B50: 0751 Viehzucht, Medizin, Betreuung, Qualitätsprüfung | C50: 6469 | D50: Tierarzt | F50: 6469 | G50: Tierarzt | P50: Glaserei | Q50: 8287
A51: 0752 | B51: 0752 Tierdressuren, Tier-hotels, Hundepflegesalons usw. | C51: 9350 | D51: Tierzucht (Haustiere) | F51: 9350 | G51: Tierzucht (Haustiere) | P51: Glasherstellung | Q51: 9625
A52: 0761 | B52: 0761 Arbeitstrupps u. Mannschaftsführer für die Landwirtschaft | C52: 9333 | D52: Landwirtschaftlicher Betrieb | F52: 9333 | G52: Landwirtschaftlicher Betrieb | P52: Heißmangel | Q52: 6024
A53: 0762 | B53: 0762 Verwaltung, Landwirtschaftl. Betrieb, Landwirtschaftl. Organisationsdienst | C53: 9333 | D53: Landwirtschaftlicher Betrieb | F53: 9333 | G53: Landwirtschaftlicher Betrieb | P53: Heizölhandel | Q53: 8331
A54: 0781 | B54: 0781 Landschaftsarchitektur, -beratung u. -planung | C54: 9315 | D54: Garten-und Landschaftsbau | F54: 9315 | G54: Garten-und Landschaftsbau | P54: Heizungsinstallationsbetrieb | Q54: 1281
A55: 0782 | B55: 0782 Rasen- u. Gartenpflege | C55: 9315 | D55: Garten-und Landschaftsbau | F55: 9315 | G55: Garten-und Landschaftsbau | P55: Hochbau | Q55: 8337
A56: 0783 | B56: 0783 Zierbäume u. Sträucher | C56: 9315 | D56: Garten-und Landschaftsbau | F56: 9315 | G56: Garten-und Landschaftsbau | P56: Hochbau und Tiefbau | Q56: 7411
A57: 0800 | B57: 0800 --- Forstwirtschaft --- | P57: Hörgeräteakustiker | Q57: 8348
A58: 0811 | B58: 0811 Nutzholzanbau | C58: 1101 | D58: Forstwirtschaftlicher Betrieb | F58: 1101 | G58: Forstwirtschaftlicher Betrieb | P58: Immobilienhandel | Q58: 7301
A59: 0831 | B59: 0831 Baumschulen und Forstprodukte | C59: 8050 | D59: Baumschule | F59: 8050 | G59: Baumschule | P59: Immobilienverkauf | Q59: 7302
A60: 0851 | B60: 0851 Forstwirtschaftl. Dienste | C60: 1101 | D60: Forstwirtschaftlicher Betrieb | F60: 1101 | G60: Forstwirtschaftlicher Betrieb | P60: Immobilienverwaltung | Q60: 7303
A61: 0900 | B61: 0900 --- Fischerei, Jagd u. Fallenstellen --- | P61: Informationstechnik | Q61: 7455
A62: 0912 | B62: 0912 Fische (Fischfang) | C62: 9306 | D62: Fischerei | F62: 9306 | G62: Fischerei | P62: Internet-Handel/e-Commerce | Q62: 8372
A63: 0913 | B63: 0913 Schalentiere (Krabben, Hummer, Shrimps, Austern) | C63: 9306 | D63: Fischerei | F63: 9306 | G63: Fischerei | P63: Investmentfonds | Q63: 7020
A64: 0919 | B64: 0919 Versch. Meeresprodukte (Perlen, Schildkröten, Wale) | C64: 9306 | D64: Fischerei | F64: 9306 | G64: Fischerei | P64: Investmentgesellschaft | Q64: 7008
A65: 0921 | B65: 0921 Fischzucht u. -Konserven | C65: 2197 | D65: Konservenherstellung | F65: 2197 | G65: Konservenherstellung | P65: Kaffee-/Teehandel | Q65: 8384
A66: 0971 | B66: 0971 Jagd u. Fallenstellerei, Wildschutz | C66: 6909 | D66: Bewachungsunternehmen | F66: 6909 | G66: Bewachungsunternehmen | P66: Kaffeerösterei | Q66: 2198
A67: 10 - 14 | B67: 10 - 14 Bergbau und Energiegewinnung | P67: Kapitalanlagegesellschaft | Q67: 8839
A68: 1000 | B68: 1000 --- Metallbergbau --- | P68: Karosseriebau | Q68: 1246
A69: 1011 | B69: 1011 Eisenerze | C69: 0001 | D69: Anfrage | F69: 1033 | G69: Versicherte Branche gem. Antrag RKL 3 USRU | P69: Kieswerk | Q69: 9618
A70: 1021 | B70: 1021 Kupfererze | C70: 0001 | D70: Anfrage | F70: 1033 | G70: Versicherte Branche gem. Antrag RKL 3 USRU | P70: Kosmetikherstellung | Q70: 2421
A71: 1031 | B71: 1031 Blei u. Zinkerze | C71: 0001 | D71: Anfrage | F71: 1033 | G71: Versicherte Branche gem. Antrag RKL 3 USRU | P71: Kraftfahrzeug-Elektrik | Q71: 4203
A72: 1041 | B72: 1041 Gold aus Erzadern | C72: 0001 | D72: Anfrage | F72: 1033 | G72: Versicherte Branche gem. Antrag RKL 3 USRU | P72: Kraftfahrzeugherstellung | Q72: 1518
A73: 1044 | B73: 1044 Silbererze | C73: 0001 | D73: Anfrage | F73: 1033 | G73: Versicherte Branche gem. Antrag RKL 3 USRU | P73: Kraftstoffhandel/Brennstoffhandel | Q73: 4250
A74: 1061 | B74: 1061 Erze für Ferrolegierungen, außer Vanadium | C74: 0001 | D74: Anfrage | F74: 1033 | G74: Versicherte Branche gem. Antrag RKL 3 USRU | P74: Kraftstoffherstellung | Q74: 1537
A75: 1081 | B75: 1081 Nebendienste f. Erzbergbau, Bergbau f. fremde Rechnung | C75: 0001 | D75: Anfrage | F75: 1033 | G75: Versicherte Branche gem. Antrag RKL 3 USRU | P75: Kraftwerk | Q75: 1001
A76: 1094 | B76: 1094 Uran-, Radium-, Vanadiumerze | C76: 0001 | D76: Anfrage | F76: 1033 | G76: Versicherte Branche gem. Antrag RKL 3 USRU | P76: Krankenkasse | Q76: 7099
A77: 1099 | B77: 1099 Andere Metallerze | C77: 0001 | D77: Anfrage | F77: 1033 | G77: Versicherte Branche gem. Antrag RKL 3 USRU | P77: Landmaschinenhandel | Q77: 3940
A78: 1200 | B78: 1200 --- Kohlebergbau --- | P78: Landmaschinenherstellung | Q78: 3941
A79: 1221 | B79: 1221 Stein- und Braunkohle-Tagebau | C79: 1007 | D79: Energie-Erzeuger (Strom, Gas, Wasser) | F79: 1007 | G79: Energie-Erzeuger (Strom, Gas, Wasser) | P79: Lebensmittelhandel | Q79: 3910
A80: 1222 | B80: 1222 Steinkohle-Untertagebau | C80: 1007 | D80: Energie-Erzeuger (Strom, Gas, Wasser) | F80: 1007 | G80: Energie-Erzeuger (Strom, Gas, Wasser) | P80: Lebensmittelherstellung | Q80: 2176
A81: 1231 | B81: 1231 Anthrazitbergbau | C81: 1007 | D81: Energie-Erzeuger (Strom, Gas, Wasser) | F81: 1007 | G81: Energie-Erzeuger (Strom, Gas, Wasser) | P81: Leuchtenhandel | Q81: 8472
A82: 1241 | B82: 1241 Kohlebergbaudienste | C82: 1007 | D82: Energie-Erzeuger (Strom, Gas, Wasser) | F82: 1007 | G82: Energie-Erzeuger (Strom, Gas, Wasser) | P82: Logistik | Q82: 7011
A83: 1300 | B83: 1300 --- Öl- u. Gasgewinnung --- | P83: Mälzerei | Q83: 2160
A84: 1311 | B84: 1311 Rohöl u. Erdgas | C84: 1007 | D84: Energie-Erzeuger (Strom, Gas, Wasser) | F84: 1007 | G84: Energie-Erzeuger (Strom, Gas, Wasser) | P84: Medizinische Apparate/Geräte (Handel) | Q84: 5458
A85: 1321 | B85: 1321 Flüssiges Erdgas | C85: 1007 | D85: Energie-Erzeuger (Strom, Gas, Wasser) | F85: 1007 | G85: Energie-Erzeuger (Strom, Gas, Wasser) | P85: Medizinische Apparate/Geräte (Herstellung) | Q85: 5459
A86: 1381 | B86: 1381 Öl-u. Gasbohrarbeiten | C86: 1007 | D86: Energie-Erzeuger (Strom, Gas, Wasser) | F86: 1007 | G86: Energie-Erzeuger (Strom, Gas, Wasser) | P86: Metzgerei | Q86: 2118
A87: 1382 | B87: 1382 Exploration von Öl-u. Gasvorkommen | C87: 1007 | D87: Energie-Erzeuger (Strom, Gas, Wasser) | F87: 1007 | G87: Energie-Erzeuger (Strom, Gas, Wasser) | P87: Metzgerei | Q87: 2118
A88: 1389 | B88: 1389 Sonstige Öl-u. Erdgasfeld-Arbeiten | C88: 1007 | D88: Energie-Erzeuger (Strom, Gas, Wasser) | F88: 1007 | G88: Energie-Erzeuger (Strom, Gas, Wasser) | P88: Milchgroßhandel | Q88: 8512
A89: 1400 | B89: 1400 --- Gewinnung von Steinen und Erden, außer Brennstoffen --- | P89: Mineralölhandel | Q89: 4249
A90: 1411 | B90: 1411 Steingewinnung | C90: 1321 | D90: Steinbruch | F90: 1321 | G90: Steinbruch | P90: Molkerei | Q90: 2194
A91: 1422 | B91: 1422 Zerkleinerter u. gebrochener Kalkstein | C91: 1321 | D91: Steinbruch | F91: 1321 | G91: Steinbruch | P91: Molkerei | Q91: 2194
A92: 1423 | B92: 1423 Zerkleinerter u. gebrochener Granit | C92: 1321 | D92: Steinbruch | F92: 1321 | G92: Steinbruch | P92: Mühlen | Q92: 1401
A93: 1429 | B93: 1429 Sonstiges zerkleinertes u. gebrochenes Gestein | C93: 1321 | D93: Steinbruch | F93: 1321 | G93: Steinbruch | P93: Mühlen | Q93: 1401
A94: 1442 | B94: 1442 Bausand u. Kies | C94: 9618 | D94: Kieswerk | F94: 9618 | G94: Kieswerk | P94: Obsthandel | Q94: 8552
A95: 1446 | B95: 1446 Industriesand | C95: 9618 | D95: Kieswerk | F95: 9618 | G95: Kieswerk | P95: Online-Dienste | Q95: 8560
A96: 1455 | B96: 1455 Kaolin u. Bindeton | C96: 9618 | D96: Kieswerk | F96: 9618 | G96: Kieswerk | P96: Personalleasing-/ Zeitarbeitsunternehmen | Q96: 8578
A97: 1459 | B97: 1459 Sonstige Tonerde, Keramik u. feuerfeste Mineralien | C97: 9618 | D97: Kieswerk | F97: 9618 | G97: Kieswerk | P97: Pharmazeutische Artikelherstellung | Q97: 2461
A98: 1474 | B98: 1474 Pottasche, Borate, Soda | C98: 9618 | D98: Kieswerk | F98: 9618 | G98: Kieswerk | P98: Pharmazeutischer Handel | Q98: 2463
A99: 1475 | B99: 1475 Phosphatgestein | C99: 0001 | D99: Anfrage | F99: 1033 | G99: Versicherte Branche gem. Antrag RKL 3 USRU | P99: Postagentur/Postbankagentur | Q99: 8612
A100: 1479 | B100: 1479 Abbau v. sonstigen Mineralien für die Chemie und für Düngemittel | C100: 0001 | D100: Anfrage | F100: 1033 | G100: Versicherte Branche gem. Antrag RKL 3 USRU | P100: Recyclingunternehmen | Q100: 1554
A101: 1481 | B101: 1481 Nichtmetallbergbaudienste (außer Brennstoffe) | C101: 9618 | D101: Kieswerk | F101: 9618 | G101: Kieswerk | P101: Reifenherstellung | Q101: 4256
A102: 1499 | B102: 1499 verschied. Steine u. Erden (außer Brennstoffe) | C102: 1321 | D102: Steinbruch | F102: 1321 | G102: Steinbruch | P102: Sanitätsartikelhandel | Q102: 8667
A103: 15 - 17 | B103: 15 - 17 Baugewerbe | P103: Schlachterei | Q103: 2193
...

Sheet Prämie - Arag
A1: Fragebogen / Tasks | B1: Antwort / Wert | C1: Zuschlag DS
A2: DS1 | B2: =limit1 -> 0 | C2: 0
A3: DS2 | B3: =limit2 -> 0 | C3: 0
A4: DS3 | B4: =limit3 -> 0 | C4: 0
A5: Sublimit1 | B5: =sublimit1 -> 0 | C5: 0
A6: Sublimit2 | B6: =sublimit2 -> 0 | C6: 0
A7: Sublimit3 | B7: =sublimit3 -> 0 | C7: 0
A9: Vollzeit | B9: =anzahlMitarbeiterVZ -> 0
A10: Teilzeit | B10: =anzahlMitarbeiterTZ -> 0
A11: Geringfügig Beschäftigte | B11: =anzahlMitarbeiterGF -> 0
A12: =Fragenkatalog!A17 -> Geltungsbereich | B12: =geltungsbereich -> 0
A14: Nettoisierung | B14: =RisikoFragen902 -> 0
A15: Provision Koopmakler | B15: =coopbrokerCourtageHPST -> 0
A17: Mitarbeiter | B17: =anzahlMitarbeiterGesamt -> 0
A18: Tarifprämie
A19: PuA Tarifprämie
A20: Zu / Abschläge aus Referrals | B20: =Referrals!J37 -> 1 | J20: Prüfen, ob koopmakler-Provision in prozent ankommt oder nicht
A21: Zuschlag Geltungsbereich | B21: =IF(geltungsbereich = "EU", -9.09, 0) -> 0
A22: Gesamtprovision Arag | B22: 0.4
B24: Angebotene Deckungssumme | C24: Kartellrecht Sublimit | D24: Jahresprämie | E24: Nettoprovision Hendricks | F24: Nettoprovision Koopmakler | G24: Tarifprämie | H24: Prämie inkl- Zu/Abschläge | I24: Prämie Kartellrecht | J24: Gesamtprämie | K24: Abzug für Nettoisierung
A25: DS1 inkl. Sublimit | B25: =B2 -> 0 | C25: =IF(AND(ISNUMBER(sublimit1), sublimit1 > 0),sublimit1,"") | D25: =J25-K25 -> #VALUE! | E25: =IF(RisikoFragen902="0",MAX(ROUND((B$22-$B$15)/(1-$B$15),4),0),MAX(ROUND((B$22-$B$15),4),0)) -> 0.4 | F25: =($B$14*$B$15/100) -> 0 | G25: ='Arag-Tarif'!$C21 -> #VALUE! | H25: =IF(AND(ISNUMBER($B$2),ISNUMBER($C$2)),ROUND(G25*((B$20)*(100+B$21)*(100+$C$2)/100)/100,2),"-") -> #VALUE! | I25: =IF(AND(ISNUMBER(sublimit1), sublimit1 > 0),ROUND(B19*(C5+100)/100, 2),0) -> 0 | J25: =H25+I25 -> #VALUE! | K25: =IF(RisikoFragen902="0",ROUND(J25*$B$15,2),0) -> 0
A26: DS1 | B26: =B2 -> 0 | D26: =J26-K26 -> #VALUE! | E26: =IF(RisikoFragen902="0",MAX(ROUND((B$22-$B$15)/(1-$B$15),4),0),MAX(ROUND((B$22-$B$15),4),0)) -> 0.4 | F26: =($B$14*$B$15/100) -> 0 | G26: ='Arag-Tarif'!$C22 -> #VALUE! | H26: =IF(AND(ISNUMBER($B$2),ISNUMBER($C$2)),ROUND(G26*((B$20)*(100+B$21)*(100+$C$2)/100)/100,2),"-") -> #VALUE! | J26: =H26+I26 -> #VALUE! | K26: =IF(RisikoFragen902="0",ROUND(J26*$B$15,2),0) -> 0
A27: DS2 inkl. Sublimit | B27: =B3 -> 0 | C27: =IF(AND(ISNUMBER(sublimit2), sublimit2 > 0),sublimit2,"") | D27: =J27-K27 -> #VALUE! | E27: =IF(RisikoFragen902="0",MAX(ROUND((B$22-$B$15)/(1-$B$15),4),0),MAX(ROUND((B$22-$B$15),4),0)) -> 0.4 | F27: =($B$14*$B$15/100) -> 0 | G27: ='Arag-Tarif'!$C23 -> #VALUE! | H27: =IF(AND(ISNUMBER($B$3),ISNUMBER($C$3)),ROUND(G27*((B$20)*(100+B$21)*(100+$C$3)/100)/100,2),"-") -> #VALUE! | I27: =IF(AND(ISNUMBER(sublimit2), sublimit2 > 0),ROUND(B19*(C6+100)/100, 2),0) -> 0 | J27: =H27+I27 -> #VALUE! | K27: =IF(RisikoFragen902="0",ROUND(J27*$B$15,2),0) -> 0
A28: DS2 | B28: =B3 -> 0 | D28: =J28-K28 -> #VALUE! | E28: =IF(RisikoFragen902="0",MAX(ROUND((B$22-$B$15)/(1-$B$15),4),0),MAX(ROUND((B$22-$B$15),4),0)) -> 0.4 | F28: =($B$14*$B$15/100) -> 0 | G28: ='Arag-Tarif'!$C24 -> #VALUE! | H28: =IF(AND(ISNUMBER($B$3),ISNUMBER($C$3)),ROUND(G28*((B$20)*(100+B$21)*(100+$C$3)/100)/100,2),"-") -> #VALUE! | J28: =H28+I28 -> #VALUE! | K28: =IF(RisikoFragen902="0",ROUND(J28*$B$15,2),0) -> 0
A29: DS3 inkl. Sublimit | B29: =B4 -> 0 | C29: =IF(AND(ISNUMBER(sublimit3), sublimit3 > 0),sublimit3,"") | D29: =J29-K29 -> #VALUE! | E29: =IF(RisikoFragen902="0",MAX(ROUND((B$22-$B$15)/(1-$B$15),4),0),MAX(ROUND((B$22-$B$15),4),0)) -> 0.4 | F29: =($B$14*$B$15/100) -> 0 | G29: ='Arag-Tarif'!$C25 -> #VALUE! | H29: =IF(AND(ISNUMBER($B$4),ISNUMBER($C$4)),ROUND(G29*((B$20)*(100+B$21)*(100+$C$4)/100)/100,2),"-") -> #VALUE! | I29: =IF(AND(ISNUMBER(sublimit3), sublimit3 > 0),ROUND(B19*(C7+100)/100, 2),0) -> 0 | J29: =H29+I29 -> #VALUE! | K29: =IF(RisikoFragen902="0",ROUND(J29*$B$15,2),0) -> 0
A30: DS3 | B30: =B4 -> 0 | D30: =J30-K30 -> #VALUE! | E30: =IF(RisikoFragen902="0",MAX(ROUND((B$22-$B$15)/(1-$B$15),4),0),MAX(ROUND((B$22-$B$15),4),0)) -> 0.4 | F30: =($B$14*$B$15/100) -> 0 | G30: ='Arag-Tarif'!$C26 -> #VALUE! | H30: =IF(AND(ISNUMBER($B$4),ISNUMBER($C$4)),ROUND(G30*((B$20)*(100+B$21)*(100+$C$4)/100)/100,2),"-") -> #VALUE! | J30: =H30+I30 -> #VALUE! | K30: =IF(RisikoFragen902="0",ROUND(J30*$B$15,2),0) -> 0

Sheet Arag-Tarif
D1: 500000 | F1: 1000000 | H1: 1500000 | J1: 2000000
A2: von | B2: bis | C2: Staffelung | D2: VS 500.000 | F2: VS 1.000.000 | H2: VS 1.500.000 | J2: VS 2.000.000 (2-fach max.)
D3: Prämie pro Mitarbeiter | E3: Mindest-Prämie | F3: Prämie pro Mitarbeiter | G3: Mindest-Prämie | H3: Prämie pro Mitarbeiter | I3: Mindest-Prämie | J3: Prämie pro Mitarbeiter | K3: Mindest-Prämie
A4: 0 | B4: 10 | C4: =IF(AND(anzahlMitarbeiterGesamt>=$A4,anzahlMitarbeiterGesamt<=$B4),"x","") -> x | E4: 649 | G4: 708 | I4: 831.9 | K4: 920.4
A5: 11 | B5: 25 | C5: =IF(AND(anzahlMitarbeiterGesamt>=$A5,anzahlMitarbeiterGesamt<=$B5),"x","") | E5: 858 | G5: 936 | I5: 1099.8 | K5: 1216.8
A6: 26 | B6: 50 | C6: =IF(AND(anzahlMitarbeiterGesamt>=$A6,anzahlMitarbeiterGesamt<=$B6),"x","") | E6: 1188 | G6: 1296 | I6: 1522.8 | K6: 1684.8
A7: 51 | B7: 75 | C7: =IF(AND(anzahlMitarbeiterGesamt>=$A7,anzahlMitarbeiterGesamt<=$B7),"x","") | E7: 1749 | G7: 1908 | I7: 2241.9 | K7: 2480.4
A8: 76 | B8: 100 | C8: =IF(AND(anzahlMitarbeiterGesamt>=$A8,anzahlMitarbeiterGesamt<=$B8),"x","") | E8: 2145 | G8: 2340 | I8: 2749.5 | K8: 3042
A9: 101 | B9: 200 | C9: =IF(AND(anzahlMitarbeiterGesamt>=$A9,anzahlMitarbeiterGesamt<=$B9),"x","") | D9: 22 | E9: 2145 | F9: 24 | G9: 2340 | H9: 28.2 | I9: 2749.5 | J9: 31.2 | K9: 3042
A10: 201 | B10: 300 | C10: =IF(AND(anzahlMitarbeiterGesamt>=$A10,anzahlMitarbeiterGesamt<=$B10),"x","") | D10: 17.6 | E10: 4400 | F10: 19.2 | G10: 4800 | H10: 22.56 | I10: 5640 | J10: 24.96 | K10: 6240
A11: 301 | B11: 500 | C11: =IF(AND(anzahlMitarbeiterGesamt>=$A11,anzahlMitarbeiterGesamt<=$B11),"x","") | D11: 13.2 | E11: 5280 | F11: 14.4 | G11: 5760 | H11: 16.92 | I11: 6768 | J11: 18.72 | K11: 7488
A12: 501 | B12: 1000 | C12: =IF(AND(anzahlMitarbeiterGesamt>=$A12,anzahlMitarbeiterGesamt<=$B12),"x","") | D12: 10.38 | E12: 6600 | F12: 11.32 | G12: 7200 | H12: 13.301 | I12: 8460 | J12: 14.716 | K12: 9360
A13: 1001 | B13: 1500 | C13: =IF(AND(anzahlMitarbeiterGesamt>=$A13,anzahlMitarbeiterGesamt<=$B13),"x","") | D13: 7.7 | E13: 10383.33 | F13: 8.4 | G13: 11316.67 | H13: 9.87 | I13: 13297.087 | J13: 10.92 | K13: 14711.671
A14: Zugehörige Staffel | B14: =CONCATENATE(INDEX('Arag-Tarif'!A4:A13,MATCH("x",'Arag-Tarif'!C4:C13,0))," - ",(INDEX('Arag-Tarif'!B4:B13,MATCH("x",'Arag-Tarif'!C4:C13,0)))) -> 0 - 10 | D14: =INDEX('Arag-Tarif'!D4:D13,MATCH("x",'Arag-Tarif'!C4:C13,0)) -> 0 | E14: =INDEX('Arag-Tarif'!E4:E13,MATCH("x",'Arag-Tarif'!C4:C13,0)) -> 649 | F14: =INDEX('Arag-Tarif'!F4:F13,MATCH("x",'Arag-Tarif'!C4:C13,0)) -> 0 | G14: =INDEX('Arag-Tarif'!G4:G13,MATCH("x",'Arag-Tarif'!C4:C13,0)) -> 708 | H14: =INDEX('Arag-Tarif'!H4:H13,MATCH("x",'Arag-Tarif'!C4:C13,0)) -> 0 | I14: =INDEX('Arag-Tarif'!I4:I13,MATCH("x",'Arag-Tarif'!C4:C13,0)) -> 831.9 | J14: =INDEX('Arag-Tarif'!J4:J13,MATCH("x",'Arag-Tarif'!C4:C13,0)) -> 0 | K14: =INDEX('Arag-Tarif'!K4:K13,MATCH("x",'Arag-Tarif'!C4:C13,0)) -> 920.4
A16: Alle Prämienangaben in EUR und zzgl. gesetzl. Vers.-St. (derzeit 19 %)
A17: Für Geltungsbereich EUROPA (geographisch) 9,09 % Abschlag
B20: Hilfstabelle | C20: Prämie | D20: Prämie pro Mitarbeiter | E20: Mindest-Prämie | F20: Prämien-Art
B21: DS 1 | C21: =MAX(E21,anzahlMitarbeiterGesamt*D21) -> #VALUE! | D21: =IF(limit1='Arag-Tarif'!$D$1,'Arag-Tarif'!$D$14,IF(limit1='Arag-Tarif'!$F$1,'Arag-Tarif'!$F$14,IF(limit1='Arag-Tarif'!$H$1,'Arag-Tarif'!$H$14,IF(limit1='Arag-Tarif'!$J$1,'Arag-Tarif'!$J$14,"")))) | E21: =IF(limit1='Arag-Tarif'!$D$1,'Arag-Tarif'!$E$14,IF(limit1='Arag-Tarif'!$F$1,'Arag-Tarif'!$G$14,IF(limit1='Arag-Tarif'!$H$1,'Arag-Tarif'!$I$14,IF(limit1='Arag-Tarif'!$J$1,'Arag-Tarif'!$K$14,"")))) | F21: =IF('Arag-Tarif'!$D$21=0,"FIXED PREMIUM",IF('Arag-Tarif'!$E$21='Arag-Tarif'!$C$21,"MINIMUM PREMIUM","PREMIUM PER EMPLOYEE")) -> #VALUE!
B22: DS 1 | C22: =MAX(E22,anzahlMitarbeiterGesamt*D22) -> #VALUE! | D22: =IF(limit1='Arag-Tarif'!$D$1,'Arag-Tarif'!$D$14,IF(limit1='Arag-Tarif'!$F$1,'Arag-Tarif'!$F$14,IF(limit1='Arag-Tarif'!$H$1,'Arag-Tarif'!$H$14,IF(limit1='Arag-Tarif'!$J$1,'Arag-Tarif'!$J$14,"")))) | E22: =IF(limit1='Arag-Tarif'!$D$1,'Arag-Tarif'!$E$14,IF(limit1='Arag-Tarif'!$F$1,'Arag-Tarif'!$G$14,IF(limit1='Arag-Tarif'!$H$1,'Arag-Tarif'!$I$14,IF(limit1='Arag-Tarif'!$J$1,'Arag-Tarif'!$K$14,"")))) | F22: =IF('Arag-Tarif'!$D$22=0,"FIXED PREMIUM",IF('Arag-Tarif'!$E$22='Arag-Tarif'!$C$22,"MINIMUM PREMIUM","PREMIUM PER EMPLOYEE")) -> #VALUE!
B23: DS 2 | C23: =MAX(E23,anzahlMitarbeiterGesamt*D23) -> #VALUE! | D23: =IF(limit2='Arag-Tarif'!$D$1,'Arag-Tarif'!$D$14,IF(limit2='Arag-Tarif'!$F$1,'Arag-Tarif'!$F$14,IF(limit2='Arag-Tarif'!$H$1,'Arag-Tarif'!$H$14,IF(limit2='Arag-Tarif'!$J$1,'Arag-Tarif'!$J$14,"")))) | E23: =IF(limit2='Arag-Tarif'!$D$1,'Arag-Tarif'!$E$14,IF(limit2='Arag-Tarif'!$F$1,'Arag-Tarif'!$G$14,IF(limit2='Arag-Tarif'!$H$1,'Arag-Tarif'!$I$14,IF(limit2='Arag-Tarif'!$J$1,'Arag-Tarif'!$K$14,"")))) | F23: =IF('Arag-Tarif'!$D$23=0,"FIXED PREMIUM",IF('Arag-Tarif'!$E$23='Arag-Tarif'!$C$23,"MINIMUM PREMIUM","PREMIUM PER EMPLOYEE")) -> #VALUE!
B24: DS 2 | C24: =MAX(E24,anzahlMitarbeiterGesamt*D24) -> #VALUE! | D24: =IF(limit2='Arag-Tarif'!$D$1,'Arag-Tarif'!$D$14,IF(limit2='Arag-Tarif'!$F$1,'Arag-Tarif'!$F$14,IF(limit2='Arag-Tarif'!$H$1,'Arag-Tarif'!$H$14,IF(limit2='Arag-Tarif'!$J$1,'Arag-Tarif'!$J$14,"")))) | E24: =IF(limit2='Arag-Tarif'!$D$1,'Arag-Tarif'!$E$14,IF(limit2='Arag-Tarif'!$F$1,'Arag-Tarif'!$G$14,IF(limit2='Arag-Tarif'!$H$1,'Arag-Tarif'!$I$14,IF(limit2='Arag-Tarif'!$J$1,'Arag-Tarif'!$K$14,"")))) | F24: =IF('Arag-Tarif'!$D$24=0,"FIXED PREMIUM",IF('Arag-Tarif'!$E$24='Arag-Tarif'!$C$24,"MINIMUM PREMIUM","PREMIUM PER EMPLOYEE")) -> #VALUE!
B25: DS 3 | C25: =MAX(E25,anzahlMitarbeiterGesamt*D25) -> #VALUE! | D25: =IF(limit3='Arag-Tarif'!$D$1,'Arag-Tarif'!$D$14,IF(limit3='Arag-Tarif'!$F$1,'Arag-Tarif'!$F$14,IF(limit3='Arag-Tarif'!$H$1,'Arag-Tarif'!$H$14,IF(limit3='Arag-Tarif'!$J$1,'Arag-Tarif'!$J$14,"")))) | E25: =IF(limit3='Arag-Tarif'!$D$1,'Arag-Tarif'!$E$14,IF(limit3='Arag-Tarif'!$F$1,'Arag-Tarif'!$G$14,IF(limit3='Arag-Tarif'!$H$1,'Arag-Tarif'!$I$14,IF(limit3='Arag-Tarif'!$J$1,'Arag-Tarif'!$K$14,"")))) | F25: =IF('Arag-Tarif'!$D$25=0,"FIXED PREMIUM",IF('Arag-Tarif'!$E$25='Arag-Tarif'!$C$25,"MINIMUM PREMIUM","PREMIUM PER EMPLOYEE")) -> #VALUE!
B26: DS 3 | C26: =MAX(E26,anzahlMitarbeiterGesamt*D26) -> #VALUE! | D26: =IF(limit3='Arag-Tarif'!$D$1,'Arag-Tarif'!$D$14,IF(limit3='Arag-Tarif'!$F$1,'Arag-Tarif'!$F$14,IF(limit3='Arag-Tarif'!$H$1,'Arag-Tarif'!$H$14,IF(limit3='Arag-Tarif'!$J$1,'Arag-Tarif'!$J$14,"")))) | E26: =IF(limit3='Arag-Tarif'!$D$1,'Arag-Tarif'!$E$14,IF(limit3='Arag-Tarif'!$F$1,'Arag-Tarif'!$G$14,IF(limit3='Arag-Tarif'!$H$1,'Arag-Tarif'!$I$14,IF(limit3='Arag-Tarif'!$J$1,'Arag-Tarif'!$K$14,"")))) | F26: =IF('Arag-Tarif'!$D$26=0,"FIXED PREMIUM",IF('Arag-Tarif'!$E$26='Arag-Tarif'!$C$26,"MINIMUM PREMIUM","PREMIUM PER EMPLOYEE")) -> #VALUE!

Sheet Prämie - Roland
A1: Fragebogen / Tasks | B1: Antwort / Wert | C1: Zuschlag DS
A2: DS1 | B2: =limit1 -> 0 | C2: {=INDEX('Zuschläge-Tarif'!E2:E5,MATCH("X",'Zuschläge-Tarif'!B2:B5,0))} -> #N/A
A3: DS2 | B3: =limit2 -> 0 | C3: {=INDEX('Zuschläge-Tarif'!E2:E5,MATCH("X",'Zuschläge-Tarif'!C2:C5,0))} -> #N/A
A4: DS3 | B4: =limit3 -> 0 | C4: {=INDEX('Zuschläge-Tarif'!E2:E5,MATCH("X",'Zuschläge-Tarif'!D2:D5,0))} -> #N/A
A5: Sublimit1 | B5: =sublimit1 -> 0 | C5: {=INDEX('Zuschläge-PuA-Tarif'!E2:E3,MATCH("X",'Zuschläge-PuA-Tarif'!B2:B3,0))} -> #N/A
A6: Sublimit2 | B6: =sublimit2 -> 0 | C6: {=INDEX('Zuschläge-PuA-Tarif'!E2:E3,MATCH("X",'Zuschläge-PuA-Tarif'!C2:C3,0))} -> #N/A
A7: Sublimit3 | B7: =sublimit3 -> 0 | C7: {=INDEX('Zuschläge-PuA-Tarif'!E2:E3,MATCH("X",'Zuschläge-PuA-Tarif'!D2:D3,0))} -> #N/A
A9: Vollzeit | B9: =anzahlMitarbeiterVZ -> 0
A10: Teilzeit | B10: =anzahlMitarbeiterTZ -> 0
A11: Geringfügig Beschäftigte | B11: =anzahlMitarbeiterGF -> 0
A12: =Fragenkatalog!A17 -> Geltungsbereich | B12: =geltungsbereich -> 0
A14: Nettoisierung | B14: =RisikoFragen902 -> 0
A15: Provision Koopmakler | B15: =coopbrokerCourtageHPST -> 0
A17: Mitarbeiter | B17: =anzahlMitarbeiterGesamt -> 0
A18: Tarifprämie | B18: =INDEX('Roland-Tarif'!C2:C70,MATCH("x",'Roland-Tarif'!E2:E70,0)) -> 420.5
A19: PuA Tarifprämie | B19: {=INDEX('Roland-PuA-Tarif'!C2:C70,MATCH("x",'Roland-PuA-Tarif'!E2:E70,0))} -> 44.01
A20: Zu / Abschläge aus Referrals | B20: =Referrals!E37 -> 1
A21: Zuschlag Geltungsbereich | B21: =IF(geltungsbereich = "EU", -10, 0) -> 0
A22: Gesamtprovision Roland | B22: 0.4
B24: Angebotene Deckungssumme | C24: Kartellrecht Sublimit | D24: Jahresprämie | E24: Nettoprovision Hendricks | F24: Nettoprovision Koopmakler | G24: Prämie inkl- Zu/Abschläge | H24: Prämie Kartellrecht | I24: Gesamtprämie | J24: Abzug für Nettoisierung
A25: DS1 inkl. Sublimit | B25: =B2 -> 0 | C25: =IF(AND(ISNUMBER(sublimit1), sublimit1 > 0),sublimit1,"") | D25: =I25-J25 -> #VALUE! | E25: =IF(RisikoFragen902="0",MAX(ROUND((B$22-$B$15)/(1-$B$15),4),0),MAX(ROUND((B$22-$B$15),4),0)) -> 0.4 | F25: =(B14*B15/100) -> 0 | G25: =IF(AND(ISNUMBER(B2),ISNUMBER(C2)),ROUND(B18*((B$20)*(100+B$21)*(100+C2)/100)/100,2),"-") -> - | H25: =IF(AND(ISNUMBER(sublimit1), sublimit1 > 0),ROUND(B19*(C5+100)/100, 2),0) -> 0 | I25: =G25+H25 -> #VALUE! | J25: =IF(RisikoFragen902="0",ROUND(I25*$B$15,2),0) -> 0
A26: DS1 | B26: =B2 -> 0 | D26: =I26-J26 -> #VALUE! | E26: =IF(RisikoFragen902="0",MAX(ROUND((B$22-$B$15)/(1-$B$15),4),0),MAX(ROUND((B$22-$B$15),4),0)) -> 0.4 | F26: =(B14*B15/100) -> 0 | G26: =IF(AND(ISNUMBER(B2),ISNUMBER(C2)),ROUND(B18*((B$20)*(100+B$21)*(100+C2)/100)/100,2),"-") -> - | I26: =G26+H26 -> #VALUE! | J26: =IF(RisikoFragen902="0",ROUND(I26*$B$15,2),0) -> 0
A27: DS2 inkl. Sublimit | B27: =B3 -> 0 | C27: =IF(AND(ISNUMBER(sublimit2), sublimit2 > 0),sublimit2,"") | D27: =I27-J27 -> #VALUE! | E27: =IF(RisikoFragen902="0",MAX(ROUND((B$22-$B$15)/(1-$B$15),4),0),MAX(ROUND((B$22-$B$15),4),0)) -> 0.4 | F27: =(B14*B15/100) -> 0 | G27: =IF(AND(ISNUMBER(B3),ISNUMBER(C3)),ROUND(B18*((B$20)*(100+B$21)*(100+C3)/100)/100,2),"-") -> - | H27: =IF(AND(ISNUMBER(sublimit2), sublimit2 > 0),ROUND(B19*(C6+100)/100, 2),0) -> 0 | I27: =G27+H27 -> #VALUE! | J27: =IF(RisikoFragen902="0",ROUND(I27*$B$15,2),0) -> 0
A28: DS2 | B28: =B3 -> 0 | D28: =I28-J28 -> #VALUE! | E28: =IF(RisikoFragen902="0",MAX(ROUND((B$22-$B$15)/(1-$B$15),4),0),MAX(ROUND((B$22-$B$15),4),0)) -> 0.4 | F28: =(B14*B15/100) -> 0 | G28: =IF(AND(ISNUMBER(B3),ISNUMBER(C3)),ROUND(B18*((B$20)*(100+B$21)*(100+C3)/100)/100,2),"-") -> - | I28: =G28+H28 -> #VALUE! | J28: =IF(RisikoFragen902="0",ROUND(I28*$B$15,2),0) -> 0
A29: DS3 inkl. Sublimit | B29: =B4 -> 0 | C29: =IF(AND(ISNUMBER(sublimit3), sublimit3 > 0),sublimit3,"") | D29: =I29-J29 -> #VALUE! | E29: =IF(RisikoFragen902="0",MAX(ROUND((B$22-$B$15)/(1-$B$15),4),0),MAX(ROUND((B$22-$B$15),4),0)) -> 0.4 | F29: =(B14*B15/100) -> 0 | G29: =IF(AND(ISNUMBER(B4),ISNUMBER(C4)),ROUND(B18*((B$20)*(100+B$21)*(100+C4)/100)/100,2),"-") -> - | H29: =IF(AND(ISNUMBER(sublimit3), sublimit3 > 0),ROUND(B19*(C7+100)/100, 2),0) -> 0 | I29: =G29+H29 -> #VALUE! | J29: =IF(RisikoFragen902="0",ROUND(I29*$B$15,2),0) -> 0
A30: DS3 | B30: =B4 -> 0 | D30: =I30-J30 -> #VALUE! | E30: =IF(RisikoFragen902="0",MAX(ROUND((B$22-$B$15)/(1-$B$15),4),0),MAX(ROUND((B$22-$B$15),4),0)) -> 0.4 | F30: =(B14*B15/100) -> 0 | G30: =IF(AND(ISNUMBER(B4),ISNUMBER(C4)),ROUND(B18*((B$20)*(100+B$21)*(100+C4)/100)/100,2),"-") -> - | I30: =G30+H30 -> #VALUE! | J30: =IF(RisikoFragen902="0",ROUND(I30*$B$15,2),0) -> 0

Sheet Roland-Tarif
A1: von | B1: bis | C1: Absolute Prämie | D1: Prämie pro Mitarbeiter | E1: FILTER
A2: 0 | B2: 0 | C2: 420.5 | E2: =IF(AND(anzahlMitarbeiterGesamt>=A2,anzahlMitarbeiterGesamt<=B2),"x","") -> x
A3: 1 | B3: 3 | C3: 542.3 | E3: =IF(AND(anzahlMitarbeiterGesamt>=A3,anzahlMitarbeiterGesamt<=B3),"x","")
A4: 4 | B4: 6 | C4: 661.2 | E4: =IF(AND(anzahlMitarbeiterGesamt>=A4,anzahlMitarbeiterGesamt<=B4),"x","")
A5: 7 | B5: 10 | C5: 783 | E5: =IF(AND(anzahlMitarbeiterGesamt>=A5,anzahlMitarbeiterGesamt<=B5),"x","")
A6: 11 | B6: 15 | C6: 900.45 | E6: =IF(AND(anzahlMitarbeiterGesamt>=A6,anzahlMitarbeiterGesamt<=B6),"x","")
A7: 16 | B7: 20 | C7: 1010.65 | E7: =IF(AND(anzahlMitarbeiterGesamt>=A7,anzahlMitarbeiterGesamt<=B7),"x","")
A8: 21 | B8: 25 | C8: 1117.95 | E8: =IF(AND(anzahlMitarbeiterGesamt>=A8,anzahlMitarbeiterGesamt<=B8),"x","")
A9: 26 | B9: 30 | C9: 1215.1 | E9: =IF(AND(anzahlMitarbeiterGesamt>=A9,anzahlMitarbeiterGesamt<=B9),"x","")
A10: 31 | B10: 40 | C10: 1313.7 | E10: =IF(AND(anzahlMitarbeiterGesamt>=A10,anzahlMitarbeiterGesamt<=B10),"x","")
A11: 41 | B11: 50 | C11: 1403.6 | E11: =IF(AND(anzahlMitarbeiterGesamt>=A11,anzahlMitarbeiterGesamt<=B11),"x","")
A12: 51 | B12: 60 | C12: 1492.05 | E12: =IF(AND(anzahlMitarbeiterGesamt>=A12,anzahlMitarbeiterGesamt<=B12),"x","")
A13: 61 | B13: 70 | C13: 1580.5 | E13: =IF(AND(anzahlMitarbeiterGesamt>=A13,anzahlMitarbeiterGesamt<=B13),"x","")
... A33: 1001 | B33: 1500 | C33: 10408.1 | E33: =IF(AND(anzahlMitarbeiterGesamt>=A33,anzahlMitarbeiterGesamt<=B33),"x","")

Sheet Roland-PuA-Tarif
A1: von | B1: bis | C1: Absolute Prämie | D1: Prämie pro Mitarbeiter | E1: FILTER
A2: 0 | B2: 0 | C2: 44.01 | E2: =IF(AND(anzahlMitarbeiterGesamt>=A2,anzahlMitarbeiterGesamt<=B2),"x","") -> x
A3: 1 | B3: 3 | C3: 56.57 | E3: =IF(AND(anzahlMitarbeiterGesamt>=A3,anzahlMitarbeiterGesamt<=B3),"x","")
A4: 4 | B4: 6 | C4: 68.85 | E4: =IF(AND(anzahlMitarbeiterGesamt>=A4,anzahlMitarbeiterGesamt<=B4),"x","")
A5: 7 | B5: 10 | C5: 81.41 | E5: =IF(AND(anzahlMitarbeiterGesamt>=A5,anzahlMitarbeiterGesamt<=B5),"x","")
A6: 11 | B6: 15 | C6: 93.42 | E6: =IF(AND(anzahlMitarbeiterGesamt>=A6,anzahlMitarbeiterGesamt<=B6),"x","")
A7: 16 | B7: 20 | C7: 104.49 | E7: =IF(AND(anzahlMitarbeiterGesamt>=A7,anzahlMitarbeiterGesamt<=B7),"x","")
A8: 21 | B8: 25 | C8: 115.56 | E8: =IF(AND(anzahlMitarbeiterGesamt>=A8,anzahlMitarbeiterGesamt<=B8),"x","")
A9: 26 | B9: 30 | C9: 125.69 | E9: =IF(AND(anzahlMitarbeiterGesamt>=A9,anzahlMitarbeiterGesamt<=B9),"x","")
A10: 31 | B10: 40 | C10: 135.81 | E10: =IF(AND(anzahlMitarbeiterGesamt>=A10,anzahlMitarbeiterGesamt<=B10),"x","")
A11: 41 | B11: 50 | C11: 145.13 | E11: =IF(AND(anzahlMitarbeiterGesamt>=A11,anzahlMitarbeiterGesamt<=B11),"x","")
A12: 51 | B12: 60 | C12: 154.31 | E12: =IF(AND(anzahlMitarbeiterGesamt>=A12,anzahlMitarbeiterGesamt<=B12),"x","")
A13: 61 | B13: 70 | C13: 163.49 | E13: =IF(AND(anzahlMitarbeiterGesamt>=A13,anzahlMitarbeiterGesamt<=B13),"x","")
... A33: 1001 | B33: 1500 | C33: 1534.5 | E33: =IF(AND(anzahlMitarbeiterGesamt>=A33,anzahlMitarbeiterGesamt<=B33),"x","")

Sheet Zuschläge-Tarif
A1: Deckungssumme | B1: DS1 | C1: DS2 | D1: DS3 | E1: Zuschlag
A2: 500000 | B2: =IF(A2=limit1,"X","") | C2: =IF(A2=limit2,"X","") | D2: =IF(A2=limit3,"X","") | E2: 0
A3: 1000000 | B3: =IF(A3=limit1,"X","") | C3: =IF(A3=limit2,"X","") | D3: =IF(A3=limit3,"X","") | E3: 10
A4: 1500000 | B4: =IF(A4=limit1,"X","") | C4: =IF(A4=limit2,"X","") | D4: =IF(A4=limit3,"X","") | E4: 40
A5: 2000000 | B5: =IF(A5=limit1,"X","") | C5: =IF(A5=limit2,"X","") | D5: =IF(A5=limit3,"X","") | E5: 60

Sheet Zuschläge-PuA-Tarif
A1: Sublimit | B1: DS1 | C1: DS2 | D1: DS3 | E1: Zuschlag
A2: 150000 | B2: =IF(A2=sublimit1,"X","") | C2: =IF(A2=sublimit2,"X","") | D2: =IF(A2=sublimit3,"X","") | E2: 60
A3: 400000 | B3: =IF(A3=sublimit1,"X","") | C3: =IF(A3=sublimit2,"X","") | D3: =IF(A3=sublimit3,"X","") | E3: 160

Sheet Mappings
A1: Mapping Daten Zahlweise
B2: Cosmo Zahlweisen | C2: ZWS_ID
B3: zahlweise-jaehrlich | C3: 51
B4: zahlweise-halbjaehrlich | C4: 50
B5: zahlweise-vierteljaehrlich | C5: 49
B6: zahlweise-monatlich | C6: 48
A8: Zahlweise In/-Out
C9: =VLOOKUP(B9,B3:C6,2,FALSE()) -> #N/A
A12: Mapping Daten Deckungssummen
B13: PBS_NAME | C13: PBS_NUMMER
B14: EWR_Straf-RS | C14: 2840
B15: EWR_U-Haft | C15: 2841
B16: EWR_Kartellrecht | C16: 2843
B17: NON_EWR_Straf-RS | C17: 3840
B18: NON_EWR_U-Haft | C18: 3841
B19: NON_EWR_Kartellrecht | C19: 3843
A21: PBS Nummer In/-Out
C22: =VLOOKUP(B22,B14:C19,2,FALSE()) -> #N/A
A24: Mapping Daten SLG
B25: Deckungssumme | C25: SLG_CODE
A26: Straf-RS | B26: 500000 | C26: I0500-4
B27: 1000000 | C27: I1000-18
B28: 1500000 | C28: I1500-7
B29: 2000000 | C29: I2000-7
B30: 2500000 | C30: I2500
B31: 3000000 | C31: I3000-7
B32: 3500000 | C32: I3500-2
B33: 4000000 | C33: I4000-2
B34: 4500000 | C34: I4500-2
B35: 5000000 | C35: I5000-3
A37: Straf-RS Nummer In/-Out
C38: =VLOOKUP(B38,B26:C35,2,FALSE()) -> #N/A
B40: Deckungssumme | C40: SLG_CODE
A41: Kartellrecht | B41: 50000 | C41: DS0050
B42: 75000 | C42: DS0075
B43: 100000 | C43: DS0100
B44: 125000 | C44: DS0125
B45: 150000 | C45: DS0150
B46: 200000 | C46: DS0200
B47: 1000000 | C47: DS1000
B48: 250000 | C48: INDS0250
B49: 300000 | C49: INDS03002
B50: 400000 | C50: INDS0400
B51: 500000 | C51: INDS05002
A53: Straf-RS Nummer In/-Out
C54: =VLOOKUP(B54,B41:C51,2,FALSE()) -> #N/A
B56: Deckungssumme (Straf-RS) | C56: SLG_CODE
A57: U-Haft | B57: 50000 | C57: IUHAFT-2
B58: 75000 | C58: IUHAFT-2
B59: 100000 | C59: IUHAFT-2
B60: 125000 | C60: IUHAFT-2
B61: 150000 | C61: IUHAFT-2
B62: 200000 | C62: IUHAFT-2
B63: 1000000 | C63: IUHAFT-2
B64: 250000 | C64: IUHAFT-2
B65: 300000 | C65: IUHAFT-2
B66: 400000 | C66: IUHAFT-2
B67: 500000 | C67: IUHAFT-2
A69: Straf-RS Nummer In/-Out
C70: =VLOOKUP(B70,B57:C67,2,FALSE()) -> #N/A

Sheet VersichererDaten
B1: Roland | C1: Arag
A2: Globaler Angebotsstatus
